Workbook
Name FirmaName: '01_Stammdaten'!$B$5
Name FirmaStrasse: '01_Stammdaten'!$B$6
Name FirmaPLZ: '01_Stammdaten'!$B$7
Name FirmaOrt: '01_Stammdaten'!$B$8
Name FirmaTel: '01_Stammdaten'!$B$9
Name FirmaMail: '01_Stammdaten'!$B$10
Name FirmaUStId: '01_Stammdaten'!$B$11
Name FirmaStNr: '01_Stammdaten'!$B$12
Name FirmaHRB: '01_Stammdaten'!$B$13
Name FirmaGF: '01_Stammdaten'!$B$14
Name FirmaIBAN: '01_Stammdaten'!$B$15
Name FirmaBIC: '01_Stammdaten'!$B$16
Name FirmaBank: '01_Stammdaten'!$B$17
Name GJ: '01_Stammdaten'!$F$5
Name UStSatz: '01_Stammdaten'!$F$6
Name SkontoPct: '01_Stammdaten'!$F$7
Name SkontoTage: '01_Stammdaten'!$F$8
Name Zahlungsziel: '01_Stammdaten'!$F$9
Name EinbehaltPct: '01_Stammdaten'!$F$10
Name GewaehrJahre: '01_Stammdaten'!$F$11
Name MindestLiq: '01_Stammdaten'!$F$12
Name AnfangsBank: '01_Stammdaten'!$F$13
Name Kreditlinie: '01_Stammdaten'!$F$14
Name SollStunden: '01_Stammdaten'!$F$15
Name VSSatz: '01_Stammdaten'!$F$16
Name AGKPct: '01_Stammdaten'!$F$17
Name WuGPct: '01_Stammdaten'!$F$18
Name BuHaName: '01_Stammdaten'!$F$19
Name lstProjektStatus: '01_Stammdaten'!$A$22:$A$28
Name lstBelegStatus: '01_Stammdaten'!$B$22:$B$27
Name lstAngebotStatus: '01_Stammdaten'!$C$22:$C$26
Name lstProjektArt: '01_Stammdaten'!$D$22:$D$27
Name lstVertrag: '01_Stammdaten'!$E$22:$E$26
Name lstARTyp: '01_Stammdaten'!$F$22:$F$26
Name lstERTyp: '01_Stammdaten'!$G$22:$G$26
Name lstZahlungArt: '01_Stammdaten'!$H$22:$H$23
Name KostenartenGruppe: '01_Stammdaten'!$C$34:$C$43
Name KundenNr: '02_Kunden'!$A$4:$A$400
Name KundenName: '02_Kunden'!$B$4:$B$400
Name LiefNr: '03_Lieferanten'!$A$4:$A$400
Name LiefName: '03_Lieferanten'!$B$4:$B$400
Name PersNr: '04_Personal'!$A$4:$A$400
Name PersName: '04_Personal'!$B$4:$B$400
Name ProjektNr: '05_Projekte'!$A$4:$A$400
Name ProjektName: '05_Projekte'!$B$4:$B$400
Name AngebotNr: '08_Angebote'!$A$4:$A$400
Name StundenKosten: '10_Stunden'!$K$4:$K$400
Name ARNr: '13_Ausgangsrechnungen'!$A$4:$A$400
Name ERNr: '14_Eingangsrechnungen'!$A$4:$A$400
Name MahnungNr: '17_Mahnwesen'!$A$4:$A$400

Sheet 24_Dashboard
A1: KPI-Dashboard Bau · Geschäftsleitung
A2: Live aus Bewegungsdaten · Bergmann Hoch- und Tiefbau GmbH · GJ 2026
A4: Umsatz Ist GJ | C4: Forecast Umsatz | E4: Auftragsbestand | G4: EBIT Forecast | I4: Rohertragsmarge | K4: EBIT-Marge Ist
A5: ='22_BWA'!B4 | C5: ='21_Forecast'!N20 | E5: =SUMIF('05_Projekte'!F:F,"in Bau",'05_Projekte'!AF:AF)+SUMIF('05_Projekte'!F:F,"beauftragt",'05_Projekte'!AF:AF)+SUMIF('05_Projekte'!F:F,"geplant",'05_Projekte'!AF:AF) | G5: ='22_BWA'!C11 | I5: ='22_BWA'!B12 | K5: ='22_BWA'!B13
A8: OP Debitoren | C8: OP Kreditoren | E8: Einbehalte | G8: Liquidität 13W | I8: Überfällige AR | K8: Hit-Rate Angebote
A9: ='22_BWA'!B14 | C9: ='22_BWA'!B15 | E9: ='22_BWA'!B16 | G9: ='20_Liquiditaet'!B14 | I9: =COUNTIFS('13_Ausgangsrechnungen'!T:T,">0",'13_Ausgangsrechnungen'!S:S,">0") | K9: =IF(COUNTA('08_Angebote'!A4:A400)=0,0,COUNTIF('08_Angebote'!I:I,"angenommen")/COUNTA('08_Angebote'!A4:A400))
A12: Frühwarnung
A13: Liquiditätsengpass in 13 Wochen | B13: =IF(COUNTIF('20_Liquiditaet'!B16:N16,"ENGPASS")>0,"JA — Disposition prüfen","nein")
A14: Mahnungen offen | B14: =COUNTIF('17_Mahnwesen'!H:H,"offen")&" offene Mahnfälle"
A15: Nachträge in Prüfung | B15: =COUNTIF('07_Nachtraege'!F:F,"in Prüfung")&" Claims ohne Freigabe"
A16: Projekte Ampel PRÜFEN | B16: =COUNTIF('23_SollIst'!N:N,"PRÜFEN")&" Projekte unter Marge / über Budget / hohe OP"
A17: Bindefrist Angebote | B17: =COUNTIF('08_Angebote'!M:M,"Bindefrist!")&" Angebote über Bindefrist"
A19: Monatswerte Umsatz / EBIT Forecast
A20: Monat | B20: ='21_Forecast'!B3 | C20: ='21_Forecast'!C3 | D20: ='21_Forecast'!D3 | E20: ='21_Forecast'!E3 | F20: ='21_Forecast'!F3 | G20: ='21_Forecast'!G3 | H20: ='21_Forecast'!H3 | I20: ='21_Forecast'!I3 | ... M20: ='21_Forecast'!M3
A21: Umsatz FC | B21: ='21_Forecast'!B20 | C21: ='21_Forecast'!C20 | D21: ='21_Forecast'!D20 | E21: ='21_Forecast'!E20 | F21: ='21_Forecast'!F20 | G21: ='21_Forecast'!G20 | H21: ='21_Forecast'!H20 | I21: ='21_Forecast'!I20 | ... M21: ='21_Forecast'!M20
A22: EBIT FC | B22: ='21_Forecast'!B26 | C22: ='21_Forecast'!C26 | D22: ='21_Forecast'!D26 | E22: ='21_Forecast'!E26 | F22: ='21_Forecast'!F26 | G22: ='21_Forecast'!G26 | H22: ='21_Forecast'!H26 | I22: ='21_Forecast'!I26 | ... M22: ='21_Forecast'!M26
A40: Top-Projekte nach Auftragswert | J40: Liquiditätsstatus
A41: Projekt | B41: Name | C41: Auftrag aktuell | D41: Fertigstellung | E41: Marge | F41: OP | J41: ='20_Liquiditaet'!B16
A42: =IF('05_Projekte'!A4="","",'05_Projekte'!A4) | B42: =IF(A42="","",'05_Projekte'!B4) | C42: =IF(A42="","",'05_Projekte'!V4) | D42: =IF(A42="","",'05_Projekte'!AE4) | E42: =IF(A42="","",'05_Projekte'!AD4) | F42: =IF(A42="","",'05_Projekte'!AG4) | J42: Kreditlinie | K42: =Kreditlinie
A43: =IF('05_Projekte'!A5="","",'05_Projekte'!A5) | B43: =IF(A43="","",'05_Projekte'!B5) | C43: =IF(A43="","",'05_Projekte'!V5) | D43: =IF(A43="","",'05_Projekte'!AE5) | E43: =IF(A43="","",'05_Projekte'!AD5) | F43: =IF(A43="","",'05_Projekte'!AG5) | J43: Mindestliquidität | K43: =MindestLiq
A44: =IF('05_Projekte'!A6="","",'05_Projekte'!A6) | B44: =IF(A44="","",'05_Projekte'!B6) | C44: =IF(A44="","",'05_Projekte'!V6) | D44: =IF(A44="","",'05_Projekte'!AE6) | E44: =IF(A44="","",'05_Projekte'!AD6) | F44: =IF(A44="","",'05_Projekte'!AG6)
A45: =IF('05_Projekte'!A7="","",'05_Projekte'!A7) | B45: =IF(A45="","",'05_Projekte'!B7) | C45: =IF(A45="","",'05_Projekte'!V7) | D45: =IF(A45="","",'05_Projekte'!AE7) | E45: =IF(A45="","",'05_Projekte'!AD7) | F45: =IF(A45="","",'05_Projekte'!AG7)
A46: =IF('05_Projekte'!A8="","",'05_Projekte'!A8) | B46: =IF(A46="","",'05_Projekte'!B8) | C46: =IF(A46="","",'05_Projekte'!V8) | D46: =IF(A46="","",'05_Projekte'!AE8) | E46: =IF(A46="","",'05_Projekte'!AD8) | F46: =IF(A46="","",'05_Projekte'!AG8)
A47: =IF('05_Projekte'!A9="","",'05_Projekte'!A9) | B47: =IF(A47="","",'05_Projekte'!B9) | C47: =IF(A47="","",'05_Projekte'!V9) | D47: =IF(A47="","",'05_Projekte'!AE9) | E47: =IF(A47="","",'05_Projekte'!AD9) | F47: =IF(A47="","",'05_Projekte'!AG9)

Sheet 00_Navi
A1: Bergmann Bau · Kaufmannsmappe
A2: Alle kaufmännischen Steuerungsblätter für das Baugewerbe · Geschäftsjahr 2026
A4: So arbeiten Sie mit der Mappe
A5: 1. Gelbe bzw. weiße Zellen sind Eingaben. Blaue Zellen sind Formeln — nicht überschreiben.
A6: 2. Neue Zeilen immer innerhalb der Tabelle einfügen (Tab-Taste am Tabellenende), dann bleiben SUMIFS erhalten.
A7: 3. Formulare: oben die Beleg- oder Projektnummer wählen, der Druckbereich füllt sich automatisch.
A8: 4. Importe: Blatt 30_Import und Skript scripts/import_csv.py. DATEV-, Bank- und Stunden-CSV möglich.
A9: 5. Dashboard, Liquidität, Cashflow, Forecast und BWA rechnen aus den Bewegungsdaten — keine Doppelpflege.
A11: Blatt | B11: Inhalt | D11: Kennzahlen-Sprung
A12: 00_Navi | B12: Start und Blattübersicht | D12: KPI-Dashboard
A13: 01_Stammdaten | B13: Firma, Steuern, Parameter | D13: Liquidität 13 Wochen
A14: 02_Kunden | B14: Auftraggeber | D14: Cashflow
A15: 03_Lieferanten | B15: Lieferanten und Nachunternehmer | D15: Forecast / Plan
A16: 04_Personal | B16: Mitarbeiter und Stundensätze | D16: Offene Posten
A17: 05_Projekte | B17: Bauvorhaben und Deckungsbeitrag | D17: Projekt-Soll-Ist
A18: 06_LV | B18: Leistungsverzeichnis
A19: 07_Nachtraege | B19: Nachträge / Claim
A20: 08_Angebote | B20: Angebotsverfolgung
A21: 09_Auftraege | B21: Beauftragte Verträge
A22: 10_Stunden | B22: Zeiterfassung
A23: 11_Material | B23: Material und Baustoffe
A24: 12_Geraete | B24: Geräte und Fuhrpark
A25: 13_Ausgangsrechnungen | B25: Abschlag, Schluss, Anzahlung
A26: 14_Eingangsrechnungen | B26: Kreditoren
A27: 15_Zahlungen | B27: Bank- und Kassenbewegungen
A28: 16_OPOS | B28: Offene Posten Debitor / Kreditor
A29: 17_Mahnwesen | B29: Mahnstufen und Fristen
... A43: 31_Anleitung | B43: Bedienung für die Buchhaltung

Sheet 01_Stammdaten
A1: Stammdaten und Steuerungsparameter
A2: Einmal pflegen — alle Formulare, USt-Berechnungen und Liquiditätsgrenzen greifen hierauf zu
A4: Firma | E4: Parameter (wirken auf alle Blätter)
A5: Firmenname | B5: Bergmann Hoch- und Tiefbau GmbH | E5: Geschäftsjahr | F5: 2026
A6: Straße | B6: Industriestraße 18 | E6: USt-Satz | F6: 0.19
A7: PLZ | B7: 85356 | E7: Skonto % | F7: 0.02
A8: Ort | B8: Freising | E8: Skonto Tage | F8: 10
A9: Telefon | B9: +49 8161 4900-0 | E9: Zahlungsziel Kunden (Tage) | F9: 30
A10: E-Mail | B10: buchhaltung@bergmann-bau.de | E10: Sicherheitseinbehalt % | F10: 0.05
A11: USt-IdNr. | B11: DE129847331 | E11: Gewährleistung Jahre | F11: 5
A12: Steuernummer | B12: 115/215/30817 | E12: Mindestliquidität | F12: 180000
A13: Handelsregister | B13: HRB 18442 Amtsgericht München | E13: Anfangsbestand Bank 01.01. | F13: 285400
A14: Geschäftsführer | B14: Andreas Bergmann | E14: Kreditlinie | F14: 250000
A15: IBAN | B15: DE89 7005 0000 0000 1844 21 | E15: Sollstunden / Monat | F15: 160
A16: BIC | B16: BYLADEM1FSI | E16: Mittl. Verrechnungssatz | F16: 68.5
A17: Bank | B17: Sparkasse Freising | E17: AGK-Zuschlag Angebot | F17: 0.12
E18: Wagnis + Gewinn | F18: 0.05
E19: Buchhaltung | F19: Claudia Meier
A20: Auswahl-Listen (Dropdown-Quellen)
A21: status_projekt | B21: status_beleg | C21: status_angebot | D21: art_projekt | E21: vertrag | F21: ar_typ | G21: er_typ | H21: zahlung_art
A22: geplant | B22: offen | C22: offen | D22: Hochbau | E22: VOB/B | F22: Abschlag | G22: Material | H22: Eingang
A23: beauftragt | B23: teilbezahlt | C23: verhandelt | D23: Tiefbau | E23: BGB | F23: Anzahlung | G23: Nachunternehmer | H23: Ausgang
A24: in Bau | B24: bezahlt | C24: angenommen | D24: Sanierung | E24: Einheitspreis | F24: Schluss | G24: Gerät
A25: abgenommen | B25: gemahnt | C25: abgelehnt | D25: Industrie | E25: Pauschal | F25: Gutschrift | G25: Dienstleistung
A26: abgeschlossen | B26: überfällig | C26: zurückgezogen | D26: Wohnungsbau | E26: GMP | F26: Nachtrag | G26: Allgemein
A27: stopp | B27: storniert | D27: Schlüsselfertig
A28: Gewährleistung
A32: Kostenarten (BWA / Soll-Ist)
A33: Nr | B33: Bezeichnung | C33: Gruppe | D33: SKR-Konto
A34: KA-10 | B34: Fertigungslöhne | C34: Personal | D34: 4100
A35: KA-11 | B35: Gehältersatz | C35: Personal | D35: 4120
A36: KA-20 | B36: Baustoffe | C36: Material | D36: 5000
A37: KA-21 | B37: Hilfsstoffe | C37: Material | D37: 5010
A38: KA-30 | B38: Nachunternehmer | C38: Fremdleistung | D38: 5900
A39: KA-40 | B39: Gerätemiete | C39: Gerät | D39: 5700
A40: KA-41 | B40: Abschreibung Geräte | C40: Gerät | D40: 4830
A41: KA-50 | B41: Baustellengemeinkosten | C41: Gemeinkosten | D41: 4760
A42: KA-60 | B42: Verwaltungsgemeinkosten | C42: Gemeinkosten | D42: 4900
A43: KA-70 | B43: Zinsen / Aval | C43: Finanz | D43: 7300

Sheet 05_Projekte
A1: Projektstamm und Deckungsbeitrag
A2: Auftrag, Nachträge, Ist-Leistung und Kosten werden automatisch verdichtet — Ampel über Marge und OP
A3: Nr | B3: Name | C3: Kunde | D3: Art | E3: Vertrag | F3: Status | G3: Start | H3: Ende Plan | I3: Ende Ist | J3: Auftrag netto | K3: Budget Material | L3: Budget NU | M3: Budget Lohn | N3: Budget Gerät | O3: Budget GK | P3: Einbehalt % | Q3: Bauleiter | R3: Polier | S3: Ort | T3: Notiz | U3: Nachträge beauftr. | V3: Auftrag aktuell | W3: Ist Leistung | X3: Ist Material | Y3: Ist NU | Z3: Ist Lohn | AA3: Ist Kosten | AB3: DB Ist | AC3: Marge % | AD3: Fertigstellung | AE3: Restumsatz | AF3: OP Debitor
A4: P-2026-001 | B4: Wohnquartier Am Park | C4: K-1001 | D4: Hochbau | E4: VOB/B | F4: in Bau | G4: 46035 | H4: 46356 | J4: 2400000 | K4: 720000 | L4: 380000 | M4: 510000 | N4: 95000 | O4: 145000 | P4: 0.05 | Q4: MA-07 | R4: MA-03 | S4: München | T4: 6 Mehrfamilienhäuser, 48 WE | U4: =IF(A4="","",SUMIFS('07_Nachtraege'!$E:$E,'07_Nachtraege'!$B:$B,A4,'07_Nachtraege'!$F:$F,"beauftragt")) | V4: =IF(A4="","",J4+U4) | W4: =IF(A4="","",SUMIFS('13_Ausgangsrechnungen'!$G:$G,'13_Ausgangsrechnungen'!$C:$C,A4)) | X4: =IF(A4="","",SUMIFS('11_Material'!$L:$L,'11_Material'!$C:$C,A4)) | Y4: =IF(A4="","",SUMIFS('14_Eingangsrechnungen'!$F:$F,'14_Eingangsrechnungen'!$C:$C,A4,'14_Eingangsrechnungen'!$E:$E,"Nachunternehmer")) | Z4: =IF(A4="","",SUMIFS('10_Stunden'!$K:$K,'10_Stunden'!$C:$C,A4)) | AA4: =IF(A4="","",X4+Y4+Z4+SUMIFS('14_Eingangsrechnungen'!$F:$F,'14_Eingangsrechnungen'!$C:$C,A4,'14_Eingangsrechnungen'!$E:$E,"Gerät")+SUMIFS('14_Eingangsrechnungen'!$F:$F,'14_Eingangsrechnungen'!$C:$C,A4,'14_Eingangsrechnungen'!$E:$E,"Dienstleistung")) | AB4: =IF(A4="","",W4-AA4) | AC4: =IF(OR(A4="",W4=0),"",AB4/W4) | AD4: =IF(OR(A4="",V4=0),"",W4/V4) | AE4: =IF(A4="","",MAX(0,V4-W4)) | AF4: =IF(A4="","",SUMIFS('13_Ausgangsrechnungen'!$R:$R,'13_Ausgangsrechnungen'!$C:$C,A4))
A5: P-2026-002 | B5: Kita Sonnenweg | C5: K-1003 | D5: Hochbau | E5: VOB/B | F5: in Bau | G5: 46083 | H5: 46310 | J5: 890000 | K5: 250000 | L5: 145000 | M5: 210000 | N5: 38000 | O5: 52000 | P5: 0.05 | Q5: MA-07 | R5: MA-03 | S5: Freising | T5: Neubau 4-gruppige Kita | U5: =IF(A5="","",SUMIFS('07_Nachtraege'!$E:$E,'07_Nachtraege'!$B:$B,A5,'07_Nachtraege'!$F:$F,"beauftragt")) | V5: =IF(A5="","",J5+U5) | W5: =IF(A5="","",SUMIFS('13_Ausgangsrechnungen'!$G:$G,'13_Ausgangsrechnungen'!$C:$C,A5)) | X5: =IF(A5="","",SUMIFS('11_Material'!$L:$L,'11_Material'!$C:$C,A5)) | Y5: =IF(A5="","",SUMIFS('14_Eingangsrechnungen'!$F:$F,'14_Eingangsrechnungen'!$C:$C,A5,'14_Eingangsrechnungen'!$E:$E,"Nachunternehmer")) | Z5: =IF(A5="","",SUMIFS('10_Stunden'!$K:$K,'10_Stunden'!$C:$C,A5)) | AA5: =IF(A5="","",X5+Y5+Z5+SUMIFS('14_Eingangsrechnungen'!$F:$F,'14_Eingangsrechnungen'!$C:$C,A5,'14_Eingangsrechnungen'!$E:$E,"Gerät")+SUMIFS('14_Eingangsrechnungen'!$F:$F,'14_Eingangsrechnungen'!$C:$C,A5,'14_Eingangsrechnungen'!$E:$E,"Dienstleistung")) | AB5: =IF(A5="","",W5-AA5) | AC5: =IF(OR(A5="",W5=0),"",AB5/W5) | AD5: =IF(OR(A5="",V5=0),"",W5/V5) | AE5: =IF(A5="","",MAX(0,V5-W5)) | AF5: =IF(A5="","",SUMIFS('13_Ausgangsrechnungen'!$R:$R,'13_Ausgangsrechnungen'!$C:$C,A5))
A6: P-2026-003 | B6: Sanierung Rathaus | C6: K-1002 | D6: Sanierung | E6: VOB/B | F6: in Bau | G6: 46069 | H6: 46374 | J6: 1100000 | K6: 210000 | L6: 320000 | M6: 245000 | N6: 42000 | O6: 68000 | P6: 0.05 | Q6: MA-07 | R6: MA-04 | S6: Freising | T6: Denkmalschutz, Nachträge wahrscheinlich | U6: =IF(A6="","",SUMIFS('07_Nachtraege'!$E:$E,'07_Nachtraege'!$B:$B,A6,'07_Nachtraege'!$F:$F,"beauftragt")) | V6: =IF(A6="","",J6+U6) | W6: =IF(A6="","",SUMIFS('13_Ausgangsrechnungen'!$G:$G,'13_Ausgangsrechnungen'!$C:$C,A6)) | X6: =IF(A6="","",SUMIFS('11_Material'!$L:$L,'11_Material'!$C:$C,A6)) | Y6: =IF(A6="","",SUMIFS('14_Eingangsrechnungen'!$F:$F,'14_Eingangsrechnungen'!$C:$C,A6,'14_Eingangsrechnungen'!$E:$E,"Nachunternehmer")) | Z6: =IF(A6="","",SUMIFS('10_Stunden'!$K:$K,'10_Stunden'!$C:$C,A6)) | AA6: =IF(A6="","",X6+Y6+Z6+SUMIFS('14_Eingangsrechnungen'!$F:$F,'14_Eingangsrechnungen'!$C:$C,A6,'14_Eingangsrechnungen'!$E:$E,"Gerät")+SUMIFS('14_Eingangsrechnungen'!$F:$F,'14_Eingangsrechnungen'!$C:$C,A6,'14_Eingangsrechnungen'!$E:$E,"Dienstleistung")) | AB6: =IF(A6="","",W6-AA6) | AC6: =IF(OR(A6="",W6=0),"",AB6/W6) | AD6: =IF(OR(A6="",V6=0),"",W6/V6) | AE6: =IF(A6="","",MAX(0,V6-W6)) | AF6: =IF(A6="","",SUMIFS('13_Ausgangsrechnungen'!$R:$R,'13_Ausgangsrechnungen'!$C:$C,A6))
A7: P-2026-004 | B7: Gewerbehalle Nord | C7: K-1004 | D7: Industrie | E7: BGB | F7: in Bau | G7: 46118 | H7: 46444 | J7: 3200000 | K7: 980000 | L7: 540000 | M7: 610000 | N7: 145000 | O7: 190000 | P7: 0.05 | Q7: MA-07 | R7: MA-03 | S7: Dachau | T7: Stahlhalle 4.200 m² + Büro | U7: =IF(A7="","",SUMIFS('07_Nachtraege'!$E:$E,'07_Nachtraege'!$B:$B,A7,'07_Nachtraege'!$F:$F,"beauftragt")) | V7: =IF(A7="","",J7+U7) | W7: =IF(A7="","",SUMIFS('13_Ausgangsrechnungen'!$G:$G,'13_Ausgangsrechnungen'!$C:$C,A7)) | X7: =IF(A7="","",SUMIFS('11_Material'!$L:$L,'11_Material'!$C:$C,A7)) | Y7: =IF(A7="","",SUMIFS('14_Eingangsrechnungen'!$F:$F,'14_Eingangsrechnungen'!$C:$C,A7,'14_Eingangsrechnungen'!$E:$E,"Nachunternehmer")) | Z7: =IF(A7="","",SUMIFS('10_Stunden'!$K:$K,'10_Stunden'!$C:$C,A7)) | AA7: =IF(A7="","",X7+Y7+Z7+SUMIFS('14_Eingangsrechnungen'!$F:$F,'14_Eingangsrechnungen'!$C:$C,A7,'14_Eingangsrechnungen'!$E:$E,"Gerät")+SUMIFS('14_Eingangsrechnungen'!$F:$F,'14_Eingangsrechnungen'!$C:$C,A7,'14_Eingangsrechnungen'!$E:$E,"Dienstleistung")) | AB7: =IF(A7="","",W7-AA7) | AC7: =IF(OR(A7="",W7=0),"",AB7/W7) | AD7: =IF(OR(A7="",V7=0),"",W7/V7) | AE7: =IF(A7="","",MAX(0,V7-W7)) | AF7: =IF(A7="","",SUMIFS('13_Ausgangsrechnungen'!$R:$R,'13_Ausgangsrechnungen'!$C:$C,A7))
A8: P-2026-005 | B8: EFH Familie Huber | C8: K-1005 | D8: Wohnungsbau | E8: BGB | F8: abgeschlossen | G8: 45908 | H8: 46142 | I8: 46134 | J8: 420000 | K8: 145000 | L8: 38000 | M8: 98000 | N8: 18000 | O8: 24000 | P8: 0.05 | Q8: MA-07 | R8: MA-04 | S8: Erding | T8: Schlussrechnung gestellt | U8: =IF(A8="","",SUMIFS('07_Nachtraege'!$E:$E,'07_Nachtraege'!$B:$B,A8,'07_Nachtraege'!$F:$F,"beauftragt")) | V8: =IF(A8="","",J8+U8) | W8: =IF(A8="","",SUMIFS('13_Ausgangsrechnungen'!$G:$G,'13_Ausgangsrechnungen'!$C:$C,A8)) | X8: =IF(A8="","",SUMIFS('11_Material'!$L:$L,'11_Material'!$C:$C,A8)) | Y8: =IF(A8="","",SUMIFS('14_Eingangsrechnungen'!$F:$F,'14_Eingangsrechnungen'!$C:$C,A8,'14_Eingangsrechnungen'!$E:$E,"Nachunternehmer")) | Z8: =IF(A8="","",SUMIFS('10_Stunden'!$K:$K,'10_Stunden'!$C:$C,A8)) | AA8: =IF(A8="","",X8+Y8+Z8+SUMIFS('14_Eingangsrechnungen'!$F:$F,'14_Eingangsrechnungen'!$C:$C,A8,'14_Eingangsrechnungen'!$E:$E,"Gerät")+SUMIFS('14_Eingangsrechnungen'!$F:$F,'14_Eingangsrechnungen'!$C:$C,A8,'14_Eingangsrechnungen'!$E:$E,"Dienstleistung")) | AB8: =IF(A8="","",W8-AA8) | AC8: =IF(OR(A8="",W8=0),"",AB8/W8) | AD8: =IF(OR(A8="",V8=0),"",W8/V8) | AE8: =IF(A8="","",MAX(0,V8-W8)) | AF8: =IF(A8="","",SUMIFS('13_Ausgangsrechnungen'!$R:$R,'13_Ausgangsrechnungen'!$C:$C,A8))
A9: P-2026-006 | B9: Straßenbau B13 Abschnitt | C9: K-1006 | D9: Tiefbau | E9: VOB/B | F9: geplant | G9: 46266 | H9: 46568 | J9: 1800000 | K9: 620000 | L9: 210000 | M9: 430000 | N9: 165000 | O9: 98000 | P9: 0.05 | Q9: MA-07 | R9: MA-06 | S9: Freising Land | T9: Zuschlag 12.08.2026, Baubeginn Sept. | U9: =IF(A9="","",SUMIFS('07_Nachtraege'!$E:$E,'07_Nachtraege'!$B:$B,A9,'07_Nachtraege'!$F:$F,"beauftragt")) | V9: =IF(A9="","",J9+U9) | W9: =IF(A9="","",SUMIFS('13_Ausgangsrechnungen'!$G:$G,'13_Ausgangsrechnungen'!$C:$C,A9)) | X9: =IF(A9="","",SUMIFS('11_Material'!$L:$L,'11_Material'!$C:$C,A9)) | Y9: =IF(A9="","",SUMIFS('14_Eingangsrechnungen'!$F:$F,'14_Eingangsrechnungen'!$C:$C,A9,'14_Eingangsrechnungen'!$E:$E,"Nachunternehmer")) | Z9: =IF(A9="","",SUMIFS('10_Stunden'!$K:$K,'10_Stunden'!$C:$C,A9)) | AA9: =IF(A9="","",X9+Y9+Z9+SUMIFS('14_Eingangsrechnungen'!$F:$F,'14_Eingangsrechnungen'!$C:$C,A9,'14_Eingangsrechnungen'!$E:$E,"Gerät")+SUMIFS('14_Eingangsrechnungen'!$F:$F,'14_Eingangsrechnungen'!$C:$C,A9,'14_Eingangsrechnungen'!$E:$E,"Dienstleistung")) | AB9: =IF(A9="","",W9-AA9) | AC9: =IF(OR(A9="",W9=0),"",AB9/W9) | AD9: =IF(OR(A9="",V9=0),"",W9/V9) | AE9: =IF(A9="","",MAX(0,V9-W9)) | AF9: =IF(A9="","",SUMIFS('13_Ausgangsrechnungen'!$R:$R,'13_Ausgangsrechnungen'!$C:$C,A9))
U10: =IF(A10="","",SUMIFS('07_Nachtraege'!$E:$E,'07_Nachtraege'!$B:$B,A10,'07_Nachtraege'!$F:$F,"beauftragt")) | V10: =IF(A10="","",J10+U10) | W10: =IF(A10="","",SUMIFS('13_Ausgangsrechnungen'!$G:$G,'13_Ausgangsrechnungen'!$C:$C,A10)) | X10: =IF(A10="","",SUMIFS('11_Material'!$L:$L,'11_Material'!$C:$C,A10)) | Y10: =IF(A10="","",SUMIFS('14_Eingangsrechnungen'!$F:$F,'14_Eingangsrechnungen'!$C:$C,A10,'14_Eingangsrechnungen'!$E:$E,"Nachunternehmer")) | Z10: =IF(A10="","",SUMIFS('10_Stunden'!$K:$K,'10_Stunden'!$C:$C,A10)) | AA10: =IF(A10="","",X10+Y10+Z10+SUMIFS('14_Eingangsrechnungen'!$F:$F,'14_Eingangsrechnungen'!$C:$C,A10,'14_Eingangsrechnungen'!$E:$E,"Gerät")+SUMIFS('14_Eingangsrechnungen'!$F:$F,'14_Eingangsrechnungen'!$C:$C,A10,'14_Eingangsrechnungen'!$E:$E,"Dienstleistung")) | AB10: =IF(A10="","",W10-AA10) | AC10: =IF(OR(A10="",W10=0),"",AB10/W10) | AD10: =IF(OR(A10="",V10=0),"",W10/V10) | AE10: =IF(A10="","",MAX(0,V10-W10)) | AF10: =IF(A10="","",SUMIFS('13_Ausgangsrechnungen'!$R:$R,'13_Ausgangsrechnungen'!$C:$C,A10))
U11: =IF(A11="","",SUMIFS('07_Nachtraege'!$E:$E,'07_Nachtraege'!$B:$B,A11,'07_Nachtraege'!$F:$F,"beauftragt")) | V11: =IF(A11="","",J11+U11) | W11: =IF(A11="","",SUMIFS('13_Ausgangsrechnungen'!$G:$G,'13_Ausgangsrechnungen'!$C:$C,A11)) | X11: =IF(A11="","",SUMIFS('11_Material'!$L:$L,'11_Material'!$C:$C,A11)) | Y11: =IF(A11="","",SUMIFS('14_Eingangsrechnungen'!$F:$F,'14_Eingangsrechnungen'!$C:$C,A11,'14_Eingangsrechnungen'!$E:$E,"Nachunternehmer")) | Z11: =IF(A11="","",SUMIFS('10_Stunden'!$K:$K,'10_Stunden'!$C:$C,A11)) | AA11: =IF(A11="","",X11+Y11+Z11+SUMIFS('14_Eingangsrechnungen'!$F:$F,'14_Eingangsrechnungen'!$C:$C,A11,'14_Eingangsrechnungen'!$E:$E,"Gerät")+SUMIFS('14_Eingangsrechnungen'!$F:$F,'14_Eingangsrechnungen'!$C:$C,A11,'14_Eingangsrechnungen'!$E:$E,"Dienstleistung")) | AB11: =IF(A11="","",W11-AA11) | AC11: =IF(OR(A11="",W11=0),"",AB11/W11) | AD11: =IF(OR(A11="",V11=0),"",W11/V11) | AE11: =IF(A11="","",MAX(0,V11-W11)) | AF11: =IF(A11="","",SUMIFS('13_Ausgangsrechnungen'!$R:$R,'13_Ausgangsrechnungen'!$C:$C,A11))
U12: =IF(A12="","",SUMIFS('07_Nachtraege'!$E:$E,'07_Nachtraege'!$B:$B,A12,'07_Nachtraege'!$F:$F,"beauftragt")) | V12: =IF(A12="","",J12+U12) | W12: =IF(A12="","",SUMIFS('13_Ausgangsrechnungen'!$G:$G,'13_Ausgangsrechnungen'!$C:$C,A12)) | X12: =IF(A12="","",SUMIFS('11_Material'!$L:$L,'11_Material'!$C:$C,A12)) | Y12: =IF(A12="","",SUMIFS('14_Eingangsrechnungen'!$F:$F,'14_Eingangsrechnungen'!$C:$C,A12,'14_Eingangsrechnungen'!$E:$E,"Nachunternehmer")) | Z12: =IF(A12="","",SUMIFS('10_Stunden'!$K:$K,'10_Stunden'!$C:$C,A12)) | AA12: =IF(A12="","",X12+Y12+Z12+SUMIFS('14_Eingangsrechnungen'!$F:$F,'14_Eingangsrechnungen'!$C:$C,A12,'14_Eingangsrechnungen'!$E:$E,"Gerät")+SUMIFS('14_Eingangsrechnungen'!$F:$F,'14_Eingangsrechnungen'!$C:$C,A12,'14_Eingangsrechnungen'!$E:$E,"Dienstleistung")) | AB12: =IF(A12="","",W12-AA12) | AC12: =IF(OR(A12="",W12=0),"",AB12/W12) | AD12: =IF(OR(A12="",V12=0),"",W12/V12) | AE12: =IF(A12="","",MAX(0,V12-W12)) | AF12: =IF(A12="","",SUMIFS('13_Ausgangsrechnungen'!$R:$R,'13_Ausgangsrechnungen'!$C:$C,A12))
U13: =IF(A13="","",SUMIFS('07_Nachtraege'!$E:$E,'07_Nachtraege'!$B:$B,A13,'07_Nachtraege'!$F:$F,"beauftragt")) | V13: =IF(A13="","",J13+U13) | W13: =IF(A13="","",SUMIFS('13_Ausgangsrechnungen'!$G:$G,'13_Ausgangsrechnungen'!$C:$C,A13)) | X13: =IF(A13="","",SUMIFS('11_Material'!$L:$L,'11_Material'!$C:$C,A13)) | Y13: =IF(A13="","",SUMIFS('14_Eingangsrechnungen'!$F:$F,'14_Eingangsrechnungen'!$C:$C,A13,'14_Eingangsrechnungen'!$E:$E,"Nachunternehmer")) | Z13: =IF(A13="","",SUMIFS('10_Stunden'!$K:$K,'10_Stunden'!$C:$C,A13)) | AA13: =IF(A13="","",X13+Y13+Z13+SUMIFS('14_Eingangsrechnungen'!$F:$F,'14_Eingangsrechnungen'!$C:$C,A13,'14_Eingangsrechnungen'!$E:$E,"Gerät")+SUMIFS('14_Eingangsrechnungen'!$F:$F,'14_Eingangsrechnungen'!$C:$C,A13,'14_Eingangsrechnungen'!$E:$E,"Dienstleistung")) | AB13: =IF(A13="","",W13-AA13) | AC13: =IF(OR(A13="",W13=0),"",AB13/W13) | AD13: =IF(OR(A13="",V13=0),"",W13/V13) | AE13: =IF(A13="","",MAX(0,V13-W13)) | AF13: =IF(A13="","",SUMIFS('13_Ausgangsrechnungen'!$R:$R,'13_Ausgangsrechnungen'!$C:$C,A13))
U14: =IF(A14="","",SUMIFS('07_Nachtraege'!$E:$E,'07_Nachtraege'!$B:$B,A14,'07_Nachtraege'!$F:$F,"beauftragt")) | V14: =IF(A14="","",J14+U14) | W14: =IF(A14="","",SUMIFS('13_Ausgangsrechnungen'!$G:$G,'13_Ausgangsrechnungen'!$C:$C,A14)) | X14: =IF(A14="","",SUMIFS('11_Material'!$L:$L,'11_Material'!$C:$C,A14)) | Y14: =IF(A14="","",SUMIFS('14_Eingangsrechnungen'!$F:$F,'14_Eingangsrechnungen'!$C:$C,A14,'14_Eingangsrechnungen'!$E:$E,"Nachunternehmer")) | Z14: =IF(A14="","",SUMIFS('10_Stunden'!$K:$K,'10_Stunden'!$C:$C,A14)) | AA14: =IF(A14="","",X14+Y14+Z14+SUMIFS('14_Eingangsrechnungen'!$F:$F,'14_Eingangsrechnungen'!$C:$C,A14,'14_Eingangsrechnungen'!$E:$E,"Gerät")+SUMIFS('14_Eingangsrechnungen'!$F:$F,'14_Eingangsrechnungen'!$C:$C,A14,'14_Eingangsrechnungen'!$E:$E,"Dienstleistung")) | AB14: =IF(A14="","",W14-AA14) | AC14: =IF(OR(A14="",W14=0),"",AB14/W14) | AD14: =IF(OR(A14="",V14=0),"",W14/V14) | AE14: =IF(A14="","",MAX(0,V14-W14)) | AF14: =IF(A14="","",SUMIFS('13_Ausgangsrechnungen'!$R:$R,'13_Ausgangsrechnungen'!$C:$C,A14))
U15: =IF(A15="","",SUMIFS('07_Nachtraege'!$E:$E,'07_Nachtraege'!$B:$B,A15,'07_Nachtraege'!$F:$F,"beauftragt")) | V15: =IF(A15="","",J15+U15) | W15: =IF(A15="","",SUMIFS('13_Ausgangsrechnungen'!$G:$G,'13_Ausgangsrechnungen'!$C:$C,A15)) | X15: =IF(A15="","",SUMIFS('11_Material'!$L:$L,'11_Material'!$C:$C,A15)) | Y15: =IF(A15="","",SUMIFS('14_Eingangsrechnungen'!$F:$F,'14_Eingangsrechnungen'!$C:$C,A15,'14_Eingangsrechnungen'!$E:$E,"Nachunternehmer")) | Z15: =IF(A15="","",SUMIFS('10_Stunden'!$K:$K,'10_Stunden'!$C:$C,A15)) | AA15: =IF(A15="","",X15+Y15+Z15+SUMIFS('14_Eingangsrechnungen'!$F:$F,'14_Eingangsrechnungen'!$C:$C,A15,'14_Eingangsrechnungen'!$E:$E,"Gerät")+SUMIFS('14_Eingangsrechnungen'!$F:$F,'14_Eingangsrechnungen'!$C:$C,A15,'14_Eingangsrechnungen'!$E:$E,"Dienstleistung")) | AB15: =IF(A15="","",W15-AA15) | AC15: =IF(OR(A15="",W15=0),"",AB15/W15) | AD15: =IF(OR(A15="",V15=0),"",W15/V15) | AE15: =IF(A15="","",MAX(0,V15-W15)) | AF15: =IF(A15="","",SUMIFS('13_Ausgangsrechnungen'!$R:$R,'13_Ausgangsrechnungen'!$C:$C,A15))
U16: =IF(A16="","",SUMIFS('07_Nachtraege'!$E:$E,'07_Nachtraege'!$B:$B,A16,'07_Nachtraege'!$F:$F,"beauftragt")) | V16: =IF(A16="","",J16+U16) | W16: =IF(A16="","",SUMIFS('13_Ausgangsrechnungen'!$G:$G,'13_Ausgangsrechnungen'!$C:$C,A16)) | X16: =IF(A16="","",SUMIFS('11_Material'!$L:$L,'11_Material'!$C:$C,A16)) | Y16: =IF(A16="","",SUMIFS('14_Eingangsrechnungen'!$F:$F,'14_Eingangsrechnungen'!$C:$C,A16,'14_Eingangsrechnungen'!$E:$E,"Nachunternehmer")) | Z16: =IF(A16="","",SUMIFS('10_Stunden'!$K:$K,'10_Stunden'!$C:$C,A16)) | AA16: =IF(A16="","",X16+Y16+Z16+SUMIFS('14_Eingangsrechnungen'!$F:$F,'14_Eingangsrechnungen'!$C:$C,A16,'14_Eingangsrechnungen'!$E:$E,"Gerät")+SUMIFS('14_Eingangsrechnungen'!$F:$F,'14_Eingangsrechnungen'!$C:$C,A16,'14_Eingangsrechnungen'!$E:$E,"Dienstleistung")) | AB16: =IF(A16="","",W16-AA16) | AC16: =IF(OR(A16="",W16=0),"",AB16/W16) | AD16: =IF(OR(A16="",V16=0),"",W16/V16) | AE16: =IF(A16="","",MAX(0,V16-W16)) | AF16: =IF(A16="","",SUMIFS('13_Ausgangsrechnungen'!$R:$R,'13_Ausgangsrechnungen'!$C:$C,A16))
U17: =IF(A17="","",SUMIFS('07_Nachtraege'!$E:$E,'07_Nachtraege'!$B:$B,A17,'07_Nachtraege'!$F:$F,"beauftragt")) | V17: =IF(A17="","",J17+U17) | W17: =IF(A17="","",SUMIFS('13_Ausgangsrechnungen'!$G:$G,'13_Ausgangsrechnungen'!$C:$C,A17)) | X17: =IF(A17="","",SUMIFS('11_Material'!$L:$L,'11_Material'!$C:$C,A17)) | Y17: =IF(A17="","",SUMIFS('14_Eingangsrechnungen'!$F:$F,'14_Eingangsrechnungen'!$C:$C,A17,'14_Eingangsrechnungen'!$E:$E,"Nachunternehmer")) | Z17: =IF(A17="","",SUMIFS('10_Stunden'!$K:$K,'10_Stunden'!$C:$C,A17)) | AA17: =IF(A17="","",X17+Y17+Z17+SUMIFS('14_Eingangsrechnungen'!$F:$F,'14_Eingangsrechnungen'!$C:$C,A17,'14_Eingangsrechnungen'!$E:$E,"Gerät")+SUMIFS('14_Eingangsrechnungen'!$F:$F,'14_Eingangsrechnungen'!$C:$C,A17,'14_Eingangsrechnungen'!$E:$E,"Dienstleistung")) | AB17: =IF(A17="","",W17-AA17) | AC17: =IF(OR(A17="",W17=0),"",AB17/W17) | AD17: =IF(OR(A17="",V17=0),"",W17/V17) | AE17: =IF(A17="","",MAX(0,V17-W17)) | AF17: =IF(A17="","",SUMIFS('13_Ausgangsrechnungen'!$R:$R,'13_Ausgangsrechnungen'!$C:$C,A17))
U18: =IF(A18="","",SUMIFS('07_Nachtraege'!$E:$E,'07_Nachtraege'!$B:$B,A18,'07_Nachtraege'!$F:$F,"beauftragt")) | V18: =IF(A18="","",J18+U18) | W18: =IF(A18="","",SUMIFS('13_Ausgangsrechnungen'!$G:$G,'13_Ausgangsrechnungen'!$C:$C,A18)) | X18: =IF(A18="","",SUMIFS('11_Material'!$L:$L,'11_Material'!$C:$C,A18)) | Y18: =IF(A18="","",SUMIFS('14_Eingangsrechnungen'!$F:$F,'14_Eingangsrechnungen'!$C:$C,A18,'14_Eingangsrechnungen'!$E:$E,"Nachunternehmer")) | Z18: =IF(A18="","",SUMIFS('10_Stunden'!$K:$K,'10_Stunden'!$C:$C,A18)) | AA18: =IF(A18="","",X18+Y18+Z18+SUMIFS('14_Eingangsrechnungen'!$F:$F,'14_Eingangsrechnungen'!$C:$C,A18,'14_Eingangsrechnungen'!$E:$E,"Gerät")+SUMIFS('14_Eingangsrechnungen'!$F:$F,'14_Eingangsrechnungen'!$C:$C,A18,'14_Eingangsrechnungen'!$E:$E,"Dienstleistung")) | AB18: =IF(A18="","",W18-AA18) | AC18: =IF(OR(A18="",W18=0),"",AB18/W18) | AD18: =IF(OR(A18="",V18=0),"",W18/V18) | AE18: =IF(A18="","",MAX(0,V18-W18)) | AF18: =IF(A18="","",SUMIFS('13_Ausgangsrechnungen'!$R:$R,'13_Ausgangsrechnungen'!$C:$C,A18))
U19: =IF(A19="","",SUMIFS('07_Nachtraege'!$E:$E,'07_Nachtraege'!$B:$B,A19,'07_Nachtraege'!$F:$F,"beauftragt")) | V19: =IF(A19="","",J19+U19) | W19: =IF(A19="","",SUMIFS('13_Ausgangsrechnungen'!$G:$G,'13_Ausgangsrechnungen'!$C:$C,A19)) | X19: =IF(A19="","",SUMIFS('11_Material'!$L:$L,'11_Material'!$C:$C,A19)) | Y19: =IF(A19="","",SUMIFS('14_Eingangsrechnungen'!$F:$F,'14_Eingangsrechnungen'!$C:$C,A19,'14_Eingangsrechnungen'!$E:$E,"Nachunternehmer")) | Z19: =IF(A19="","",SUMIFS('10_Stunden'!$K:$K,'10_Stunden'!$C:$C,A19)) | AA19: =IF(A19="","",X19+Y19+Z19+SUMIFS('14_Eingangsrechnungen'!$F:$F,'14_Eingangsrechnungen'!$C:$C,A19,'14_Eingangsrechnungen'!$E:$E,"Gerät")+SUMIFS('14_Eingangsrechnungen'!$F:$F,'14_Eingangsrechnungen'!$C:$C,A19,'14_Eingangsrechnungen'!$E:$E,"Dienstleistung")) | AB19: =IF(A19="","",W19-AA19) | AC19: =IF(OR(A19="",W19=0),"",AB19/W19) | AD19: =IF(OR(A19="",V19=0),"",W19/V19) | AE19: =IF(A19="","",MAX(0,V19-W19)) | AF19: =IF(A19="","",SUMIFS('13_Ausgangsrechnungen'!$R:$R,'13_Ausgangsrechnungen'!$C:$C,A19))
U20: =IF(A20="","",SUMIFS('07_Nachtraege'!$E:$E,'07_Nachtraege'!$B:$B,A20,'07_Nachtraege'!$F:$F,"beauftragt")) | V20: =IF(A20="","",J20+U20) | W20: =IF(A20="","",SUMIFS('13_Ausgangsrechnungen'!$G:$G,'13_Ausgangsrechnungen'!$C:$C,A20)) | X20: =IF(A20="","",SUMIFS('11_Material'!$L:$L,'11_Material'!$C:$C,A20)) | Y20: =IF(A20="","",SUMIFS('14_Eingangsrechnungen'!$F:$F,'14_Eingangsrechnungen'!$C:$C,A20,'14_Eingangsrechnungen'!$E:$E,"Nachunternehmer")) | Z20: =IF(A20="","",SUMIFS('10_Stunden'!$K:$K,'10_Stunden'!$C:$C,A20)) | AA20: =IF(A20="","",X20+Y20+Z20+SUMIFS('14_Eingangsrechnungen'!$F:$F,'14_Eingangsrechnungen'!$C:$C,A20,'14_Eingangsrechnungen'!$E:$E,"Gerät")+SUMIFS('14_Eingangsrechnungen'!$F:$F,'14_Eingangsrechnungen'!$C:$C,A20,'14_Eingangsrechnungen'!$E:$E,"Dienstleistung")) | AB20: =IF(A20="","",W20-AA20) | AC20: =IF(OR(A20="",W20=0),"",AB20/W20) | AD20: =IF(OR(A20="",V20=0),"",W20/V20) | AE20: =IF(A20="","",MAX(0,V20-W20)) | AF20: =IF(A20="","",SUMIFS('13_Ausgangsrechnungen'!$R:$R,'13_Ausgangsrechnungen'!$C:$C,A20))
U21: =IF(A21="","",SUMIFS('07_Nachtraege'!$E:$E,'07_Nachtraege'!$B:$B,A21,'07_Nachtraege'!$F:$F,"beauftragt")) | V21: =IF(A21="","",J21+U21) | W21: =IF(A21="","",SUMIFS('13_Ausgangsrechnungen'!$G:$G,'13_Ausgangsrechnungen'!$C:$C,A21)) | X21: =IF(A21="","",SUMIFS('11_Material'!$L:$L,'11_Material'!$C:$C,A21)) | Y21: =IF(A21="","",SUMIFS('14_Eingangsrechnungen'!$F:$F,'14_Eingangsrechnungen'!$C:$C,A21,'14_Eingangsrechnungen'!$E:$E,"Nachunternehmer")) | Z21: =IF(A21="","",SUMIFS('10_Stunden'!$K:$K,'10_Stunden'!$C:$C,A21)) | AA21: =IF(A21="","",X21+Y21+Z21+SUMIFS('14_Eingangsrechnungen'!$F:$F,'14_Eingangsrechnungen'!$C:$C,A21,'14_Eingangsrechnungen'!$E:$E,"Gerät")+SUMIFS('14_Eingangsrechnungen'!$F:$F,'14_Eingangsrechnungen'!$C:$C,A21,'14_Eingangsrechnungen'!$E:$E,"Dienstleistung")) | AB21: =IF(A21="","",W21-AA21) | AC21: =IF(OR(A21="",W21=0),"",AB21/W21) | AD21: =IF(OR(A21="",V21=0),"",W21/V21) | AE21: =IF(A21="","",MAX(0,V21-W21)) | AF21: =IF(A21="","",SUMIFS('13_Ausgangsrechnungen'!$R:$R,'13_Ausgangsrechnungen'!$C:$C,A21))
... U400: =IF(A400="","",SUMIFS('07_Nachtraege'!$E:$E,'07_Nachtraege'!$B:$B,A400,'07_Nachtraege'!$F:$F,"beauftragt")) | V400: =IF(A400="","",J400+U400) | W400: =IF(A400="","",SUMIFS('13_Ausgangsrechnungen'!$G:$G,'13_Ausgangsrechnungen'!$C:$C,A400)) | X400: =IF(A400="","",SUMIFS('11_Material'!$L:$L,'11_Material'!$C:$C,A400)) | Y400: =IF(A400="","",SUMIFS('14_Eingangsrechnungen'!$F:$F,'14_Eingangsrechnungen'!$C:$C,A400,'14_Eingangsrechnungen'!$E:$E,"Nachunternehmer")) | Z400: =IF(A400="","",SUMIFS('10_Stunden'!$K:$K,'10_Stunden'!$C:$C,A400)) | AA400: =IF(A400="","",X400+Y400+Z400+SUMIFS('14_Eingangsrechnungen'!$F:$F,'14_Eingangsrechnungen'!$C:$C,A400,'14_Eingangsrechnungen'!$E:$E,"Gerät")+SUMIFS('14_Eingangsrechnungen'!$F:$F,'14_Eingangsrechnungen'!$C:$C,A400,'14_Eingangsrechnungen'!$E:$E,"Dienstleistung")) | AB400: =IF(A400="","",W400-AA400) | AC400: =IF(OR(A400="",W400=0),"",AB400/W400) | AD400: =IF(OR(A400="",V400=0),"",W400/V400) | AE400: =IF(A400="","",MAX(0,V400-W400)) | AF400: =IF(A400="","",SUMIFS('13_Ausgangsrechnungen'!$R:$R,'13_Ausgangsrechnungen'!$C:$C,A400))

Sheet 23_SollIst
A1: Projekt-Soll-Ist
A2: Eine Zeile je Projekt — Werte kommen aus dem Projektstamm, Nachträgen und Ist-Kosten
A3: Projekt | B3: Name | C3: Auftrag aktuell | D3: Ist Leistung | E3: Budget Kosten | F3: Ist Kosten | G3: Δ Kosten | H3: DB Soll | I3: DB Ist | J3: Marge Ist | K3: Fertigstellung | L3: Restleistung | M3: OP Debitor | N3: Ampel
A4: =IF('05_Projekte'!A4="","",'05_Projekte'!A4) | B4: =IF(A4="","",'05_Projekte'!B4) | C4: =IF(A4="","",'05_Projekte'!V4) | D4: =IF(A4="","",'05_Projekte'!W4) | E4: =IF(A4="","",'05_Projekte'!K4+'05_Projekte'!L4+'05_Projekte'!M4+'05_Projekte'!N4+'05_Projekte'!O4) | F4: =IF(A4="","",'05_Projekte'!AA4) | G4: =IF(A4="","",F4-E4) | H4: =IF(A4="","",C4-E4) | I4: =IF(A4="","",'05_Projekte'!AB4) | J4: =IF(A4="","",'05_Projekte'!AD4) | K4: =IF(A4="","",'05_Projekte'!AE4) | L4: =IF(A4="","",'05_Projekte'!AF4) | M4: =IF(A4="","",'05_Projekte'!AG4) | N4: =IF(A4="","",IF(OR(J4<0.08,G4>0,M4>50000),"PRÜFEN","OK"))
A5: =IF('05_Projekte'!A5="","",'05_Projekte'!A5) | B5: =IF(A5="","",'05_Projekte'!B5) | C5: =IF(A5="","",'05_Projekte'!V5) | D5: =IF(A5="","",'05_Projekte'!W5) | E5: =IF(A5="","",'05_Projekte'!K5+'05_Projekte'!L5+'05_Projekte'!M5+'05_Projekte'!N5+'05_Projekte'!O5) | F5: =IF(A5="","",'05_Projekte'!AA5) | G5: =IF(A5="","",F5-E5) | H5: =IF(A5="","",C5-E5) | I5: =IF(A5="","",'05_Projekte'!AB5) | J5: =IF(A5="","",'05_Projekte'!AD5) | K5: =IF(A5="","",'05_Projekte'!AE5) | L5: =IF(A5="","",'05_Projekte'!AF5) | M5: =IF(A5="","",'05_Projekte'!AG5) | N5: =IF(A5="","",IF(OR(J5<0.08,G5>0,M5>50000),"PRÜFEN","OK"))
A6: =IF('05_Projekte'!A6="","",'05_Projekte'!A6) | B6: =IF(A6="","",'05_Projekte'!B6) | C6: =IF(A6="","",'05_Projekte'!V6) | D6: =IF(A6="","",'05_Projekte'!W6) | E6: =IF(A6="","",'05_Projekte'!K6+'05_Projekte'!L6+'05_Projekte'!M6+'05_Projekte'!N6+'05_Projekte'!O6) | F6: =IF(A6="","",'05_Projekte'!AA6) | G6: =IF(A6="","",F6-E6) | H6: =IF(A6="","",C6-E6) | I6: =IF(A6="","",'05_Projekte'!AB6) | J6: =IF(A6="","",'05_Projekte'!AD6) | K6: =IF(A6="","",'05_Projekte'!AE6) | L6: =IF(A6="","",'05_Projekte'!AF6) | M6: =IF(A6="","",'05_Projekte'!AG6) | N6: =IF(A6="","",IF(OR(J6<0.08,G6>0,M6>50000),"PRÜFEN","OK"))
A7: =IF('05_Projekte'!A7="","",'05_Projekte'!A7) | B7: =IF(A7="","",'05_Projekte'!B7) | C7: =IF(A7="","",'05_Projekte'!V7) | D7: =IF(A7="","",'05_Projekte'!W7) | E7: =IF(A7="","",'05_Projekte'!K7+'05_Projekte'!L7+'05_Projekte'!M7+'05_Projekte'!N7+'05_Projekte'!O7) | F7: =IF(A7="","",'05_Projekte'!AA7) | G7: =IF(A7="","",F7-E7) | H7: =IF(A7="","",C7-E7) | I7: =IF(A7="","",'05_Projekte'!AB7) | J7: =IF(A7="","",'05_Projekte'!AD7) | K7: =IF(A7="","",'05_Projekte'!AE7) | L7: =IF(A7="","",'05_Projekte'!AF7) | M7: =IF(A7="","",'05_Projekte'!AG7) | N7: =IF(A7="","",IF(OR(J7<0.08,G7>0,M7>50000),"PRÜFEN","OK"))
A8: =IF('05_Projekte'!A8="","",'05_Projekte'!A8) | B8: =IF(A8="","",'05_Projekte'!B8) | C8: =IF(A8="","",'05_Projekte'!V8) | D8: =IF(A8="","",'05_Projekte'!W8) | E8: =IF(A8="","",'05_Projekte'!K8+'05_Projekte'!L8+'05_Projekte'!M8+'05_Projekte'!N8+'05_Projekte'!O8) | F8: =IF(A8="","",'05_Projekte'!AA8) | G8: =IF(A8="","",F8-E8) | H8: =IF(A8="","",C8-E8) | I8: =IF(A8="","",'05_Projekte'!AB8) | J8: =IF(A8="","",'05_Projekte'!AD8) | K8: =IF(A8="","",'05_Projekte'!AE8) | L8: =IF(A8="","",'05_Projekte'!AF8) | M8: =IF(A8="","",'05_Projekte'!AG8) | N8: =IF(A8="","",IF(OR(J8<0.08,G8>0,M8>50000),"PRÜFEN","OK"))
A9: =IF('05_Projekte'!A9="","",'05_Projekte'!A9) | B9: =IF(A9="","",'05_Projekte'!B9) | C9: =IF(A9="","",'05_Projekte'!V9) | D9: =IF(A9="","",'05_Projekte'!W9) | E9: =IF(A9="","",'05_Projekte'!K9+'05_Projekte'!L9+'05_Projekte'!M9+'05_Projekte'!N9+'05_Projekte'!O9) | F9: =IF(A9="","",'05_Projekte'!AA9) | G9: =IF(A9="","",F9-E9) | H9: =IF(A9="","",C9-E9) | I9: =IF(A9="","",'05_Projekte'!AB9) | J9: =IF(A9="","",'05_Projekte'!AD9) | K9: =IF(A9="","",'05_Projekte'!AE9) | L9: =IF(A9="","",'05_Projekte'!AF9) | M9: =IF(A9="","",'05_Projekte'!AG9) | N9: =IF(A9="","",IF(OR(J9<0.08,G9>0,M9>50000),"PRÜFEN","OK"))
A10: =IF('05_Projekte'!A10="","",'05_Projekte'!A10) | B10: =IF(A10="","",'05_Projekte'!B10) | C10: =IF(A10="","",'05_Projekte'!V10) | D10: =IF(A10="","",'05_Projekte'!W10) | E10: =IF(A10="","",'05_Projekte'!K10+'05_Projekte'!L10+'05_Projekte'!M10+'05_Projekte'!N10+'05_Projekte'!O10) | F10: =IF(A10="","",'05_Projekte'!AA10) | G10: =IF(A10="","",F10-E10) | H10: =IF(A10="","",C10-E10) | I10: =IF(A10="","",'05_Projekte'!AB10) | J10: =IF(A10="","",'05_Projekte'!AD10) | K10: =IF(A10="","",'05_Projekte'!AE10) | L10: =IF(A10="","",'05_Projekte'!AF10) | M10: =IF(A10="","",'05_Projekte'!AG10) | N10: =IF(A10="","",IF(OR(J10<0.08,G10>0,M10>50000),"PRÜFEN","OK"))
A11: =IF('05_Projekte'!A11="","",'05_Projekte'!A11) | B11: =IF(A11="","",'05_Projekte'!B11) | C11: =IF(A11="","",'05_Projekte'!V11) | D11: =IF(A11="","",'05_Projekte'!W11) | E11: =IF(A11="","",'05_Projekte'!K11+'05_Projekte'!L11+'05_Projekte'!M11+'05_Projekte'!N11+'05_Projekte'!O11) | F11: =IF(A11="","",'05_Projekte'!AA11) | G11: =IF(A11="","",F11-E11) | H11: =IF(A11="","",C11-E11) | I11: =IF(A11="","",'05_Projekte'!AB11) | J11: =IF(A11="","",'05_Projekte'!AD11) | K11: =IF(A11="","",'05_Projekte'!AE11) | L11: =IF(A11="","",'05_Projekte'!AF11) | M11: =IF(A11="","",'05_Projekte'!AG11) | N11: =IF(A11="","",IF(OR(J11<0.08,G11>0,M11>50000),"PRÜFEN","OK"))
A12: =IF('05_Projekte'!A12="","",'05_Projekte'!A12) | B12: =IF(A12="","",'05_Projekte'!B12) | C12: =IF(A12="","",'05_Projekte'!V12) | D12: =IF(A12="","",'05_Projekte'!W12) | E12: =IF(A12="","",'05_Projekte'!K12+'05_Projekte'!L12+'05_Projekte'!M12+'05_Projekte'!N12+'05_Projekte'!O12) | F12: =IF(A12="","",'05_Projekte'!AA12) | G12: =IF(A12="","",F12-E12) | H12: =IF(A12="","",C12-E12) | I12: =IF(A12="","",'05_Projekte'!AB12) | J12: =IF(A12="","",'05_Projekte'!AD12) | K12: =IF(A12="","",'05_Projekte'!AE12) | L12: =IF(A12="","",'05_Projekte'!AF12) | M12: =IF(A12="","",'05_Projekte'!AG12) | N12: =IF(A12="","",IF(OR(J12<0.08,G12>0,M12>50000),"PRÜFEN","OK"))
A13: =IF('05_Projekte'!A13="","",'05_Projekte'!A13) | B13: =IF(A13="","",'05_Projekte'!B13) | C13: =IF(A13="","",'05_Projekte'!V13) | D13: =IF(A13="","",'05_Projekte'!W13) | E13: =IF(A13="","",'05_Projekte'!K13+'05_Projekte'!L13+'05_Projekte'!M13+'05_Projekte'!N13+'05_Projekte'!O13) | F13: =IF(A13="","",'05_Projekte'!AA13) | G13: =IF(A13="","",F13-E13) | H13: =IF(A13="","",C13-E13) | I13: =IF(A13="","",'05_Projekte'!AB13) | J13: =IF(A13="","",'05_Projekte'!AD13) | K13: =IF(A13="","",'05_Projekte'!AE13) | L13: =IF(A13="","",'05_Projekte'!AF13) | M13: =IF(A13="","",'05_Projekte'!AG13) | N13: =IF(A13="","",IF(OR(J13<0.08,G13>0,M13>50000),"PRÜFEN","OK"))
A14: =IF('05_Projekte'!A14="","",'05_Projekte'!A14) | B14: =IF(A14="","",'05_Projekte'!B14) | C14: =IF(A14="","",'05_Projekte'!V14) | D14: =IF(A14="","",'05_Projekte'!W14) | E14: =IF(A14="","",'05_Projekte'!K14+'05_Projekte'!L14+'05_Projekte'!M14+'05_Projekte'!N14+'05_Projekte'!O14) | F14: =IF(A14="","",'05_Projekte'!AA14) | G14: =IF(A14="","",F14-E14) | H14: =IF(A14="","",C14-E14) | I14: =IF(A14="","",'05_Projekte'!AB14) | J14: =IF(A14="","",'05_Projekte'!AD14) | K14: =IF(A14="","",'05_Projekte'!AE14) | L14: =IF(A14="","",'05_Projekte'!AF14) | M14: =IF(A14="","",'05_Projekte'!AG14) | N14: =IF(A14="","",IF(OR(J14<0.08,G14>0,M14>50000),"PRÜFEN","OK"))
A15: =IF('05_Projekte'!A15="","",'05_Projekte'!A15) | B15: =IF(A15="","",'05_Projekte'!B15) | C15: =IF(A15="","",'05_Projekte'!V15) | D15: =IF(A15="","",'05_Projekte'!W15) | E15: =IF(A15="","",'05_Projekte'!K15+'05_Projekte'!L15+'05_Projekte'!M15+'05_Projekte'!N15+'05_Projekte'!O15) | F15: =IF(A15="","",'05_Projekte'!AA15) | G15: =IF(A15="","",F15-E15) | H15: =IF(A15="","",C15-E15) | I15: =IF(A15="","",'05_Projekte'!AB15) | J15: =IF(A15="","",'05_Projekte'!AD15) | K15: =IF(A15="","",'05_Projekte'!AE15) | L15: =IF(A15="","",'05_Projekte'!AF15) | M15: =IF(A15="","",'05_Projekte'!AG15) | N15: =IF(A15="","",IF(OR(J15<0.08,G15>0,M15>50000),"PRÜFEN","OK"))
... A53: =IF('05_Projekte'!A53="","",'05_Projekte'!A53) | B53: =IF(A53="","",'05_Projekte'!B53) | C53: =IF(A53="","",'05_Projekte'!V53) | D53: =IF(A53="","",'05_Projekte'!W53) | E53: =IF(A53="","",'05_Projekte'!K53+'05_Projekte'!L53+'05_Projekte'!M53+'05_Projekte'!N53+'05_Projekte'!O53) | F53: =IF(A53="","",'05_Projekte'!AA53) | G53: =IF(A53="","",F53-E53) | H53: =IF(A53="","",C53-E53) | I53: =IF(A53="","",'05_Projekte'!AB53) | J53: =IF(A53="","",'05_Projekte'!AD53) | K53: =IF(A53="","",'05_Projekte'!AE53) | L53: =IF(A53="","",'05_Projekte'!AF53) | M53: =IF(A53="","",'05_Projekte'!AG53) | N53: =IF(A53="","",IF(OR(J53<0.08,G53>0,M53>50000),"PRÜFEN","OK"))

Sheet 20_Liquiditaet
A1: Liquiditätsplanung 13 Wochen + 12 Monate
A2: Gelbe Zellen = Disposition ( savis, bekannte Zahlungen, Lohnlauf ). Ampel gegen Mindestliquidität aus den Stammdaten.
A4: 13-Wochen-Liquidität (rollierend)
A5: Woche ab | B5: 46301 | C5: 46308 | D5: 46315 | E5: 46322 | F5: 46329 | G5: 46336 | H5: 46343 | I5: 46350 | J5: 46357 | K5: 46364 | L5: 46371 | M5: 46378 | N5: 46385
A6: Einzahlungen Kunden erwartet | B6: 142000 | C6: 185000 | D6: 0 | E6: 420000 | F6: 62000 | G6: 0 | H6: 248000 | I6: 0 | J6: 310000 | K6: 95000 | L6: 0 | M6: 180000 | N6: 220000 | O6: =SUM(B6:N6)
A7: Löhne / Soka / SV | B7: 0 | C7: 0 | D7: 0 | E7: 69110 | F7: 0 | G7: 0 | H7: 0 | I7: 69800 | J7: 0 | K7: 0 | L7: 0 | M7: 70500 | N7: 0 | O7: =SUM(B7:N7)
A8: Nachunternehmer / Kreditoren | B8: 23000 | C8: 18000 | D8: 45000 | E8: 28600 | F8: 15800 | G8: 12000 | H8: 34000 | I8: 22000 | J8: 41000 | K8: 19000 | L8: 15000 | M8: 28000 | N8: 21000 | O8: =SUM(B8:N8)
A9: Material / Baustoffe | B9: 14500 | C9: 26400 | D9: 8000 | E9: 6200 | F9: 18000 | G9: 22000 | H9: 31000 | I9: 16000 | J9: 27000 | K9: 14000 | L9: 9000 | M9: 24000 | N9: 17000 | O9: =SUM(B9:N9)
A10: Steuer / USt | B10: 0 | C10: 18640 | D10: 0 | E10: 0 | F10: 0 | G10: 21400 | H10: 0 | I10: 0 | J10: 0 | K10: 19800 | L10: 0 | M10: 0 | N10: 24000 | O10: =SUM(B10:N10)
A11: Miete, Leasing, Sonstiges | B11: 8200 | C11: 4500 | D11: 6200 | E11: 4800 | F11: 5100 | G11: 4300 | H11: 8900 | I11: 4700 | J11: 5200 | K11: 6100 | L11: 4400 | M11: 7800 | N11: 5000 | O11: =SUM(B11:N11)
A13: Anfangsbestand | B13: =AnfangsBank+'19_Cashflow'!I18 | C13: =B14 | D13: =C14 | E13: =D14 | F13: =E14 | G13: =F14 | H13: =G14 | I13: =H14 | J13: =I14 | ... N13: =M14
A14: Endbestand | B14: =B13+B6-B7-B8-B9-B10-B11 | C14: =C13+C6-C7-C8-C9-C10-C11 | D14: =D13+D6-D7-D8-D9-D10-D11 | E14: =E13+E6-E7-E8-E9-E10-E11 | F14: =F13+F6-F7-F8-F9-F10-F11 | G14: =G13+G6-G7-G8-G9-G10-G11 | H14: =H13+H6-H7-H8-H9-H10-H11 | I14: =I13+I6-I7-I8-I9-I10-I11 | ... N14: =N13+N6-N7-N8-N9-N10-N11
A15: vs. Mindestliquidität | B15: =B14-MindestLiq | C15: =C14-MindestLiq | D15: =D14-MindestLiq | E15: =E14-MindestLiq | F15: =F14-MindestLiq | G15: =G14-MindestLiq | H15: =H14-MindestLiq | I15: =I14-MindestLiq | ... N15: =N14-MindestLiq
A16: Status | B16: =IF(B14<MindestLiq,"ENGPASS",IF(B14<MindestLiq*1.25,"ENG","OK")) | C16: =IF(C14<MindestLiq,"ENGPASS",IF(C14<MindestLiq*1.25,"ENG","OK")) | D16: =IF(D14<MindestLiq,"ENGPASS",IF(D14<MindestLiq*1.25,"ENG","OK")) | E16: =IF(E14<MindestLiq,"ENGPASS",IF(E14<MindestLiq*1.25,"ENG","OK")) | F16: =IF(F14<MindestLiq,"ENGPASS",IF(F14<MindestLiq*1.25,"ENG","OK")) | G16: =IF(G14<MindestLiq,"ENGPASS",IF(G14<MindestLiq*1.25,"ENG","OK")) | H16: =IF(H14<MindestLiq,"ENGPASS",IF(H14<MindestLiq*1.25,"ENG","OK")) | I16: =IF(I14<MindestLiq,"ENGPASS",IF(I14<MindestLiq*1.25,"ENG","OK")) | ... N16: =IF(N14<MindestLiq,"ENGPASS",IF(N14<MindestLiq*1.25,"ENG","OK"))
A18: 12-Monats-Liquidität
A19: Monat | B19: Jan | C19: Feb | D19: Mrz | E19: Apr | F19: Mai | G19: Jun | H19: Jul | I19: Aug | J19: Sep | K19: Okt | L19: Nov | M19: Dez
A20: Einzahlungen (Forecast brutto ca.) | B20: ='21_Forecast'!B20*1.19 | C20: ='21_Forecast'!C20*1.19 | D20: ='21_Forecast'!D20*1.19 | E20: ='21_Forecast'!E20*1.19 | F20: ='21_Forecast'!F20*1.19 | G20: ='21_Forecast'!G20*1.19 | H20: ='21_Forecast'!H20*1.19 | I20: ='21_Forecast'!I20*1.19 | ... M20: ='21_Forecast'!M20*1.19
A21: Auszahlungen gesamt | B21: ='21_Forecast'!B21+'21_Forecast'!B22+'21_Forecast'!B23+'21_Forecast'!B24+'21_Forecast'!B25 | C21: ='21_Forecast'!C21+'21_Forecast'!C22+'21_Forecast'!C23+'21_Forecast'!C24+'21_Forecast'!C25 | D21: ='21_Forecast'!D21+'21_Forecast'!D22+'21_Forecast'!D23+'21_Forecast'!D24+'21_Forecast'!D25 | E21: ='21_Forecast'!E21+'21_Forecast'!E22+'21_Forecast'!E23+'21_Forecast'!E24+'21_Forecast'!E25 | F21: ='21_Forecast'!F21+'21_Forecast'!F22+'21_Forecast'!F23+'21_Forecast'!F24+'21_Forecast'!F25 | G21: ='21_Forecast'!G21+'21_Forecast'!G22+'21_Forecast'!G23+'21_Forecast'!G24+'21_Forecast'!G25 | H21: ='21_Forecast'!H21+'21_Forecast'!H22+'21_Forecast'!H23+'21_Forecast'!H24+'21_Forecast'!H25 | I21: ='21_Forecast'!I21+'21_Forecast'!I22+'21_Forecast'!I23+'21_Forecast'!I24+'21_Forecast'!I25 | ... M21: ='21_Forecast'!M21+'21_Forecast'!M22+'21_Forecast'!M23+'21_Forecast'!M24+'21_Forecast'!M25
A22: Saldo Monat | B22: =B20-B21 | C22: =C20-C21 | D22: =D20-D21 | E22: =E20-E21 | F22: =F20-F21 | G22: =G20-G21 | H22: =H20-H21 | I22: =I20-I21 | ... M22: =M20-M21
A23: Bestand kumuliert | B23: =AnfangsBank+B22 | C23: =B23+C22 | D23: =C23+D22 | E23: =D23+E22 | F23: =E23+F22 | G23: =F23+G22 | H23: =G23+H22 | I23: =H23+I22 | J23: =I23+J22 | ... M23: =L23+M22

Sheet 19_Cashflow
A1: Cashflow-Rechnung
A2: Operativer, investiver und finanzieller Cashflow aus Zahlungen — Monatsscheiben für das Geschäftsjahr
A4: Position | B4: Jan | C4: Feb | D4: Mrz | E4: Apr | F4: Mai | G4: Jun | H4: Jul | I4: Aug | J4: Sep | K4: Okt | L4: Nov | M4: Dez | N4: GJ 2026
A5: Einzahlungen Kunden | B5: =SUMIFS('15_Zahlungen'!$F:$F,'15_Zahlungen'!$C:$C,"Eingang",'15_Zahlungen'!$I:$I,1,'15_Zahlungen'!$J:$J,GJ) | C5: =SUMIFS('15_Zahlungen'!$F:$F,'15_Zahlungen'!$C:$C,"Eingang",'15_Zahlungen'!$I:$I,2,'15_Zahlungen'!$J:$J,GJ) | D5: =SUMIFS('15_Zahlungen'!$F:$F,'15_Zahlungen'!$C:$C,"Eingang",'15_Zahlungen'!$I:$I,3,'15_Zahlungen'!$J:$J,GJ) | E5: =SUMIFS('15_Zahlungen'!$F:$F,'15_Zahlungen'!$C:$C,"Eingang",'15_Zahlungen'!$I:$I,4,'15_Zahlungen'!$J:$J,GJ) | F5: =SUMIFS('15_Zahlungen'!$F:$F,'15_Zahlungen'!$C:$C,"Eingang",'15_Zahlungen'!$I:$I,5,'15_Zahlungen'!$J:$J,GJ) | G5: =SUMIFS('15_Zahlungen'!$F:$F,'15_Zahlungen'!$C:$C,"Eingang",'15_Zahlungen'!$I:$I,6,'15_Zahlungen'!$J:$J,GJ) | H5: =SUMIFS('15_Zahlungen'!$F:$F,'15_Zahlungen'!$C:$C,"Eingang",'15_Zahlungen'!$I:$I,7,'15_Zahlungen'!$J:$J,GJ) | I5: =SUMIFS('15_Zahlungen'!$F:$F,'15_Zahlungen'!$C:$C,"Eingang",'15_Zahlungen'!$I:$I,8,'15_Zahlungen'!$J:$J,GJ) | J5: =SUMIFS('15_Zahlungen'!$F:$F,'15_Zahlungen'!$C:$C,"Eingang",'15_Zahlungen'!$I:$I,9,'15_Zahlungen'!$J:$J,GJ) | K5: =SUMIFS('15_Zahlungen'!$F:$F,'15_Zahlungen'!$C:$C,"Eingang",'15_Zahlungen'!$I:$I,10,'15_Zahlungen'!$J:$J,GJ) | L5: =SUMIFS('15_Zahlungen'!$F:$F,'15_Zahlungen'!$C:$C,"Eingang",'15_Zahlungen'!$I:$I,11,'15_Zahlungen'!$J:$J,GJ) | M5: =SUMIFS('15_Zahlungen'!$F:$F,'15_Zahlungen'!$C:$C,"Eingang",'15_Zahlungen'!$I:$I,12,'15_Zahlungen'!$J:$J,GJ) | N5: =SUM(B5:M5)
A6: sonstige Einzahlungen | B6: =SUMIFS('15_Zahlungen'!$F:$F,'15_Zahlungen'!$C:$C,"Eingang",'15_Zahlungen'!$I:$I,1,'15_Zahlungen'!$J:$J,GJ,'15_Zahlungen'!$D:$D,"") | C6: =SUMIFS('15_Zahlungen'!$F:$F,'15_Zahlungen'!$C:$C,"Eingang",'15_Zahlungen'!$I:$I,2,'15_Zahlungen'!$J:$J,GJ,'15_Zahlungen'!$D:$D,"") | D6: =SUMIFS('15_Zahlungen'!$F:$F,'15_Zahlungen'!$C:$C,"Eingang",'15_Zahlungen'!$I:$I,3,'15_Zahlungen'!$J:$J,GJ,'15_Zahlungen'!$D:$D,"") | E6: =SUMIFS('15_Zahlungen'!$F:$F,'15_Zahlungen'!$C:$C,"Eingang",'15_Zahlungen'!$I:$I,4,'15_Zahlungen'!$J:$J,GJ,'15_Zahlungen'!$D:$D,"") | F6: =SUMIFS('15_Zahlungen'!$F:$F,'15_Zahlungen'!$C:$C,"Eingang",'15_Zahlungen'!$I:$I,5,'15_Zahlungen'!$J:$J,GJ,'15_Zahlungen'!$D:$D,"") | G6: =SUMIFS('15_Zahlungen'!$F:$F,'15_Zahlungen'!$C:$C,"Eingang",'15_Zahlungen'!$I:$I,6,'15_Zahlungen'!$J:$J,GJ,'15_Zahlungen'!$D:$D,"") | H6: =SUMIFS('15_Zahlungen'!$F:$F,'15_Zahlungen'!$C:$C,"Eingang",'15_Zahlungen'!$I:$I,7,'15_Zahlungen'!$J:$J,GJ,'15_Zahlungen'!$D:$D,"") | I6: =SUMIFS('15_Zahlungen'!$F:$F,'15_Zahlungen'!$C:$C,"Eingang",'15_Zahlungen'!$I:$I,8,'15_Zahlungen'!$J:$J,GJ,'15_Zahlungen'!$D:$D,"") | J6: =SUMIFS('15_Zahlungen'!$F:$F,'15_Zahlungen'!$C:$C,"Eingang",'15_Zahlungen'!$I:$I,9,'15_Zahlungen'!$J:$J,GJ,'15_Zahlungen'!$D:$D,"") | K6: =SUMIFS('15_Zahlungen'!$F:$F,'15_Zahlungen'!$C:$C,"Eingang",'15_Zahlungen'!$I:$I,10,'15_Zahlungen'!$J:$J,GJ,'15_Zahlungen'!$D:$D,"") | L6: =SUMIFS('15_Zahlungen'!$F:$F,'15_Zahlungen'!$C:$C,"Eingang",'15_Zahlungen'!$I:$I,11,'15_Zahlungen'!$J:$J,GJ,'15_Zahlungen'!$D:$D,"") | M6: =SUMIFS('15_Zahlungen'!$F:$F,'15_Zahlungen'!$C:$C,"Eingang",'15_Zahlungen'!$I:$I,12,'15_Zahlungen'!$J:$J,GJ,'15_Zahlungen'!$D:$D,"") | N6: =SUM(B6:M6)
A7: Auszahlungen Lieferanten / NU | B7: =SUMIFS('15_Zahlungen'!$F:$F,'15_Zahlungen'!$C:$C,"Ausgang",'15_Zahlungen'!$I:$I,1,'15_Zahlungen'!$J:$J,GJ)-SUMIFS('15_Zahlungen'!$F:$F,'15_Zahlungen'!$C:$C,"Ausgang",'15_Zahlungen'!$I:$I,1,'15_Zahlungen'!$J:$J,GJ,'15_Zahlungen'!$E:$E,"Personal")-SUMIFS('15_Zahlungen'!$F:$F,'15_Zahlungen'!$C:$C,"Ausgang",'15_Zahlungen'!$I:$I,1,'15_Zahlungen'!$J:$J,GJ,'15_Zahlungen'!$E:$E,"Finanzamt")-SUMIFS('15_Zahlungen'!$F:$F,'15_Zahlungen'!$C:$C,"Ausgang",'15_Zahlungen'!$I:$I,1,'15_Zahlungen'!$J:$J,GJ,'15_Zahlungen'!$E:$E,"Sozialkasse") | C7: =SUMIFS('15_Zahlungen'!$F:$F,'15_Zahlungen'!$C:$C,"Ausgang",'15_Zahlungen'!$I:$I,2,'15_Zahlungen'!$J:$J,GJ)-SUMIFS('15_Zahlungen'!$F:$F,'15_Zahlungen'!$C:$C,"Ausgang",'15_Zahlungen'!$I:$I,2,'15_Zahlungen'!$J:$J,GJ,'15_Zahlungen'!$E:$E,"Personal")-SUMIFS('15_Zahlungen'!$F:$F,'15_Zahlungen'!$C:$C,"Ausgang",'15_Zahlungen'!$I:$I,2,'15_Zahlungen'!$J:$J,GJ,'15_Zahlungen'!$E:$E,"Finanzamt")-SUMIFS('15_Zahlungen'!$F:$F,'15_Zahlungen'!$C:$C,"Ausgang",'15_Zahlungen'!$I:$I,2,'15_Zahlungen'!$J:$J,GJ,'15_Zahlungen'!$E:$E,"Sozialkasse") | D7: =SUMIFS('15_Zahlungen'!$F:$F,'15_Zahlungen'!$C:$C,"Ausgang",'15_Zahlungen'!$I:$I,3,'15_Zahlungen'!$J:$J,GJ)-SUMIFS('15_Zahlungen'!$F:$F,'15_Zahlungen'!$C:$C,"Ausgang",'15_Zahlungen'!$I:$I,3,'15_Zahlungen'!$J:$J,GJ,'15_Zahlungen'!$E:$E,"Personal")-SUMIFS('15_Zahlungen'!$F:$F,'15_Zahlungen'!$C:$C,"Ausgang",'15_Zahlungen'!$I:$I,3,'15_Zahlungen'!$J:$J,GJ,'15_Zahlungen'!$E:$E,"Finanzamt")-SUMIFS('15_Zahlungen'!$F:$F,'15_Zahlungen'!$C:$C,"Ausgang",'15_Zahlungen'!$I:$I,3,'15_Zahlungen'!$J:$J,GJ,'15_Zahlungen'!$E:$E,"Sozialkasse") | E7: =SUMIFS('15_Zahlungen'!$F:$F,'15_Zahlungen'!$C:$C,"Ausgang",'15_Zahlungen'!$I:$I,4,'15_Zahlungen'!$J:$J,GJ)-SUMIFS('15_Zahlungen'!$F:$F,'15_Zahlungen'!$C:$C,"Ausgang",'15_Zahlungen'!$I:$I,4,'15_Zahlungen'!$J:$J,GJ,'15_Zahlungen'!$E:$E,"Personal")-SUMIFS('15_Zahlungen'!$F:$F,'15_Zahlungen'!$C:$C,"Ausgang",'15_Zahlungen'!$I:$I,4,'15_Zahlungen'!$J:$J,GJ,'15_Zahlungen'!$E:$E,"Finanzamt")-SUMIFS('15_Zahlungen'!$F:$F,'15_Zahlungen'!$C:$C,"Ausgang",'15_Zahlungen'!$I:$I,4,'15_Zahlungen'!$J:$J,GJ,'15_Zahlungen'!$E:$E,"Sozialkasse") | F7: =SUMIFS('15_Zahlungen'!$F:$F,'15_Zahlungen'!$C:$C,"Ausgang",'15_Zahlungen'!$I:$I,5,'15_Zahlungen'!$J:$J,GJ)-SUMIFS('15_Zahlungen'!$F:$F,'15_Zahlungen'!$C:$C,"Ausgang",'15_Zahlungen'!$I:$I,5,'15_Zahlungen'!$J:$J,GJ,'15_Zahlungen'!$E:$E,"Personal")-SUMIFS('15_Zahlungen'!$F:$F,'15_Zahlungen'!$C:$C,"Ausgang",'15_Zahlungen'!$I:$I,5,'15_Zahlungen'!$J:$J,GJ,'15_Zahlungen'!$E:$E,"Finanzamt")-SUMIFS('15_Zahlungen'!$F:$F,'15_Zahlungen'!$C:$C,"Ausgang",'15_Zahlungen'!$I:$I,5,'15_Zahlungen'!$J:$J,GJ,'15_Zahlungen'!$E:$E,"Sozialkasse") | G7: =SUMIFS('15_Zahlungen'!$F:$F,'15_Zahlungen'!$C:$C,"Ausgang",'15_Zahlungen'!$I:$I,6,'15_Zahlungen'!$J:$J,GJ)-SUMIFS('15_Zahlungen'!$F:$F,'15_Zahlungen'!$C:$C,"Ausgang",'15_Zahlungen'!$I:$I,6,'15_Zahlungen'!$J:$J,GJ,'15_Zahlungen'!$E:$E,"Personal")-SUMIFS('15_Zahlungen'!$F:$F,'15_Zahlungen'!$C:$C,"Ausgang",'15_Zahlungen'!$I:$I,6,'15_Zahlungen'!$J:$J,GJ,'15_Zahlungen'!$E:$E,"Finanzamt")-SUMIFS('15_Zahlungen'!$F:$F,'15_Zahlungen'!$C:$C,"Ausgang",'15_Zahlungen'!$I:$I,6,'15_Zahlungen'!$J:$J,GJ,'15_Zahlungen'!$E:$E,"Sozialkasse") | H7: =SUMIFS('15_Zahlungen'!$F:$F,'15_Zahlungen'!$C:$C,"Ausgang",'15_Zahlungen'!$I:$I,7,'15_Zahlungen'!$J:$J,GJ)-SUMIFS('15_Zahlungen'!$F:$F,'15_Zahlungen'!$C:$C,"Ausgang",'15_Zahlungen'!$I:$I,7,'15_Zahlungen'!$J:$J,GJ,'15_Zahlungen'!$E:$E,"Personal")-SUMIFS('15_Zahlungen'!$F:$F,'15_Zahlungen'!$C:$C,"Ausgang",'15_Zahlungen'!$I:$I,7,'15_Zahlungen'!$J:$J,GJ,'15_Zahlungen'!$E:$E,"Finanzamt")-SUMIFS('15_Zahlungen'!$F:$F,'15_Zahlungen'!$C:$C,"Ausgang",'15_Zahlungen'!$I:$I,7,'15_Zahlungen'!$J:$J,GJ,'15_Zahlungen'!$E:$E,"Sozialkasse") | I7: =SUMIFS('15_Zahlungen'!$F:$F,'15_Zahlungen'!$C:$C,"Ausgang",'15_Zahlungen'!$I:$I,8,'15_Zahlungen'!$J:$J,GJ)-SUMIFS('15_Zahlungen'!$F:$F,'15_Zahlungen'!$C:$C,"Ausgang",'15_Zahlungen'!$I:$I,8,'15_Zahlungen'!$J:$J,GJ,'15_Zahlungen'!$E:$E,"Personal")-SUMIFS('15_Zahlungen'!$F:$F,'15_Zahlungen'!$C:$C,"Ausgang",'15_Zahlungen'!$I:$I,8,'15_Zahlungen'!$J:$J,GJ,'15_Zahlungen'!$E:$E,"Finanzamt")-SUMIFS('15_Zahlungen'!$F:$F,'15_Zahlungen'!$C:$C,"Ausgang",'15_Zahlungen'!$I:$I,8,'15_Zahlungen'!$J:$J,GJ,'15_Zahlungen'!$E:$E,"Sozialkasse") | J7: =SUMIFS('15_Zahlungen'!$F:$F,'15_Zahlungen'!$C:$C,"Ausgang",'15_Zahlungen'!$I:$I,9,'15_Zahlungen'!$J:$J,GJ)-SUMIFS('15_Zahlungen'!$F:$F,'15_Zahlungen'!$C:$C,"Ausgang",'15_Zahlungen'!$I:$I,9,'15_Zahlungen'!$J:$J,GJ,'15_Zahlungen'!$E:$E,"Personal")-SUMIFS('15_Zahlungen'!$F:$F,'15_Zahlungen'!$C:$C,"Ausgang",'15_Zahlungen'!$I:$I,9,'15_Zahlungen'!$J:$J,GJ,'15_Zahlungen'!$E:$E,"Finanzamt")-SUMIFS('15_Zahlungen'!$F:$F,'15_Zahlungen'!$C:$C,"Ausgang",'15_Zahlungen'!$I:$I,9,'15_Zahlungen'!$J:$J,GJ,'15_Zahlungen'!$E:$E,"Sozialkasse") | K7: =SUMIFS('15_Zahlungen'!$F:$F,'15_Zahlungen'!$C:$C,"Ausgang",'15_Zahlungen'!$I:$I,10,'15_Zahlungen'!$J:$J,GJ)-SUMIFS('15_Zahlungen'!$F:$F,'15_Zahlungen'!$C:$C,"Ausgang",'15_Zahlungen'!$I:$I,10,'15_Zahlungen'!$J:$J,GJ,'15_Zahlungen'!$E:$E,"Personal")-SUMIFS('15_Zahlungen'!$F:$F,'15_Zahlungen'!$C:$C,"Ausgang",'15_Zahlungen'!$I:$I,10,'15_Zahlungen'!$J:$J,GJ,'15_Zahlungen'!$E:$E,"Finanzamt")-SUMIFS('15_Zahlungen'!$F:$F,'15_Zahlungen'!$C:$C,"Ausgang",'15_Zahlungen'!$I:$I,10,'15_Zahlungen'!$J:$J,GJ,'15_Zahlungen'!$E:$E,"Sozialkasse") | L7: =SUMIFS('15_Zahlungen'!$F:$F,'15_Zahlungen'!$C:$C,"Ausgang",'15_Zahlungen'!$I:$I,11,'15_Zahlungen'!$J:$J,GJ)-SUMIFS('15_Zahlungen'!$F:$F,'15_Zahlungen'!$C:$C,"Ausgang",'15_Zahlungen'!$I:$I,11,'15_Zahlungen'!$J:$J,GJ,'15_Zahlungen'!$E:$E,"Personal")-SUMIFS('15_Zahlungen'!$F:$F,'15_Zahlungen'!$C:$C,"Ausgang",'15_Zahlungen'!$I:$I,11,'15_Zahlungen'!$J:$J,GJ,'15_Zahlungen'!$E:$E,"Finanzamt")-SUMIFS('15_Zahlungen'!$F:$F,'15_Zahlungen'!$C:$C,"Ausgang",'15_Zahlungen'!$I:$I,11,'15_Zahlungen'!$J:$J,GJ,'15_Zahlungen'!$E:$E,"Sozialkasse") | M7: =SUMIFS('15_Zahlungen'!$F:$F,'15_Zahlungen'!$C:$C,"Ausgang",'15_Zahlungen'!$I:$I,12,'15_Zahlungen'!$J:$J,GJ)-SUMIFS('15_Zahlungen'!$F:$F,'15_Zahlungen'!$C:$C,"Ausgang",'15_Zahlungen'!$I:$I,12,'15_Zahlungen'!$J:$J,GJ,'15_Zahlungen'!$E:$E,"Personal")-SUMIFS('15_Zahlungen'!$F:$F,'15_Zahlungen'!$C:$C,"Ausgang",'15_Zahlungen'!$I:$I,12,'15_Zahlungen'!$J:$J,GJ,'15_Zahlungen'!$E:$E,"Finanzamt")-SUMIFS('15_Zahlungen'!$F:$F,'15_Zahlungen'!$C:$C,"Ausgang",'15_Zahlungen'!$I:$I,12,'15_Zahlungen'!$J:$J,GJ,'15_Zahlungen'!$E:$E,"Sozialkasse") | N7: =SUM(B7:M7)
A8: Löhne / Gehälter | B8: =SUMIFS('15_Zahlungen'!$F:$F,'15_Zahlungen'!$C:$C,"Ausgang",'15_Zahlungen'!$I:$I,1,'15_Zahlungen'!$J:$J,GJ,'15_Zahlungen'!$E:$E,"Personal") | C8: =SUMIFS('15_Zahlungen'!$F:$F,'15_Zahlungen'!$C:$C,"Ausgang",'15_Zahlungen'!$I:$I,2,'15_Zahlungen'!$J:$J,GJ,'15_Zahlungen'!$E:$E,"Personal") | D8: =SUMIFS('15_Zahlungen'!$F:$F,'15_Zahlungen'!$C:$C,"Ausgang",'15_Zahlungen'!$I:$I,3,'15_Zahlungen'!$J:$J,GJ,'15_Zahlungen'!$E:$E,"Personal") | E8: =SUMIFS('15_Zahlungen'!$F:$F,'15_Zahlungen'!$C:$C,"Ausgang",'15_Zahlungen'!$I:$I,4,'15_Zahlungen'!$J:$J,GJ,'15_Zahlungen'!$E:$E,"Personal") | F8: =SUMIFS('15_Zahlungen'!$F:$F,'15_Zahlungen'!$C:$C,"Ausgang",'15_Zahlungen'!$I:$I,5,'15_Zahlungen'!$J:$J,GJ,'15_Zahlungen'!$E:$E,"Personal") | G8: =SUMIFS('15_Zahlungen'!$F:$F,'15_Zahlungen'!$C:$C,"Ausgang",'15_Zahlungen'!$I:$I,6,'15_Zahlungen'!$J:$J,GJ,'15_Zahlungen'!$E:$E,"Personal") | H8: =SUMIFS('15_Zahlungen'!$F:$F,'15_Zahlungen'!$C:$C,"Ausgang",'15_Zahlungen'!$I:$I,7,'15_Zahlungen'!$J:$J,GJ,'15_Zahlungen'!$E:$E,"Personal") | I8: =SUMIFS('15_Zahlungen'!$F:$F,'15_Zahlungen'!$C:$C,"Ausgang",'15_Zahlungen'!$I:$I,8,'15_Zahlungen'!$J:$J,GJ,'15_Zahlungen'!$E:$E,"Personal") | J8: =SUMIFS('15_Zahlungen'!$F:$F,'15_Zahlungen'!$C:$C,"Ausgang",'15_Zahlungen'!$I:$I,9,'15_Zahlungen'!$J:$J,GJ,'15_Zahlungen'!$E:$E,"Personal") | K8: =SUMIFS('15_Zahlungen'!$F:$F,'15_Zahlungen'!$C:$C,"Ausgang",'15_Zahlungen'!$I:$I,10,'15_Zahlungen'!$J:$J,GJ,'15_Zahlungen'!$E:$E,"Personal") | L8: =SUMIFS('15_Zahlungen'!$F:$F,'15_Zahlungen'!$C:$C,"Ausgang",'15_Zahlungen'!$I:$I,11,'15_Zahlungen'!$J:$J,GJ,'15_Zahlungen'!$E:$E,"Personal") | M8: =SUMIFS('15_Zahlungen'!$F:$F,'15_Zahlungen'!$C:$C,"Ausgang",'15_Zahlungen'!$I:$I,12,'15_Zahlungen'!$J:$J,GJ,'15_Zahlungen'!$E:$E,"Personal") | N8: =SUM(B8:M8)
A9: Steuern / SV / Soka | B9: =SUMIFS('15_Zahlungen'!$F:$F,'15_Zahlungen'!$C:$C,"Ausgang",'15_Zahlungen'!$I:$I,1,'15_Zahlungen'!$J:$J,GJ,'15_Zahlungen'!$E:$E,"Finanzamt")+SUMIFS('15_Zahlungen'!$F:$F,'15_Zahlungen'!$C:$C,"Ausgang",'15_Zahlungen'!$I:$I,1,'15_Zahlungen'!$J:$J,GJ,'15_Zahlungen'!$E:$E,"Sozialkasse") | C9: =SUMIFS('15_Zahlungen'!$F:$F,'15_Zahlungen'!$C:$C,"Ausgang",'15_Zahlungen'!$I:$I,2,'15_Zahlungen'!$J:$J,GJ,'15_Zahlungen'!$E:$E,"Finanzamt")+SUMIFS('15_Zahlungen'!$F:$F,'15_Zahlungen'!$C:$C,"Ausgang",'15_Zahlungen'!$I:$I,2,'15_Zahlungen'!$J:$J,GJ,'15_Zahlungen'!$E:$E,"Sozialkasse") | D9: =SUMIFS('15_Zahlungen'!$F:$F,'15_Zahlungen'!$C:$C,"Ausgang",'15_Zahlungen'!$I:$I,3,'15_Zahlungen'!$J:$J,GJ,'15_Zahlungen'!$E:$E,"Finanzamt")+SUMIFS('15_Zahlungen'!$F:$F,'15_Zahlungen'!$C:$C,"Ausgang",'15_Zahlungen'!$I:$I,3,'15_Zahlungen'!$J:$J,GJ,'15_Zahlungen'!$E:$E,"Sozialkasse") | E9: =SUMIFS('15_Zahlungen'!$F:$F,'15_Zahlungen'!$C:$C,"Ausgang",'15_Zahlungen'!$I:$I,4,'15_Zahlungen'!$J:$J,GJ,'15_Zahlungen'!$E:$E,"Finanzamt")+SUMIFS('15_Zahlungen'!$F:$F,'15_Zahlungen'!$C:$C,"Ausgang",'15_Zahlungen'!$I:$I,4,'15_Zahlungen'!$J:$J,GJ,'15_Zahlungen'!$E:$E,"Sozialkasse") | F9: =SUMIFS('15_Zahlungen'!$F:$F,'15_Zahlungen'!$C:$C,"Ausgang",'15_Zahlungen'!$I:$I,5,'15_Zahlungen'!$J:$J,GJ,'15_Zahlungen'!$E:$E,"Finanzamt")+SUMIFS('15_Zahlungen'!$F:$F,'15_Zahlungen'!$C:$C,"Ausgang",'15_Zahlungen'!$I:$I,5,'15_Zahlungen'!$J:$J,GJ,'15_Zahlungen'!$E:$E,"Sozialkasse") | G9: =SUMIFS('15_Zahlungen'!$F:$F,'15_Zahlungen'!$C:$C,"Ausgang",'15_Zahlungen'!$I:$I,6,'15_Zahlungen'!$J:$J,GJ,'15_Zahlungen'!$E:$E,"Finanzamt")+SUMIFS('15_Zahlungen'!$F:$F,'15_Zahlungen'!$C:$C,"Ausgang",'15_Zahlungen'!$I:$I,6,'15_Zahlungen'!$J:$J,GJ,'15_Zahlungen'!$E:$E,"Sozialkasse") | H9: =SUMIFS('15_Zahlungen'!$F:$F,'15_Zahlungen'!$C:$C,"Ausgang",'15_Zahlungen'!$I:$I,7,'15_Zahlungen'!$J:$J,GJ,'15_Zahlungen'!$E:$E,"Finanzamt")+SUMIFS('15_Zahlungen'!$F:$F,'15_Zahlungen'!$C:$C,"Ausgang",'15_Zahlungen'!$I:$I,7,'15_Zahlungen'!$J:$J,GJ,'15_Zahlungen'!$E:$E,"Sozialkasse") | I9: =SUMIFS('15_Zahlungen'!$F:$F,'15_Zahlungen'!$C:$C,"Ausgang",'15_Zahlungen'!$I:$I,8,'15_Zahlungen'!$J:$J,GJ,'15_Zahlungen'!$E:$E,"Finanzamt")+SUMIFS('15_Zahlungen'!$F:$F,'15_Zahlungen'!$C:$C,"Ausgang",'15_Zahlungen'!$I:$I,8,'15_Zahlungen'!$J:$J,GJ,'15_Zahlungen'!$E:$E,"Sozialkasse") | J9: =SUMIFS('15_Zahlungen'!$F:$F,'15_Zahlungen'!$C:$C,"Ausgang",'15_Zahlungen'!$I:$I,9,'15_Zahlungen'!$J:$J,GJ,'15_Zahlungen'!$E:$E,"Finanzamt")+SUMIFS('15_Zahlungen'!$F:$F,'15_Zahlungen'!$C:$C,"Ausgang",'15_Zahlungen'!$I:$I,9,'15_Zahlungen'!$J:$J,GJ,'15_Zahlungen'!$E:$E,"Sozialkasse") | K9: =SUMIFS('15_Zahlungen'!$F:$F,'15_Zahlungen'!$C:$C,"Ausgang",'15_Zahlungen'!$I:$I,10,'15_Zahlungen'!$J:$J,GJ,'15_Zahlungen'!$E:$E,"Finanzamt")+SUMIFS('15_Zahlungen'!$F:$F,'15_Zahlungen'!$C:$C,"Ausgang",'15_Zahlungen'!$I:$I,10,'15_Zahlungen'!$J:$J,GJ,'15_Zahlungen'!$E:$E,"Sozialkasse") | L9: =SUMIFS('15_Zahlungen'!$F:$F,'15_Zahlungen'!$C:$C,"Ausgang",'15_Zahlungen'!$I:$I,11,'15_Zahlungen'!$J:$J,GJ,'15_Zahlungen'!$E:$E,"Finanzamt")+SUMIFS('15_Zahlungen'!$F:$F,'15_Zahlungen'!$C:$C,"Ausgang",'15_Zahlungen'!$I:$I,11,'15_Zahlungen'!$J:$J,GJ,'15_Zahlungen'!$E:$E,"Sozialkasse") | M9: =SUMIFS('15_Zahlungen'!$F:$F,'15_Zahlungen'!$C:$C,"Ausgang",'15_Zahlungen'!$I:$I,12,'15_Zahlungen'!$J:$J,GJ,'15_Zahlungen'!$E:$E,"Finanzamt")+SUMIFS('15_Zahlungen'!$F:$F,'15_Zahlungen'!$C:$C,"Ausgang",'15_Zahlungen'!$I:$I,12,'15_Zahlungen'!$J:$J,GJ,'15_Zahlungen'!$E:$E,"Sozialkasse") | N9: =SUM(B9:M9)
A10: sonstige Auszahlungen | B10: 0 | C10: 0 | D10: 0 | E10: 0 | F10: 0 | G10: 0 | H10: 0 | I10: 0 | J10: 0 | K10: 0 | L10: 0 | M10: 0 | N10: =SUM(B10:M10)
A12: Cashflow operativ | B12: =B5+B6-B7-B8-B9-B10 | C12: =C5+C6-C7-C8-C9-C10 | D12: =D5+D6-D7-D8-D9-D10 | E12: =E5+E6-E7-E8-E9-E10 | F12: =F5+F6-F7-F8-F9-F10 | G12: =G5+G6-G7-G8-G9-G10 | H12: =H5+H6-H7-H8-H9-H10 | I12: =I5+I6-I7-I8-I9-I10 | ... N12: =N5+N6-N7-N8-N9-N10
A14: Investitionen Geräte (manuell) | N14: =SUM(B14:M14)
A15: Kreditaufnahme / Tilgung (manuell) | N15: =SUM(B15:M15)
A16: Cashflow gesamt | B16: =B12-B14+B15 | C16: =C12-C14+C15 | D16: =D12-D14+D15 | E16: =E12-E14+E15 | F16: =F12-F14+F15 | G16: =G12-G14+G15 | H16: =H12-H14+H15 | I16: =I12-I14+I15 | ... M16: =M12-M14+M15 | N16: =SUM(B16:M16)
A18: Endbestand Bank (kumuliert aus Anfangsbestand) | B18: =AnfangsBank+B16 | C18: =B18+C16 | D18: =C18+D16 | E18: =D18+E16 | F18: =E18+F16 | G18: =F18+G16 | H18: =G18+H16 | I18: =H18+I16 | J18: =I18+J16 | ... M18: =L18+M16 | N18: =M18

Sheet 21_Forecast
A1: Forecast Umsatz, Kosten, Ergebnis
A2: Plan (Budget) · Forecast (rollierend) · Ist aus Rechnungen und Kosten · Abweichung für die Geschäftsleitung
A3: Kennzahl | B3: Jan | C3: Feb | D3: Mrz | E3: Apr | F3: Mai | G3: Jun | H3: Jul | I3: Aug | J3: Sep | K3: Okt | L3: Nov | M3: Dez | N3: Jahr
A4: Umsatz Plan | B4: 210000 | C4: 280000 | D4: 340000 | E4: 410000 | F4: 455000 | G4: 490000 | H4: 520000 | I4: 505000 | J4: 560000 | K4: 610000 | L4: 580000 | M4: 420000 | N4: =SUM(B4:M4)
A5: Material Plan | B5: 72000 | C5: 95000 | D5: 118000 | E5: 145000 | F5: 152000 | G5: 168000 | H5: 175000 | I5: 162000 | J5: 188000 | K5: 205000 | L5: 190000 | M5: 130000 | N5: =SUM(B5:M5)
A6: Nachunternehmer Plan | B6: 28000 | C6: 42000 | D6: 55000 | E6: 68000 | F6: 74000 | G6: 82000 | H6: 90000 | I6: 88000 | J6: 96000 | K6: 110000 | L6: 98000 | M6: 62000 | N6: =SUM(B6:M6)
A7: Personal Plan | B7: 72000 | C7: 72000 | D7: 74000 | E7: 76000 | F7: 78000 | G7: 78000 | H7: 80000 | I7: 80000 | J7: 82000 | K7: 84000 | L7: 82000 | M7: 78000 | N7: =SUM(B7:M7)
A8: Gerät Plan | B8: 12000 | C8: 14000 | D8: 16000 | E8: 18000 | F8: 19000 | G8: 21000 | H8: 22000 | I8: 21000 | J8: 24000 | K8: 26000 | L8: 23000 | M8: 18000 | N8: =SUM(B8:M8)
A9: Gemeinkosten Plan | B9: 28000 | C9: 28000 | D9: 29000 | E9: 30000 | F9: 30000 | G9: 31000 | H9: 31000 | I9: 31000 | J9: 32000 | K9: 32000 | L9: 32000 | M9: 32000 | N9: =SUM(B9:M9)
A10: DB I Plan (Umsatz-Mat-NU) | B10: =B4-B5-B6 | C10: =C4-C5-C6 | D10: =D4-D5-D6 | E10: =E4-E5-E6 | F10: =F4-F5-F6 | G10: =G4-G5-G6 | H10: =H4-H5-H6 | I10: =I4-I5-I6 | ... N10: =N4-N5-N6
A11: EBIT Plan | B11: =B10-B7-B8-B9 | C11: =C10-C7-C8-C9 | D11: =D10-D7-D8-D9 | E11: =E10-E7-E8-E9 | F11: =F10-F7-F8-F9 | G11: =G10-G7-G8-G9 | H11: =H10-H7-H8-H9 | I11: =I10-I7-I8-I9 | ... N11: =N10-N7-N8-N9
A13: Ist und rollierender Forecast (ab aktuellem Monat = Plan, davor Ist)
A14: Umsatz Ist (AR-Netto im Monat) | B14: =SUMIFS('13_Ausgangsrechnungen'!$G:$G,'13_Ausgangsrechnungen'!$B:$B,">="&DATE(GJ,1,1),'13_Ausgangsrechnungen'!$B:$B,"<"&DATE(GJ,1+1,1)) | C14: =SUMIFS('13_Ausgangsrechnungen'!$G:$G,'13_Ausgangsrechnungen'!$B:$B,">="&DATE(GJ,2,1),'13_Ausgangsrechnungen'!$B:$B,"<"&DATE(GJ,2+1,1)) | D14: =SUMIFS('13_Ausgangsrechnungen'!$G:$G,'13_Ausgangsrechnungen'!$B:$B,">="&DATE(GJ,3,1),'13_Ausgangsrechnungen'!$B:$B,"<"&DATE(GJ,3+1,1)) | E14: =SUMIFS('13_Ausgangsrechnungen'!$G:$G,'13_Ausgangsrechnungen'!$B:$B,">="&DATE(GJ,4,1),'13_Ausgangsrechnungen'!$B:$B,"<"&DATE(GJ,4+1,1)) | F14: =SUMIFS('13_Ausgangsrechnungen'!$G:$G,'13_Ausgangsrechnungen'!$B:$B,">="&DATE(GJ,5,1),'13_Ausgangsrechnungen'!$B:$B,"<"&DATE(GJ,5+1,1)) | G14: =SUMIFS('13_Ausgangsrechnungen'!$G:$G,'13_Ausgangsrechnungen'!$B:$B,">="&DATE(GJ,6,1),'13_Ausgangsrechnungen'!$B:$B,"<"&DATE(GJ,6+1,1)) | H14: =SUMIFS('13_Ausgangsrechnungen'!$G:$G,'13_Ausgangsrechnungen'!$B:$B,">="&DATE(GJ,7,1),'13_Ausgangsrechnungen'!$B:$B,"<"&DATE(GJ,7+1,1)) | I14: =SUMIFS('13_Ausgangsrechnungen'!$G:$G,'13_Ausgangsrechnungen'!$B:$B,">="&DATE(GJ,8,1),'13_Ausgangsrechnungen'!$B:$B,"<"&DATE(GJ,8+1,1)) | J14: =SUMIFS('13_Ausgangsrechnungen'!$G:$G,'13_Ausgangsrechnungen'!$B:$B,">="&DATE(GJ,9,1),'13_Ausgangsrechnungen'!$B:$B,"<"&DATE(GJ,9+1,1)) | K14: =SUMIFS('13_Ausgangsrechnungen'!$G:$G,'13_Ausgangsrechnungen'!$B:$B,">="&DATE(GJ,10,1),'13_Ausgangsrechnungen'!$B:$B,"<"&DATE(GJ,10+1,1)) | L14: =SUMIFS('13_Ausgangsrechnungen'!$G:$G,'13_Ausgangsrechnungen'!$B:$B,">="&DATE(GJ,11,1),'13_Ausgangsrechnungen'!$B:$B,"<"&DATE(GJ,11+1,1)) | M14: =SUMIFS('13_Ausgangsrechnungen'!$G:$G,'13_Ausgangsrechnungen'!$B:$B,">="&DATE(GJ,12,1),'13_Ausgangsrechnungen'!$B:$B,"<"&DATE(GJ+1,1,1)) | N14: =SUM(B14:M14)
A15: Material Ist | B15: =SUMIFS('11_Material'!$L:$L,'11_Material'!$B:$B,">="&DATE(GJ,1,1),'11_Material'!$B:$B,"<"&DATE(GJ,1+1,1)) | C15: =SUMIFS('11_Material'!$L:$L,'11_Material'!$B:$B,">="&DATE(GJ,2,1),'11_Material'!$B:$B,"<"&DATE(GJ,2+1,1)) | D15: =SUMIFS('11_Material'!$L:$L,'11_Material'!$B:$B,">="&DATE(GJ,3,1),'11_Material'!$B:$B,"<"&DATE(GJ,3+1,1)) | E15: =SUMIFS('11_Material'!$L:$L,'11_Material'!$B:$B,">="&DATE(GJ,4,1),'11_Material'!$B:$B,"<"&DATE(GJ,4+1,1)) | F15: =SUMIFS('11_Material'!$L:$L,'11_Material'!$B:$B,">="&DATE(GJ,5,1),'11_Material'!$B:$B,"<"&DATE(GJ,5+1,1)) | G15: =SUMIFS('11_Material'!$L:$L,'11_Material'!$B:$B,">="&DATE(GJ,6,1),'11_Material'!$B:$B,"<"&DATE(GJ,6+1,1)) | H15: =SUMIFS('11_Material'!$L:$L,'11_Material'!$B:$B,">="&DATE(GJ,7,1),'11_Material'!$B:$B,"<"&DATE(GJ,7+1,1)) | I15: =SUMIFS('11_Material'!$L:$L,'11_Material'!$B:$B,">="&DATE(GJ,8,1),'11_Material'!$B:$B,"<"&DATE(GJ,8+1,1)) | J15: =SUMIFS('11_Material'!$L:$L,'11_Material'!$B:$B,">="&DATE(GJ,9,1),'11_Material'!$B:$B,"<"&DATE(GJ,9+1,1)) | K15: =SUMIFS('11_Material'!$L:$L,'11_Material'!$B:$B,">="&DATE(GJ,10,1),'11_Material'!$B:$B,"<"&DATE(GJ,10+1,1)) | L15: =SUMIFS('11_Material'!$L:$L,'11_Material'!$B:$B,">="&DATE(GJ,11,1),'11_Material'!$B:$B,"<"&DATE(GJ,11+1,1)) | M15: =SUMIFS('11_Material'!$L:$L,'11_Material'!$B:$B,">="&DATE(GJ,12,1),'11_Material'!$B:$B,"<"&DATE(GJ+1,1,1)) | N15: =SUM(B15:M15)
A16: NU Ist | B16: =SUMIFS('14_Eingangsrechnungen'!$F:$F,'14_Eingangsrechnungen'!$E:$E,"Nachunternehmer",'14_Eingangsrechnungen'!$B:$B,">="&DATE(GJ,1,1),'14_Eingangsrechnungen'!$B:$B,"<"&DATE(GJ,1+1,1)) | C16: =SUMIFS('14_Eingangsrechnungen'!$F:$F,'14_Eingangsrechnungen'!$E:$E,"Nachunternehmer",'14_Eingangsrechnungen'!$B:$B,">="&DATE(GJ,2,1),'14_Eingangsrechnungen'!$B:$B,"<"&DATE(GJ,2+1,1)) | D16: =SUMIFS('14_Eingangsrechnungen'!$F:$F,'14_Eingangsrechnungen'!$E:$E,"Nachunternehmer",'14_Eingangsrechnungen'!$B:$B,">="&DATE(GJ,3,1),'14_Eingangsrechnungen'!$B:$B,"<"&DATE(GJ,3+1,1)) | E16: =SUMIFS('14_Eingangsrechnungen'!$F:$F,'14_Eingangsrechnungen'!$E:$E,"Nachunternehmer",'14_Eingangsrechnungen'!$B:$B,">="&DATE(GJ,4,1),'14_Eingangsrechnungen'!$B:$B,"<"&DATE(GJ,4+1,1)) | F16: =SUMIFS('14_Eingangsrechnungen'!$F:$F,'14_Eingangsrechnungen'!$E:$E,"Nachunternehmer",'14_Eingangsrechnungen'!$B:$B,">="&DATE(GJ,5,1),'14_Eingangsrechnungen'!$B:$B,"<"&DATE(GJ,5+1,1)) | G16: =SUMIFS('14_Eingangsrechnungen'!$F:$F,'14_Eingangsrechnungen'!$E:$E,"Nachunternehmer",'14_Eingangsrechnungen'!$B:$B,">="&DATE(GJ,6,1),'14_Eingangsrechnungen'!$B:$B,"<"&DATE(GJ,6+1,1)) | H16: =SUMIFS('14_Eingangsrechnungen'!$F:$F,'14_Eingangsrechnungen'!$E:$E,"Nachunternehmer",'14_Eingangsrechnungen'!$B:$B,">="&DATE(GJ,7,1),'14_Eingangsrechnungen'!$B:$B,"<"&DATE(GJ,7+1,1)) | I16: =SUMIFS('14_Eingangsrechnungen'!$F:$F,'14_Eingangsrechnungen'!$E:$E,"Nachunternehmer",'14_Eingangsrechnungen'!$B:$B,">="&DATE(GJ,8,1),'14_Eingangsrechnungen'!$B:$B,"<"&DATE(GJ,8+1,1)) | J16: =SUMIFS('14_Eingangsrechnungen'!$F:$F,'14_Eingangsrechnungen'!$E:$E,"Nachunternehmer",'14_Eingangsrechnungen'!$B:$B,">="&DATE(GJ,9,1),'14_Eingangsrechnungen'!$B:$B,"<"&DATE(GJ,9+1,1)) | K16: =SUMIFS('14_Eingangsrechnungen'!$F:$F,'14_Eingangsrechnungen'!$E:$E,"Nachunternehmer",'14_Eingangsrechnungen'!$B:$B,">="&DATE(GJ,10,1),'14_Eingangsrechnungen'!$B:$B,"<"&DATE(GJ,10+1,1)) | L16: =SUMIFS('14_Eingangsrechnungen'!$F:$F,'14_Eingangsrechnungen'!$E:$E,"Nachunternehmer",'14_Eingangsrechnungen'!$B:$B,">="&DATE(GJ,11,1),'14_Eingangsrechnungen'!$B:$B,"<"&DATE(GJ,11+1,1)) | M16: =SUMIFS('14_Eingangsrechnungen'!$F:$F,'14_Eingangsrechnungen'!$E:$E,"Nachunternehmer",'14_Eingangsrechnungen'!$B:$B,">="&DATE(GJ,12,1),'14_Eingangsrechnungen'!$B:$B,"<"&DATE(GJ+1,1,1)) | N16: =SUM(B16:M16)
A17: Personal Ist (Stundenkosten + Lohnzahlung Fallback) | B17: =SUMIFS('10_Stunden'!$K:$K,'10_Stunden'!$B:$B,">="&DATE(GJ,1,1),'10_Stunden'!$B:$B,"<"&DATE(GJ,1+1,1)) | C17: =SUMIFS('10_Stunden'!$K:$K,'10_Stunden'!$B:$B,">="&DATE(GJ,2,1),'10_Stunden'!$B:$B,"<"&DATE(GJ,2+1,1)) | D17: =SUMIFS('10_Stunden'!$K:$K,'10_Stunden'!$B:$B,">="&DATE(GJ,3,1),'10_Stunden'!$B:$B,"<"&DATE(GJ,3+1,1)) | E17: =SUMIFS('10_Stunden'!$K:$K,'10_Stunden'!$B:$B,">="&DATE(GJ,4,1),'10_Stunden'!$B:$B,"<"&DATE(GJ,4+1,1)) | F17: =SUMIFS('10_Stunden'!$K:$K,'10_Stunden'!$B:$B,">="&DATE(GJ,5,1),'10_Stunden'!$B:$B,"<"&DATE(GJ,5+1,1)) | G17: =SUMIFS('10_Stunden'!$K:$K,'10_Stunden'!$B:$B,">="&DATE(GJ,6,1),'10_Stunden'!$B:$B,"<"&DATE(GJ,6+1,1)) | H17: =SUMIFS('10_Stunden'!$K:$K,'10_Stunden'!$B:$B,">="&DATE(GJ,7,1),'10_Stunden'!$B:$B,"<"&DATE(GJ,7+1,1)) | I17: =SUMIFS('10_Stunden'!$K:$K,'10_Stunden'!$B:$B,">="&DATE(GJ,8,1),'10_Stunden'!$B:$B,"<"&DATE(GJ,8+1,1)) | J17: =SUMIFS('10_Stunden'!$K:$K,'10_Stunden'!$B:$B,">="&DATE(GJ,9,1),'10_Stunden'!$B:$B,"<"&DATE(GJ,9+1,1)) | K17: =SUMIFS('10_Stunden'!$K:$K,'10_Stunden'!$B:$B,">="&DATE(GJ,10,1),'10_Stunden'!$B:$B,"<"&DATE(GJ,10+1,1)) | L17: =SUMIFS('10_Stunden'!$K:$K,'10_Stunden'!$B:$B,">="&DATE(GJ,11,1),'10_Stunden'!$B:$B,"<"&DATE(GJ,11+1,1)) | M17: =SUMIFS('10_Stunden'!$K:$K,'10_Stunden'!$B:$B,">="&DATE(GJ,12,1),'10_Stunden'!$B:$B,"<"&DATE(GJ+1,1,1)) | N17: =SUM(B17:M17)
A19: Umsatz Forecast (Ist wenn >0 sonst Plan)
A20: Umsatz Forecast | B20: =IF(B14>0,B14,B4) | C20: =IF(C14>0,C14,C4) | D20: =IF(D14>0,D14,D4) | E20: =IF(E14>0,E14,E4) | F20: =IF(F14>0,F14,F4) | G20: =IF(G14>0,G14,G4) | H20: =IF(H14>0,H14,H4) | I20: =IF(I14>0,I14,I4) | ... M20: =IF(M14>0,M14,M4) | N20: =SUM(B20:M20)
A21: Material Forecast | B21: =IF(B15>0,B15,B5) | C21: =IF(C15>0,C15,C5) | D21: =IF(D15>0,D15,D5) | E21: =IF(E15>0,E15,E5) | F21: =IF(F15>0,F15,F5) | G21: =IF(G15>0,G15,G5) | H21: =IF(H15>0,H15,H5) | I21: =IF(I15>0,I15,I5) | ... M21: =IF(M15>0,M15,M5) | N21: =SUM(B21:M21)
A22: NU Forecast | B22: =IF(B16>0,B16,B6) | C22: =IF(C16>0,C16,C6) | D22: =IF(D16>0,D16,D6) | E22: =IF(E16>0,E16,E6) | F22: =IF(F16>0,F16,F6) | G22: =IF(G16>0,G16,G6) | H22: =IF(H16>0,H16,H6) | I22: =IF(I16>0,I16,I6) | ... M22: =IF(M16>0,M16,M6) | N22: =SUM(B22:M22)
A23: Personal Forecast | B23: =IF(B17>0,B17,B7) | C23: =IF(C17>0,C17,C7) | D23: =IF(D17>0,D17,D7) | E23: =IF(E17>0,E17,E7) | F23: =IF(F17>0,F17,F7) | G23: =IF(G17>0,G17,G7) | H23: =IF(H17>0,H17,H7) | I23: =IF(I17>0,I17,I7) | ... M23: =IF(M17>0,M17,M7) | N23: =SUM(B23:M23)
A24: Gerät Forecast | B24: =B8 | C24: =C8 | D24: =D8 | E24: =E8 | F24: =F8 | G24: =G8 | H24: =H8 | I24: =I8 | ... M24: =M8 | N24: =SUM(B24:M24)
A25: GK Forecast | B25: =B9 | C25: =C9 | D25: =D9 | E25: =E9 | F25: =F9 | G25: =G9 | H25: =H9 | I25: =I9 | ... M25: =M9 | N25: =SUM(B25:M25)
A26: EBIT Forecast | B26: =B20-B21-B22-B23-B24-B25 | C26: =C20-C21-C22-C23-C24-C25 | D26: =D20-D21-D22-D23-D24-D25 | E26: =E20-E21-E22-E23-E24-E25 | F26: =F20-F21-F22-F23-F24-F25 | G26: =G20-G21-G22-G23-G24-G25 | H26: =H20-H21-H22-H23-H24-H25 | I26: =I20-I21-I22-I23-I24-I25 | ... M26: =M20-M21-M22-M23-M24-M25 | N26: =SUM(B26:M26)
A27: Abweichung EBIT vs Plan | B27: =B26-B11 | C27: =C26-C11 | D27: =D26-D11 | E27: =E26-E11 | F27: =F26-F11 | G27: =G26-G11 | H27: =H26-H11 | I27: =I26-I11 | ... M27: =M26-M11 | N27: =SUM(B27:M27)

Sheet 22_BWA
A1: Kurz-BWA / GuV Baubetrieb
A2: Verdichtung aus Ausgangsrechnungen, Eingangsrechnungen, Stunden und Forecast-Gemeinkosten
A3: Position | B3: Ist GJ | C3: Forecast GJ | D3: Abw. | E3: % vom Umsatz Ist | F3: Vormonat | G3: Hinweis
A4: Umsatzerlöse (AR netto) | B4: ='21_Forecast'!N14 | C4: ='21_Forecast'!N20 | D4: =IF(C4="","",B4-C4) | E4: =IF($B$4=0,"",B4/$B$4)
A5: Material / Baustoffe | B5: ='21_Forecast'!N15 | C5: ='21_Forecast'!N21 | D5: =IF(C5="","",B5-C5) | E5: =IF($B$4=0,"",B5/$B$4)
A6: Nachunternehmer | B6: ='21_Forecast'!N16 | C6: ='21_Forecast'!N22 | D6: =IF(C6="","",B6-C6) | E6: =IF($B$4=0,"",B6/$B$4)
A7: Rohertrag | B7: =B4-B5-B6 | C7: =C4-C5-C6 | D7: =IF(C7="","",B7-C7) | E7: =IF($B$4=0,"",B7/$B$4)
A8: Personal (Stundenkosten) | B8: ='21_Forecast'!N17 | C8: ='21_Forecast'!N23 | D8: =IF(C8="","",B8-C8) | E8: =IF($B$4=0,"",B8/$B$4)
A9: Geräte / Mieten | B9: =SUMIFS('14_Eingangsrechnungen'!F:F,'14_Eingangsrechnungen'!E:E,"Gerät") | C9: ='21_Forecast'!N24 | D9: =IF(C9="","",B9-C9) | E9: =IF($B$4=0,"",B9/$B$4)
A10: Gemeinkosten (Plan/Forecast) | B10: ='21_Forecast'!N9 | C10: ='21_Forecast'!N25 | D10: =IF(C10="","",B10-C10) | E10: =IF($B$4=0,"",B10/$B$4)
A11: Betriebsergebnis / EBIT | B11: =B7-B8-B9-B10 | C11: =C7-C8-C9-C10 | D11: =IF(C11="","",B11-C11) | E11: =IF($B$4=0,"",B11/$B$4)
A12: Rohertragsmarge | B12: =IF(B4=0,0,B7/B4) | C12: =IF(C4=0,0,C7/C4) | D12: =B12-C12
A13: EBIT-Marge | B13: =IF(B4=0,0,B11/B4) | C13: =IF(C4=0,0,C11/C4) | D13: =B13-C13
A14: Offene Forderungen brutto | B14: =SUM('13_Ausgangsrechnungen'!S4:S400) | D14: =IF(C14="","",B14-C14)
A15: Offene Verbindlichkeiten brutto | B15: =SUM('14_Eingangsrechnungen'!O4:O400) | D15: =IF(C15="","",B15-C15)
A16: Einbehalte gebunden | B16: =SUM('18_Gewaehrleistung'!F4:F400) | D16: =IF(C16="","",B16-C16)
A17: Working Capital (Ford.-Verb.) | B17: =B14-B15 | D17: =IF(C17="","",B17-C17)

Sheet 16_OPOS
A1: Offene Posten Debitoren und Kreditoren
A2: Links Debitoren · rechts Kreditoren · Zeilen ohne Offenbetrag bleiben leer
A3: Seite | B3: Beleg | C3: Datum | D3: Partner | E3: Projekt | F3: Typ | G3: Brutto | H3: Offen | I3: Fällig | J3: Tage | L3: Seite | M3: Beleg | N3: Datum | O3: Partner | P3: Projekt | Q3: Typ | R3: Brutto | S3: Offen | T3: Fällig | U3: Tage
A4: =IF('13_Ausgangsrechnungen'!A4="","",IF('13_Ausgangsrechnungen'!S4>0.5,"Debitor","")) | B4: =IF(A4="","",'13_Ausgangsrechnungen'!A4) | C4: =IF(A4="","",'13_Ausgangsrechnungen'!B4) | D4: =IF(A4="","",'13_Ausgangsrechnungen'!D4) | E4: =IF(A4="","",'13_Ausgangsrechnungen'!C4) | F4: =IF(A4="","",'13_Ausgangsrechnungen'!E4) | G4: =IF(A4="","",'13_Ausgangsrechnungen'!Q4) | H4: =IF(A4="","",'13_Ausgangsrechnungen'!S4) | I4: =IF(A4="","",'13_Ausgangsrechnungen'!J4) | J4: =IF(A4="","",'13_Ausgangsrechnungen'!T4) | L4: =IF('14_Eingangsrechnungen'!A4="","",IF('14_Eingangsrechnungen'!O4>0.5,"Kreditor","")) | M4: =IF(L4="","",'14_Eingangsrechnungen'!A4) | N4: =IF(L4="","",'14_Eingangsrechnungen'!B4) | O4: =IF(L4="","",'14_Eingangsrechnungen'!D4) | P4: =IF(L4="","",'14_Eingangsrechnungen'!C4) | Q4: =IF(L4="","",'14_Eingangsrechnungen'!E4) | R4: =IF(L4="","",'14_Eingangsrechnungen'!M4) | S4: =IF(L4="","",'14_Eingangsrechnungen'!O4) | T4: =IF(L4="","",'14_Eingangsrechnungen'!H4) | U4: =IF(L4="","",'14_Eingangsrechnungen'!P4)
A5: =IF('13_Ausgangsrechnungen'!A5="","",IF('13_Ausgangsrechnungen'!S5>0.5,"Debitor","")) | B5: =IF(A5="","",'13_Ausgangsrechnungen'!A5) | C5: =IF(A5="","",'13_Ausgangsrechnungen'!B5) | D5: =IF(A5="","",'13_Ausgangsrechnungen'!D5) | E5: =IF(A5="","",'13_Ausgangsrechnungen'!C5) | F5: =IF(A5="","",'13_Ausgangsrechnungen'!E5) | G5: =IF(A5="","",'13_Ausgangsrechnungen'!Q5) | H5: =IF(A5="","",'13_Ausgangsrechnungen'!S5) | I5: =IF(A5="","",'13_Ausgangsrechnungen'!J5) | J5: =IF(A5="","",'13_Ausgangsrechnungen'!T5) | L5: =IF('14_Eingangsrechnungen'!A5="","",IF('14_Eingangsrechnungen'!O5>0.5,"Kreditor","")) | M5: =IF(L5="","",'14_Eingangsrechnungen'!A5) | N5: =IF(L5="","",'14_Eingangsrechnungen'!B5) | O5: =IF(L5="","",'14_Eingangsrechnungen'!D5) | P5: =IF(L5="","",'14_Eingangsrechnungen'!C5) | Q5: =IF(L5="","",'14_Eingangsrechnungen'!E5) | R5: =IF(L5="","",'14_Eingangsrechnungen'!M5) | S5: =IF(L5="","",'14_Eingangsrechnungen'!O5) | T5: =IF(L5="","",'14_Eingangsrechnungen'!H5) | U5: =IF(L5="","",'14_Eingangsrechnungen'!P5)
A6: =IF('13_Ausgangsrechnungen'!A6="","",IF('13_Ausgangsrechnungen'!S6>0.5,"Debitor","")) | B6: =IF(A6="","",'13_Ausgangsrechnungen'!A6) | C6: =IF(A6="","",'13_Ausgangsrechnungen'!B6) | D6: =IF(A6="","",'13_Ausgangsrechnungen'!D6) | E6: =IF(A6="","",'13_Ausgangsrechnungen'!C6) | F6: =IF(A6="","",'13_Ausgangsrechnungen'!E6) | G6: =IF(A6="","",'13_Ausgangsrechnungen'!Q6) | H6: =IF(A6="","",'13_Ausgangsrechnungen'!S6) | I6: =IF(A6="","",'13_Ausgangsrechnungen'!J6) | J6: =IF(A6="","",'13_Ausgangsrechnungen'!T6) | L6: =IF('14_Eingangsrechnungen'!A6="","",IF('14_Eingangsrechnungen'!O6>0.5,"Kreditor","")) | M6: =IF(L6="","",'14_Eingangsrechnungen'!A6) | N6: =IF(L6="","",'14_Eingangsrechnungen'!B6) | O6: =IF(L6="","",'14_Eingangsrechnungen'!D6) | P6: =IF(L6="","",'14_Eingangsrechnungen'!C6) | Q6: =IF(L6="","",'14_Eingangsrechnungen'!E6) | R6: =IF(L6="","",'14_Eingangsrechnungen'!M6) | S6: =IF(L6="","",'14_Eingangsrechnungen'!O6) | T6: =IF(L6="","",'14_Eingangsrechnungen'!H6) | U6: =IF(L6="","",'14_Eingangsrechnungen'!P6)
A7: =IF('13_Ausgangsrechnungen'!A7="","",IF('13_Ausgangsrechnungen'!S7>0.5,"Debitor","")) | B7: =IF(A7="","",'13_Ausgangsrechnungen'!A7) | C7: =IF(A7="","",'13_Ausgangsrechnungen'!B7) | D7: =IF(A7="","",'13_Ausgangsrechnungen'!D7) | E7: =IF(A7="","",'13_Ausgangsrechnungen'!C7) | F7: =IF(A7="","",'13_Ausgangsrechnungen'!E7) | G7: =IF(A7="","",'13_Ausgangsrechnungen'!Q7) | H7: =IF(A7="","",'13_Ausgangsrechnungen'!S7) | I7: =IF(A7="","",'13_Ausgangsrechnungen'!J7) | J7: =IF(A7="","",'13_Ausgangsrechnungen'!T7) | L7: =IF('14_Eingangsrechnungen'!A7="","",IF('14_Eingangsrechnungen'!O7>0.5,"Kreditor","")) | M7: =IF(L7="","",'14_Eingangsrechnungen'!A7) | N7: =IF(L7="","",'14_Eingangsrechnungen'!B7) | O7: =IF(L7="","",'14_Eingangsrechnungen'!D7) | P7: =IF(L7="","",'14_Eingangsrechnungen'!C7) | Q7: =IF(L7="","",'14_Eingangsrechnungen'!E7) | R7: =IF(L7="","",'14_Eingangsrechnungen'!M7) | S7: =IF(L7="","",'14_Eingangsrechnungen'!O7) | T7: =IF(L7="","",'14_Eingangsrechnungen'!H7) | U7: =IF(L7="","",'14_Eingangsrechnungen'!P7)
A8: =IF('13_Ausgangsrechnungen'!A8="","",IF('13_Ausgangsrechnungen'!S8>0.5,"Debitor","")) | B8: =IF(A8="","",'13_Ausgangsrechnungen'!A8) | C8: =IF(A8="","",'13_Ausgangsrechnungen'!B8) | D8: =IF(A8="","",'13_Ausgangsrechnungen'!D8) | E8: =IF(A8="","",'13_Ausgangsrechnungen'!C8) | F8: =IF(A8="","",'13_Ausgangsrechnungen'!E8) | G8: =IF(A8="","",'13_Ausgangsrechnungen'!Q8) | H8: =IF(A8="","",'13_Ausgangsrechnungen'!S8) | I8: =IF(A8="","",'13_Ausgangsrechnungen'!J8) | J8: =IF(A8="","",'13_Ausgangsrechnungen'!T8) | L8: =IF('14_Eingangsrechnungen'!A8="","",IF('14_Eingangsrechnungen'!O8>0.5,"Kreditor","")) | M8: =IF(L8="","",'14_Eingangsrechnungen'!A8) | N8: =IF(L8="","",'14_Eingangsrechnungen'!B8) | O8: =IF(L8="","",'14_Eingangsrechnungen'!D8) | P8: =IF(L8="","",'14_Eingangsrechnungen'!C8) | Q8: =IF(L8="","",'14_Eingangsrechnungen'!E8) | R8: =IF(L8="","",'14_Eingangsrechnungen'!M8) | S8: =IF(L8="","",'14_Eingangsrechnungen'!O8) | T8: =IF(L8="","",'14_Eingangsrechnungen'!H8) | U8: =IF(L8="","",'14_Eingangsrechnungen'!P8)
A9: =IF('13_Ausgangsrechnungen'!A9="","",IF('13_Ausgangsrechnungen'!S9>0.5,"Debitor","")) | B9: =IF(A9="","",'13_Ausgangsrechnungen'!A9) | C9: =IF(A9="","",'13_Ausgangsrechnungen'!B9) | D9: =IF(A9="","",'13_Ausgangsrechnungen'!D9) | E9: =IF(A9="","",'13_Ausgangsrechnungen'!C9) | F9: =IF(A9="","",'13_Ausgangsrechnungen'!E9) | G9: =IF(A9="","",'13_Ausgangsrechnungen'!Q9) | H9: =IF(A9="","",'13_Ausgangsrechnungen'!S9) | I9: =IF(A9="","",'13_Ausgangsrechnungen'!J9) | J9: =IF(A9="","",'13_Ausgangsrechnungen'!T9) | L9: =IF('14_Eingangsrechnungen'!A9="","",IF('14_Eingangsrechnungen'!O9>0.5,"Kreditor","")) | M9: =IF(L9="","",'14_Eingangsrechnungen'!A9) | N9: =IF(L9="","",'14_Eingangsrechnungen'!B9) | O9: =IF(L9="","",'14_Eingangsrechnungen'!D9) | P9: =IF(L9="","",'14_Eingangsrechnungen'!C9) | Q9: =IF(L9="","",'14_Eingangsrechnungen'!E9) | R9: =IF(L9="","",'14_Eingangsrechnungen'!M9) | S9: =IF(L9="","",'14_Eingangsrechnungen'!O9) | T9: =IF(L9="","",'14_Eingangsrechnungen'!H9) | U9: =IF(L9="","",'14_Eingangsrechnungen'!P9)
A10: =IF('13_Ausgangsrechnungen'!A10="","",IF('13_Ausgangsrechnungen'!S10>0.5,"Debitor","")) | B10: =IF(A10="","",'13_Ausgangsrechnungen'!A10) | C10: =IF(A10="","",'13_Ausgangsrechnungen'!B10) | D10: =IF(A10="","",'13_Ausgangsrechnungen'!D10) | E10: =IF(A10="","",'13_Ausgangsrechnungen'!C10) | F10: =IF(A10="","",'13_Ausgangsrechnungen'!E10) | G10: =IF(A10="","",'13_Ausgangsrechnungen'!Q10) | H10: =IF(A10="","",'13_Ausgangsrechnungen'!S10) | I10: =IF(A10="","",'13_Ausgangsrechnungen'!J10) | J10: =IF(A10="","",'13_Ausgangsrechnungen'!T10) | L10: =IF('14_Eingangsrechnungen'!A10="","",IF('14_Eingangsrechnungen'!O10>0.5,"Kreditor","")) | M10: =IF(L10="","",'14_Eingangsrechnungen'!A10) | N10: =IF(L10="","",'14_Eingangsrechnungen'!B10) | O10: =IF(L10="","",'14_Eingangsrechnungen'!D10) | P10: =IF(L10="","",'14_Eingangsrechnungen'!C10) | Q10: =IF(L10="","",'14_Eingangsrechnungen'!E10) | R10: =IF(L10="","",'14_Eingangsrechnungen'!M10) | S10: =IF(L10="","",'14_Eingangsrechnungen'!O10) | T10: =IF(L10="","",'14_Eingangsrechnungen'!H10) | U10: =IF(L10="","",'14_Eingangsrechnungen'!P10)
A11: =IF('13_Ausgangsrechnungen'!A11="","",IF('13_Ausgangsrechnungen'!S11>0.5,"Debitor","")) | B11: =IF(A11="","",'13_Ausgangsrechnungen'!A11) | C11: =IF(A11="","",'13_Ausgangsrechnungen'!B11) | D11: =IF(A11="","",'13_Ausgangsrechnungen'!D11) | E11: =IF(A11="","",'13_Ausgangsrechnungen'!C11) | F11: =IF(A11="","",'13_Ausgangsrechnungen'!E11) | G11: =IF(A11="","",'13_Ausgangsrechnungen'!Q11) | H11: =IF(A11="","",'13_Ausgangsrechnungen'!S11) | I11: =IF(A11="","",'13_Ausgangsrechnungen'!J11) | J11: =IF(A11="","",'13_Ausgangsrechnungen'!T11) | L11: =IF('14_Eingangsrechnungen'!A11="","",IF('14_Eingangsrechnungen'!O11>0.5,"Kreditor","")) | M11: =IF(L11="","",'14_Eingangsrechnungen'!A11) | N11: =IF(L11="","",'14_Eingangsrechnungen'!B11) | O11: =IF(L11="","",'14_Eingangsrechnungen'!D11) | P11: =IF(L11="","",'14_Eingangsrechnungen'!C11) | Q11: =IF(L11="","",'14_Eingangsrechnungen'!E11) | R11: =IF(L11="","",'14_Eingangsrechnungen'!M11) | S11: =IF(L11="","",'14_Eingangsrechnungen'!O11) | T11: =IF(L11="","",'14_Eingangsrechnungen'!H11) | U11: =IF(L11="","",'14_Eingangsrechnungen'!P11)
A12: =IF('13_Ausgangsrechnungen'!A12="","",IF('13_Ausgangsrechnungen'!S12>0.5,"Debitor","")) | B12: =IF(A12="","",'13_Ausgangsrechnungen'!A12) | C12: =IF(A12="","",'13_Ausgangsrechnungen'!B12) | D12: =IF(A12="","",'13_Ausgangsrechnungen'!D12) | E12: =IF(A12="","",'13_Ausgangsrechnungen'!C12) | F12: =IF(A12="","",'13_Ausgangsrechnungen'!E12) | G12: =IF(A12="","",'13_Ausgangsrechnungen'!Q12) | H12: =IF(A12="","",'13_Ausgangsrechnungen'!S12) | I12: =IF(A12="","",'13_Ausgangsrechnungen'!J12) | J12: =IF(A12="","",'13_Ausgangsrechnungen'!T12) | L12: =IF('14_Eingangsrechnungen'!A12="","",IF('14_Eingangsrechnungen'!O12>0.5,"Kreditor","")) | M12: =IF(L12="","",'14_Eingangsrechnungen'!A12) | N12: =IF(L12="","",'14_Eingangsrechnungen'!B12) | O12: =IF(L12="","",'14_Eingangsrechnungen'!D12) | P12: =IF(L12="","",'14_Eingangsrechnungen'!C12) | Q12: =IF(L12="","",'14_Eingangsrechnungen'!E12) | R12: =IF(L12="","",'14_Eingangsrechnungen'!M12) | S12: =IF(L12="","",'14_Eingangsrechnungen'!O12) | T12: =IF(L12="","",'14_Eingangsrechnungen'!H12) | U12: =IF(L12="","",'14_Eingangsrechnungen'!P12)
A13: =IF('13_Ausgangsrechnungen'!A13="","",IF('13_Ausgangsrechnungen'!S13>0.5,"Debitor","")) | B13: =IF(A13="","",'13_Ausgangsrechnungen'!A13) | C13: =IF(A13="","",'13_Ausgangsrechnungen'!B13) | D13: =IF(A13="","",'13_Ausgangsrechnungen'!D13) | E13: =IF(A13="","",'13_Ausgangsrechnungen'!C13) | F13: =IF(A13="","",'13_Ausgangsrechnungen'!E13) | G13: =IF(A13="","",'13_Ausgangsrechnungen'!Q13) | H13: =IF(A13="","",'13_Ausgangsrechnungen'!S13) | I13: =IF(A13="","",'13_Ausgangsrechnungen'!J13) | J13: =IF(A13="","",'13_Ausgangsrechnungen'!T13) | L13: =IF('14_Eingangsrechnungen'!A13="","",IF('14_Eingangsrechnungen'!O13>0.5,"Kreditor","")) | M13: =IF(L13="","",'14_Eingangsrechnungen'!A13) | N13: =IF(L13="","",'14_Eingangsrechnungen'!B13) | O13: =IF(L13="","",'14_Eingangsrechnungen'!D13) | P13: =IF(L13="","",'14_Eingangsrechnungen'!C13) | Q13: =IF(L13="","",'14_Eingangsrechnungen'!E13) | R13: =IF(L13="","",'14_Eingangsrechnungen'!M13) | S13: =IF(L13="","",'14_Eingangsrechnungen'!O13) | T13: =IF(L13="","",'14_Eingangsrechnungen'!H13) | U13: =IF(L13="","",'14_Eingangsrechnungen'!P13)
A14: =IF('13_Ausgangsrechnungen'!A14="","",IF('13_Ausgangsrechnungen'!S14>0.5,"Debitor","")) | B14: =IF(A14="","",'13_Ausgangsrechnungen'!A14) | C14: =IF(A14="","",'13_Ausgangsrechnungen'!B14) | D14: =IF(A14="","",'13_Ausgangsrechnungen'!D14) | E14: =IF(A14="","",'13_Ausgangsrechnungen'!C14) | F14: =IF(A14="","",'13_Ausgangsrechnungen'!E14) | G14: =IF(A14="","",'13_Ausgangsrechnungen'!Q14) | H14: =IF(A14="","",'13_Ausgangsrechnungen'!S14) | I14: =IF(A14="","",'13_Ausgangsrechnungen'!J14) | J14: =IF(A14="","",'13_Ausgangsrechnungen'!T14) | L14: =IF('14_Eingangsrechnungen'!A14="","",IF('14_Eingangsrechnungen'!O14>0.5,"Kreditor","")) | M14: =IF(L14="","",'14_Eingangsrechnungen'!A14) | N14: =IF(L14="","",'14_Eingangsrechnungen'!B14) | O14: =IF(L14="","",'14_Eingangsrechnungen'!D14) | P14: =IF(L14="","",'14_Eingangsrechnungen'!C14) | Q14: =IF(L14="","",'14_Eingangsrechnungen'!E14) | R14: =IF(L14="","",'14_Eingangsrechnungen'!M14) | S14: =IF(L14="","",'14_Eingangsrechnungen'!O14) | T14: =IF(L14="","",'14_Eingangsrechnungen'!H14) | U14: =IF(L14="","",'14_Eingangsrechnungen'!P14)
A15: =IF('13_Ausgangsrechnungen'!A15="","",IF('13_Ausgangsrechnungen'!S15>0.5,"Debitor","")) | B15: =IF(A15="","",'13_Ausgangsrechnungen'!A15) | C15: =IF(A15="","",'13_Ausgangsrechnungen'!B15) | D15: =IF(A15="","",'13_Ausgangsrechnungen'!D15) | E15: =IF(A15="","",'13_Ausgangsrechnungen'!C15) | F15: =IF(A15="","",'13_Ausgangsrechnungen'!E15) | G15: =IF(A15="","",'13_Ausgangsrechnungen'!Q15) | H15: =IF(A15="","",'13_Ausgangsrechnungen'!S15) | I15: =IF(A15="","",'13_Ausgangsrechnungen'!J15) | J15: =IF(A15="","",'13_Ausgangsrechnungen'!T15) | L15: =IF('14_Eingangsrechnungen'!A15="","",IF('14_Eingangsrechnungen'!O15>0.5,"Kreditor","")) | M15: =IF(L15="","",'14_Eingangsrechnungen'!A15) | N15: =IF(L15="","",'14_Eingangsrechnungen'!B15) | O15: =IF(L15="","",'14_Eingangsrechnungen'!D15) | P15: =IF(L15="","",'14_Eingangsrechnungen'!C15) | Q15: =IF(L15="","",'14_Eingangsrechnungen'!E15) | R15: =IF(L15="","",'14_Eingangsrechnungen'!M15) | S15: =IF(L15="","",'14_Eingangsrechnungen'!O15) | T15: =IF(L15="","",'14_Eingangsrechnungen'!H15) | U15: =IF(L15="","",'14_Eingangsrechnungen'!P15)
... A400: =IF('13_Ausgangsrechnungen'!A400="","",IF('13_Ausgangsrechnungen'!S400>0.5,"Debitor","")) | B400: =IF(A400="","",'13_Ausgangsrechnungen'!A400) | C400: =IF(A400="","",'13_Ausgangsrechnungen'!B400) | D400: =IF(A400="","",'13_Ausgangsrechnungen'!D400) | E400: =IF(A400="","",'13_Ausgangsrechnungen'!C400) | F400: =IF(A400="","",'13_Ausgangsrechnungen'!E400) | G400: =IF(A400="","",'13_Ausgangsrechnungen'!Q400) | H400: =IF(A400="","",'13_Ausgangsrechnungen'!S400) | I400: =IF(A400="","",'13_Ausgangsrechnungen'!J400) | J400: =IF(A400="","",'13_Ausgangsrechnungen'!T400) | L400: =IF('14_Eingangsrechnungen'!A400="","",IF('14_Eingangsrechnungen'!O400>0.5,"Kreditor","")) | M400: =IF(L400="","",'14_Eingangsrechnungen'!A400) | N400: =IF(L400="","",'14_Eingangsrechnungen'!B400) | O400: =IF(L400="","",'14_Eingangsrechnungen'!D400) | P400: =IF(L400="","",'14_Eingangsrechnungen'!C400) | Q400: =IF(L400="","",'14_Eingangsrechnungen'!E400) | R400: =IF(L400="","",'14_Eingangsrechnungen'!M400) | S400: =IF(L400="","",'14_Eingangsrechnungen'!O400) | T400: =IF(L400="","",'14_Eingangsrechnungen'!H400) | U400: =IF(L400="","",'14_Eingangsrechnungen'!P400)

Sheet 13_Ausgangsrechnungen
A1: Ausgangsrechnungen (Abschlag, Anzahlung, Schluss)
A2: Einbehalt und USt rechnen automatisch · Bezahlt kommt aus dem Zahlungsblatt · Offen speist OPOS, Liquidität und Dashboard
A3: Nr | B3: Datum | C3: Projekt | D3: Kunde | E3: Typ | F3: Abschlag-Nr | G3: Netto | H3: Einbehalt % | I3: USt % | J3: Fällig | K3: Bezahlt am | L3: Status | M3: Text | N3: Einbehalt EUR | O3: Netto fällig | P3: USt EUR | Q3: Brutto | R3: Bezahlt | S3: Offen | T3: Tage überfällig
A4: AR-26001 | B4: 46081 | C4: P-2026-001 | D4: K-1001 | E4: Abschlag | F4: 1 | G4: 360000 | H4: 0.05 | I4: 0.19 | J4: 46111 | K4: 46105 | L4: bezahlt | M4: 1. Abschlag Rohbau | N4: =IF(A4="","",G4*H4) | O4: =IF(A4="","",G4-N4) | P4: =IF(A4="","",O4*I4) | Q4: =IF(A4="","",O4+P4) | R4: =IF(A4="","",SUMIFS('15_Zahlungen'!$F:$F,'15_Zahlungen'!$D:$D,A4,'15_Zahlungen'!$C:$C,"Eingang")) | S4: =IF(A4="","",MAX(0,Q4-R4)) | T4: =IF(OR(A4="",L4="bezahlt",J4=""),"",MAX(0,TODAY()-J4))
A5: AR-26002 | B5: 46142 | C5: P-2026-001 | D5: K-1001 | E5: Abschlag | F5: 2 | G5: 420000 | H5: 0.05 | I5: 0.19 | J5: 46172 | K5: 46164 | L5: bezahlt | M5: 2. Abschlag Geschosse | N5: =IF(A5="","",G5*H5) | O5: =IF(A5="","",G5-N5) | P5: =IF(A5="","",O5*I5) | Q5: =IF(A5="","",O5+P5) | R5: =IF(A5="","",SUMIFS('15_Zahlungen'!$F:$F,'15_Zahlungen'!$D:$D,A5,'15_Zahlungen'!$C:$C,"Eingang")) | S5: =IF(A5="","",MAX(0,Q5-R5)) | T5: =IF(OR(A5="",L5="bezahlt",J5=""),"",MAX(0,TODAY()-J5))
A6: AR-26003 | B6: 46234 | C6: P-2026-001 | D6: K-1001 | E6: Abschlag | F6: 3 | G6: 380000 | H6: 0.05 | I6: 0.19 | J6: 46264 | K6: 46269 | L6: bezahlt | M6: 3. Abschlag inkl. Nachtrag N-002 | N6: =IF(A6="","",G6*H6) | O6: =IF(A6="","",G6-N6) | P6: =IF(A6="","",O6*I6) | Q6: =IF(A6="","",O6+P6) | R6: =IF(A6="","",SUMIFS('15_Zahlungen'!$F:$F,'15_Zahlungen'!$D:$D,A6,'15_Zahlungen'!$C:$C,"Eingang")) | S6: =IF(A6="","",MAX(0,Q6-R6)) | T6: =IF(OR(A6="",L6="bezahlt",J6=""),"",MAX(0,TODAY()-J6))
A7: AR-26004 | B7: 46295 | C7: P-2026-001 | D7: K-1001 | E7: Abschlag | F7: 4 | G7: 310000 | H7: 0.05 | I7: 0.19 | J7: 46325 | L7: offen | M7: 4. Abschlag Dachbeginn | N7: =IF(A7="","",G7*H7) | O7: =IF(A7="","",G7-N7) | P7: =IF(A7="","",O7*I7) | Q7: =IF(A7="","",O7+P7) | R7: =IF(A7="","",SUMIFS('15_Zahlungen'!$F:$F,'15_Zahlungen'!$D:$D,A7,'15_Zahlungen'!$C:$C,"Eingang")) | S7: =IF(A7="","",MAX(0,Q7-R7)) | T7: =IF(OR(A7="",L7="bezahlt",J7=""),"",MAX(0,TODAY()-J7))
A8: AR-26005 | B8: 46127 | C8: P-2026-002 | D8: K-1003 | E8: Abschlag | F8: 1 | G8: 178000 | H8: 0.05 | I8: 0.19 | J8: 46148 | K8: 46144 | L8: bezahlt | M8: 1. Abschlag Kita | N8: =IF(A8="","",G8*H8) | O8: =IF(A8="","",G8-N8) | P8: =IF(A8="","",O8*I8) | Q8: =IF(A8="","",O8+P8) | R8: =IF(A8="","",SUMIFS('15_Zahlungen'!$F:$F,'15_Zahlungen'!$D:$D,A8,'15_Zahlungen'!$C:$C,"Eingang")) | S8: =IF(A8="","",MAX(0,Q8-R8)) | T8: =IF(OR(A8="",L8="bezahlt",J8=""),"",MAX(0,TODAY()-J8))
A9: AR-26006 | B9: 46223 | C9: P-2026-002 | D9: K-1003 | E9: Abschlag | F9: 2 | G9: 210000 | H9: 0.05 | I9: 0.19 | J9: 46244 | L9: gemahnt | M9: 2. Abschlag Rohbau | N9: =IF(A9="","",G9*H9) | O9: =IF(A9="","",G9-N9) | P9: =IF(A9="","",O9*I9) | Q9: =IF(A9="","",O9+P9) | R9: =IF(A9="","",SUMIFS('15_Zahlungen'!$F:$F,'15_Zahlungen'!$D:$D,A9,'15_Zahlungen'!$C:$C,"Eingang")) | S9: =IF(A9="","",MAX(0,Q9-R9)) | T9: =IF(OR(A9="",L9="bezahlt",J9=""),"",MAX(0,TODAY()-J9))
A10: AR-26007 | B10: 46173 | C10: P-2026-003 | D10: K-1002 | E10: Abschlag | F10: 1 | G10: 220000 | H10: 0.05 | I10: 0.19 | J10: 46218 | K10: 46214 | L10: bezahlt | M10: 1. Abschlag Rathaus | N10: =IF(A10="","",G10*H10) | O10: =IF(A10="","",G10-N10) | P10: =IF(A10="","",O10*I10) | Q10: =IF(A10="","",O10+P10) | R10: =IF(A10="","",SUMIFS('15_Zahlungen'!$F:$F,'15_Zahlungen'!$D:$D,A10,'15_Zahlungen'!$C:$C,"Eingang")) | S10: =IF(A10="","",MAX(0,Q10-R10)) | T10: =IF(OR(A10="",L10="bezahlt",J10=""),"",MAX(0,TODAY()-J10))
A11: AR-26008 | B11: 46265 | C11: P-2026-003 | D11: K-1002 | E11: Abschlag | F11: 2 | G11: 185000 | H11: 0.05 | I11: 0.19 | J11: 46310 | L11: offen | M11: 2. Abschlag Fassade | N11: =IF(A11="","",G11*H11) | O11: =IF(A11="","",G11-N11) | P11: =IF(A11="","",O11*I11) | Q11: =IF(A11="","",O11+P11) | R11: =IF(A11="","",SUMIFS('15_Zahlungen'!$F:$F,'15_Zahlungen'!$D:$D,A11,'15_Zahlungen'!$C:$C,"Eingang")) | S11: =IF(A11="","",MAX(0,Q11-R11)) | T11: =IF(OR(A11="",L11="bezahlt",J11=""),"",MAX(0,TODAY()-J11))
A12: AR-26009 | B12: 46203 | C12: P-2026-004 | D12: K-1004 | E12: Abschlag | F12: 1 | G12: 480000 | H12: 0.05 | I12: 0.19 | J12: 46233 | K12: 46224 | L12: bezahlt | M12: 1. Abschlag Erdbau/Bodenplatte | N12: =IF(A12="","",G12*H12) | O12: =IF(A12="","",G12-N12) | P12: =IF(A12="","",O12*I12) | Q12: =IF(A12="","",O12+P12) | R12: =IF(A12="","",SUMIFS('15_Zahlungen'!$F:$F,'15_Zahlungen'!$D:$D,A12,'15_Zahlungen'!$C:$C,"Eingang")) | S12: =IF(A12="","",MAX(0,Q12-R12)) | T12: =IF(OR(A12="",L12="bezahlt",J12=""),"",MAX(0,TODAY()-J12))
A13: AR-26010 | B13: 46280 | C13: P-2026-004 | D13: K-1004 | E13: Abschlag | F13: 2 | G13: 520000 | H13: 0.05 | I13: 0.19 | J13: 46310 | L13: offen | M13: 2. Abschlag Stahl | N13: =IF(A13="","",G13*H13) | O13: =IF(A13="","",G13-N13) | P13: =IF(A13="","",O13*I13) | Q13: =IF(A13="","",O13+P13) | R13: =IF(A13="","",SUMIFS('15_Zahlungen'!$F:$F,'15_Zahlungen'!$D:$D,A13,'15_Zahlungen'!$C:$C,"Eingang")) | S13: =IF(A13="","",MAX(0,Q13-R13)) | T13: =IF(OR(A13="",L13="bezahlt",J13=""),"",MAX(0,TODAY()-J13))
A14: AR-26011 | B14: 46053 | C14: P-2026-005 | D14: K-1005 | E14: Abschlag | F14: 3 | G14: 84000 | H14: 0.05 | I14: 0.19 | J14: 46067 | K14: 46063 | L14: bezahlt | M14: 3. Abschlag EFH | N14: =IF(A14="","",G14*H14) | O14: =IF(A14="","",G14-N14) | P14: =IF(A14="","",O14*I14) | Q14: =IF(A14="","",O14+P14) | R14: =IF(A14="","",SUMIFS('15_Zahlungen'!$F:$F,'15_Zahlungen'!$D:$D,A14,'15_Zahlungen'!$C:$C,"Eingang")) | S14: =IF(A14="","",MAX(0,Q14-R14)) | T14: =IF(OR(A14="",L14="bezahlt",J14=""),"",MAX(0,TODAY()-J14))
A15: AR-26012 | B15: 46136 | C15: P-2026-005 | D15: K-1005 | E15: Schluss | F15: 4 | G15: 126000 | H15: 0.05 | I15: 0.19 | J15: 46150 | K15: 46148 | L15: bezahlt | M15: Schlussrechnung EFH, Einbehalt 5 % | N15: =IF(A15="","",G15*H15) | O15: =IF(A15="","",G15-N15) | P15: =IF(A15="","",O15*I15) | Q15: =IF(A15="","",O15+P15) | R15: =IF(A15="","",SUMIFS('15_Zahlungen'!$F:$F,'15_Zahlungen'!$D:$D,A15,'15_Zahlungen'!$C:$C,"Eingang")) | S15: =IF(A15="","",MAX(0,Q15-R15)) | T15: =IF(OR(A15="",L15="bezahlt",J15=""),"",MAX(0,TODAY()-J15))
A16: AR-26013 | B16: 46300 | C16: P-2026-006 | D16: K-1006 | E16: Anzahlung | F16: 1 | G16: 180000 | H16: 0 | I16: 0.19 | J16: 46360 | L16: offen | M16: 1. Abschlag nach Baubeginn | N16: =IF(A16="","",G16*H16) | O16: =IF(A16="","",G16-N16) | P16: =IF(A16="","",O16*I16) | Q16: =IF(A16="","",O16+P16) | R16: =IF(A16="","",SUMIFS('15_Zahlungen'!$F:$F,'15_Zahlungen'!$D:$D,A16,'15_Zahlungen'!$C:$C,"Eingang")) | S16: =IF(A16="","",MAX(0,Q16-R16)) | T16: =IF(OR(A16="",L16="bezahlt",J16=""),"",MAX(0,TODAY()-J16))
N17: =IF(A17="","",G17*H17) | O17: =IF(A17="","",G17-N17) | P17: =IF(A17="","",O17*I17) | Q17: =IF(A17="","",O17+P17) | R17: =IF(A17="","",SUMIFS('15_Zahlungen'!$F:$F,'15_Zahlungen'!$D:$D,A17,'15_Zahlungen'!$C:$C,"Eingang")) | S17: =IF(A17="","",MAX(0,Q17-R17)) | T17: =IF(OR(A17="",L17="bezahlt",J17=""),"",MAX(0,TODAY()-J17))
N18: =IF(A18="","",G18*H18) | O18: =IF(A18="","",G18-N18) | P18: =IF(A18="","",O18*I18) | Q18: =IF(A18="","",O18+P18) | R18: =IF(A18="","",SUMIFS('15_Zahlungen'!$F:$F,'15_Zahlungen'!$D:$D,A18,'15_Zahlungen'!$C:$C,"Eingang")) | S18: =IF(A18="","",MAX(0,Q18-R18)) | T18: =IF(OR(A18="",L18="bezahlt",J18=""),"",MAX(0,TODAY()-J18))
N19: =IF(A19="","",G19*H19) | O19: =IF(A19="","",G19-N19) | P19: =IF(A19="","",O19*I19) | Q19: =IF(A19="","",O19+P19) | R19: =IF(A19="","",SUMIFS('15_Zahlungen'!$F:$F,'15_Zahlungen'!$D:$D,A19,'15_Zahlungen'!$C:$C,"Eingang")) | S19: =IF(A19="","",MAX(0,Q19-R19)) | T19: =IF(OR(A19="",L19="bezahlt",J19=""),"",MAX(0,TODAY()-J19))
N20: =IF(A20="","",G20*H20) | O20: =IF(A20="","",G20-N20) | P20: =IF(A20="","",O20*I20) | Q20: =IF(A20="","",O20+P20) | R20: =IF(A20="","",SUMIFS('15_Zahlungen'!$F:$F,'15_Zahlungen'!$D:$D,A20,'15_Zahlungen'!$C:$C,"Eingang")) | S20: =IF(A20="","",MAX(0,Q20-R20)) | T20: =IF(OR(A20="",L20="bezahlt",J20=""),"",MAX(0,TODAY()-J20))
N21: =IF(A21="","",G21*H21) | O21: =IF(A21="","",G21-N21) | P21: =IF(A21="","",O21*I21) | Q21: =IF(A21="","",O21+P21) | R21: =IF(A21="","",SUMIFS('15_Zahlungen'!$F:$F,'15_Zahlungen'!$D:$D,A21,'15_Zahlungen'!$C:$C,"Eingang")) | S21: =IF(A21="","",MAX(0,Q21-R21)) | T21: =IF(OR(A21="",L21="bezahlt",J21=""),"",MAX(0,TODAY()-J21))
N22: =IF(A22="","",G22*H22) | O22: =IF(A22="","",G22-N22) | P22: =IF(A22="","",O22*I22) | Q22: =IF(A22="","",O22+P22) | R22: =IF(A22="","",SUMIFS('15_Zahlungen'!$F:$F,'15_Zahlungen'!$D:$D,A22,'15_Zahlungen'!$C:$C,"Eingang")) | S22: =IF(A22="","",MAX(0,Q22-R22)) | T22: =IF(OR(A22="",L22="bezahlt",J22=""),"",MAX(0,TODAY()-J22))
N23: =IF(A23="","",G23*H23) | O23: =IF(A23="","",G23-N23) | P23: =IF(A23="","",O23*I23) | Q23: =IF(A23="","",O23+P23) | R23: =IF(A23="","",SUMIFS('15_Zahlungen'!$F:$F,'15_Zahlungen'!$D:$D,A23,'15_Zahlungen'!$C:$C,"Eingang")) | S23: =IF(A23="","",MAX(0,Q23-R23)) | T23: =IF(OR(A23="",L23="bezahlt",J23=""),"",MAX(0,TODAY()-J23))
N24: =IF(A24="","",G24*H24) | O24: =IF(A24="","",G24-N24) | P24: =IF(A24="","",O24*I24) | Q24: =IF(A24="","",O24+P24) | R24: =IF(A24="","",SUMIFS('15_Zahlungen'!$F:$F,'15_Zahlungen'!$D:$D,A24,'15_Zahlungen'!$C:$C,"Eingang")) | S24: =IF(A24="","",MAX(0,Q24-R24)) | T24: =IF(OR(A24="",L24="bezahlt",J24=""),"",MAX(0,TODAY()-J24))
N25: =IF(A25="","",G25*H25) | O25: =IF(A25="","",G25-N25) | P25: =IF(A25="","",O25*I25) | Q25: =IF(A25="","",O25+P25) | R25: =IF(A25="","",SUMIFS('15_Zahlungen'!$F:$F,'15_Zahlungen'!$D:$D,A25,'15_Zahlungen'!$C:$C,"Eingang")) | S25: =IF(A25="","",MAX(0,Q25-R25)) | T25: =IF(OR(A25="",L25="bezahlt",J25=""),"",MAX(0,TODAY()-J25))
N26: =IF(A26="","",G26*H26) | O26: =IF(A26="","",G26-N26) | P26: =IF(A26="","",O26*I26) | Q26: =IF(A26="","",O26+P26) | R26: =IF(A26="","",SUMIFS('15_Zahlungen'!$F:$F,'15_Zahlungen'!$D:$D,A26,'15_Zahlungen'!$C:$C,"Eingang")) | S26: =IF(A26="","",MAX(0,Q26-R26)) | T26: =IF(OR(A26="",L26="bezahlt",J26=""),"",MAX(0,TODAY()-J26))
N27: =IF(A27="","",G27*H27) | O27: =IF(A27="","",G27-N27) | P27: =IF(A27="","",O27*I27) | Q27: =IF(A27="","",O27+P27) | R27: =IF(A27="","",SUMIFS('15_Zahlungen'!$F:$F,'15_Zahlungen'!$D:$D,A27,'15_Zahlungen'!$C:$C,"Eingang")) | S27: =IF(A27="","",MAX(0,Q27-R27)) | T27: =IF(OR(A27="",L27="bezahlt",J27=""),"",MAX(0,TODAY()-J27))
N28: =IF(A28="","",G28*H28) | O28: =IF(A28="","",G28-N28) | P28: =IF(A28="","",O28*I28) | Q28: =IF(A28="","",O28+P28) | R28: =IF(A28="","",SUMIFS('15_Zahlungen'!$F:$F,'15_Zahlungen'!$D:$D,A28,'15_Zahlungen'!$C:$C,"Eingang")) | S28: =IF(A28="","",MAX(0,Q28-R28)) | T28: =IF(OR(A28="",L28="bezahlt",J28=""),"",MAX(0,TODAY()-J28))
... N400: =IF(A400="","",G400*H400) | O400: =IF(A400="","",G400-N400) | P400: =IF(A400="","",O400*I400) | Q400: =IF(A400="","",O400+P400) | R400: =IF(A400="","",SUMIFS('15_Zahlungen'!$F:$F,'15_Zahlungen'!$D:$D,A400,'15_Zahlungen'!$C:$C,"Eingang")) | S400: =IF(A400="","",MAX(0,Q400-R400)) | T400: =IF(OR(A400="",L400="bezahlt",J400=""),"",MAX(0,TODAY()-J400))

Sheet 14_Eingangsrechnungen
A1: Eingangsrechnungen / Kreditoren
A2: Material, Nachunternehmer, Gerät — steuert Cash-out, BWA und offene Verbindlichkeiten
A3: Nr | B3: Datum | C3: Projekt | D3: Lieferant | E3: Typ | F3: Netto | G3: USt % | H3: Fällig | I3: Bezahlt am | J3: Status | K3: Text | L3: USt EUR | M3: Brutto | N3: Bezahlt | O3: Offen | P3: Tage überfällig
A4: ER-5401 | B4: 46225 | C4: P-2026-005 | D4: L-2001 | E4: Material | F4: 3441 | G4: 0.19 | H4: 46255 | I4: 46246 | J4: bezahlt | K4: Estrich | L4: =IF(A4="","",F4*G4) | M4: =IF(A4="","",F4+L4) | N4: =IF(A4="","",SUMIFS('15_Zahlungen'!$F:$F,'15_Zahlungen'!$D:$D,A4,'15_Zahlungen'!$C:$C,"Ausgang")) | O4: =IF(A4="","",MAX(0,M4-N4)) | P4: =IF(OR(A4="",J4="bezahlt",H4=""),"",MAX(0,TODAY()-H4))
A5: ER-5512 | B5: 46246 | C5: P-2026-001 | D5: L-2001 | E5: Material | F5: 12212 | G5: 0.19 | H5: 46276 | I5: 46269 | J5: bezahlt | K5: Transportbeton | L5: =IF(A5="","",F5*G5) | M5: =IF(A5="","",F5+L5) | N5: =IF(A5="","",SUMIFS('15_Zahlungen'!$F:$F,'15_Zahlungen'!$D:$D,A5,'15_Zahlungen'!$C:$C,"Ausgang")) | O5: =IF(A5="","",MAX(0,M5-N5)) | P5: =IF(OR(A5="",J5="bezahlt",H5=""),"",MAX(0,TODAY()-H5))
A6: ER-5518 | B6: 46248 | C6: P-2026-001 | D6: L-2002 | E6: Material | F6: 12152 | G6: 0.19 | H6: 46278 | I6: 46262 | J6: bezahlt | K6: Betonstahl Skonto | L6: =IF(A6="","",F6*G6) | M6: =IF(A6="","",F6+L6) | N6: =IF(A6="","",SUMIFS('15_Zahlungen'!$F:$F,'15_Zahlungen'!$D:$D,A6,'15_Zahlungen'!$C:$C,"Ausgang")) | O6: =IF(A6="","",MAX(0,M6-N6)) | P6: =IF(OR(A6="",J6="bezahlt",H6=""),"",MAX(0,TODAY()-H6))
A7: ER-5531 | B7: 46254 | C7: P-2026-002 | D7: L-2001 | E7: Material | F7: 4692 | G7: 0.19 | H7: 46284 | J7: offen | K7: Beton Kita | L7: =IF(A7="","",F7*G7) | M7: =IF(A7="","",F7+L7) | N7: =IF(A7="","",SUMIFS('15_Zahlungen'!$F:$F,'15_Zahlungen'!$D:$D,A7,'15_Zahlungen'!$C:$C,"Ausgang")) | O7: =IF(A7="","",MAX(0,M7-N7)) | P7: =IF(OR(A7="",J7="bezahlt",H7=""),"",MAX(0,TODAY()-H7))
A8: ER-5540 | B8: 46259 | C8: P-2026-001 | D8: L-2003 | E8: Nachunternehmer | F8: 28600 | G8: 0.19 | H8: 46280 | J8: offen | K8: Elektro Steigstränge | L8: =IF(A8="","",F8*G8) | M8: =IF(A8="","",F8+L8) | N8: =IF(A8="","",SUMIFS('15_Zahlungen'!$F:$F,'15_Zahlungen'!$D:$D,A8,'15_Zahlungen'!$C:$C,"Ausgang")) | O8: =IF(A8="","",MAX(0,M8-N8)) | P8: =IF(OR(A8="",J8="bezahlt",H8=""),"",MAX(0,TODAY()-H8))
A9: ER-5555 | B9: 46262 | C9: P-2026-003 | D9: L-2004 | E9: Nachunternehmer | F9: 19400 | G9: 0.19 | H9: 46283 | I9: 46275 | J9: bezahlt | K9: HLS 1. Rate | L9: =IF(A9="","",F9*G9) | M9: =IF(A9="","",F9+L9) | N9: =IF(A9="","",SUMIFS('15_Zahlungen'!$F:$F,'15_Zahlungen'!$D:$D,A9,'15_Zahlungen'!$C:$C,"Ausgang")) | O9: =IF(A9="","",MAX(0,M9-N9)) | P9: =IF(OR(A9="",J9="bezahlt",H9=""),"",MAX(0,TODAY()-H9))
A10: ER-5602 | B10: 46267 | C10: P-2026-004 | D10: L-2002 | E10: Material | F10: 26412 | G10: 0.19 | H10: 46297 | J10: offen | K10: Stahlträger | L10: =IF(A10="","",F10*G10) | M10: =IF(A10="","",F10+L10) | N10: =IF(A10="","",SUMIFS('15_Zahlungen'!$F:$F,'15_Zahlungen'!$D:$D,A10,'15_Zahlungen'!$C:$C,"Ausgang")) | O10: =IF(A10="","",MAX(0,M10-N10)) | P10: =IF(OR(A10="",J10="bezahlt",H10=""),"",MAX(0,TODAY()-H10))
A11: ER-5610 | B11: 46270 | C11: P-2026-003 | D11: L-2007 | E11: Nachunternehmer | F11: 4800 | G11: 0.19 | H11: 46284 | J11: offen | K11: Gerüstmiete | L11: =IF(A11="","",F11*G11) | M11: =IF(A11="","",F11+L11) | N11: =IF(A11="","",SUMIFS('15_Zahlungen'!$F:$F,'15_Zahlungen'!$D:$D,A11,'15_Zahlungen'!$C:$C,"Ausgang")) | O11: =IF(A11="","",MAX(0,M11-N11)) | P11: =IF(OR(A11="",J11="bezahlt",H11=""),"",MAX(0,TODAY()-H11))
A12: ER-5622 | B12: 46273 | C12: Allgemein | D12: L-2005 | E12: Gerät | F12: 6200 | G12: 0.19 | H12: 46287 | J12: offen | K12: Kranmiete September | L12: =IF(A12="","",F12*G12) | M12: =IF(A12="","",F12+L12) | N12: =IF(A12="","",SUMIFS('15_Zahlungen'!$F:$F,'15_Zahlungen'!$D:$D,A12,'15_Zahlungen'!$C:$C,"Ausgang")) | O12: =IF(A12="","",MAX(0,M12-N12)) | P12: =IF(OR(A12="",J12="bezahlt",H12=""),"",MAX(0,TODAY()-H12))
A13: ER-5630 | B13: 46275 | C13: P-2026-002 | D13: L-2004 | E13: Nachunternehmer | F13: 15800 | G13: 0.19 | H13: 46296 | J13: offen | K13: HLS Kita | L13: =IF(A13="","",F13*G13) | M13: =IF(A13="","",F13+L13) | N13: =IF(A13="","",SUMIFS('15_Zahlungen'!$F:$F,'15_Zahlungen'!$D:$D,A13,'15_Zahlungen'!$C:$C,"Ausgang")) | O13: =IF(A13="","",MAX(0,M13-N13)) | P13: =IF(OR(A13="",J13="bezahlt",H13=""),"",MAX(0,TODAY()-H13))
L14: =IF(A14="","",F14*G14) | M14: =IF(A14="","",F14+L14) | N14: =IF(A14="","",SUMIFS('15_Zahlungen'!$F:$F,'15_Zahlungen'!$D:$D,A14,'15_Zahlungen'!$C:$C,"Ausgang")) | O14: =IF(A14="","",MAX(0,M14-N14)) | P14: =IF(OR(A14="",J14="bezahlt",H14=""),"",MAX(0,TODAY()-H14))
L15: =IF(A15="","",F15*G15) | M15: =IF(A15="","",F15+L15) | N15: =IF(A15="","",SUMIFS('15_Zahlungen'!$F:$F,'15_Zahlungen'!$D:$D,A15,'15_Zahlungen'!$C:$C,"Ausgang")) | O15: =IF(A15="","",MAX(0,M15-N15)) | P15: =IF(OR(A15="",J15="bezahlt",H15=""),"",MAX(0,TODAY()-H15))
L16: =IF(A16="","",F16*G16) | M16: =IF(A16="","",F16+L16) | N16: =IF(A16="","",SUMIFS('15_Zahlungen'!$F:$F,'15_Zahlungen'!$D:$D,A16,'15_Zahlungen'!$C:$C,"Ausgang")) | O16: =IF(A16="","",MAX(0,M16-N16)) | P16: =IF(OR(A16="",J16="bezahlt",H16=""),"",MAX(0,TODAY()-H16))
L17: =IF(A17="","",F17*G17) | M17: =IF(A17="","",F17+L17) | N17: =IF(A17="","",SUMIFS('15_Zahlungen'!$F:$F,'15_Zahlungen'!$D:$D,A17,'15_Zahlungen'!$C:$C,"Ausgang")) | O17: =IF(A17="","",MAX(0,M17-N17)) | P17: =IF(OR(A17="",J17="bezahlt",H17=""),"",MAX(0,TODAY()-H17))
L18: =IF(A18="","",F18*G18) | M18: =IF(A18="","",F18+L18) | N18: =IF(A18="","",SUMIFS('15_Zahlungen'!$F:$F,'15_Zahlungen'!$D:$D,A18,'15_Zahlungen'!$C:$C,"Ausgang")) | O18: =IF(A18="","",MAX(0,M18-N18)) | P18: =IF(OR(A18="",J18="bezahlt",H18=""),"",MAX(0,TODAY()-H18))
L19: =IF(A19="","",F19*G19) | M19: =IF(A19="","",F19+L19) | N19: =IF(A19="","",SUMIFS('15_Zahlungen'!$F:$F,'15_Zahlungen'!$D:$D,A19,'15_Zahlungen'!$C:$C,"Ausgang")) | O19: =IF(A19="","",MAX(0,M19-N19)) | P19: =IF(OR(A19="",J19="bezahlt",H19=""),"",MAX(0,TODAY()-H19))
L20: =IF(A20="","",F20*G20) | M20: =IF(A20="","",F20+L20) | N20: =IF(A20="","",SUMIFS('15_Zahlungen'!$F:$F,'15_Zahlungen'!$D:$D,A20,'15_Zahlungen'!$C:$C,"Ausgang")) | O20: =IF(A20="","",MAX(0,M20-N20)) | P20: =IF(OR(A20="",J20="bezahlt",H20=""),"",MAX(0,TODAY()-H20))
L21: =IF(A21="","",F21*G21) | M21: =IF(A21="","",F21+L21) | N21: =IF(A21="","",SUMIFS('15_Zahlungen'!$F:$F,'15_Zahlungen'!$D:$D,A21,'15_Zahlungen'!$C:$C,"Ausgang")) | O21: =IF(A21="","",MAX(0,M21-N21)) | P21: =IF(OR(A21="",J21="bezahlt",H21=""),"",MAX(0,TODAY()-H21))
L22: =IF(A22="","",F22*G22) | M22: =IF(A22="","",F22+L22) | N22: =IF(A22="","",SUMIFS('15_Zahlungen'!$F:$F,'15_Zahlungen'!$D:$D,A22,'15_Zahlungen'!$C:$C,"Ausgang")) | O22: =IF(A22="","",MAX(0,M22-N22)) | P22: =IF(OR(A22="",J22="bezahlt",H22=""),"",MAX(0,TODAY()-H22))
L23: =IF(A23="","",F23*G23) | M23: =IF(A23="","",F23+L23) | N23: =IF(A23="","",SUMIFS('15_Zahlungen'!$F:$F,'15_Zahlungen'!$D:$D,A23,'15_Zahlungen'!$C:$C,"Ausgang")) | O23: =IF(A23="","",MAX(0,M23-N23)) | P23: =IF(OR(A23="",J23="bezahlt",H23=""),"",MAX(0,TODAY()-H23))
L24: =IF(A24="","",F24*G24) | M24: =IF(A24="","",F24+L24) | N24: =IF(A24="","",SUMIFS('15_Zahlungen'!$F:$F,'15_Zahlungen'!$D:$D,A24,'15_Zahlungen'!$C:$C,"Ausgang")) | O24: =IF(A24="","",MAX(0,M24-N24)) | P24: =IF(OR(A24="",J24="bezahlt",H24=""),"",MAX(0,TODAY()-H24))
L25: =IF(A25="","",F25*G25) | M25: =IF(A25="","",F25+L25) | N25: =IF(A25="","",SUMIFS('15_Zahlungen'!$F:$F,'15_Zahlungen'!$D:$D,A25,'15_Zahlungen'!$C:$C,"Ausgang")) | O25: =IF(A25="","",MAX(0,M25-N25)) | P25: =IF(OR(A25="",J25="bezahlt",H25=""),"",MAX(0,TODAY()-H25))
... L400: =IF(A400="","",F400*G400) | M400: =IF(A400="","",F400+L400) | N400: =IF(A400="","",SUMIFS('15_Zahlungen'!$F:$F,'15_Zahlungen'!$D:$D,A400,'15_Zahlungen'!$C:$C,"Ausgang")) | O400: =IF(A400="","",MAX(0,M400-N400)) | P400: =IF(OR(A400="",J400="bezahlt",H400=""),"",MAX(0,TODAY()-H400))

Sheet 15_Zahlungen
A1: Zahlungen und Bankumsätze
A2: Importziel für Bank-CSV · Belegnummer verknüpft automatisch Debitoren- und Kreditoren-OP
A3: Nr | B3: Datum | C3: Art | D3: Beleg | E3: Partner | F3: Betrag | G3: Weg | H3: Text | I3: Monat | J3: Jahr
A4: Z-001 | B4: 46105 | C4: Eingang | D4: AR-26001 | E4: K-1001 | F4: 406980 | G4: Bank | H4: Wohnquartier Abschlag 1 | I4: =IF(B4="","",MONTH(B4)) | J4: =IF(B4="","",YEAR(B4))
A5: Z-002 | B5: 46164 | C5: Eingang | D5: AR-26002 | E5: K-1001 | F5: 474810 | G5: Bank | H5: Wohnquartier Abschlag 2 | I5: =IF(B5="","",MONTH(B5)) | J5: =IF(B5="","",YEAR(B5))
A6: Z-003 | B6: 46144 | C6: Eingang | D6: AR-26005 | E6: K-1003 | F6: 201249 | G6: Bank | H6: Kita Abschlag 1 | I6: =IF(B6="","",MONTH(B6)) | J6: =IF(B6="","",YEAR(B6))
A7: Z-004 | B7: 46214 | C7: Eingang | D7: AR-26007 | E7: K-1002 | F7: 248710 | G7: Bank | H7: Rathaus Abschlag 1 | I7: =IF(B7="","",MONTH(B7)) | J7: =IF(B7="","",YEAR(B7))
A8: Z-005 | B8: 46224 | C8: Eingang | D8: AR-26009 | E8: K-1004 | F8: 542640 | G8: Bank | H8: Halle Abschlag 1 | I8: =IF(B8="","",MONTH(B8)) | J8: =IF(B8="","",YEAR(B8))
A9: Z-006 | B9: 46063 | C9: Eingang | D9: AR-26011 | E9: K-1005 | F9: 94962 | G9: Bank | H9: EFH Abschlag 3 | I9: =IF(B9="","",MONTH(B9)) | J9: =IF(B9="","",YEAR(B9))
A10: Z-007 | B10: 46148 | C10: Eingang | D10: AR-26012 | E10: K-1005 | F10: 142443 | G10: Bank | H10: EFH Schluss | I10: =IF(B10="","",MONTH(B10)) | J10: =IF(B10="","",YEAR(B10))
A11: Z-008 | B11: 46269 | C11: Eingang | D11: AR-26003 | E11: K-1001 | F11: 429570 | G11: Bank | H11: Wohnquartier Abschlag 3 | I11: =IF(B11="","",MONTH(B11)) | J11: =IF(B11="","",YEAR(B11))
A12: Z-009 | B12: 46246 | C12: Ausgang | D12: ER-5401 | E12: L-2001 | F12: 4094.79 | G12: Bank | H12: Estrich | I12: =IF(B12="","",MONTH(B12)) | J12: =IF(B12="","",YEAR(B12))
A13: Z-010 | B13: 46269 | C13: Ausgang | D13: ER-5512 | E13: L-2001 | F13: 14532.28 | G13: Bank | H13: Transportbeton | I13: =IF(B13="","",MONTH(B13)) | J13: =IF(B13="","",YEAR(B13))
A14: Z-011 | B14: 46262 | C14: Ausgang | D14: ER-5518 | E14: L-2002 | F14: 14043.56 | G14: Bank | H14: Stahl inkl. Skonto | I14: =IF(B14="","",MONTH(B14)) | J14: =IF(B14="","",YEAR(B14))
A15: Z-012 | B15: 46275 | C15: Ausgang | D15: ER-5555 | E15: L-2004 | F15: 23086 | G15: Bank | H15: HLS Rathaus | I15: =IF(B15="","",MONTH(B15)) | J15: =IF(B15="","",YEAR(B15))
A16: Z-013 | B16: 46265 | C16: Ausgang | E16: Personal | F16: 68420 | G16: Bank | H16: Löhne August | I16: =IF(B16="","",MONTH(B16)) | J16: =IF(B16="","",YEAR(B16))
A17: Z-014 | B17: 46249 | C17: Ausgang | E17: Finanzamt | F17: 18640 | G17: Bank | H17: USt-Vorauszahlung Juli | I17: =IF(B17="","",MONTH(B17)) | J17: =IF(B17="","",YEAR(B17))
A18: Z-015 | B18: 46295 | C18: Ausgang | E18: Personal | F18: 69110 | G18: Bank | H18: Löhne September | I18: =IF(B18="","",MONTH(B18)) | J18: =IF(B18="","",YEAR(B18))
A19: Z-016 | B19: 46277 | C19: Ausgang | E19: Sozialkasse | F19: 12480 | G19: Bank | H19: Soka-Bau / BG Bau | I19: =IF(B19="","",MONTH(B19)) | J19: =IF(B19="","",YEAR(B19))
I20: =IF(B20="","",MONTH(B20)) | J20: =IF(B20="","",YEAR(B20))
I21: =IF(B21="","",MONTH(B21)) | J21: =IF(B21="","",YEAR(B21))
I22: =IF(B22="","",MONTH(B22)) | J22: =IF(B22="","",YEAR(B22))
I23: =IF(B23="","",MONTH(B23)) | J23: =IF(B23="","",YEAR(B23))
I24: =IF(B24="","",MONTH(B24)) | J24: =IF(B24="","",YEAR(B24))
I25: =IF(B25="","",MONTH(B25)) | J25: =IF(B25="","",YEAR(B25))
I26: =IF(B26="","",MONTH(B26)) | J26: =IF(B26="","",YEAR(B26))
I27: =IF(B27="","",MONTH(B27)) | J27: =IF(B27="","",YEAR(B27))
I28: =IF(B28="","",MONTH(B28)) | J28: =IF(B28="","",YEAR(B28))
I29: =IF(B29="","",MONTH(B29)) | J29: =IF(B29="","",YEAR(B29))
I30: =IF(B30="","",MONTH(B30)) | J30: =IF(B30="","",YEAR(B30))
I31: =IF(B31="","",MONTH(B31)) | J31: =IF(B31="","",YEAR(B31))
... I400: =IF(B400="","",MONTH(B400)) | J400: =IF(B400="","",YEAR(B400))

Sheet 17_Mahnwesen
A1: Mahnwesen
A2: Stufe und Frist · offener Rechnungsbetrag wird gezogen · Formular 29_Form_Mahnung druckt die gewählte Mahnung
A3: Nr | B3: Rechnung | C3: Kunde | D3: Datum | E3: Stufe | F3: Frist Tage | G3: Art | H3: Status | I3: Text | J3: Fällig Mahnung | K3: Rechnungs-Offen
A4: MAH-01 | B4: AR-26006 | C4: K-1003 | D4: 46259 | E4: 1 | F4: 21 | G4: 1. Mahnung | H4: offen | I4: Zahlungserinnerung Kita | J4: =IF(A4="","",D4+F4) | K4: =IF(A4="","",IFERROR(VLOOKUP(B4,'13_Ausgangsrechnungen'!$A$4:$S$400,19,FALSE),0))
A5: MAH-02 | B5: AR-26006 | C5: K-1003 | D5: 46285 | E5: 2 | F5: 14 | G5: 2. Mahnung + Verzug | H5: offen | I5: Frist 04.10.2026 | J5: =IF(A5="","",D5+F5) | K5: =IF(A5="","",IFERROR(VLOOKUP(B5,'13_Ausgangsrechnungen'!$A$4:$S$400,19,FALSE),0))
J6: =IF(A6="","",D6+F6) | K6: =IF(A6="","",IFERROR(VLOOKUP(B6,'13_Ausgangsrechnungen'!$A$4:$S$400,19,FALSE),0))
J7: =IF(A7="","",D7+F7) | K7: =IF(A7="","",IFERROR(VLOOKUP(B7,'13_Ausgangsrechnungen'!$A$4:$S$400,19,FALSE),0))
J8: =IF(A8="","",D8+F8) | K8: =IF(A8="","",IFERROR(VLOOKUP(B8,'13_Ausgangsrechnungen'!$A$4:$S$400,19,FALSE),0))
J9: =IF(A9="","",D9+F9) | K9: =IF(A9="","",IFERROR(VLOOKUP(B9,'13_Ausgangsrechnungen'!$A$4:$S$400,19,FALSE),0))
J10: =IF(A10="","",D10+F10) | K10: =IF(A10="","",IFERROR(VLOOKUP(B10,'13_Ausgangsrechnungen'!$A$4:$S$400,19,FALSE),0))
J11: =IF(A11="","",D11+F11) | K11: =IF(A11="","",IFERROR(VLOOKUP(B11,'13_Ausgangsrechnungen'!$A$4:$S$400,19,FALSE),0))
J12: =IF(A12="","",D12+F12) | K12: =IF(A12="","",IFERROR(VLOOKUP(B12,'13_Ausgangsrechnungen'!$A$4:$S$400,19,FALSE),0))
J13: =IF(A13="","",D13+F13) | K13: =IF(A13="","",IFERROR(VLOOKUP(B13,'13_Ausgangsrechnungen'!$A$4:$S$400,19,FALSE),0))
J14: =IF(A14="","",D14+F14) | K14: =IF(A14="","",IFERROR(VLOOKUP(B14,'13_Ausgangsrechnungen'!$A$4:$S$400,19,FALSE),0))
J15: =IF(A15="","",D15+F15) | K15: =IF(A15="","",IFERROR(VLOOKUP(B15,'13_Ausgangsrechnungen'!$A$4:$S$400,19,FALSE),0))
J16: =IF(A16="","",D16+F16) | K16: =IF(A16="","",IFERROR(VLOOKUP(B16,'13_Ausgangsrechnungen'!$A$4:$S$400,19,FALSE),0))
J17: =IF(A17="","",D17+F17) | K17: =IF(A17="","",IFERROR(VLOOKUP(B17,'13_Ausgangsrechnungen'!$A$4:$S$400,19,FALSE),0))
... J400: =IF(A400="","",D400+F400) | K400: =IF(A400="","",IFERROR(VLOOKUP(B400,'13_Ausgangsrechnungen'!$A$4:$S$400,19,FALSE),0))

Sheet 18_Gewaehrleistung
A1: Sicherheitseinbehalte und Gewährleistung
A2: Einbehalte, Bürgschaften, Aval — Restlaufzeit steuert die Liquiditätsbindung nach Abnahme
A3: Nr | B3: Projekt | C3: Beleg | D3: Beginn | E3: Ende | F3: Betrag | G3: Art | H3: Status | I3: Text | J3: Restlaufzeit Jahre
A4: GW-01 | B4: P-2026-005 | C4: AR-26012 | D4: 46134 | E4: 47959 | F4: 21000 | G4: Einbehalt | H4: laufend | I4: 5 % Schlussrechnung EFH | J4: =IF(A4="","",MAX(0,(E4-TODAY())/365))
A5: GW-02 | B5: P-2026-001 | C5: AR-26001 | D5: 46105 | E5: 48182 | F5: 18000 | G5: Einbehalt | H5: laufend | I5: kumuliert Abschläge Wohnquartier | J5: =IF(A5="","",MAX(0,(E5-TODAY())/365))
A6: GW-03 | B6: P-2026-001 | C6: AR-26002 | D6: 46164 | E6: 48182 | F6: 21000 | G6: Einbehalt | H6: laufend | J6: =IF(A6="","",MAX(0,(E6-TODAY())/365))
A7: GW-04 | B7: P-2026-001 | C7: AR-26003 | D7: 46269 | E7: 48182 | F7: 19000 | G7: Einbehalt | H7: laufend | J7: =IF(A7="","",MAX(0,(E7-TODAY())/365))
J8: =IF(A8="","",MAX(0,(E8-TODAY())/365))
J9: =IF(A9="","",MAX(0,(E9-TODAY())/365))
J10: =IF(A10="","",MAX(0,(E10-TODAY())/365))
J11: =IF(A11="","",MAX(0,(E11-TODAY())/365))
J12: =IF(A12="","",MAX(0,(E12-TODAY())/365))
J13: =IF(A13="","",MAX(0,(E13-TODAY())/365))
J14: =IF(A14="","",MAX(0,(E14-TODAY())/365))
J15: =IF(A15="","",MAX(0,(E15-TODAY())/365))
J16: =IF(A16="","",MAX(0,(E16-TODAY())/365))
J17: =IF(A17="","",MAX(0,(E17-TODAY())/365))
J18: =IF(A18="","",MAX(0,(E18-TODAY())/365))
J19: =IF(A19="","",MAX(0,(E19-TODAY())/365))
... J400: =IF(A400="","",MAX(0,(E400-TODAY())/365))

Sheet 08_Angebote
A1: Angebotsverfolgung
A2: Hit-Rate, Bindefrist und Zuschläge AGK / Wagnis+Gewinn aus Stammdaten vorbelegt
A3: Nr | B3: Datum | C3: Kunde | D3: Projekt | E3: Bezeichnung | F3: Netto | G3: AGK % | H3: W+G % | I3: Status | J3: Entscheidung | K3: Bindefrist Tage | L3: Angebotssumme inkl. Zuschlag | M3: Hit-Rate-Hilfe
A4: AN-26001 | B4: 45979 | C4: K-1001 | D4: P-2026-001 | E4: Wohnquartier Am Park | F4: 2400000 | G4: 0.12 | H4: 0.05 | I4: angenommen | J4: 46000 | K4: 90 | L4: =IF(A4="","",F4*(1+G4)*(1+H4)) | M4: =IF(A4="","",IF(I4="angenommen","Auftrag",IF(AND(I4="offen",TODAY()>B4+K4),"Bindefrist!","")))
A5: AN-26002 | B5: 46036 | C5: K-1003 | D5: P-2026-002 | E5: Kita Sonnenweg | F5: 890000 | G5: 0.12 | H5: 0.05 | I5: angenommen | J5: 46063 | K5: 60 | L5: =IF(A5="","",F5*(1+G5)*(1+H5)) | M5: =IF(A5="","",IF(I5="angenommen","Auftrag",IF(AND(I5="offen",TODAY()>B5+K5),"Bindefrist!","")))
A6: AN-26003 | B6: 46030 | C6: K-1002 | D6: P-2026-003 | E6: Sanierung Rathaus | F6: 1100000 | G6: 0.14 | H6: 0.06 | I6: angenommen | J6: 46055 | K6: 90 | L6: =IF(A6="","",F6*(1+G6)*(1+H6)) | M6: =IF(A6="","",IF(I6="angenommen","Auftrag",IF(AND(I6="offen",TODAY()>B6+K6),"Bindefrist!","")))
A7: AN-26004 | B7: 46073 | C7: K-1004 | D7: P-2026-004 | E7: Gewerbehalle Nord | F7: 3200000 | G7: 0.11 | H7: 0.05 | I7: angenommen | J7: 46099 | K7: 90 | L7: =IF(A7="","",F7*(1+G7)*(1+H7)) | M7: =IF(A7="","",IF(I7="angenommen","Auftrag",IF(AND(I7="offen",TODAY()>B7+K7),"Bindefrist!","")))
A8: AN-26005 | B8: 45840 | C8: K-1005 | D8: P-2026-005 | E8: EFH Familie Huber | F8: 420000 | G8: 0.13 | H8: 0.05 | I8: angenommen | J8: 45860 | K8: 30 | L8: =IF(A8="","",F8*(1+G8)*(1+H8)) | M8: =IF(A8="","",IF(I8="angenommen","Auftrag",IF(AND(I8="offen",TODAY()>B8+K8),"Bindefrist!","")))
A9: AN-26006 | B9: 46184 | C9: K-1006 | D9: P-2026-006 | E9: Straßenbau B13 | F9: 1800000 | G9: 0.1 | H9: 0.05 | I9: angenommen | J9: 46246 | K9: 120 | L9: =IF(A9="","",F9*(1+G9)*(1+H9)) | M9: =IF(A9="","",IF(I9="angenommen","Auftrag",IF(AND(I9="offen",TODAY()>B9+K9),"Bindefrist!","")))
A10: AN-26007 | B10: 46273 | C10: K-1001 | E10: Wohnquartier Phase 2 | F10: 1650000 | G10: 0.12 | H10: 0.05 | I10: offen | K10: 60 | L10: =IF(A10="","",F10*(1+G10)*(1+H10)) | M10: =IF(A10="","",IF(I10="angenommen","Auftrag",IF(AND(I10="offen",TODAY()>B10+K10),"Bindefrist!","")))
A11: AN-26008 | B11: 46287 | C11: K-1004 | E11: Büroanbau Halle Nord | F11: 480000 | G11: 0.12 | H11: 0.05 | I11: offen | K11: 45 | L11: =IF(A11="","",F11*(1+G11)*(1+H11)) | M11: =IF(A11="","",IF(I11="angenommen","Auftrag",IF(AND(I11="offen",TODAY()>B11+K11),"Bindefrist!","")))
L12: =IF(A12="","",F12*(1+G12)*(1+H12)) | M12: =IF(A12="","",IF(I12="angenommen","Auftrag",IF(AND(I12="offen",TODAY()>B12+K12),"Bindefrist!","")))
L13: =IF(A13="","",F13*(1+G13)*(1+H13)) | M13: =IF(A13="","",IF(I13="angenommen","Auftrag",IF(AND(I13="offen",TODAY()>B13+K13),"Bindefrist!","")))
L14: =IF(A14="","",F14*(1+G14)*(1+H14)) | M14: =IF(A14="","",IF(I14="angenommen","Auftrag",IF(AND(I14="offen",TODAY()>B14+K14),"Bindefrist!","")))
L15: =IF(A15="","",F15*(1+G15)*(1+H15)) | M15: =IF(A15="","",IF(I15="angenommen","Auftrag",IF(AND(I15="offen",TODAY()>B15+K15),"Bindefrist!","")))
L16: =IF(A16="","",F16*(1+G16)*(1+H16)) | M16: =IF(A16="","",IF(I16="angenommen","Auftrag",IF(AND(I16="offen",TODAY()>B16+K16),"Bindefrist!","")))
L17: =IF(A17="","",F17*(1+G17)*(1+H17)) | M17: =IF(A17="","",IF(I17="angenommen","Auftrag",IF(AND(I17="offen",TODAY()>B17+K17),"Bindefrist!","")))
L18: =IF(A18="","",F18*(1+G18)*(1+H18)) | M18: =IF(A18="","",IF(I18="angenommen","Auftrag",IF(AND(I18="offen",TODAY()>B18+K18),"Bindefrist!","")))
L19: =IF(A19="","",F19*(1+G19)*(1+H19)) | M19: =IF(A19="","",IF(I19="angenommen","Auftrag",IF(AND(I19="offen",TODAY()>B19+K19),"Bindefrist!","")))
L20: =IF(A20="","",F20*(1+G20)*(1+H20)) | M20: =IF(A20="","",IF(I20="angenommen","Auftrag",IF(AND(I20="offen",TODAY()>B20+K20),"Bindefrist!","")))
L21: =IF(A21="","",F21*(1+G21)*(1+H21)) | M21: =IF(A21="","",IF(I21="angenommen","Auftrag",IF(AND(I21="offen",TODAY()>B21+K21),"Bindefrist!","")))
L22: =IF(A22="","",F22*(1+G22)*(1+H22)) | M22: =IF(A22="","",IF(I22="angenommen","Auftrag",IF(AND(I22="offen",TODAY()>B22+K22),"Bindefrist!","")))
L23: =IF(A23="","",F23*(1+G23)*(1+H23)) | M23: =IF(A23="","",IF(I23="angenommen","Auftrag",IF(AND(I23="offen",TODAY()>B23+K23),"Bindefrist!","")))
... L400: =IF(A400="","",F400*(1+G400)*(1+H400)) | M400: =IF(A400="","",IF(I400="angenommen","Auftrag",IF(AND(I400="offen",TODAY()>B400+K400),"Bindefrist!","")))

Sheet 09_Auftraege
A1: Auftragsbestand
A2: Vertragsdaten und aktueller Auftragswert inkl. beauftragter Nachträge
A3: Nr | B3: Angebot | C3: Projekt | D3: Kunde | E3: Datum | F3: Auftrag netto | G3: Vertragsart | H3: Einbehalt % | I3: Status | J3: Notiz | K3: Nachträge | L3: Auftrag aktuell
A4: AU-26001 | B4: AN-26001 | C4: P-2026-001 | D4: K-1001 | E4: 46000 | F4: 2400000 | G4: VOB/B | H4: 0.05 | I4: laufend | J4: Einbehalt 5 % bis Abnahme | K4: =IF(A4="","",SUMIFS('07_Nachtraege'!$E:$E,'07_Nachtraege'!$B:$B,C4,'07_Nachtraege'!$F:$F,"beauftragt")) | L4: =IF(A4="","",F4+K4)
A5: AU-26002 | B5: AN-26002 | C5: P-2026-002 | D5: K-1003 | E5: 46063 | F5: 890000 | G5: VOB/B | H5: 0.05 | I5: laufend | K5: =IF(A5="","",SUMIFS('07_Nachtraege'!$E:$E,'07_Nachtraege'!$B:$B,C5,'07_Nachtraege'!$F:$F,"beauftragt")) | L5: =IF(A5="","",F5+K5)
A6: AU-26003 | B6: AN-26003 | C6: P-2026-003 | D6: K-1002 | E6: 46055 | F6: 1100000 | G6: VOB/B | H6: 0.05 | I6: laufend | J6: Sicherheit durch Bürgschaft möglich | K6: =IF(A6="","",SUMIFS('07_Nachtraege'!$E:$E,'07_Nachtraege'!$B:$B,C6,'07_Nachtraege'!$F:$F,"beauftragt")) | L6: =IF(A6="","",F6+K6)
A7: AU-26004 | B7: AN-26004 | C7: P-2026-004 | D7: K-1004 | E7: 46099 | F7: 3200000 | G7: BGB | H7: 0.05 | I7: laufend | K7: =IF(A7="","",SUMIFS('07_Nachtraege'!$E:$E,'07_Nachtraege'!$B:$B,C7,'07_Nachtraege'!$F:$F,"beauftragt")) | L7: =IF(A7="","",F7+K7)
A8: AU-26005 | B8: AN-26005 | C8: P-2026-005 | D8: K-1005 | E8: 45860 | F8: 420000 | G8: BGB | H8: 0.05 | I8: abgenommen | J8: Abnahme 22.04.2026 | K8: =IF(A8="","",SUMIFS('07_Nachtraege'!$E:$E,'07_Nachtraege'!$B:$B,C8,'07_Nachtraege'!$F:$F,"beauftragt")) | L8: =IF(A8="","",F8+K8)
A9: AU-26006 | B9: AN-26006 | C9: P-2026-006 | D9: K-1006 | E9: 46246 | F9: 1800000 | G9: VOB/B | H9: 0.05 | I9: beauftragt | J9: Baubeginn 01.09.2026 | K9: =IF(A9="","",SUMIFS('07_Nachtraege'!$E:$E,'07_Nachtraege'!$B:$B,C9,'07_Nachtraege'!$F:$F,"beauftragt")) | L9: =IF(A9="","",F9+K9)
K10: =IF(A10="","",SUMIFS('07_Nachtraege'!$E:$E,'07_Nachtraege'!$B:$B,C10,'07_Nachtraege'!$F:$F,"beauftragt")) | L10: =IF(A10="","",F10+K10)
K11: =IF(A11="","",SUMIFS('07_Nachtraege'!$E:$E,'07_Nachtraege'!$B:$B,C11,'07_Nachtraege'!$F:$F,"beauftragt")) | L11: =IF(A11="","",F11+K11)
K12: =IF(A12="","",SUMIFS('07_Nachtraege'!$E:$E,'07_Nachtraege'!$B:$B,C12,'07_Nachtraege'!$F:$F,"beauftragt")) | L12: =IF(A12="","",F12+K12)
K13: =IF(A13="","",SUMIFS('07_Nachtraege'!$E:$E,'07_Nachtraege'!$B:$B,C13,'07_Nachtraege'!$F:$F,"beauftragt")) | L13: =IF(A13="","",F13+K13)
K14: =IF(A14="","",SUMIFS('07_Nachtraege'!$E:$E,'07_Nachtraege'!$B:$B,C14,'07_Nachtraege'!$F:$F,"beauftragt")) | L14: =IF(A14="","",F14+K14)
K15: =IF(A15="","",SUMIFS('07_Nachtraege'!$E:$E,'07_Nachtraege'!$B:$B,C15,'07_Nachtraege'!$F:$F,"beauftragt")) | L15: =IF(A15="","",F15+K15)
K16: =IF(A16="","",SUMIFS('07_Nachtraege'!$E:$E,'07_Nachtraege'!$B:$B,C16,'07_Nachtraege'!$F:$F,"beauftragt")) | L16: =IF(A16="","",F16+K16)
K17: =IF(A17="","",SUMIFS('07_Nachtraege'!$E:$E,'07_Nachtraege'!$B:$B,C17,'07_Nachtraege'!$F:$F,"beauftragt")) | L17: =IF(A17="","",F17+K17)
K18: =IF(A18="","",SUMIFS('07_Nachtraege'!$E:$E,'07_Nachtraege'!$B:$B,C18,'07_Nachtraege'!$F:$F,"beauftragt")) | L18: =IF(A18="","",F18+K18)
K19: =IF(A19="","",SUMIFS('07_Nachtraege'!$E:$E,'07_Nachtraege'!$B:$B,C19,'07_Nachtraege'!$F:$F,"beauftragt")) | L19: =IF(A19="","",F19+K19)
K20: =IF(A20="","",SUMIFS('07_Nachtraege'!$E:$E,'07_Nachtraege'!$B:$B,C20,'07_Nachtraege'!$F:$F,"beauftragt")) | L20: =IF(A20="","",F20+K20)
K21: =IF(A21="","",SUMIFS('07_Nachtraege'!$E:$E,'07_Nachtraege'!$B:$B,C21,'07_Nachtraege'!$F:$F,"beauftragt")) | L21: =IF(A21="","",F21+K21)
... K400: =IF(A400="","",SUMIFS('07_Nachtraege'!$E:$E,'07_Nachtraege'!$B:$B,C400,'07_Nachtraege'!$F:$F,"beauftragt")) | L400: =IF(A400="","",F400+K400)

Sheet 07_Nachtraege
A1: Nachträge und Claims
A2: Nur Status „beauftragt“ erhöht den aktuellen Auftragswert im Projektstamm
A3: Nr | B3: Projekt | C3: Datum | D3: Bezeichnung | E3: Betrag netto | F3: Status | G3: Kunde | H3: Begründung | I3: Auftragswirksam
A4: N-001 | B4: P-2026-001 | C4: 46154 | D4: Zusätzliche Drainage Ost | E4: 28500 | F4: angeboten | G4: K-1001 | H4: Baugrund weicher als Gutachten | I4: =IF(A4="","",IF(F4="beauftragt",E4,0))
A5: N-002 | B5: P-2026-001 | C5: 46206 | D5: Aufzugsturm extra Schacht | E5: 64000 | F5: beauftragt | G5: K-1001 | H5: Planungsänderung Architekt | I5: =IF(A5="","",IF(F5="beauftragt",E5,0))
A6: N-003 | B6: P-2026-003 | C6: 46191 | D6: Zusätzlicher Holzschutz Dachstuhl | E6: 19200 | F6: beauftragt | G6: K-1002 | H6: Befall nach Öffnung | I6: =IF(A6="","",IF(F6="beauftragt",E6,0))
A7: N-004 | B7: P-2026-003 | C7: 46256 | D7: Statische Ertüchtigung Decke EG | E7: 47800 | F7: in Prüfung | G7: K-1002 | H7: Auflage Statiker | I7: =IF(A7="","",IF(F7="beauftragt",E7,0))
A8: N-005 | B8: P-2026-004 | C8: 46238 | D8: Zusätzliche Toranlage Süd | E8: 33600 | F8: angeboten | G8: K-1004 | H8: Nutzerwunsch | I8: =IF(A8="","",IF(F8="beauftragt",E8,0))
I9: =IF(A9="","",IF(F9="beauftragt",E9,0))
I10: =IF(A10="","",IF(F10="beauftragt",E10,0))
I11: =IF(A11="","",IF(F11="beauftragt",E11,0))
I12: =IF(A12="","",IF(F12="beauftragt",E12,0))
I13: =IF(A13="","",IF(F13="beauftragt",E13,0))
I14: =IF(A14="","",IF(F14="beauftragt",E14,0))
I15: =IF(A15="","",IF(F15="beauftragt",E15,0))
I16: =IF(A16="","",IF(F16="beauftragt",E16,0))
I17: =IF(A17="","",IF(F17="beauftragt",E17,0))
I18: =IF(A18="","",IF(F18="beauftragt",E18,0))
I19: =IF(A19="","",IF(F19="beauftragt",E19,0))
I20: =IF(A20="","",IF(F20="beauftragt",E20,0))
... I400: =IF(A400="","",IF(F400="beauftragt",E400,0))

Sheet 06_LV
A1: Leistungsverzeichnis
A2: Einheitspreisvertrag: Menge × EP × Faktor = Positionssumme, verdichtet je Projekt
A3: Pos-Nr | B3: Projekt | C3: OZ | D3: Bezeichnung | E3: ME | F3: Menge | G3: EP netto | H3: Faktor | I3: Gewerk | J3: Status | K3: Gesamt netto
A4: LV-001 | B4: P-2026-001 | C4: 01.01 | D4: Baugrube / Aushub | E4: m³ | F4: 1850 | G4: 28.5 | H4: 1 | I4: Rohbau | J4: erledigt | K4: =IF(A4="","",F4*G4*H4)
A5: LV-002 | B5: P-2026-001 | C5: 02.10 | D5: Ortbeton Fundamente | E5: m³ | F5: 420 | G5: 285 | H5: 1 | I5: Rohbau | J5: erledigt | K5: =IF(A5="","",F5*G5*H5)
A6: LV-003 | B6: P-2026-001 | C6: 03.20 | D6: Mauerwerk KG/EG | E6: m² | F6: 2100 | G6: 92 | H6: 1 | I6: Rohbau | J6: in Arbeit | K6: =IF(A6="","",F6*G6*H6)
A7: LV-004 | B7: P-2026-001 | C7: 04.10 | D7: Stahlbeton Decken | E7: m² | F7: 1680 | G7: 145 | H7: 1 | I7: Rohbau | J7: in Arbeit | K7: =IF(A7="","",F7*G7*H7)
A8: LV-005 | B8: P-2026-001 | C8: 07.00 | D8: Dachkonstruktion | E8: m² | F8: 980 | G8: 168 | H8: 1 | I8: Ausbau | J8: offen | K8: =IF(A8="","",F8*G8*H8)
A9: LV-006 | B9: P-2026-002 | C9: 01.00 | D9: Erdbau / Fundament | E9: pauschal | F9: 1 | G9: 78000 | H9: 1 | I9: Rohbau | J9: erledigt | K9: =IF(A9="","",F9*G9*H9)
A10: LV-007 | B10: P-2026-002 | C10: 02.00 | D10: Rohbau Kita | E10: m² | F10: 640 | G10: 620 | H10: 1 | I10: Rohbau | J10: in Arbeit | K10: =IF(A10="","",F10*G10*H10)
A11: LV-008 | B11: P-2026-002 | C11: 05.00 | D11: Fassade WDVS | E11: m² | F11: 780 | G11: 118 | H11: 1 | I11: Ausbau | J11: offen | K11: =IF(A11="","",F11*G11*H11)
A12: LV-009 | B12: P-2026-003 | C12: 10.00 | D12: Fassadensanierung | E12: m² | F12: 920 | G12: 245 | H12: 1 | I12: Sanierung | J12: in Arbeit | K12: =IF(A12="","",F12*G12*H12)
A13: LV-010 | B13: P-2026-003 | C13: 12.00 | D13: Fenster Denkmalschutz | E13: Stk | F13: 64 | G13: 1850 | H13: 1 | I13: Ausbau | J13: offen | K13: =IF(A13="","",F13*G13*H13)
A14: LV-011 | B14: P-2026-004 | C14: 01.00 | D14: Bodenplatte Halle | E14: m² | F14: 4200 | G14: 95 | H14: 1 | I14: Rohbau | J14: in Arbeit | K14: =IF(A14="","",F14*G14*H14)
A15: LV-012 | B15: P-2026-004 | C15: 03.00 | D15: Stahltragwerk | E15: t | F15: 186 | G15: 2850 | H15: 1 | I15: Rohbau | J15: offen | K15: =IF(A15="","",F15*G15*H15)
... A18: LV-015 | B18: P-2026-006 | C18: 21.00 | D18: Entwässerung | E18: m | F18: 1860 | G18: 185 | H18: 1 | I18: Tiefbau | J18: offen | K18: =IF(A18="","",F18*G18*H18)
K19: =IF(A19="","",F19*G19*H19)
K20: =IF(A20="","",F20*G20*H20)
K21: =IF(A21="","",F21*G21*H21)
K22: =IF(A22="","",F22*G22*H22)
K23: =IF(A23="","",F23*G23*H23)
K24: =IF(A24="","",F24*G24*H24)
K25: =IF(A25="","",F25*G25*H25)
K26: =IF(A26="","",F26*G26*H26)
K27: =IF(A27="","",F27*G27*H27)
K28: =IF(A28="","",F28*G28*H28)
K29: =IF(A29="","",F29*G29*H29)
K30: =IF(A30="","",F30*G30*H30)
... K400: =IF(A400="","",F400*G400*H400)

Sheet 10_Stunden
A1: Zeiterfassung
A2: Kosten = Stunden × Kostensatz Mitarbeiter · Leistungswert = Stunden × Verrechnungssatz bei verrechenbar
A3: Nr | B3: Datum | C3: Projekt | D3: Mitarbeiter | E3: Stunden | F3: Gewerk | G3: Tätigkeit | H3: Verrechenbar | I3: Kostensatz | J3: Verrechnung | K3: Kosten | L3: Leistungswert | M3: Deckungsbeitrag Std.
A4: ST-1001 | B4: 46266 | C4: P-2026-001 | D4: MA-03 | E4: 10 | F4: Rohbau | G4: Polier Wohnquartier | H4: JA | I4: =IF(D4="","",IFERROR(VLOOKUP(D4,'04_Personal'!$A$4:$G$400,7,FALSE),0)) | J4: =IF(D4="","",IFERROR(VLOOKUP(D4,'04_Personal'!$A$4:$G$400,6,FALSE),VSSatz)) | K4: =IF(A4="","",E4*I4) | L4: =IF(A4="","",IF(H4="JA",E4*J4,0)) | M4: =IF(A4="","",L4-K4)
A5: ST-1002 | B5: 46266 | C5: P-2026-001 | D5: MA-04 | E5: 9.5 | F5: Rohbau | G5: Mauerwerk Block C | H5: JA | I5: =IF(D5="","",IFERROR(VLOOKUP(D5,'04_Personal'!$A$4:$G$400,7,FALSE),0)) | J5: =IF(D5="","",IFERROR(VLOOKUP(D5,'04_Personal'!$A$4:$G$400,6,FALSE),VSSatz)) | K5: =IF(A5="","",E5*I5) | L5: =IF(A5="","",IF(H5="JA",E5*J5,0)) | M5: =IF(A5="","",L5-K5)
A6: ST-1003 | B6: 46266 | C6: P-2026-001 | D6: MA-05 | E6: 9.5 | F6: Rohbau | G6: Mauerwerk Block C | H6: JA | I6: =IF(D6="","",IFERROR(VLOOKUP(D6,'04_Personal'!$A$4:$G$400,7,FALSE),0)) | J6: =IF(D6="","",IFERROR(VLOOKUP(D6,'04_Personal'!$A$4:$G$400,6,FALSE),VSSatz)) | K6: =IF(A6="","",E6*I6) | L6: =IF(A6="","",IF(H6="JA",E6*J6,0)) | M6: =IF(A6="","",L6-K6)
A7: ST-1004 | B7: 46266 | C7: P-2026-002 | D7: MA-07 | E7: 8 | F7: Bauleitung | G7: Terminplan Kita | H7: JA | I7: =IF(D7="","",IFERROR(VLOOKUP(D7,'04_Personal'!$A$4:$G$400,7,FALSE),0)) | J7: =IF(D7="","",IFERROR(VLOOKUP(D7,'04_Personal'!$A$4:$G$400,6,FALSE),VSSatz)) | K7: =IF(A7="","",E7*I7) | L7: =IF(A7="","",IF(H7="JA",E7*J7,0)) | M7: =IF(A7="","",L7-K7)
A8: ST-1005 | B8: 46267 | C8: P-2026-003 | D8: MA-04 | E8: 9 | F8: Sanierung | G8: Fassade Süd | H8: JA | I8: =IF(D8="","",IFERROR(VLOOKUP(D8,'04_Personal'!$A$4:$G$400,7,FALSE),0)) | J8: =IF(D8="","",IFERROR(VLOOKUP(D8,'04_Personal'!$A$4:$G$400,6,FALSE),VSSatz)) | K8: =IF(A8="","",E8*I8) | L8: =IF(A8="","",IF(H8="JA",E8*J8,0)) | M8: =IF(A8="","",L8-K8)
A9: ST-1006 | B9: 46267 | C9: P-2026-004 | D9: MA-03 | E9: 6 | F9: Rohbau | G9: Bodenplatte Abschnitt 2 | H9: JA | I9: =IF(D9="","",IFERROR(VLOOKUP(D9,'04_Personal'!$A$4:$G$400,7,FALSE),0)) | J9: =IF(D9="","",IFERROR(VLOOKUP(D9,'04_Personal'!$A$4:$G$400,6,FALSE),VSSatz)) | K9: =IF(A9="","",E9*I9) | L9: =IF(A9="","",IF(H9="JA",E9*J9,0)) | M9: =IF(A9="","",L9-K9)
A10: ST-1007 | B10: 46267 | C10: P-2026-004 | D10: MA-06 | E10: 9.5 | F10: Tiefbau | G10: Kanalanschluss | H10: JA | I10: =IF(D10="","",IFERROR(VLOOKUP(D10,'04_Personal'!$A$4:$G$400,7,FALSE),0)) | J10: =IF(D10="","",IFERROR(VLOOKUP(D10,'04_Personal'!$A$4:$G$400,6,FALSE),VSSatz)) | K10: =IF(A10="","",E10*I10) | L10: =IF(A10="","",IF(H10="JA",E10*J10,0)) | M10: =IF(A10="","",L10-K10)
A11: ST-1008 | B11: 46268 | C11: P-2026-001 | D11: MA-05 | E11: 10 | F11: Rohbau | G11: Decke OG1 | H11: JA | I11: =IF(D11="","",IFERROR(VLOOKUP(D11,'04_Personal'!$A$4:$G$400,7,FALSE),0)) | J11: =IF(D11="","",IFERROR(VLOOKUP(D11,'04_Personal'!$A$4:$G$400,6,FALSE),VSSatz)) | K11: =IF(A11="","",E11*I11) | L11: =IF(A11="","",IF(H11="JA",E11*J11,0)) | M11: =IF(A11="","",L11-K11)
A12: ST-1009 | B12: 46268 | C12: P-2026-002 | D12: MA-05 | E12: 8.5 | F12: Rohbau | G12: Innenwände | H12: JA | I12: =IF(D12="","",IFERROR(VLOOKUP(D12,'04_Personal'!$A$4:$G$400,7,FALSE),0)) | J12: =IF(D12="","",IFERROR(VLOOKUP(D12,'04_Personal'!$A$4:$G$400,6,FALSE),VSSatz)) | K12: =IF(A12="","",E12*I12) | L12: =IF(A12="","",IF(H12="JA",E12*J12,0)) | M12: =IF(A12="","",L12-K12)
A13: ST-1010 | B13: 46269 | C13: P-2026-006 | D13: MA-06 | E13: 4 | F13: Vorbereitung | G13: Einmessen Achse | H13: JA | I13: =IF(D13="","",IFERROR(VLOOKUP(D13,'04_Personal'!$A$4:$G$400,7,FALSE),0)) | J13: =IF(D13="","",IFERROR(VLOOKUP(D13,'04_Personal'!$A$4:$G$400,6,FALSE),VSSatz)) | K13: =IF(A13="","",E13*I13) | L13: =IF(A13="","",IF(H13="JA",E13*J13,0)) | M13: =IF(A13="","",L13-K13)
A14: ST-1011 | B14: 46269 | D14: MA-02 | E14: 8 | F14: Verwaltung | G14: OPOS / Mahnwesen | H14: NEIN | I14: =IF(D14="","",IFERROR(VLOOKUP(D14,'04_Personal'!$A$4:$G$400,7,FALSE),0)) | J14: =IF(D14="","",IFERROR(VLOOKUP(D14,'04_Personal'!$A$4:$G$400,6,FALSE),VSSatz)) | K14: =IF(A14="","",E14*I14) | L14: =IF(A14="","",IF(H14="JA",E14*J14,0)) | M14: =IF(A14="","",L14-K14)
A15: ST-1012 | B15: 46270 | C15: P-2026-001 | D15: MA-08 | E15: 8 | F15: Rohbau | G15: Mörtel / Hilfsarbeiten | H15: JA | I15: =IF(D15="","",IFERROR(VLOOKUP(D15,'04_Personal'!$A$4:$G$400,7,FALSE),0)) | J15: =IF(D15="","",IFERROR(VLOOKUP(D15,'04_Personal'!$A$4:$G$400,6,FALSE),VSSatz)) | K15: =IF(A15="","",E15*I15) | L15: =IF(A15="","",IF(H15="JA",E15*J15,0)) | M15: =IF(A15="","",L15-K15)
A16: ST-1013 | B16: 46262 | C16: P-2026-003 | D16: MA-03 | E16: 9 | F16: Sanierung | G16: Gerüstabnahme | H16: JA | I16: =IF(D16="","",IFERROR(VLOOKUP(D16,'04_Personal'!$A$4:$G$400,7,FALSE),0)) | J16: =IF(D16="","",IFERROR(VLOOKUP(D16,'04_Personal'!$A$4:$G$400,6,FALSE),VSSatz)) | K16: =IF(A16="","",E16*I16) | L16: =IF(A16="","",IF(H16="JA",E16*J16,0)) | M16: =IF(A16="","",L16-K16)
A17: ST-1014 | B17: 46262 | C17: P-2026-004 | D17: MA-04 | E17: 10 | F17: Rohbau | G17: Bewehrung Bodenplatte | H17: JA | I17: =IF(D17="","",IFERROR(VLOOKUP(D17,'04_Personal'!$A$4:$G$400,7,FALSE),0)) | J17: =IF(D17="","",IFERROR(VLOOKUP(D17,'04_Personal'!$A$4:$G$400,6,FALSE),VSSatz)) | K17: =IF(A17="","",E17*I17) | L17: =IF(A17="","",IF(H17="JA",E17*J17,0)) | M17: =IF(A17="","",L17-K17)
A18: ST-1015 | B18: 46263 | C18: P-2026-002 | D18: MA-07 | E18: 9 | F18: Bauleitung | G18: SIGeKO Begehung | H18: JA | I18: =IF(D18="","",IFERROR(VLOOKUP(D18,'04_Personal'!$A$4:$G$400,7,FALSE),0)) | J18: =IF(D18="","",IFERROR(VLOOKUP(D18,'04_Personal'!$A$4:$G$400,6,FALSE),VSSatz)) | K18: =IF(A18="","",E18*I18) | L18: =IF(A18="","",IF(H18="JA",E18*J18,0)) | M18: =IF(A18="","",L18-K18)
I19: =IF(D19="","",IFERROR(VLOOKUP(D19,'04_Personal'!$A$4:$G$400,7,FALSE),0)) | J19: =IF(D19="","",IFERROR(VLOOKUP(D19,'04_Personal'!$A$4:$G$400,6,FALSE),VSSatz)) | K19: =IF(A19="","",E19*I19) | L19: =IF(A19="","",IF(H19="JA",E19*J19,0)) | M19: =IF(A19="","",L19-K19)
I20: =IF(D20="","",IFERROR(VLOOKUP(D20,'04_Personal'!$A$4:$G$400,7,FALSE),0)) | J20: =IF(D20="","",IFERROR(VLOOKUP(D20,'04_Personal'!$A$4:$G$400,6,FALSE),VSSatz)) | K20: =IF(A20="","",E20*I20) | L20: =IF(A20="","",IF(H20="JA",E20*J20,0)) | M20: =IF(A20="","",L20-K20)
I21: =IF(D21="","",IFERROR(VLOOKUP(D21,'04_Personal'!$A$4:$G$400,7,FALSE),0)) | J21: =IF(D21="","",IFERROR(VLOOKUP(D21,'04_Personal'!$A$4:$G$400,6,FALSE),VSSatz)) | K21: =IF(A21="","",E21*I21) | L21: =IF(A21="","",IF(H21="JA",E21*J21,0)) | M21: =IF(A21="","",L21-K21)
I22: =IF(D22="","",IFERROR(VLOOKUP(D22,'04_Personal'!$A$4:$G$400,7,FALSE),0)) | J22: =IF(D22="","",IFERROR(VLOOKUP(D22,'04_Personal'!$A$4:$G$400,6,FALSE),VSSatz)) | K22: =IF(A22="","",E22*I22) | L22: =IF(A22="","",IF(H22="JA",E22*J22,0)) | M22: =IF(A22="","",L22-K22)
I23: =IF(D23="","",IFERROR(VLOOKUP(D23,'04_Personal'!$A$4:$G$400,7,FALSE),0)) | J23: =IF(D23="","",IFERROR(VLOOKUP(D23,'04_Personal'!$A$4:$G$400,6,FALSE),VSSatz)) | K23: =IF(A23="","",E23*I23) | L23: =IF(A23="","",IF(H23="JA",E23*J23,0)) | M23: =IF(A23="","",L23-K23)
I24: =IF(D24="","",IFERROR(VLOOKUP(D24,'04_Personal'!$A$4:$G$400,7,FALSE),0)) | J24: =IF(D24="","",IFERROR(VLOOKUP(D24,'04_Personal'!$A$4:$G$400,6,FALSE),VSSatz)) | K24: =IF(A24="","",E24*I24) | L24: =IF(A24="","",IF(H24="JA",E24*J24,0)) | M24: =IF(A24="","",L24-K24)
I25: =IF(D25="","",IFERROR(VLOOKUP(D25,'04_Personal'!$A$4:$G$400,7,FALSE),0)) | J25: =IF(D25="","",IFERROR(VLOOKUP(D25,'04_Personal'!$A$4:$G$400,6,FALSE),VSSatz)) | K25: =IF(A25="","",E25*I25) | L25: =IF(A25="","",IF(H25="JA",E25*J25,0)) | M25: =IF(A25="","",L25-K25)
I26: =IF(D26="","",IFERROR(VLOOKUP(D26,'04_Personal'!$A$4:$G$400,7,FALSE),0)) | J26: =IF(D26="","",IFERROR(VLOOKUP(D26,'04_Personal'!$A$4:$G$400,6,FALSE),VSSatz)) | K26: =IF(A26="","",E26*I26) | L26: =IF(A26="","",IF(H26="JA",E26*J26,0)) | M26: =IF(A26="","",L26-K26)
I27: =IF(D27="","",IFERROR(VLOOKUP(D27,'04_Personal'!$A$4:$G$400,7,FALSE),0)) | J27: =IF(D27="","",IFERROR(VLOOKUP(D27,'04_Personal'!$A$4:$G$400,6,FALSE),VSSatz)) | K27: =IF(A27="","",E27*I27) | L27: =IF(A27="","",IF(H27="JA",E27*J27,0)) | M27: =IF(A27="","",L27-K27)
I28: =IF(D28="","",IFERROR(VLOOKUP(D28,'04_Personal'!$A$4:$G$400,7,FALSE),0)) | J28: =IF(D28="","",IFERROR(VLOOKUP(D28,'04_Personal'!$A$4:$G$400,6,FALSE),VSSatz)) | K28: =IF(A28="","",E28*I28) | L28: =IF(A28="","",IF(H28="JA",E28*J28,0)) | M28: =IF(A28="","",L28-K28)
I29: =IF(D29="","",IFERROR(VLOOKUP(D29,'04_Personal'!$A$4:$G$400,7,FALSE),0)) | J29: =IF(D29="","",IFERROR(VLOOKUP(D29,'04_Personal'!$A$4:$G$400,6,FALSE),VSSatz)) | K29: =IF(A29="","",E29*I29) | L29: =IF(A29="","",IF(H29="JA",E29*J29,0)) | M29: =IF(A29="","",L29-K29)
I30: =IF(D30="","",IFERROR(VLOOKUP(D30,'04_Personal'!$A$4:$G$400,7,FALSE),0)) | J30: =IF(D30="","",IFERROR(VLOOKUP(D30,'04_Personal'!$A$4:$G$400,6,FALSE),VSSatz)) | K30: =IF(A30="","",E30*I30) | L30: =IF(A30="","",IF(H30="JA",E30*J30,0)) | M30: =IF(A30="","",L30-K30)
... I400: =IF(D400="","",IFERROR(VLOOKUP(D400,'04_Personal'!$A$4:$G$400,7,FALSE),0)) | J400: =IF(D400="","",IFERROR(VLOOKUP(D400,'04_Personal'!$A$4:$G$400,6,FALSE),VSSatz)) | K400: =IF(A400="","",E400*I400) | L400: =IF(A400="","",IF(H400="JA",E400*J400,0)) | M400: =IF(A400="","",L400-K400)

Sheet 11_Material
A1: Material und Baustoffeinsatz
A2: Summe netto = Menge × EP · Zuordnung zur Eingangsrechnung über ER-Nr für den Abgleich Einkauf / Rechnung
A3: Nr | B3: Datum | C3: Projekt | D3: Lieferant | E3: ER-Nr | F3: Bezeichnung | G3: ME | H3: Menge | I3: EP netto | J3: Kategorie | K3: Status | L3: Summe netto
A4: MAT-01 | B4: 46246 | C4: P-2026-001 | D4: L-2001 | E4: ER-5512 | F4: Transportbeton C25/30 | G4: m³ | H4: 86 | I4: 142 | J4: Beton | K4: verbucht | L4: =IF(A4="","",H4*I4)
A5: MAT-02 | B5: 46248 | C5: P-2026-001 | D5: L-2002 | E5: ER-5518 | F5: Betonstahl B500B | G5: t | H5: 12.4 | I5: 980 | J5: Stahl | K5: verbucht | L5: =IF(A5="","",H5*I5)
A6: MAT-03 | B6: 46254 | C6: P-2026-002 | D6: L-2001 | E6: ER-5531 | F6: Transportbeton C20/25 | G6: m³ | H6: 34 | I6: 138 | J6: Beton | K6: verbucht | L6: =IF(A6="","",H6*I6)
A7: MAT-04 | B7: 46267 | C7: P-2026-004 | D7: L-2002 | E7: ER-5602 | F7: Stahlträger HEB 300 | G7: t | H7: 18.6 | I7: 1420 | J7: Stahl | K7: offen | L7: =IF(A7="","",H7*I7)
A8: MAT-05 | B8: 46269 | C8: P-2026-003 | D8: L-2007 | F8: Gerüstmiete September | G8: Monat | H8: 1 | I8: 4800 | J8: Gerüst | K8: offen | L8: =IF(A8="","",H8*I8)
A9: MAT-06 | B9: 46225 | C9: P-2026-005 | D9: L-2001 | E9: ER-5401 | F9: Estrichmaterial | G9: m² | H9: 186 | I9: 18.5 | J9: Ausbau | K9: verbucht | L9: =IF(A9="","",H9*I9)
A10: MAT-07 | B10: 46273 | C10: P-2026-001 | D10: L-2006 | F10: Aushubabfuhr | G10: t | H10: 42 | I10: 28 | J10: Entsorgung | K10: offen | L10: =IF(A10="","",H10*I10)
L11: =IF(A11="","",H11*I11)
L12: =IF(A12="","",H12*I12)
L13: =IF(A13="","",H13*I13)
L14: =IF(A14="","",H14*I14)
L15: =IF(A15="","",H15*I15)
L16: =IF(A16="","",H16*I16)
L17: =IF(A17="","",H17*I17)
L18: =IF(A18="","",H18*I18)
L19: =IF(A19="","",H19*I19)
L20: =IF(A20="","",H20*I20)
L21: =IF(A21="","",H21*I21)
L22: =IF(A22="","",H22*I22)
... L400: =IF(A400="","",H400*I400)

Sheet 12_Geraete
A1: Geräte und Fuhrpark
A2: Lineare AfA, Restbuchwert und internem Verrechnungssatz für Kalkulation und BWA
A3: Nr | B3: Bezeichnung | C3: Typ | D3: Eigentum | E3: Anschaffung | F3: Inbetrieb | G3: ND Jahre | H3: Satz/h | I3: Einsatz | J3: Status | K3: AfA p.a. | L3: Restbuchwert 2026
A4: GE-01 | B4: Raupenbagger CAT 320 | C4: Bagger | D4: eigen | E4: 185000 | F4: 44287 | G4: 8 | H4: 95 | I4: P-2026-004 | J4: Einsatzfähig | K4: =IF(OR(A4="",E4="",G4=0),"",E4/G4) | L4: =IF(A4="","",MAX(0,E4-K4*MAX(0,GJ-YEAR(F4))))
A5: GE-02 | B5: Turmdrehkran Liebherr 81 K | C5: Kran | D5: Miete | E5: 0 | F5: 46032 | G5: 5 | H5: 210 | I5: P-2026-001 | J5: Einsatzfähig | K5: =IF(OR(A5="",E5="",G5=0),"",E5/G5) | L5: =IF(A5="","",MAX(0,E5-K5*MAX(0,GJ-YEAR(F5))))
A6: GE-03 | B6: LKW MAN TGS 26.480 | C6: LKW | D6: eigen | E6: 98000 | F6: 43617 | G6: 8 | H6: 62 | I6: Pool | J6: Einsatzfähig | K6: =IF(OR(A6="",E6="",G6=0),"",E6/G6) | L6: =IF(A6="","",MAX(0,E6-K6*MAX(0,GJ-YEAR(F6))))
A7: GE-04 | B7: Minibagger Kubota U27 | C7: Bagger | D7: eigen | E7: 42000 | F7: 45000 | G7: 6 | H7: 48 | I7: P-2026-002 | J7: Werkstatt | K7: =IF(OR(A7="",E7="",G7=0),"",E7/G7) | L7: =IF(A7="","",MAX(0,E7-K7*MAX(0,GJ-YEAR(F7))))
A8: GE-05 | B8: Gerüstsatz 800 m² | C8: Gerüst | D8: Miete | E8: 0 | F8: 46054 | G8: 4 | H8: 18 | I8: P-2026-003 | J8: Einsatzfähig | K8: =IF(OR(A8="",E8="",G8=0),"",E8/G8) | L8: =IF(A8="","",MAX(0,E8-K8*MAX(0,GJ-YEAR(F8))))
K9: =IF(OR(A9="",E9="",G9=0),"",E9/G9) | L9: =IF(A9="","",MAX(0,E9-K9*MAX(0,GJ-YEAR(F9))))
K10: =IF(OR(A10="",E10="",G10=0),"",E10/G10) | L10: =IF(A10="","",MAX(0,E10-K10*MAX(0,GJ-YEAR(F10))))
K11: =IF(OR(A11="",E11="",G11=0),"",E11/G11) | L11: =IF(A11="","",MAX(0,E11-K11*MAX(0,GJ-YEAR(F11))))
K12: =IF(OR(A12="",E12="",G12=0),"",E12/G12) | L12: =IF(A12="","",MAX(0,E12-K12*MAX(0,GJ-YEAR(F12))))
K13: =IF(OR(A13="",E13="",G13=0),"",E13/G13) | L13: =IF(A13="","",MAX(0,E13-K13*MAX(0,GJ-YEAR(F13))))
K14: =IF(OR(A14="",E14="",G14=0),"",E14/G14) | L14: =IF(A14="","",MAX(0,E14-K14*MAX(0,GJ-YEAR(F14))))
K15: =IF(OR(A15="",E15="",G15=0),"",E15/G15) | L15: =IF(A15="","",MAX(0,E15-K15*MAX(0,GJ-YEAR(F15))))
K16: =IF(OR(A16="",E16="",G16=0),"",E16/G16) | L16: =IF(A16="","",MAX(0,E16-K16*MAX(0,GJ-YEAR(F16))))
K17: =IF(OR(A17="",E17="",G17=0),"",E17/G17) | L17: =IF(A17="","",MAX(0,E17-K17*MAX(0,GJ-YEAR(F17))))
K18: =IF(OR(A18="",E18="",G18=0),"",E18/G18) | L18: =IF(A18="","",MAX(0,E18-K18*MAX(0,GJ-YEAR(F18))))
K19: =IF(OR(A19="",E19="",G19=0),"",E19/G19) | L19: =IF(A19="","",MAX(0,E19-K19*MAX(0,GJ-YEAR(F19))))
K20: =IF(OR(A20="",E20="",G20=0),"",E20/G20) | L20: =IF(A20="","",MAX(0,E20-K20*MAX(0,GJ-YEAR(F20))))
... K400: =IF(OR(A400="",E400="",G400=0),"",E400/G400) | L400: =IF(A400="","",MAX(0,E400-K400*MAX(0,GJ-YEAR(F400))))

Sheet 02_Kunden
A1: Kunden / Auftraggeber
A2: Debitorenstamm für Angebote, Aufträge, Rechnungen und Mahnungen
A3: Nr | B3: Name | C3: Typ | D3: Ansprechpartner | E3: Straße | F3: PLZ | G3: Ort | H3: Telefon | I3: E-Mail | J3: Zahlungsziel | K3: Skonto | L3: ABC | M3: Status | N3: Notiz
A4: K-1001 | B4: Wohnbau Alpenland AG | C4: Firma | D4: Lisa Hartmann | E4: Prinzregentenstr. 22 | F4: 80538 | G4: München | H4: 089 1200 440 | I4: l.hartmann@wohnbau-alpenland.de | J4: 30 | K4: 0.02 | L4: A | M4: Aktiv | N4: Großkunde Wohnungsbau
A5: K-1002 | B5: Stadt Freising | C5: Kommune | D5: Amt Hochbau | E5: Obere Hauptstr. 2 | F5: 85354 | G5: Freising | H5: 08161 17-0 | I5: hochbau@freising.de | J5: 45 | K5: 0 | L5: A | M5: Aktiv | N5: Öffentlicher Auftraggeber VOB/A
A6: K-1003 | B6: Kita Träger Freising e.V. | C6: Verein | D6: Sabine Kohl | E6: Sonnenweg 4 | F6: 85354 | G6: Freising | H6: 08161 88910 | I6: verwaltung@kita-freising.de | J6: 21 | K6: 0.02 | L6: B | M6: Aktiv | N6: Sozialer Träger
A7: K-1004 | B7: Nordpark Gewerbe GmbH | C7: Firma | D7: Thomas Reiter | E7: Am Nordpark 9 | F7: 85221 | G7: Dachau | H7: 08131 55620 | I7: t.reiter@nordpark-gewerbe.de | J7: 30 | K7: 0.02 | L7: A | M7: Aktiv | N7: Industrie / Halle
A8: K-1005 | B8: Familie Huber | C8: Privat | D8: Martin Huber | E8: Lindenweg 7 | F8: 85435 | G8: Erding | H8: 08122 9912 | I8: martin.huber@web.de | J8: 14 | K8: 0 | L8: C | M8: Aktiv | N8: EFH Privatkunde
A9: K-1006 | B9: Staatliches Bauamt Freising | C9: Behörde | D9: Vergabestelle | E9: Landshuter Str. 31 | F9: 85356 | G9: Freising | H9: 08161 403-0 | I9: vergabe@stba-fs.bayern.de | J9: 60 | K9: 0 | L9: A | M9: Aktiv | N9: Straßen- und Tiefbau

Sheet 03_Lieferanten
A1: Lieferanten und Nachunternehmer
A2: Kreditorenstamm inkl. Skonto und Zahlungsziel für Liquiditätsplanung
A3: Nr | B3: Name | C3: Art | D3: Ansprechpartner | E3: IBAN | F3: Skonto Tage | G3: Skonto % | H3: Zahlungsziel | I3: E-Mail | J3: Status | K3: Notiz
A4: L-2001 | B4: BayernZement GmbH | C4: Material | D4: Einkauf | E4: DE14 7015 0000 0000 3321 09 | F4: 14 | G4: 0.02 | H4: 30 | I4: zement@bayernzement.de | J4: Aktiv | K4: Beton / Zement
A5: L-2002 | B5: Holz & Stahl Süd AG | C5: Material | D5: Vertrieb Süd | E5: DE22 7605 0101 0000 8841 33 | F5: 10 | G5: 0.03 | H5: 30 | I5: auftrag@holzstahl-sued.de | J5: Aktiv | K5: Bewehrung / Stahl
A6: L-2003 | B6: Elektro Fuchs GmbH | C6: Nachunternehmer | D6: Werner Fuchs | E6: DE77 7001 0080 0012 4455 01 | F6: 10 | G6: 0.02 | H6: 21 | I6: office@elektro-fuchs.de | J6: Aktiv | K6: Elektroinstallation
A7: L-2004 | B7: Haustechnik Lang KG | C7: Nachunternehmer | D7: Petra Lang | E7: DE55 7602 0070 0019 3300 18 | F7: 14 | G7: 0.02 | H7: 21 | I7: info@ht-lang.de | J7: Aktiv | K7: HLS / Sanitär
A8: L-2005 | B8: Mietpark Geräte GmbH | C8: Gerät | D8: Disposition | E8: DE33 7015 0000 0099 1200 44 | F8: 7 | G8: 0 | H8: 14 | I8: dispo@mietpark-geraete.de | J8: Aktiv | K8: Bagger / Kran / Gerüst
A9: L-2006 | B9: Spedition Huber | C9: Dienstleistung | D9: Fuhrpark | E9: DE10 7005 0000 0044 2210 87 | F9: 7 | G9: 0 | H9: 14 | I9: disposition@spedition-huber.de | J9: Aktiv | K9: Aushub / Entsorgung
A10: L-2007 | B10: Gerüstbau Huber | C10: Nachunternehmer | D10: Josef Huber | E10: DE41 7016 0000 0008 7712 55 | F10: 10 | G10: 0.02 | H10: 21 | I10: buero@geruestbau-huber.de | J10: Aktiv | K10: Fassade / Gerüst

Sheet 04_Personal
A1: Personal und Verrechnungssätze
A2: Mitarbeiterstamm · Kostensatz = Arbeitgebervollkosten je Stunde inkl. SV, Soka-Bau, BG
A3: Nr | B3: Name | C3: Funktion | D3: Kolonne | E3: Soll-h/Monat | F3: Verrechnung | G3: Kosten/h | H3: Eintritt | I3: Status | J3: Notiz
A4: MA-01 | B4: Andreas Bergmann | C4: Geschäftsführung | D4: GF | E4: 0 | F4: 85 | G4: 42 | H4: 40969 | I4: Aktiv | J4: Geschäftsführer
A5: MA-02 | B5: Claudia Meier | C5: Kaufmännisch | D5: BuHa | E5: 0 | F5: 62 | G5: 34 | H5: 43252 | I5: Aktiv | J5: Buchhaltung / Controlling
A6: MA-03 | B6: Markus Wolf | C6: Polier | D6: Bauleitung | E6: 160 | F6: 58 | G6: 41.5 | H6: 42095 | I6: Aktiv | J6: Polier Hochbau
A7: MA-04 | B7: Jonas Keller | C7: Vorarbeiter | D7: Rohbau | E7: 168 | F7: 48 | G7: 36.2 | H7: 43692 | I7: Aktiv | J7: Rohbau
A8: MA-05 | B8: Emre Yildiz | C8: Facharbeiter | D8: Rohbau | E8: 168 | F8: 42 | G8: 32.4 | H8: 44228 | I8: Aktiv | J8: Maurer
A9: MA-06 | B9: Stefan Vogel | C9: Facharbeiter | D9: Tiefbau | E9: 168 | F9: 44 | G9: 33.1 | H9: 42979 | I9: Aktiv | J9: Tiefbauer
A10: MA-07 | B10: Anna Schuster | C10: Bauleitung | D10: BL | E10: 160 | F10: 64 | G10: 45 | H10: 43837 | I10: Aktiv | J10: Bauleiterin
A11: MA-08 | B11: Lukas Berger | C11: Azubi | D11: Rohbau | E11: 140 | F11: 18 | G11: 14.5 | H11: 45536 | I11: Aktiv | J11: Auszubildender 2. LJ

Sheet 25_Form_Angebot
A1: ANGEBOT
A2: =FirmaName&" · "&FirmaStrasse&" · "&FirmaPLZ&" "&FirmaOrt&" · USt-Id "&FirmaUStId
A4: Angebots-Nr. wählen | B4: AN-26007
A6: Angebots-Nr. | B6: =IF(B4="","",B4)
A7: Datum | B7: =IF(B4="","",IFERROR(VLOOKUP(B4,'08_Angebote'!$A$4:$M$400,2,FALSE),""))
A8: Kunde | B8: =IF(B4="","",IFERROR(VLOOKUP(VLOOKUP(B4,'08_Angebote'!$A$4:$M$400,3,FALSE),'02_Kunden'!$A$4:$B$400,2,FALSE),""))
A9: Projekt | B9: =IF(B4="","",IFERROR(VLOOKUP(B4,'08_Angebote'!$A$4:$M$400,5,FALSE),""))
A10: Netto Angebot | B10: =IF(B4="","",IFERROR(VLOOKUP(B4,'08_Angebote'!$A$4:$M$400,6,FALSE),0))
A11: AGK | B11: =IF(B4="","",IFERROR(VLOOKUP(B4,'08_Angebote'!$A$4:$M$400,7,FALSE),0))
A12: Wagnis + Gewinn | B12: =IF(B4="","",IFERROR(VLOOKUP(B4,'08_Angebote'!$A$4:$M$400,8,FALSE),0))
A13: Angebotssumme netto | B13: =IF(B4="","",IFERROR(VLOOKUP(B4,'08_Angebote'!$A$4:$M$400,12,FALSE),0))
A14: zzgl. USt | B14: =IF(B4="","",B13*UStSatz)
A15: Angebot brutto | B15: =IF(B4="","",B13+B14)
A16: Bindefrist bis | B16: =IF(B4="","",B7+IFERROR(VLOOKUP(B4,'08_Angebote'!$A$4:$M$400,11,FALSE),0))
A17: Status | B17: =IF(B4="","",IFERROR(VLOOKUP(B4,'08_Angebote'!$A$4:$M$400,9,FALSE),""))
A19: Leistungsbeschreibung (Kurztext)
A20: Wir bieten die im Leistungsverzeichnis beschriebenen Arbeiten gemäß VOB/B bzw. BGB zu umseitig genannten Bedingungen an. Nachträge nur nach schriftlicher Beauftragung.
A26: Zahlungsbedingungen
A27: ="Abschläge nach Baufortschritt, Zahlungsziel "&Zahlungsziel&" Tage, Skonto "&TEXT(SkontoPct,"0.0%")&" bei Zahlung binnen "&SkontoTage&" Tagen. Sicherheitseinbehalt "&TEXT(EinbehaltPct,"0.0%")&"."
A30: Ort, Datum | C30: Stempel / Unterschrift Bieter
A31: =FirmaOrt&", "&TEXT(TODAY(),"DD.MM.YYYY")
A34: Gültig ohne Unterschrift im Systemdruck — Original unterschrieben der Vergabe beilegen.

Sheet 26_Form_Rechnung
A1: RECHNUNG / ABSCHLAG
A2: =FirmaName&" · "&FirmaStrasse&" · "&FirmaPLZ&" "&FirmaOrt&" · USt-Id "&FirmaUStId
A4: Rechnungs-Nr. wählen | B4: AR-26004
A6: Rechnungs-Nr. | B6: =B4
A7: Datum | B7: =IF(B4="","",IFERROR(VLOOKUP(B4,'13_Ausgangsrechnungen'!$A$4:$T$400,2,FALSE),""))
A8: Typ | B8: =IF(B4="","",IFERROR(VLOOKUP(B4,'13_Ausgangsrechnungen'!$A$4:$T$400,5,FALSE),""))
A9: Projekt | B9: =IF(B4="","",IFERROR(VLOOKUP(B4,'13_Ausgangsrechnungen'!$A$4:$T$400,3,FALSE),""))
A10: Projektname | B10: =IF(B9="","",IFERROR(VLOOKUP(B9,'05_Projekte'!$A$4:$B$400,2,FALSE),""))
A11: Kunde | B11: =IF(B4="","",IFERROR(VLOOKUP(VLOOKUP(B4,'13_Ausgangsrechnungen'!$A$4:$T$400,4,FALSE),'02_Kunden'!$A$4:$B$400,2,FALSE),""))
A12: Leistung netto | B12: =IF(B4="","",IFERROR(VLOOKUP(B4,'13_Ausgangsrechnungen'!$A$4:$T$400,7,FALSE),0))
A13: abzgl. Einbehalt | B13: =IF(B4="","",IFERROR(VLOOKUP(B4,'13_Ausgangsrechnungen'!$A$4:$T$400,14,FALSE),0))
A14: Netto fällig | B14: =IF(B4="","",IFERROR(VLOOKUP(B4,'13_Ausgangsrechnungen'!$A$4:$T$400,15,FALSE),0))
A15: USt | B15: =IF(B4="","",IFERROR(VLOOKUP(B4,'13_Ausgangsrechnungen'!$A$4:$T$400,16,FALSE),0))
A16: Brutto fällig | B16: =IF(B4="","",IFERROR(VLOOKUP(B4,'13_Ausgangsrechnungen'!$A$4:$T$400,17,FALSE),0))
A17: bereits bezahlt | B17: =IF(B4="","",IFERROR(VLOOKUP(B4,'13_Ausgangsrechnungen'!$A$4:$T$400,18,FALSE),0))
A18: Offen | B18: =IF(B4="","",IFERROR(VLOOKUP(B4,'13_Ausgangsrechnungen'!$A$4:$T$400,19,FALSE),0))
A19: Fällig am | B19: =IF(B4="","",IFERROR(VLOOKUP(B4,'13_Ausgangsrechnungen'!$A$4:$T$400,10,FALSE),""))
A20: Leistungsbeschreibung | B20: =IF(B4="","",IFERROR(VLOOKUP(B4,'13_Ausgangsrechnungen'!$A$4:$T$400,13,FALSE),""))
A22: Zahlungsempfänger
A23: =FirmaName&" · IBAN "&FirmaIBAN&" · BIC "&FirmaBIC&" · "&FirmaBank
A26: ="Bitte überweisen Sie den offenen Betrag unter Angabe der Rechnungsnummer bis zum "&TEXT(B19,"DD.MM.YYYY")&". Bei Zahlung bis "&TEXT(B7+SkontoTage,"DD.MM.YYYY")&" gewähren wir "&TEXT(SkontoPct,"0.0%")&" Skonto."
A30: Hinweis Einbehalt: Der Sicherheitseinbehalt wird bis zur Abnahme / Ablauf der Gewährleistung einbehalten bzw. gegen Bürgschaft ausgezahlt.

Sheet 27_Form_Abnahme
A1: ABNAHMEPROTOKOLL
A2: =FirmaName&" · "&FirmaStrasse&" · "&FirmaPLZ&" "&FirmaOrt&" · USt-Id "&FirmaUStId
A4: Projekt wählen | B4: P-2026-005
A6: Projekt | B6: =B4
A7: Bezeichnung | B7: =IF(B4="","",IFERROR(VLOOKUP(B4,'05_Projekte'!$A$4:$T$400,2,FALSE),""))
A8: Auftraggeber | B8: =IF(B4="","",IFERROR(VLOOKUP(VLOOKUP(B4,'05_Projekte'!$A$4:$C$400,3,FALSE),'02_Kunden'!$A$4:$B$400,2,FALSE),""))
A9: Vertragsart | B9: =IF(B4="","",IFERROR(VLOOKUP(B4,'05_Projekte'!$A$4:$T$400,5,FALSE),""))
A10: Bauleiter | B10: =IF(B4="","",IFERROR(VLOOKUP(B4,'05_Projekte'!$A$4:$R$400,17,FALSE),""))
A11: Ort der Baustelle | B11: =IF(B4="","",IFERROR(VLOOKUP(B4,'05_Projekte'!$A$4:$T$400,19,FALSE),""))
A12: Auftrag netto | B12: =IF(B4="","",IFERROR(VLOOKUP(B4,'05_Projekte'!$A$4:$V$400,22,FALSE),0))
A14: Abnahmedatum
A15: Art der Abnahme | B15: förmlich nach VOB/B § 12
A17: Feststellungen / Mängel
A18: Keine wesentlichen Mängel. Restarbeiten gemäß Mängelliste Anlage 1 innerhalb von 14 Werktagen.
A26: Beginn Gewährleistung | B26: =IF(B14="","",B14)
A27: Ende Gewährleistung | B27: =IF(B14="","",DATE(YEAR(B14)+GewaehrJahre,MONTH(B14),DAY(B14)))
A29: Auftragnehmer | D29: Auftraggeber
A30: =FirmaGF
A32: ______________________________ | D32: ______________________________
A33: Unterschrift / Datum | D33: Unterschrift / Datum

Sheet 28_Form_Bautage
A1: BAUTAGESBERICHT
A2: =FirmaName&" · "&FirmaStrasse&" · "&FirmaPLZ&" "&FirmaOrt&" · USt-Id "&FirmaUStId
A4: Projekt | B4: P-2026-001
A5: Datum | B5: 46307
A6: Bauleiter / Polier | B6: =IF(B4="","",IFERROR(VLOOKUP(B4,'05_Projekte'!$A$4:$R$400,17,FALSE),"")) | C6: =IF(B4="","",IFERROR(VLOOKUP(B4,'05_Projekte'!$A$4:$R$400,18,FALSE),""))
A8: Wetter / Temperatur | B8: heiter, 12 °C, trocken
A9: Personal auf der Baustelle | B9: =IF(B4="","",COUNTIFS('10_Stunden'!C:C,B4,'10_Stunden'!B:B,B5))
A10: Stunden gesamt | B10: =IF(B4="","",SUMIFS('10_Stunden'!E:E,'10_Stunden'!C:C,B4,'10_Stunden'!B:B,B5))
A12: Ausgeführte Leistungen
A13: Rohbau Block C: Mauerwerk OG1, Deckenbewehrung vorbereitet. Nachunternehmer Elektro in Steigzone.
A20: Geräte / Material / Behinderungen
A21: Kran 81K in Betrieb. Betonlieferung 08:30. Keine Behinderung.
A26: Unfälle / besondere Vorkommnisse: keine
A28: Unterschrift Bauleitung | D28: Kenntnisnahme AG (optional)

Sheet 29_Form_Mahnung
A1: MAHNUNG
A2: =FirmaName&" · "&FirmaStrasse&" · "&FirmaPLZ&" "&FirmaOrt&" · USt-Id "&FirmaUStId
A4: Mahnung wählen | B4: MAH-02
A6: Mahnung | B6: =B4
A7: Rechnung | B7: =IF(B4="","",IFERROR(VLOOKUP(B4,'17_Mahnwesen'!$A$4:$K$400,2,FALSE),""))
A8: Kunde | B8: =IF(B4="","",IFERROR(VLOOKUP(VLOOKUP(B4,'17_Mahnwesen'!$A$4:$C$400,3,FALSE),'02_Kunden'!$A$4:$B$400,2,FALSE),""))
A9: Mahnstufe | B9: =IF(B4="","",IFERROR(VLOOKUP(B4,'17_Mahnwesen'!$A$4:$K$400,7,FALSE),""))
A10: Offener Betrag | B10: =IF(B4="","",IFERROR(VLOOKUP(B4,'17_Mahnwesen'!$A$4:$K$400,11,FALSE),0))
A11: Neue Frist | B11: =IF(B4="","",IFERROR(VLOOKUP(B4,'17_Mahnwesen'!$A$4:$K$400,10,FALSE),""))
A13: ="Sehr geehrte Damen und Herren,"&CHAR(10)&CHAR(10)&"trotz fälliger Rechnung "&B7&" ist der Betrag von "&TEXT(B10,"#,##0.00 €")&" noch offen. "&"Wir fordern Sie auf, den Betrag bis spätestens "&TEXT(B11,"DD.MM.YYYY")&" auf unser Konto "&FirmaIBAN&" zu überweisen. "&"Bei weiterem Verzug behalten wir uns Verzugszinsen, Mahnkosten und die Abgabe an unseren Rechtsanwalt vor."&CHAR(10)&CHAR(10)&"Mit freundlichen Grüßen"&CHAR(10)&FirmaName&CHAR(10)&BuHaName

Sheet 30_Import
A1: Automatische Importe
A2: CSV-Vorlagen im Ordner templates/ · Python-Skript scripts/import_csv.py · optional Power Query
A4: 1. Empfohlener Weg: Python-Import (ohne Excel-Makros)
A5: Im Projektordner: python scripts/import_csv.py --workbook Baucontrolling_Kaufmann.xlsx --typ bank --datei templates/bankumsatz.csv Typen: kunden | lieferanten | personal | projekte | stunden | material | ar | er | zahlungen | bank | datev Das Skript hängt Zeilen an die richtige Tabelle an und vergibt laufende Nummern, wenn die Nr. leer ist.
A10: 2. Power Query (Excel: Daten → Aus Text/CSV)
A11: Datei wählen → Trennzeichen Semikolon → Laden in Tabelle. Anschließend Abfrage so benennen wie unten. Beim nächsten Mal: Daten → Alle aktualisieren. Spaltenüberschriften müssen exakt zur Ziel-Tabelle passen (siehe Vorlagen).
A16: Zielblatt | B16: CSV-Vorlage | C16: Typ-Flag | D16: Trennzeichen | E16: Encoding | F16: Bemerkung
A17: 02_Kunden | B17: templates/kunden.csv | C17: kunden | D17: ; | E17: utf-8-sig | F17: Debitorenstamm
A18: 03_Lieferanten | B18: templates/lieferanten.csv | C18: lieferanten | D18: ; | E18: utf-8-sig | F18: Kreditorenstamm
A19: 04_Personal | B19: templates/personal.csv | C19: personal | D19: ; | E19: utf-8-sig | F19: Sätze überschreiben bestehendes Nr.
A20: 05_Projekte | B20: templates/projekte.csv | C20: projekte | D20: ; | E20: utf-8-sig | F20: nur Stammdaten-Spalten A–T
A21: 10_Stunden | B21: templates/stunden.csv | C21: stunden | D21: ; | E21: utf-8-sig | F21: aus Terminal / App exportieren
A22: 11_Material | B22: templates/material.csv | C22: material | D22: ; | E22: utf-8-sig | F22: Lieferscheinpositionen
A23: 13_Ausgangsrechnungen | B23: templates/ausgangsrechnungen.csv | C23: ar | D23: ; | E23: utf-8-sig | F23: keine Formelspalten importieren
A24: 14_Eingangsrechnungen | B24: templates/eingangsrechnungen.csv | C24: er | D24: ; | E24: utf-8-sig | F24: DATEV können gemappt werden
A25: 15_Zahlungen | B25: templates/zahlungen.csv | C25: zahlungen | D25: ; | E25: utf-8-sig | F25: manuelle Zahlungen
A26: 15_Zahlungen | B26: templates/bankumsatz.csv | C26: bank | D26: ; | E26: utf-8-sig | F26: Sparkasse/VR-CAMT-ähnlich
A27: 15_Zahlungen | B27: templates/datev_buchungen.csv | C27: datev | D27: ; | E27: utf-8-sig | F27: Buchungsstapel EXTFähig
A30: 3. Bank-CSV Spaltenzuordnung (Typ bank)
A31: CSV-Spalte | B31: Bedeutung
A32: Datum | B32: Buchungstag oder Valuta
A33: Betrag | B33: positiv = Eingang, negativ = Ausgang — Skript dreht das Vorzeichen in Art um
A34: Gegenkonto / Partner | B34: wird Partner
A35: Verwendungszweck | B35: Skript sucht AR-xxxx oder ER-xxxx und setzt Beleg
A36: BIC/Bank | B36: Weg = Bank
A39: 4. DATEV-Buchungsstapel (Typ datev)
A40: Erwartete Spalten: Umsatz (ohne Soll/Haben-KZ), Soll/Haben-KZ, Konto, Gegenkonto, Belegdatum, Buchungstext, Belegfeld1. Konten 8400–8599 bzw. 4400–4499 werden als Ausgangsrechnung grob erkannt, Eingangsrechnungen über Aufwandskonten 3000–7999. Für den produktiven Betrieb Kontenrahmen in scripts/import_csv.py anpassen.
A44: Letzter Import (manuell notieren)
A45: Datum | B45: Datei | C45: Typ | D45: Zeilen | E45: wer

Sheet 31_Anleitung
A1: Bedienung für Inhaber, Bauleitung und Buchhaltung
A2: Diese Mappe ersetzt kein DATEV-Rechnungswesen, steuert aber Liquidität, Projekte, Forecast und Formulare im Alltag
A4: Tägliche Arbeit Bauleitung | B4: Stunden auf 10_Stunden buchen, Material auf 11_Material, Bautagesbericht über 28_Form_Bautage drucken (Projekt + Datum wählen). Nachträge sofort auf 07_Nachtraege mit Status angeboten / in Prüfung / beauftragt.
A8: Wöchentlich Buchhaltung | B8: Eingangsrechnungen auf 14_ erfassen, Zahlungen importieren (Bank-CSV), OPOS 16_ prüfen, Mahnwesen 17_ eine Stufe weiter, Dashboard 24_ mit der GF besprechen. Gelbe Zellen in 20_Liquiditaet auf bekannte Abschläge und Lohnläufe aktualisieren.
A12: Monatlich Kaufmann / GF | B12: Forecast 21_ rollierend machen (Ist bleibt Formel, Plan in den gelben Planzeilen). BWA 22_ und Soll-Ist 23_ gegen Nachkalkulation lesen. Einbehalte auf 18_ nachziehen. Angebote ohne Entscheidung in 08_ bereinigen.
A16: Projekt neu | B16: Kunde anlegen → Angebot 08_ → bei Zuschlag Auftrag 09_ und Projekt 05_ → LV-Positionen 06_ → Budgets in 05_ (Material, NU, Lohn, Gerät, GK). Ab dann laufen DB, Fertigstellung und OP automatisch.
A20: Rechnung schreiben | B20: Zeile in 13_Ausgangsrechnungen anlegen (Typ Abschlag/Schluss, Netto, Einbehalt %). Blatt 26_Form_Rechnung öffnen, Nummer wählen, drucken. Zahlung später per Import — Offen und Status folgen der Bank.
A24: Was die Mappe bewusst nicht ist | B24: Kein Ersatz für Lohnabrechnung, Anlagenbuchhaltung oder die USt-Voranmeldung. Keine GoBD-revisionssichere Buchführung. Belege bleiben im DATEV/Unternehmen-online; diese Datei ist das Steuerungs-Cockpit.
A28: Ampeln | B28: OK = unkritisch. ENG = unter 125 % der Mindestliquidität. ENGPASS = unter Mindestliquidität. PRÜFEN im Soll-Ist = Marge < 8 %, Kosten über Budget oder OP > 50 T€.
A32: Datensicherheit | B32: Datei auf dem Firmenlaufwerk versionieren, monatlich unter Archiv/JJJJ-MM speichern. Personal- und Bankdaten nicht in ungesicherte Cloud-Ordner legen.
