Workbook
Name Berichtswahrung: '00_Start'!$B$12
Name DD_Stichtag: '00_Start'!$B$8
Name DealImpact: '_Listen'!$L$2:$L$9
Name DokStatus: '_Listen'!$E$2:$E$7
Name JaNeinPruefen: '_Listen'!$D$2:$D$4
Name MassStatus: '_Listen'!$H$2:$H$6
Name Phase: '_Listen'!$C$2:$C$6
Name Prioritaet: '_Listen'!$B$2:$B$5
Name Pruefstatus: '_Listen'!$A$2:$A$7
Name QAStatus: '_Listen'!$I$2:$I$7
Name Reifegrad: '_Listen'!$M$2:$M$6
Name RisikoStatus: '_Listen'!$G$2:$G$6
Name Transaktionstyp: '_Listen'!$K$2:$K$8
Name Transaktionstyp_Auswahl: '00_Start'!$B$6
Name Vertragstyp: '_Listen'!$N$2:$N$11
Name Vertraulichkeit: '_Listen'!$J$2:$J$5
Name Vollstaendigkeit: '_Listen'!$F$2:$F$5
Name Zielunternehmen: '00_Start'!$B$5

Sheet _Listen
A1: Pruefstatus | B1: Prioritaet | C1: Phase | D1: JaNeinPruefen | E1: DokStatus | F1: Vollstaendigkeit | G1: RisikoStatus | H1: MassStatus | I1: QAStatus | J1: Vertraulichkeit | K1: Transaktionstyp | L1: DealImpact | M1: Reifegrad | N1: Vertragstyp
A2: Nicht begonnen | B2: Kritisch | C2: Screening | D2: Ja | E2: Nicht angefordert | F2: Ungeprüft | G2: Zu verifizieren | H2: Nicht gestartet | I2: Entwurf | J2: Normal | K2: Share Deal | L2: Bewertung/Kaufpreis | M2: 0 – Nicht vorhanden | N2: Kunde
A3: In Prüfung | B3: Hoch | C3: Vollprüfung | D3: Nein | E3: Angefordert | F3: Unvollständig | G3: Bestätigt | H3: In Arbeit | I3: Gesendet | J3: Vertraulich | K3: Asset Deal | L3: SPA/Haftung | M3: 1 – Ad hoc | N3: Lieferant
A4: Rückfrage | B4: Mittel | C4: Signing | D4: Zu prüfen | E4: Teilweise | F4: Plausibel | G4: Entkräftet | H4: Blockiert | I4: Teilbeantwortet | J4: Streng vertraulich | K4: Beteiligung | L4: Closing-Bedingung | M4: 2 – Definiert | N4: Finanzierung
A5: Blockiert | B5: Niedrig | C5: Closing | E5: Vollständig | F5: Verifiziert | G5: Mitigiert | H5: Erledigt | I5: Beantwortet | J5: Clean Team | K5: Carve-out | L5: Finanzierung | M5: 3 – Implementiert | N5: Miete
A6: Abgeschlossen | C6: Post-Closing | E6: Nicht verfügbar | G6: Akzeptiert | H6: Verworfen | I6: Nachfrage | K6: IPO | L6: Integration/100-Tage-Plan | M6: 4 – Gemessen/optimiert | N6: Lizenz
A7: Nicht anwendbar | E7: Nicht anwendbar | I7: Geschlossen | K7: Refinanzierung | L7: Abbruch/No-go | N7: IT/Cloud
K8: Sonstige | L8: Kein direkter | N8: Distribution
L9: Zu prüfen | N9: Kooperation/JV
N10: Versicherung
N11: Sonstige

Sheet 00_Start
A1: Due-Diligence-Arbeitsmappe
A2: Branchenneutrale, risikoorientierte Arbeitsvorlage. Gelbe Zellen sind Eingaben, blaue Zellen enthalten Formeln. Alle Vorschläge sind auf den konkreten Deal anzupassen.
A4: Projektparameter
A5: Zielunternehmen | D5: Empfohlener Ablauf
A6: Transaktionstyp | B6: Share Deal | D6: 1. Scope & Hypothesen | E6: Perimeter, Materialität, No-go-Kriterien und Workstreams freigeben.
A7: Käufer / Investor | D7: 2. Datenraum & Q&A | E7: Dokumente anfordern, Versionen kontrollieren, Lücken und Widersprüche eskalieren.
A8: DD-Stichtag | D8: 3. Analyse & Triangulation | E8: Management-Daten mit Verträgen, Hauptbuch, externen Quellen und Stichproben belegen.
A9: Projektleitung | D9: 4. Findings & Quantifizierung | E9: Sachverhalt, Evidenz, Ursache, Eintritt, Auswirkung und Exposure trennen.
A10: Version | B10: 1.0 | D10: 5. Deal-Entscheidung | E10: Preis, SPA-Schutz, Closing-Bedingungen, Finanzierung und No-go bewerten.
A11: Vertraulichkeit | B11: Streng vertraulich | D11: 6. Maßnahmen & Übergabe | E11: Owner, Frist, Budget, KPI sowie Day-1-/100-Tage-Plan festlegen.
A12: Berichtswährung | B12: EUR
A13: Materialitätsschwelle (€)
A15: Risiko-Scoring
A16: Wert | B16: Eintrittswahrscheinlichkeit | C16: Auswirkung | D16: Orientierung | E16: Risikoklasse = Eintritt × Auswirkung
A17: 1 | B17: Sehr gering | C17: Unwesentlich | D17: Kein relevanter Einfluss; normale Steuerung
A18: 2 | B18: Gering | C18: Begrenzt | D18: Unter Materialität; lokale Korrektur | E18: 1–4 | F18: Niedrig | G18: Dokumentieren / regulär überwachen
A19: 3 | B19: Möglich | C19: Wesentlich | D19: Management Attention; quantifizieren | E19: 5–9 | F19: Mittel | G19: Maßnahme mit Owner und Frist
A20: 4 | B20: Wahrscheinlich | C20: Schwerwiegend | D20: Deal-/SPA-relevant; IC-Eskalation | E20: 10–16 | F20: Hoch | G20: Quantifizieren und Deal-Schutz entscheiden
A21: 5 | B21: Sehr wahrscheinlich | C21: Existenz-/Deal-kritisch | D21: No-go oder zwingende Vorbedingung | E21: 17–25 | F21: Kritisch | G21: Sofort eskalieren; No-go/CP/Freistellung prüfen
A23: Nutzungshinweise
A24: • Prüfpunkte sind Hypothesen und keine Feststellungen. Findings erst nach belegbarer Evidenz eintragen.
A25: • Risikoscore nicht ausfüllen, bevor Eintritt und Auswirkung begründet sind. Exposure (Low/Base/High) separat quantifizieren.
A26: • Kaufpreisanpassung, Freistellung und operative Maßnahme dürfen dasselbe Risiko nicht unbemerkt doppelt erfassen.
A27: • Personenbezogene Daten minimieren; sensible HR-, Gesundheits- und Kundendaten nur über geeignete Clean-Team-Prozesse verarbeiten.
A28: • Die Vorlage ersetzt keine Rechts-, Steuer-, Wirtschaftsprüfungs-, Cyber- oder Umweltberatung. Rechtslage und Standards zum Transaktionszeitpunkt prüfen.

Sheet 00_Ausfüllhilfe
A1: Ausfüllhilfe & Feldhandbuch
A2: Startpunkt für die Bearbeitung: Tabellen filtern, gewünschtes Arbeitsblatt öffnen und Hinweise in den kommentierten Spaltenköpfen beachten.
A4: Schnellstart
A5: 1 | B5: Im Blatt 00_Start Zielunternehmen, Deal-Typ, Stichtag, Projektleitung, Währung und Materialität festlegen.
A6: 2 | B6: In 03_Dokumente die Request List versenden, Owner und Fristen setzen; Datenqualität und VDR-Pfade laufend pflegen.
A7: 3 | B7: In 02_Checkliste Status, Evidenz und Analyse dokumentieren. Ein Finding erst nach nachvollziehbarer Primärevidenz erfassen.
A8: 4 | B8: Bestätigte Risiken nach 04_Risiken übertragen bzw. dort bewerten: Eintritt, Auswirkung und Exposure Low/Base/High getrennt bestimmen.
A9: 5 | B9: In 05_Maßnahmen nur passende Vorschläge aktivieren; genau einen Owner, Termin, Budget, KPI und ein messbares Abnahmekriterium festlegen.
A10: 6 | B10: Dashboard und Entscheidungs-Gates vor Signing/Closing reviewen; Preis-, SPA-, Finanzierungs- und Integrationsfolgen beschließen.
A12: Farben und Bedienung
A13: Gelb | B13: Eingabe oder aktiv zu bestätigende Auswahl
A14: Hellblau | B14: Automatische Formel – nicht überschreiben
A15: Rot/Orange | B15: Eskalation, hohe Priorität oder überfälliger Punkt
A16: Kommentarindikator | B16: Spaltenkopf oder Feld auswählen/überfahren, um die kontextbezogene Ausfüllhilfe zu lesen
A18: Blattnavigation und Bearbeitungsreihenfolge
A19: Arbeitsblatt | B19: Zweck | C19: Wer füllt aus? | D19: Wann? | E19: Hauptausgabe
A20: 00_Start | B20: Projektparameter, Scoring und Grundregeln festlegen | C20: M&A-Projektleitung | D20: Projektstart / Scope-Änderung | E20: Freigegebene Projektbasis
A21: 00_Ausfüllhilfe | B21: Felddefinitionen, Beispiele und Qualitätsregeln nachschlagen | C21: Alle Bearbeiter | D21: Vor und während jeder Eingabe | E21: Einheitliche Datenerfassung
A22: 01_Dashboard | B22: Fortschritt und Entscheidungsreife überwachen | C22: PMO / Deal Lead | D22: Wöchentlich und vor Gates | E22: Management- und IC-Übersicht
A23: 02_Checkliste | B23: Alle Prüfhypothesen bearbeiten und Findings dokumentieren | C23: Workstream Leads | D23: Laufend | E23: Vollständiger DD-Status
A24: 03_Dokumente | B24: VDR-Anforderungen, Fristen und Datenqualität steuern | C24: PMO / Zielunternehmen | D24: Ab Scope-Freigabe | E24: Vollständige Request List
A25: 04_Risiken | B25: Bestätigte Risiken bewerten, quantifizieren und entscheiden | C25: Workstream Leads / Deal Lead | D25: Nach Evidenz | E25: Priorisiertes Risikoregister
A26: 05_Maßnahmen | B26: Mitigation, Deal-Schutz und Umsetzung nachhalten | C26: Maßnahmen-Owner | D26: Nach Finding / bis Closing | E26: Verbindlicher Aktionsplan
A27: 06_Q&A | B27: Offene Fragen und schriftliche Antworten steuern | C27: Prüfer / Management | D27: Während der Analyse | E27: Nachvollziehbarer Q&A-Audit-Trail
A28: 07_Finanzanalyse | B28: Historische Entwicklung, Cash Conversion und Bilanzkennzahlen analysieren | C28: Financial-DD-Team | D28: Nach Datenlieferung | E28: Normalisierte Finanzbasis
A29: 08_QoE | B29: EBITDA-Normalisierungen einzeln belegen und entscheiden | C29: Financial-DD-Team | D29: Nach GuV-/Kontenanalyse | E29: Reported-to-normalized Bridge
A30: 09_NWC_NetDebt | B30: NWC-Peg und Net-Debt-/Debt-like-Definition vorbereiten | C30: Finance / Legal | D30: Vor SPA-Verhandlung | E30: Closing-Mechanik
... A36: 15_Quellen | B36: Methodische und rechtliche Ausgangsquellen nachvollziehen | C36: Alle Workstreams | D36: Bei Methodik-/Rechtsfragen | E36: Quellenverzeichnis
A38: Detaillierte Feldhilfe – nach Arbeitsblatt oder Feld filtern
A39: Arbeitsblatt | B39: Feld / Spalte | C39: Bearbeitung | D39: Pflichtgrad | E39: Was eintragen? | F39: Beispiel | G39: Format | H39: Quelle / Nachweis | I39: Qualitätsregel / typischer Fehler
A40: 00_Start | B40: Zielunternehmen | C40: Eingabe | D40: Pflicht | E40: Vollständige rechtliche Firma des Prüfungsobjekts eintragen. | F40: Muster GmbH | G40: Text | H40: Handelsregister / Term Sheet | I40: Bei Carve-outs den exakten Perimeter ergänzen.
A41: 00_Start | B41: Transaktionstyp | C41: Eingabe | D41: Pflicht | E41: Geplante rechtliche bzw. wirtschaftliche Transaktionsform auswählen. | F41: Share Deal | G41: Dropdown | H41: Term Sheet / Strukturmemorandum | I41: Bei Mischformen die primäre Struktur auswählen und Details kommentieren.
A42: 00_Start | B42: Käufer / Investor | C42: Eingabe | D42: Pflicht | E42: Erwerbende Gesellschaft bzw. Investorengruppe nennen. | F42: Investor Holding GmbH | G42: Text | H42: Term Sheet | I42: Nicht nur den Projektnamen verwenden.
A43: 00_Start | B43: DD-Stichtag | C43: Eingabe | D43: Pflicht | E43: Informations- bzw. Bewertungsstichtag der Prüfung eintragen. | F43: 30.09.2026 | G43: Datum TT.MM.JJJJ | H43: Projektauftrag | I43: Nicht mit Signing- oder Closing-Datum verwechseln.
A44: 00_Start | B44: Projektleitung | C44: Eingabe | D44: Pflicht | E44: Gesamtverantwortliche Person mit Rolle nennen. | F44: Max Beispiel, M&A Director | G44: Text | H44: Projekt-RACI | I44: Genau eine Gesamtverantwortung festlegen.
A45: 00_Start | B45: Version | C45: Eingabe | D45: Pflicht | E45: Freigabestand der Arbeitsmappe führen. | F45: 1.1 | G45: Versionsnummer | H45: Dokumentenlenkung | I45: Bei materiellen Änderungen Version erhöhen.
A46: 00_Start | B46: Vertraulichkeit | C46: Eingabe | D46: Pflicht | E46: Höchste Schutzstufe für die gesamte Arbeitsmappe auswählen. | F46: Streng vertraulich | G46: Dropdown | H46: NDA / Clean-Team-Regeln | I46: Einzelblätter können eine höhere Schutzstufe benötigen.
A47: 00_Start | B47: Berichtswährung | C47: Eingabe | D47: Pflicht | E47: Einheitliche Währung für alle monetären Eingaben festlegen. | F47: EUR | G47: ISO-Währungscode | H47: Investment Case | I47: Fremdwährungsumrechnung und Stichtagskurs separat dokumentieren.
A48: 00_Start | B48: Materialitätsschwelle (€) | C48: Eingabe | D48: Pflicht | E48: Vom Deal-Team genehmigte quantitative Basisschwelle eintragen. | F48: 100000 | G48: Betrag in Berichtswährung | H48: DD-Scope / Risikotoleranz | I48: Qualitative No-go-Themen bleiben unabhängig vom Betrag wesentlich.
A49: 02_Checkliste | B49: ID | C49: Vorbelegt | D49: Automatisch | E49: Eindeutige Kennung beibehalten; nur beim Ergänzen neuer Zeilen fortlaufend vergeben. | F49: R-014 | G49: Text, eindeutig | H49: Arbeitsmappe | I49: Keine ID doppelt vergeben oder nachträglich umnummerieren.
A50: 02_Checkliste | B50: Prüfbereich | C50: Eingabe | D50: Pflicht | E50: Sachverhalt einer eindeutigen Kategorie zuordnen. | F50: Financial – Working Capital | G50: Auswahl oder kurzer Text | H50: DD-Scope / Master-Checkliste | I50: Nicht mehrere unverbundene Themen in einer Zeile mischen.
... A344: 01_Dashboard | B344: Entscheidung / Kommentar | C344: Eingabe | D344: Bei Abweichung/Entscheidung | E344: Entscheidung, Begründung, Annahmen und offene Einschränkungen knapp dokumentieren. | F344: IC akzeptiert Restrisiko unter Bedingung eines 300 T€ Escrows. | G344: Kurzer Audit-Trail | H344: Meeting-/Entscheidungsprotokoll | I344: Datum und Entscheider nennen; keine vertraulichen Nebendaten kopieren.

Sheet 01_Dashboard
A1: Due-Diligence-Dashboard
A2: Automatische Übersicht aus Checkliste, Dokumenten-, Risiko- und Maßnahmenregistern. Excel berechnet die Kennzahlen beim Öffnen neu.
A3: Zielunternehmen | B3: =Zielunternehmen | E3: Transaktion | F3: =Transaktionstyp_Auswahl -> Share Deal | I3: Stichtag | J3: =DD_Stichtag | L3: Checklistenpunkte | M3: 156
A5: Prüfpunkte gesamt | E5: Abgeschlossen | I5: Fortschritt | M5: Risiko unbewertet
A6: =COUNTA('02_Checkliste'!$A$5:$A$1000) -> 156 | E6: =COUNTIF('02_Checkliste'!$J$5:$J$1000,"Abgeschlossen") -> 0 | I6: =IFERROR(COUNTIF('02_Checkliste'!$J$5:$J$1000,"Abgeschlossen")/COUNTA('02_Checkliste'!$A$5:$A$1000),0) -> 0 | M6: =COUNTIFS('02_Checkliste'!$A$5:$A$1000,"<>",'02_Checkliste'!$P$5:$P$1000,"") -> 156
A9: Hoch / kritisch | E9: Kritische Doks offen | I9: Maßnahmen überfällig | M9: Exposure Base
A10: =COUNTIF('02_Checkliste'!$P$5:$P$1000,"Hoch")+COUNTIF('02_Checkliste'!$P$5:$P$1000,"Kritisch") -> 0 | E10: =COUNTIFS('03_Dokumente'!$F$5:$F$1000,"Kritisch",'03_Dokumente'!$L$5:$L$1000,"<>Vollständig") -> 89 | I10: =COUNTIFS('05_Maßnahmen'!$L$5:$L$500,"<"&TODAY(),'05_Maßnahmen'!$L$5:$L$500,"<>",'05_Maßnahmen'!$M$5:$M$500,"<>Erledigt") -> 0 | M10: =SUM('04_Risiken'!$M$5:$M$500) -> 0
A13: Fortschritt nach Prüfbereich
A14: Prüfbereich | B14: Umfang | C14: Abgeschlossen | D14: Fortschritt | E14: Unbewertet | F14: Hoch/kritisch
A15: Transaktion & Scope | B15: =COUNTIF('02_Checkliste'!$B$5:$B$1000,"Transaktion & Scope") -> 8 | C15: =COUNTIFS('02_Checkliste'!$B$5:$B$1000,"Transaktion & Scope",'02_Checkliste'!$J$5:$J$1000,"Abgeschlossen") -> 0 | D15: =IFERROR(C15/B15,0) -> 0 | E15: =COUNTIFS('02_Checkliste'!$B$5:$B$1000,"Transaktion & Scope",'02_Checkliste'!$P$5:$P$1000,"") -> 8 | F15: =COUNTIFS('02_Checkliste'!$B$5:$B$1000,"Transaktion & Scope",'02_Checkliste'!$P$5:$P$1000,"Hoch")+COUNTIFS('02_Checkliste'!$B$5:$B$1000,"Transaktion & Scope",'02_Checkliste'!$P$5:$P$1000,"Kritisch") -> 0
A16: Corporate & Governance | B16: =COUNTIF('02_Checkliste'!$B$5:$B$1000,"Corporate & Governance") -> 9 | C16: =COUNTIFS('02_Checkliste'!$B$5:$B$1000,"Corporate & Governance",'02_Checkliste'!$J$5:$J$1000,"Abgeschlossen") -> 0 | D16: =IFERROR(C16/B16,0) -> 0 | E16: =COUNTIFS('02_Checkliste'!$B$5:$B$1000,"Corporate & Governance",'02_Checkliste'!$P$5:$P$1000,"") -> 9 | F16: =COUNTIFS('02_Checkliste'!$B$5:$B$1000,"Corporate & Governance",'02_Checkliste'!$P$5:$P$1000,"Hoch")+COUNTIFS('02_Checkliste'!$B$5:$B$1000,"Corporate & Governance",'02_Checkliste'!$P$5:$P$1000,"Kritisch") -> 0
A17: Financial | B17: =COUNTIF('02_Checkliste'!$B$5:$B$1000,"Financial") -> 16 | C17: =COUNTIFS('02_Checkliste'!$B$5:$B$1000,"Financial",'02_Checkliste'!$J$5:$J$1000,"Abgeschlossen") -> 0 | D17: =IFERROR(C17/B17,0) -> 0 | E17: =COUNTIFS('02_Checkliste'!$B$5:$B$1000,"Financial",'02_Checkliste'!$P$5:$P$1000,"") -> 16 | F17: =COUNTIFS('02_Checkliste'!$B$5:$B$1000,"Financial",'02_Checkliste'!$P$5:$P$1000,"Hoch")+COUNTIFS('02_Checkliste'!$B$5:$B$1000,"Financial",'02_Checkliste'!$P$5:$P$1000,"Kritisch") -> 0
A18: Commercial | B18: =COUNTIF('02_Checkliste'!$B$5:$B$1000,"Commercial") -> 10 | C18: =COUNTIFS('02_Checkliste'!$B$5:$B$1000,"Commercial",'02_Checkliste'!$J$5:$J$1000,"Abgeschlossen") -> 0 | D18: =IFERROR(C18/B18,0) -> 0 | E18: =COUNTIFS('02_Checkliste'!$B$5:$B$1000,"Commercial",'02_Checkliste'!$P$5:$P$1000,"") -> 10 | F18: =COUNTIFS('02_Checkliste'!$B$5:$B$1000,"Commercial",'02_Checkliste'!$P$5:$P$1000,"Hoch")+COUNTIFS('02_Checkliste'!$B$5:$B$1000,"Commercial",'02_Checkliste'!$P$5:$P$1000,"Kritisch") -> 0
A19: Tax | B19: =COUNTIF('02_Checkliste'!$B$5:$B$1000,"Tax") -> 11 | C19: =COUNTIFS('02_Checkliste'!$B$5:$B$1000,"Tax",'02_Checkliste'!$J$5:$J$1000,"Abgeschlossen") -> 0 | D19: =IFERROR(C19/B19,0) -> 0 | E19: =COUNTIFS('02_Checkliste'!$B$5:$B$1000,"Tax",'02_Checkliste'!$P$5:$P$1000,"") -> 11 | F19: =COUNTIFS('02_Checkliste'!$B$5:$B$1000,"Tax",'02_Checkliste'!$P$5:$P$1000,"Hoch")+COUNTIFS('02_Checkliste'!$B$5:$B$1000,"Tax",'02_Checkliste'!$P$5:$P$1000,"Kritisch") -> 0
A20: Legal | B20: =COUNTIF('02_Checkliste'!$B$5:$B$1000,"Legal") -> 13 | C20: =COUNTIFS('02_Checkliste'!$B$5:$B$1000,"Legal",'02_Checkliste'!$J$5:$J$1000,"Abgeschlossen") -> 0 | D20: =IFERROR(C20/B20,0) -> 0 | E20: =COUNTIFS('02_Checkliste'!$B$5:$B$1000,"Legal",'02_Checkliste'!$P$5:$P$1000,"") -> 13 | F20: =COUNTIFS('02_Checkliste'!$B$5:$B$1000,"Legal",'02_Checkliste'!$P$5:$P$1000,"Hoch")+COUNTIFS('02_Checkliste'!$B$5:$B$1000,"Legal",'02_Checkliste'!$P$5:$P$1000,"Kritisch") -> 0
A21: Operations | B21: =COUNTIF('02_Checkliste'!$B$5:$B$1000,"Operations") -> 9 | C21: =COUNTIFS('02_Checkliste'!$B$5:$B$1000,"Operations",'02_Checkliste'!$J$5:$J$1000,"Abgeschlossen") -> 0 | D21: =IFERROR(C21/B21,0) -> 0 | E21: =COUNTIFS('02_Checkliste'!$B$5:$B$1000,"Operations",'02_Checkliste'!$P$5:$P$1000,"") -> 9 | F21: =COUNTIFS('02_Checkliste'!$B$5:$B$1000,"Operations",'02_Checkliste'!$P$5:$P$1000,"Hoch")+COUNTIFS('02_Checkliste'!$B$5:$B$1000,"Operations",'02_Checkliste'!$P$5:$P$1000,"Kritisch") -> 0
A22: Supply Chain | B22: =COUNTIF('02_Checkliste'!$B$5:$B$1000,"Supply Chain") -> 7 | C22: =COUNTIFS('02_Checkliste'!$B$5:$B$1000,"Supply Chain",'02_Checkliste'!$J$5:$J$1000,"Abgeschlossen") -> 0 | D22: =IFERROR(C22/B22,0) -> 0 | E22: =COUNTIFS('02_Checkliste'!$B$5:$B$1000,"Supply Chain",'02_Checkliste'!$P$5:$P$1000,"") -> 7 | F22: =COUNTIFS('02_Checkliste'!$B$5:$B$1000,"Supply Chain",'02_Checkliste'!$P$5:$P$1000,"Hoch")+COUNTIFS('02_Checkliste'!$B$5:$B$1000,"Supply Chain",'02_Checkliste'!$P$5:$P$1000,"Kritisch") -> 0
A23: IT & Cyber | B23: =COUNTIF('02_Checkliste'!$B$5:$B$1000,"IT & Cyber") -> 12 | C23: =COUNTIFS('02_Checkliste'!$B$5:$B$1000,"IT & Cyber",'02_Checkliste'!$J$5:$J$1000,"Abgeschlossen") -> 0 | D23: =IFERROR(C23/B23,0) -> 0 | E23: =COUNTIFS('02_Checkliste'!$B$5:$B$1000,"IT & Cyber",'02_Checkliste'!$P$5:$P$1000,"") -> 12 | F23: =COUNTIFS('02_Checkliste'!$B$5:$B$1000,"IT & Cyber",'02_Checkliste'!$P$5:$P$1000,"Hoch")+COUNTIFS('02_Checkliste'!$B$5:$B$1000,"IT & Cyber",'02_Checkliste'!$P$5:$P$1000,"Kritisch") -> 0
A24: Datenschutz | B24: =COUNTIF('02_Checkliste'!$B$5:$B$1000,"Datenschutz") -> 7 | C24: =COUNTIFS('02_Checkliste'!$B$5:$B$1000,"Datenschutz",'02_Checkliste'!$J$5:$J$1000,"Abgeschlossen") -> 0 | D24: =IFERROR(C24/B24,0) -> 0 | E24: =COUNTIFS('02_Checkliste'!$B$5:$B$1000,"Datenschutz",'02_Checkliste'!$P$5:$P$1000,"") -> 7 | F24: =COUNTIFS('02_Checkliste'!$B$5:$B$1000,"Datenschutz",'02_Checkliste'!$P$5:$P$1000,"Hoch")+COUNTIFS('02_Checkliste'!$B$5:$B$1000,"Datenschutz",'02_Checkliste'!$P$5:$P$1000,"Kritisch") -> 0
A25: HR & Pensions | B25: =COUNTIF('02_Checkliste'!$B$5:$B$1000,"HR & Pensions") -> 10 | C25: =COUNTIFS('02_Checkliste'!$B$5:$B$1000,"HR & Pensions",'02_Checkliste'!$J$5:$J$1000,"Abgeschlossen") -> 0 | D25: =IFERROR(C25/B25,0) -> 0 | E25: =COUNTIFS('02_Checkliste'!$B$5:$B$1000,"HR & Pensions",'02_Checkliste'!$P$5:$P$1000,"") -> 10 | F25: =COUNTIFS('02_Checkliste'!$B$5:$B$1000,"HR & Pensions",'02_Checkliste'!$P$5:$P$1000,"Hoch")+COUNTIFS('02_Checkliste'!$B$5:$B$1000,"HR & Pensions",'02_Checkliste'!$P$5:$P$1000,"Kritisch") -> 0
A26: Intellectual Property | B26: =COUNTIF('02_Checkliste'!$B$5:$B$1000,"Intellectual Property") -> 7 | C26: =COUNTIFS('02_Checkliste'!$B$5:$B$1000,"Intellectual Property",'02_Checkliste'!$J$5:$J$1000,"Abgeschlossen") -> 0 | D26: =IFERROR(C26/B26,0) -> 0 | E26: =COUNTIFS('02_Checkliste'!$B$5:$B$1000,"Intellectual Property",'02_Checkliste'!$P$5:$P$1000,"") -> 7 | F26: =COUNTIFS('02_Checkliste'!$B$5:$B$1000,"Intellectual Property",'02_Checkliste'!$P$5:$P$1000,"Hoch")+COUNTIFS('02_Checkliste'!$B$5:$B$1000,"Intellectual Property",'02_Checkliste'!$P$5:$P$1000,"Kritisch") -> 0
A27: ESG, EHS & Produkt | B27: =COUNTIF('02_Checkliste'!$B$5:$B$1000,"ESG, EHS & Produkt") -> 9 | C27: =COUNTIFS('02_Checkliste'!$B$5:$B$1000,"ESG, EHS & Produkt",'02_Checkliste'!$J$5:$J$1000,"Abgeschlossen") -> 0 | D27: =IFERROR(C27/B27,0) -> 0 | E27: =COUNTIFS('02_Checkliste'!$B$5:$B$1000,"ESG, EHS & Produkt",'02_Checkliste'!$P$5:$P$1000,"") -> 9 | F27: =COUNTIFS('02_Checkliste'!$B$5:$B$1000,"ESG, EHS & Produkt",'02_Checkliste'!$P$5:$P$1000,"Hoch")+COUNTIFS('02_Checkliste'!$B$5:$B$1000,"ESG, EHS & Produkt",'02_Checkliste'!$P$5:$P$1000,"Kritisch") -> 0
A28: Real Estate & Assets | B28: =COUNTIF('02_Checkliste'!$B$5:$B$1000,"Real Estate & Assets") -> 5 | C28: =COUNTIFS('02_Checkliste'!$B$5:$B$1000,"Real Estate & Assets",'02_Checkliste'!$J$5:$J$1000,"Abgeschlossen") -> 0 | D28: =IFERROR(C28/B28,0) -> 0 | E28: =COUNTIFS('02_Checkliste'!$B$5:$B$1000,"Real Estate & Assets",'02_Checkliste'!$P$5:$P$1000,"") -> 5 | F28: =COUNTIFS('02_Checkliste'!$B$5:$B$1000,"Real Estate & Assets",'02_Checkliste'!$P$5:$P$1000,"Hoch")+COUNTIFS('02_Checkliste'!$B$5:$B$1000,"Real Estate & Assets",'02_Checkliste'!$P$5:$P$1000,"Kritisch") -> 0
A29: Insurance | B29: =COUNTIF('02_Checkliste'!$B$5:$B$1000,"Insurance") -> 5 | C29: =COUNTIFS('02_Checkliste'!$B$5:$B$1000,"Insurance",'02_Checkliste'!$J$5:$J$1000,"Abgeschlossen") -> 0 | D29: =IFERROR(C29/B29,0) -> 0 | E29: =COUNTIFS('02_Checkliste'!$B$5:$B$1000,"Insurance",'02_Checkliste'!$P$5:$P$1000,"") -> 5 | F29: =COUNTIFS('02_Checkliste'!$B$5:$B$1000,"Insurance",'02_Checkliste'!$P$5:$P$1000,"Hoch")+COUNTIFS('02_Checkliste'!$B$5:$B$1000,"Insurance",'02_Checkliste'!$P$5:$P$1000,"Kritisch") -> 0
A30: Compliance, AML & Sanctions | B30: =COUNTIF('02_Checkliste'!$B$5:$B$1000,"Compliance, AML & Sanctions") -> 9 | C30: =COUNTIFS('02_Checkliste'!$B$5:$B$1000,"Compliance, AML & Sanctions",'02_Checkliste'!$J$5:$J$1000,"Abgeschlossen") -> 0 | D30: =IFERROR(C30/B30,0) -> 0 | E30: =COUNTIFS('02_Checkliste'!$B$5:$B$1000,"Compliance, AML & Sanctions",'02_Checkliste'!$P$5:$P$1000,"") -> 9 | F30: =COUNTIFS('02_Checkliste'!$B$5:$B$1000,"Compliance, AML & Sanctions",'02_Checkliste'!$P$5:$P$1000,"Hoch")+COUNTIFS('02_Checkliste'!$B$5:$B$1000,"Compliance, AML & Sanctions",'02_Checkliste'!$P$5:$P$1000,"Kritisch") -> 0
A31: Carve-out & Integration | B31: =COUNTIF('02_Checkliste'!$B$5:$B$1000,"Carve-out & Integration") -> 9 | C31: =COUNTIFS('02_Checkliste'!$B$5:$B$1000,"Carve-out & Integration",'02_Checkliste'!$J$5:$J$1000,"Abgeschlossen") -> 0 | D31: =IFERROR(C31/B31,0) -> 0 | E31: =COUNTIFS('02_Checkliste'!$B$5:$B$1000,"Carve-out & Integration",'02_Checkliste'!$P$5:$P$1000,"") -> 9 | F31: =COUNTIFS('02_Checkliste'!$B$5:$B$1000,"Carve-out & Integration",'02_Checkliste'!$P$5:$P$1000,"Hoch")+COUNTIFS('02_Checkliste'!$B$5:$B$1000,"Carve-out & Integration",'02_Checkliste'!$P$5:$P$1000,"Kritisch") -> 0
A34: Entscheidungs-Gates
A35: Gate | B35: Leitfrage | C35: Status | D35: Owner | E35: Entscheidung / Kommentar
A36: G1 | B36: Sind Deal Perimeter und Eigentum zweifelsfrei? | C36: Offen
A37: G2 | B37: Sind normalisiertes EBITDA, Net Debt und NWC belastbar? | C37: Offen
A38: G3 | B38: Sind Genehmigungen, Consents und Finanzierung auf kritischem Pfad gesichert? | C38: Offen
A39: G4 | B39: Sind wesentliche Legal-, Tax-, Compliance-, Cyber- und ESG-Risiken mitigiert? | C39: Offen
A40: G5 | B40: Sind Day 1, TSA und Schlüsselpersonen einsatzbereit? | C40: Offen
A41: G6 | B41: Ist der verbleibende Downside innerhalb der genehmigten Risikotoleranz? | C41: Offen

Sheet 02_Checkliste
A1: Master-Checkliste
A2: 156 risikoorientierte Prüfpunkte. Vorschläge sind Hypothesen; tatsächliche Feststellungen benötigen Evidenz.
A4: ID | B4: Prüfbereich | C4: Unterbereich | D4: Prüfziel / Prüffrage | E4: Benötigte Unterlagen / Daten | F4: Empfohlene Analyse | G4: Typische Red Flags | H4: Priorität | I4: Phase | J4: Status | K4: Verantwortlich | L4: Fälligkeit | M4: Eintritt (1–5) | N4: Auswirkung (1–5) | O4: Risikoscore | P4: Risikoklasse | Q4: Feststellung / Evidenz | R4: Maßnahmenvorschlag | S4: Deal-Implikation | T4: Kaufpreiseffekt (€) | U4: SPA-/Schutzmechanismus | V4: Dokument-/Q&A-Referenz | W4: Quelle | X4: Letzte Aktualisierung | Y4: Reviewer
A5: TRX-01 | B5: Transaktion & Scope | C5: Deal Perimeter | D5: Sind Zielgesellschaften, Vermögenswerte, Schulden und ausgenommene Positionen eindeutig abgegrenzt? | E5: Strukturdiagramm, Term Sheet, Perimeter-Liste, Asset- und Beteiligungsverzeichnis | F5: Perimeter mit Abschlüssen, Verträgen und Bewertungsmodell abstimmen; Lückenliste erstellen. | G5: Nicht konsolidierte Einheiten, nicht übertragbare Assets, unklare Haftungszuordnung | H5: Kritisch | I5: Screening | J5: Nicht begonnen | O5: =IF(OR(M5="",N5=""),"",M5*N5) | P5: =IF(O5="","",IF(O5>=17,"Kritisch",IF(O5>=10,"Hoch",IF(O5>=5,"Mittel","Niedrig")))) | R5: Perimeter verbindlich festlegen und Abweichungen im SPA sowie Kaufpreismodell abbilden. | S5: Bewertung/Kaufpreis | U5: Definitionen, Closing Accounts, Freistellung | W5: S03
A6: TRX-02 | B6: Transaktion & Scope | C6: Transaktionsstruktur | D6: Ist Share Deal, Asset Deal oder Mischform wirtschaftlich, rechtlich und steuerlich belastbar? | E6: Term Sheet, Strukturmemorandum, Steuer- und Rechtsgutachten | F6: Alternativen nach Steuern, Haftungsübergang, Übertragbarkeit und Umsetzungsrisiko vergleichen. | G6: Struktur nur steuergetrieben, unerforderliche Zustimmungen, ungeklärte Gesamtrechtsnachfolge | H6: Kritisch | I6: Screening | J6: Nicht begonnen | O6: =IF(OR(M6="",N6=""),"",M6*N6) | P6: =IF(O6="","",IF(O6>=17,"Kritisch",IF(O6>=10,"Hoch",IF(O6>=5,"Mittel","Niedrig")))) | R6: Strukturoptionen mit Entscheidungsmatrix dokumentieren und bevorzugte Struktur freigeben. | S6: Abbruch/No-go | U6: Closing-Bedingung, Struktur-Covenant | W6: S03
A7: TRX-03 | B7: Transaktion & Scope | C7: Materialität | D7: Sind Materialitätsschwellen je Prüfungsbereich definiert und konsistent? | E7: DD-Scope, Bewertungsmodell, Risikotoleranz, Finanzierungsvorgaben | F7: Quantitative und qualitative Schwellen einschließlich No-go-Kriterien festlegen. | G7: Beliebige Einzelfallentscheidungen, kleine wiederkehrende Fehler werden unterschätzt | H7: Hoch | I7: Screening | J7: Nicht begonnen | O7: =IF(OR(M7="",N7=""),"",M7*N7) | P7: =IF(O7="","",IF(O7>=17,"Kritisch",IF(O7>=10,"Hoch",IF(O7>=5,"Mittel","Niedrig")))) | R7: Materialitätsmatrix mit Eskalations- und Genehmigungsstufen beschließen. | S7: Integration/100-Tage-Plan | U7: Reporting-Covenant | W7: S01
A8: TRX-04 | B8: Transaktion & Scope | C8: Stichtag & Zeitraum | D8: Decken Prüfungszeitraum und Stichtag die Werttreiber und aktuelle Entwicklung angemessen ab? | E8: Jahresabschlüsse, Monatsreporting, LTM-Daten, Ereignisse nach Stichtag | F8: Historie, LTM und aktuelle Monatsdaten überleiten; Subsequent Events prüfen. | G8: Veraltete Daten, starke Abweichung nach Stichtag, fehlende Monatsabschlüsse | H8: Hoch | I8: Vollprüfung | J8: Nicht begonnen | O8: =IF(OR(M8="",N8=""),"",M8*N8) | P8: =IF(O8="","",IF(O8>=17,"Kritisch",IF(O8>=10,"Hoch",IF(O8>=5,"Mittel","Niedrig")))) | R8: Bring-down-Daten und Aktualisierung vor Signing/Closing vertraglich verlangen. | S8: SPA/Haftung | U8: Bring-down, Closing-Bedingung | W8: S05
A9: TRX-05 | B9: Transaktion & Scope | C9: Datenraumqualität | D9: Sind Datenraum, Index, Versionierung und Vollständigkeit prüfbar? | E9: VDR-Index, Upload-Log, Berechtigungsmatrix, Vollständigkeitserklärung | F9: Index gegen Request List abgleichen; Dubletten, fehlende Versionen und späte Uploads markieren. | G9: Massen-Uploads kurz vor Deadline, widersprüchliche Versionen, gelöschte Dateien | H9: Kritisch | I9: Vollprüfung | J9: Nicht begonnen | O9: =IF(OR(M9="",N9=""),"",M9*N9) | P9: =IF(O9="","",IF(O9>=17,"Kritisch",IF(O9>=10,"Hoch",IF(O9>=5,"Mittel","Niedrig")))) | R9: VDR-Governance, Cut-off und finale Datenraum-DVD/Archiv vereinbaren. | S9: SPA/Haftung | U9: Disclosure-Regeln, Vollständigkeitserklärung | W9: S02
A10: TRX-06 | B10: Transaktion & Scope | C10: Management-Auskünfte | D10: Sind Management-Aussagen dokumentiert, konsistent und evidenzbasiert? | E10: Q&A-Protokolle, Management-Präsentation, Datenquellen, Representation Letter | F10: Aussagen triangulieren und wesentliche mündliche Zusagen schriftlich bestätigen lassen. | G10: Ausweichende Antworten, häufige Korrekturen, fehlende Evidenz | H10: Hoch | I10: Vollprüfung | J10: Nicht begonnen | O10: =IF(OR(M10="",N10=""),"",M10*N10) | P10: =IF(O10="","",IF(O10>=17,"Kritisch",IF(O10>=10,"Hoch",IF(O10>=5,"Mittel","Niedrig")))) | R10: Offene Aussagen in Q&A nachverfolgen und als Garantie oder Closing Deliverable absichern. | S10: SPA/Haftung | U10: Garantie, Covenant, Closing Deliverable | W10: S03
A11: TRX-07 | B11: Transaktion & Scope | C11: Interessenkonflikte | D11: Sind Management-Incentives, Verkäuferinteressen und Beraterabhängigkeiten transparent? | E11: Bonuspläne, MIP, Beraterverträge, Related-Party-Liste | F11: Anreize auf mögliche Ergebnissteuerung, Retention und Deal-Abhängigkeit analysieren. | G11: Transaktionsbonus nur bei hohem Kaufpreis, undisclosed related parties | H11: Hoch | I11: Screening | J11: Nicht begonnen | O11: =IF(OR(M11="",N11=""),"",M11*N11) | P11: =IF(O11="","",IF(O11>=17,"Kritisch",IF(O11>=10,"Hoch",IF(O11>=5,"Mittel","Niedrig")))) | R11: Konflikte offenlegen, unabhängige Validierung und angepasste Incentives vorsehen. | S11: Bewertung/Kaufpreis | U11: Disclosure, Retention-Vereinbarung | W11: S01
A12: TRX-08 | B12: Transaktion & Scope | C12: Regulatorischer Pfad | D12: Sind erforderliche Fusionskontroll-, Investitionskontroll- und Branchenfreigaben identifiziert? | E12: Umsatzdaten nach Land, Eigentümerstruktur, Lizenzen, Regulatory Memo | F12: Schwellenwerte, Zuständigkeiten, Long-stop Date und Vollzugsrisiko prüfen. | G12: Gun jumping, übersehene Anmeldung, kritische ausländische Beteiligung | H12: Kritisch | I12: Screening | J12: Nicht begonnen | O12: =IF(OR(M12="",N12=""),"",M12*N12) | P12: =IF(O12="","",IF(O12>=17,"Kritisch",IF(O12>=10,"Hoch",IF(O12>=5,"Mittel","Niedrig")))) | R12: Anmeldestrategie, Verantwortlichkeiten und Long-stop-/Termination-Regelung festlegen. | S12: Closing-Bedingung | U12: Condition precedent, Long-stop Date | W12: S03
A13: COR-01 | B13: Corporate & Governance | C13: Existenz & Vertretung | D13: Sind Gesellschaften wirksam errichtet und Vertretungsbefugnisse aktuell? | E13: Registerauszüge, Satzungen, Geschäftsführerlisten, Vollmachten | F13: Registerdaten mit internen Unterlagen und Signaturrechten abgleichen. | G13: Abweichende Geschäftsführer, abgelaufene Vollmachten, fehlende Eintragung | H13: Kritisch | I13: Vollprüfung | J13: Nicht begonnen | O13: =IF(OR(M13="",N13=""),"",M13*N13) | P13: =IF(O13="","",IF(O13>=17,"Kritisch",IF(O13>=10,"Hoch",IF(O13>=5,"Mittel","Niedrig")))) | R13: Register und Vollmachten vor Closing bereinigen. | S13: Closing-Bedingung | U13: Closing Deliverable, Garantie | W13: S03
A14: COR-02 | B14: Corporate & Governance | C14: Cap Table | D14: Ist die Eigentümerstruktur vollständig verwässert und frei von unbekannten Rechten? | E14: Gesellschafterliste, Aktienbuch, Optionen, Wandeldarlehen, VSOP/ESOP | F14: Fully diluted Cap Table rechnen und auf Abschlüsse sowie Verträge abstimmen. | G14: Nicht erfasste Optionen, Side Letters, strittige Anteile | H14: Kritisch | I14: Vollprüfung | J14: Nicht begonnen | O14: =IF(OR(M14="",N14=""),"",M14*N14) | P14: =IF(O14="","",IF(O14>=17,"Kritisch",IF(O14>=10,"Hoch",IF(O14>=5,"Mittel","Niedrig")))) | R14: Alle Rechte ablösen oder in Kaufpreis und Closing-Mechanik integrieren. | S14: Bewertung/Kaufpreis | U14: Closing-Bedingung, Freistellung | W14: S03
A15: COR-03 | B15: Corporate & Governance | C15: Belastungen | D15: Sind Anteile und wesentliche Assets frei von Pfandrechten oder sonstigen Belastungen? | E15: Pfandverträge, Register, Sicherheitenverzeichnis, Bankbestätigungen | F15: Sicherheiten auf Eigentümer, Rang, Freigabebedingung und Vollständigkeit prüfen. | G15: Nicht freigabefähige Sicherheiten, Cross-Collateral, negative pledge | H15: Kritisch | I15: Vollprüfung | J15: Nicht begonnen | O15: =IF(OR(M15="",N15=""),"",M15*N15) | P15: =IF(O15="","",IF(O15>=17,"Kritisch",IF(O15>=10,"Hoch",IF(O15>=5,"Mittel","Niedrig")))) | R15: Payoff Letter und Freigaben als Closing Deliverables verlangen. | S15: Finanzierung | U15: Debt payoff, Release Condition | W15: S03
A16: COR-04 | B16: Corporate & Governance | C16: Beschlusslage | D16: Sind wesentliche Organbeschlüsse und Transaktionen ordnungsgemäß genehmigt? | E16: Protokolle der letzten fünf Jahre, Geschäftsordnungen, Zustimmungslisten | F16: Beschlüsse auf Form, Quorum, Interessenkonflikte und Folgepflichten prüfen. | G16: Fehlende Genehmigung, rückdatierte Protokolle, dauerhafte Kompetenzverstöße | H16: Hoch | I16: Vollprüfung | J16: Nicht begonnen | O16: =IF(OR(M16="",N16=""),"",M16*N16) | P16: =IF(O16="","",IF(O16>=17,"Kritisch",IF(O16>=10,"Hoch",IF(O16>=5,"Mittel","Niedrig")))) | R16: Heilungsbeschlüsse und aktualisierte Geschäftsordnung umsetzen. | S16: SPA/Haftung | U16: Garantie, Closing Deliverable | W16: S03
... A160: INT-09 | B160: Carve-out & Integration | C160: Integration Governance | D160: Gibt es klare Entscheidungsrechte, Baselines und Benefit Tracking? | E160: IMO-Charter, RACI, Workstreams, KPI, Risiko-/Entscheidungslog | F160: Governance gegen Deal Thesis und kritischen Pfad prüfen. | G160: Kein Baseline Owner, Entscheidungen ohne Eskalationsweg | H160: Hoch | I160: Closing | J160: Nicht begonnen | O160: =IF(OR(M160="",N160=""),"",M160*N160) | P160: =IF(O160="","",IF(O160>=17,"Kritisch",IF(O160>=10,"Hoch",IF(O160>=5,"Mittel","Niedrig")))) | R160: IMO/SteerCo mit KPI, Cadence und Eskalation vor Day 1 aktivieren. | S160: Integration/100-Tage-Plan | U160: Covenant | W160: S03

Sheet 03_Dokumente
A1: Dokumentenanforderung / VDR-Tracker
A2: Aus der Master-Checkliste abgeleitete Request List. Eine Zeile kann bei Bedarf in einzelne Dateien/Datenpakete aufgeteilt werden.
A4: Dok-ID | B4: Prüfbereich | C4: Unterlage / Datensatz | D4: Zeitraum / Scope | E4: Analysezweck | F4: Priorität | G4: Pflicht? | H4: Owner Zielunternehmen | I4: Angefordert am | J4: Fällig am | K4: Erhalten am | L4: Status | M4: Vollständigkeit | N4: Vertraulichkeit | O4: VDR-Pfad / Link | P4: Checklisten-Ref. | Q4: Offene Punkte | R4: Tage überfällig | S4: Reviewer
A5: DOC-001 | B5: Transaktion & Scope | C5: Strukturdiagramm, Term Sheet, Perimeter-Liste, Asset- und Beteiligungsverzeichnis | D5: Aktuell; historische Fälle soweit relevant | E5: Sind Zielgesellschaften, Vermögenswerte, Schulden und ausgenommene Positionen eindeutig abgegrenzt? | F5: Kritisch | G5: Ja | H5: M&A / Legal | L5: Nicht angefordert | M5: Ungeprüft | N5: Vertraulich | P5: TRX-01 | R5: =IF(OR(J5="",L5="Vollständig",L5="Nicht anwendbar"),"",MAX(0,TODAY()-J5))
A6: DOC-002 | B6: Transaktion & Scope | C6: Term Sheet, Strukturmemorandum, Steuer- und Rechtsgutachten | D6: Aktuell; historische Fälle soweit relevant | E6: Ist Share Deal, Asset Deal oder Mischform wirtschaftlich, rechtlich und steuerlich belastbar? | F6: Kritisch | G6: Ja | H6: M&A / Legal | L6: Nicht angefordert | M6: Ungeprüft | N6: Vertraulich | P6: TRX-02 | R6: =IF(OR(J6="",L6="Vollständig",L6="Nicht anwendbar"),"",MAX(0,TODAY()-J6))
A7: DOC-003 | B7: Transaktion & Scope | C7: DD-Scope, Bewertungsmodell, Risikotoleranz, Finanzierungsvorgaben | D7: Aktuell; historische Fälle soweit relevant | E7: Sind Materialitätsschwellen je Prüfungsbereich definiert und konsistent? | F7: Hoch | G7: Ja | H7: M&A / Legal | L7: Nicht angefordert | M7: Ungeprüft | N7: Vertraulich | P7: TRX-03 | R7: =IF(OR(J7="",L7="Vollständig",L7="Nicht anwendbar"),"",MAX(0,TODAY()-J7))
A8: DOC-004 | B8: Transaktion & Scope | C8: Jahresabschlüsse, Monatsreporting, LTM-Daten, Ereignisse nach Stichtag | D8: Aktuell; historische Fälle soweit relevant | E8: Decken Prüfungszeitraum und Stichtag die Werttreiber und aktuelle Entwicklung angemessen ab? | F8: Hoch | G8: Ja | H8: M&A / Legal | L8: Nicht angefordert | M8: Ungeprüft | N8: Vertraulich | P8: TRX-04 | R8: =IF(OR(J8="",L8="Vollständig",L8="Nicht anwendbar"),"",MAX(0,TODAY()-J8))
A9: DOC-005 | B9: Transaktion & Scope | C9: VDR-Index, Upload-Log, Berechtigungsmatrix, Vollständigkeitserklärung | D9: Aktuell; historische Fälle soweit relevant | E9: Sind Datenraum, Index, Versionierung und Vollständigkeit prüfbar? | F9: Kritisch | G9: Ja | H9: M&A / Legal | L9: Nicht angefordert | M9: Ungeprüft | N9: Vertraulich | P9: TRX-05 | R9: =IF(OR(J9="",L9="Vollständig",L9="Nicht anwendbar"),"",MAX(0,TODAY()-J9))
A10: DOC-006 | B10: Transaktion & Scope | C10: Q&A-Protokolle, Management-Präsentation, Datenquellen, Representation Letter | D10: Aktuell; historische Fälle soweit relevant | E10: Sind Management-Aussagen dokumentiert, konsistent und evidenzbasiert? | F10: Hoch | G10: Ja | H10: M&A / Legal | L10: Nicht angefordert | M10: Ungeprüft | N10: Vertraulich | P10: TRX-06 | R10: =IF(OR(J10="",L10="Vollständig",L10="Nicht anwendbar"),"",MAX(0,TODAY()-J10))
A11: DOC-007 | B11: Transaktion & Scope | C11: Bonuspläne, MIP, Beraterverträge, Related-Party-Liste | D11: Aktuell; historische Fälle soweit relevant | E11: Sind Management-Incentives, Verkäuferinteressen und Beraterabhängigkeiten transparent? | F11: Hoch | G11: Ja | H11: M&A / Legal | L11: Nicht angefordert | M11: Ungeprüft | N11: Vertraulich | P11: TRX-07 | R11: =IF(OR(J11="",L11="Vollständig",L11="Nicht anwendbar"),"",MAX(0,TODAY()-J11))
A12: DOC-008 | B12: Transaktion & Scope | C12: Umsatzdaten nach Land, Eigentümerstruktur, Lizenzen, Regulatory Memo | D12: Aktuell; historische Fälle soweit relevant | E12: Sind erforderliche Fusionskontroll-, Investitionskontroll- und Branchenfreigaben identifiziert? | F12: Kritisch | G12: Ja | H12: M&A / Legal | L12: Nicht angefordert | M12: Ungeprüft | N12: Vertraulich | P12: TRX-08 | R12: =IF(OR(J12="",L12="Vollständig",L12="Nicht anwendbar"),"",MAX(0,TODAY()-J12))
A13: DOC-009 | B13: Corporate & Governance | C13: Registerauszüge, Satzungen, Geschäftsführerlisten, Vollmachten | D13: Aktuell; historische Fälle soweit relevant | E13: Sind Gesellschaften wirksam errichtet und Vertretungsbefugnisse aktuell? | F13: Kritisch | G13: Ja | H13: Legal / Corporate | L13: Nicht angefordert | M13: Ungeprüft | N13: Vertraulich | P13: COR-01 | R13: =IF(OR(J13="",L13="Vollständig",L13="Nicht anwendbar"),"",MAX(0,TODAY()-J13))
A14: DOC-010 | B14: Corporate & Governance | C14: Gesellschafterliste, Aktienbuch, Optionen, Wandeldarlehen, VSOP/ESOP | D14: Aktuell; historische Fälle soweit relevant | E14: Ist die Eigentümerstruktur vollständig verwässert und frei von unbekannten Rechten? | F14: Kritisch | G14: Ja | H14: Legal / Corporate | L14: Nicht angefordert | M14: Ungeprüft | N14: Vertraulich | P14: COR-02 | R14: =IF(OR(J14="",L14="Vollständig",L14="Nicht anwendbar"),"",MAX(0,TODAY()-J14))
A15: DOC-011 | B15: Corporate & Governance | C15: Pfandverträge, Register, Sicherheitenverzeichnis, Bankbestätigungen | D15: Aktuell; historische Fälle soweit relevant | E15: Sind Anteile und wesentliche Assets frei von Pfandrechten oder sonstigen Belastungen? | F15: Kritisch | G15: Ja | H15: Legal / Corporate | L15: Nicht angefordert | M15: Ungeprüft | N15: Vertraulich | P15: COR-03 | R15: =IF(OR(J15="",L15="Vollständig",L15="Nicht anwendbar"),"",MAX(0,TODAY()-J15))
A16: DOC-012 | B16: Corporate & Governance | C16: Protokolle der letzten fünf Jahre, Geschäftsordnungen, Zustimmungslisten | D16: Aktuell; historische Fälle soweit relevant | E16: Sind wesentliche Organbeschlüsse und Transaktionen ordnungsgemäß genehmigt? | F16: Hoch | G16: Ja | H16: Legal / Corporate | L16: Nicht angefordert | M16: Ungeprüft | N16: Vertraulich | P16: COR-04 | R16: =IF(OR(J16="",L16="Vollständig",L16="Nicht anwendbar"),"",MAX(0,TODAY()-J16))
... A160: DOC-156 | B160: Carve-out & Integration | C160: IMO-Charter, RACI, Workstreams, KPI, Risiko-/Entscheidungslog | D160: Aktuell; historische Fälle soweit relevant | E160: Gibt es klare Entscheidungsrechte, Baselines und Benefit Tracking? | F160: Hoch | G160: Ja | H160: PMO / Separation | L160: Nicht angefordert | M160: Ungeprüft | N160: Vertraulich | P160: INT-09 | R160: =IF(OR(J160="",L160="Vollständig",L160="Nicht anwendbar"),"",MAX(0,TODAY()-J160))

Sheet 04_Risiken
A1: Risikoregister
A2: Vorausgefüllte Prüfhypothesen – ausdrücklich keine bestätigten Findings. Eintritt, Auswirkung und Exposure erst nach Evidenz bewerten.
A4: Risiko-ID | B4: Prüfbereich | C4: Prüfhypothese / Szenario | D4: Indikatoren / benötigte Evidenz | E4: Analyse / Test | F4: Bewertungsstatus | G4: Feststellung / Evidenz | H4: Eintritt (1–5) | I4: Auswirkung (1–5) | J4: Score | K4: Klasse | L4: Exposure Low (€) | M4: Exposure Base (€) | N4: Exposure High (€) | O4: Gegenmaßnahme | P4: Owner | Q4: Fälligkeit | R4: Maßnahmenstatus | S4: Transaktionsfolge | T4: Checklisten-Ref. | U4: Resteintritt | V4: Restauswirkung | W4: Restscore | X4: Restklasse | Y4: Entscheidung / Kommentar | Z4: Reviewer
A5: R-001 | B5: Transaktion & Scope | C5: Nicht konsolidierte Einheiten, nicht übertragbare Assets, unklare Haftungszuordnung | D5: Strukturdiagramm, Term Sheet, Perimeter-Liste, Asset- und Beteiligungsverzeichnis | E5: Perimeter mit Abschlüssen, Verträgen und Bewertungsmodell abstimmen; Lückenliste erstellen. | F5: Zu verifizieren | J5: =IF(OR(H5="",I5=""),"",H5*I5) | K5: =IF(J5="","",IF(J5>=17,"Kritisch",IF(J5>=10,"Hoch",IF(J5>=5,"Mittel","Niedrig")))) | O5: Perimeter verbindlich festlegen und Abweichungen im SPA sowie Kaufpreismodell abbilden. | R5: Nicht gestartet | S5: Bewertung/Kaufpreis | T5: TRX-01 | W5: =IF(OR(U5="",V5=""),"",U5*V5) | X5: =IF(W5="","",IF(W5>=17,"Kritisch",IF(W5>=10,"Hoch",IF(W5>=5,"Mittel","Niedrig"))))
A6: R-002 | B6: Transaktion & Scope | C6: Struktur nur steuergetrieben, unerforderliche Zustimmungen, ungeklärte Gesamtrechtsnachfolge | D6: Term Sheet, Strukturmemorandum, Steuer- und Rechtsgutachten | E6: Alternativen nach Steuern, Haftungsübergang, Übertragbarkeit und Umsetzungsrisiko vergleichen. | F6: Zu verifizieren | J6: =IF(OR(H6="",I6=""),"",H6*I6) | K6: =IF(J6="","",IF(J6>=17,"Kritisch",IF(J6>=10,"Hoch",IF(J6>=5,"Mittel","Niedrig")))) | O6: Strukturoptionen mit Entscheidungsmatrix dokumentieren und bevorzugte Struktur freigeben. | R6: Nicht gestartet | S6: Abbruch/No-go | T6: TRX-02 | W6: =IF(OR(U6="",V6=""),"",U6*V6) | X6: =IF(W6="","",IF(W6>=17,"Kritisch",IF(W6>=10,"Hoch",IF(W6>=5,"Mittel","Niedrig"))))
A7: R-003 | B7: Transaktion & Scope | C7: Massen-Uploads kurz vor Deadline, widersprüchliche Versionen, gelöschte Dateien | D7: VDR-Index, Upload-Log, Berechtigungsmatrix, Vollständigkeitserklärung | E7: Index gegen Request List abgleichen; Dubletten, fehlende Versionen und späte Uploads markieren. | F7: Zu verifizieren | J7: =IF(OR(H7="",I7=""),"",H7*I7) | K7: =IF(J7="","",IF(J7>=17,"Kritisch",IF(J7>=10,"Hoch",IF(J7>=5,"Mittel","Niedrig")))) | O7: VDR-Governance, Cut-off und finale Datenraum-DVD/Archiv vereinbaren. | R7: Nicht gestartet | S7: SPA/Haftung | T7: TRX-05 | W7: =IF(OR(U7="",V7=""),"",U7*V7) | X7: =IF(W7="","",IF(W7>=17,"Kritisch",IF(W7>=10,"Hoch",IF(W7>=5,"Mittel","Niedrig"))))
A8: R-004 | B8: Transaktion & Scope | C8: Gun jumping, übersehene Anmeldung, kritische ausländische Beteiligung | D8: Umsatzdaten nach Land, Eigentümerstruktur, Lizenzen, Regulatory Memo | E8: Schwellenwerte, Zuständigkeiten, Long-stop Date und Vollzugsrisiko prüfen. | F8: Zu verifizieren | J8: =IF(OR(H8="",I8=""),"",H8*I8) | K8: =IF(J8="","",IF(J8>=17,"Kritisch",IF(J8>=10,"Hoch",IF(J8>=5,"Mittel","Niedrig")))) | O8: Anmeldestrategie, Verantwortlichkeiten und Long-stop-/Termination-Regelung festlegen. | R8: Nicht gestartet | S8: Closing-Bedingung | T8: TRX-08 | W8: =IF(OR(U8="",V8=""),"",U8*V8) | X8: =IF(W8="","",IF(W8>=17,"Kritisch",IF(W8>=10,"Hoch",IF(W8>=5,"Mittel","Niedrig"))))
A9: R-005 | B9: Corporate & Governance | C9: Abweichende Geschäftsführer, abgelaufene Vollmachten, fehlende Eintragung | D9: Registerauszüge, Satzungen, Geschäftsführerlisten, Vollmachten | E9: Registerdaten mit internen Unterlagen und Signaturrechten abgleichen. | F9: Zu verifizieren | J9: =IF(OR(H9="",I9=""),"",H9*I9) | K9: =IF(J9="","",IF(J9>=17,"Kritisch",IF(J9>=10,"Hoch",IF(J9>=5,"Mittel","Niedrig")))) | O9: Register und Vollmachten vor Closing bereinigen. | R9: Nicht gestartet | S9: Closing-Bedingung | T9: COR-01 | W9: =IF(OR(U9="",V9=""),"",U9*V9) | X9: =IF(W9="","",IF(W9>=17,"Kritisch",IF(W9>=10,"Hoch",IF(W9>=5,"Mittel","Niedrig"))))
A10: R-006 | B10: Corporate & Governance | C10: Nicht erfasste Optionen, Side Letters, strittige Anteile | D10: Gesellschafterliste, Aktienbuch, Optionen, Wandeldarlehen, VSOP/ESOP | E10: Fully diluted Cap Table rechnen und auf Abschlüsse sowie Verträge abstimmen. | F10: Zu verifizieren | J10: =IF(OR(H10="",I10=""),"",H10*I10) | K10: =IF(J10="","",IF(J10>=17,"Kritisch",IF(J10>=10,"Hoch",IF(J10>=5,"Mittel","Niedrig")))) | O10: Alle Rechte ablösen oder in Kaufpreis und Closing-Mechanik integrieren. | R10: Nicht gestartet | S10: Bewertung/Kaufpreis | T10: COR-02 | W10: =IF(OR(U10="",V10=""),"",U10*V10) | X10: =IF(W10="","",IF(W10>=17,"Kritisch",IF(W10>=10,"Hoch",IF(W10>=5,"Mittel","Niedrig"))))
A11: R-007 | B11: Corporate & Governance | C11: Nicht freigabefähige Sicherheiten, Cross-Collateral, negative pledge | D11: Pfandverträge, Register, Sicherheitenverzeichnis, Bankbestätigungen | E11: Sicherheiten auf Eigentümer, Rang, Freigabebedingung und Vollständigkeit prüfen. | F11: Zu verifizieren | J11: =IF(OR(H11="",I11=""),"",H11*I11) | K11: =IF(J11="","",IF(J11>=17,"Kritisch",IF(J11>=10,"Hoch",IF(J11>=5,"Mittel","Niedrig")))) | O11: Payoff Letter und Freigaben als Closing Deliverables verlangen. | R11: Nicht gestartet | S11: Finanzierung | T11: COR-03 | W11: =IF(OR(U11="",V11=""),"",U11*V11) | X11: =IF(W11="","",IF(W11>=17,"Kritisch",IF(W11>=10,"Hoch",IF(W11>=5,"Mittel","Niedrig"))))
A12: R-008 | B12: Corporate & Governance | C12: Unkündbare Vetorechte, fehlende Drag-Ausübung, Zustimmung Dritter | D12: Gesellschaftervereinbarungen, Side Letters, Beteiligungsverträge | E12: Rechte je Transaktionsschritt und benötigte Waiver dokumentieren. | F12: Zu verifizieren | J12: =IF(OR(H12="",I12=""),"",H12*I12) | K12: =IF(J12="","",IF(J12>=17,"Kritisch",IF(J12>=10,"Hoch",IF(J12>=5,"Mittel","Niedrig")))) | O12: Waiver/Zustimmungen vor Signing oder als Closing-Bedingung beschaffen. | R12: Nicht gestartet | S12: Closing-Bedingung | T12: COR-05 | W12: =IF(OR(U12="",V12=""),"",U12*V12) | X12: =IF(W12="","",IF(W12>=17,"Kritisch",IF(W12>=10,"Hoch",IF(W12>=5,"Mittel","Niedrig"))))
A13: R-009 | B13: Corporate & Governance | C13: Kostenlose Leistungen, sofortige Kündigung, unklare IP-Nutzung | D13: Service-, Darlehens-, Cash-Pool-, Lizenz- und Steuerumlageverträge | E13: Leistungsumfang, Preis, Laufzeit, Kündigung und Stand-alone-Kosten prüfen. | F13: Zu verifizieren | J13: =IF(OR(H13="",I13=""),"",H13*I13) | K13: =IF(J13="","",IF(J13>=17,"Kritisch",IF(J13>=10,"Hoch",IF(J13>=5,"Mittel","Niedrig")))) | O13: TSA oder neue Stand-alone-Verträge mit marktgerechten Konditionen vereinbaren. | R13: Nicht gestartet | S13: Integration/100-Tage-Plan | T13: COR-07 | W13: =IF(OR(U13="",V13=""),"",U13*V13) | X13: =IF(W13="","",IF(W13>=17,"Kritisch",IF(W13>=10,"Hoch",IF(W13>=5,"Mittel","Niedrig"))))
A14: R-010 | B14: Financial | C14: Ungeklärte Überleitungsdifferenzen, häufige Nachbuchungen, eingeschränkter Bestätigungsvermerk | D14: Abschlüsse 3–5 Jahre, Prüfungsberichte, Summen-/Saldenlisten, Kontenpläne | E14: Trial Balance zu Abschluss und Management Reporting überleiten; Differenzen erklären. | F14: Zu verifizieren | J14: =IF(OR(H14="",I14=""),"",H14*I14) | K14: =IF(J14="","",IF(J14>=17,"Kritisch",IF(J14>=10,"Hoch",IF(J14>=5,"Mittel","Niedrig")))) | O14: Datenbereinigung, Abschlussgarantie und belastbare Closing Accounts verlangen. | R14: Nicht gestartet | S14: Bewertung/Kaufpreis | T14: FIN-01 | W14: =IF(OR(U14="",V14=""),"",U14*V14) | X14: =IF(W14="","",IF(W14>=17,"Kritisch",IF(W14>=10,"Hoch",IF(W14>=5,"Mittel","Niedrig"))))
A15: R-011 | B15: Financial | C15: Bill-and-hold, Side Letters, vorgezogener Umsatz, hohe Stornos | D15: Top-Rechnungen, Verträge, Lieferscheine, Gutschriften nach Stichtag | E15: Stichproben um Periodenende; Vertragsbedingungen und nachträgliche Gutschriften prüfen. | F15: Zu verifizieren | J15: =IF(OR(H15="",I15=""),"",H15*I15) | K15: =IF(J15="","",IF(J15>=17,"Kritisch",IF(J15>=10,"Hoch",IF(J15>=5,"Mittel","Niedrig")))) | O15: Umsatz/EBITDA normalisieren und Garantie bzw. Escrow für Fehlbuchungen vereinbaren. | R15: Nicht gestartet | S15: Bewertung/Kaufpreis | T15: FIN-03 | W15: =IF(OR(U15="",V15=""),"",U15*V15) | X15: =IF(W15="","",IF(W15>=17,"Kritisch",IF(W15>=10,"Hoch",IF(W15>=5,"Mittel","Niedrig"))))
A16: R-012 | B16: Financial | C16: Synergien als Ist-EBITDA, wiederkehrende 'Einmaleffekte', unbelegte Adjustments | D16: GuV monatlich, Kontendetails, Einmaleffekte, Management Adjustments | E16: Reported-to-adjusted EBITDA Bridge; Wiederkehr, Cash-Wirkung und Run-rate einzeln belegen. | F16: Zu verifizieren | J16: =IF(OR(H16="",I16=""),"",H16*I16) | K16: =IF(J16="","",IF(J16>=17,"Kritisch",IF(J16>=10,"Hoch",IF(J16>=5,"Mittel","Niedrig")))) | O16: Nur belegte, nachhaltige Adjustments akzeptieren und Bewertungsbasis anpassen. | R16: Nicht gestartet | S16: Bewertung/Kaufpreis | T16: FIN-04 | W16: =IF(OR(U16="",V16=""),"",U16*V16) | X16: =IF(W16="","",IF(W16>=17,"Kritisch",IF(W16>=10,"Hoch",IF(W16>=5,"Mittel","Niedrig"))))
... A64: R-060 | B64: HR & Pensions | C64: Unterlassene Konsultation, nachwirkende Vereinbarung, Streikrisiko | D64: Betriebsvereinbarungen, Tarifverträge, Gremien, Verhandlungsstatus | E64: Transaktions- und Integrationsschritte gegen Pflichten/Fristen planen. | F64: Zu verifizieren | J64: =IF(OR(H64="",I64=""),"",H64*I64) | K64: =IF(J64="","",IF(J64>=17,"Kritisch",IF(J64>=10,"Hoch",IF(J64>=5,"Mittel","Niedrig")))) | O64: Mitbestimmungsfahrplan und Kommunikationsplan als kritischen Pfad führen. | R64: Nicht gestartet | S64: Closing-Bedingung | T64: HR-06 | W64: =IF(OR(U64="",V64=""),"",U64*V64) | X64: =IF(W64="","",IF(W64>=17,"Kritisch",IF(W64>=10,"Hoch",IF(W64>=5,"Mittel","Niedrig"))))

Sheet 05_Maßnahmen
A1: Maßnahmenplan
A2: Vorschläge werden erst nach Bestätigung eines Findings aktiviert. Jede aktive Maßnahme benötigt Owner, Termin und messbares Abnahmekriterium.
A4: Maßnahmen-ID | B4: Aktivieren? | C4: Risiko-/Finding-Ref. | D4: Phase | E4: Prüfbereich | F4: Maßnahmenvorschlag | G4: Ergebnis / Abnahmekriterium | H4: Priorität | I4: Owner | J4: Support | K4: Start | L4: Fällig | M4: Status | N4: Fortschritt | O4: Abhängigkeit | P4: Budget (€) | Q4: Erwartete Wirkung | R4: KPI / Nachweis | S4: Eskalationstrigger | T4: Deal-Mechanismus | U4: Kommentar
A5: M-001 | B5: Zu prüfen | C5: R-001 / TRX-01 | D5: SPA / Signing | E5: Transaktion & Scope | F5: Perimeter verbindlich festlegen und Abweichungen im SPA sowie Kaufpreismodell abbilden. | G5: Maßnahme für TRX-01 dokumentiert, fachlich abgenommen und durch belastbare Evidenz geschlossen. | H5: Kritisch | M5: Nicht gestartet | N5: 0 | Q5: Bewertung/Kaufpreis | R5: Evidenz im VDR; Reviewer-Freigabe | S5: Fristüberschreitung oder Score ≥17 | T5: Definitionen, Closing Accounts, Freistellung
A6: M-002 | B6: Zu prüfen | C6: R-002 / TRX-02 | D6: Pre-Signing | E6: Transaktion & Scope | F6: Strukturoptionen mit Entscheidungsmatrix dokumentieren und bevorzugte Struktur freigeben. | G6: Maßnahme für TRX-02 dokumentiert, fachlich abgenommen und durch belastbare Evidenz geschlossen. | H6: Kritisch | M6: Nicht gestartet | N6: 0 | Q6: Abbruch/No-go | R6: Evidenz im VDR; Reviewer-Freigabe | S6: Fristüberschreitung oder Score ≥17 | T6: Closing-Bedingung, Struktur-Covenant
A7: M-003 | B7: Zu prüfen | C7: R-003 / TRX-05 | D7: SPA / Signing | E7: Transaktion & Scope | F7: VDR-Governance, Cut-off und finale Datenraum-DVD/Archiv vereinbaren. | G7: Maßnahme für TRX-05 dokumentiert, fachlich abgenommen und durch belastbare Evidenz geschlossen. | H7: Kritisch | M7: Nicht gestartet | N7: 0 | Q7: SPA/Haftung | R7: Evidenz im VDR; Reviewer-Freigabe | S7: Fristüberschreitung oder Score ≥17 | T7: Disclosure-Regeln, Vollständigkeitserklärung
A8: M-004 | B8: Zu prüfen | C8: R-004 / TRX-08 | D8: Pre-Signing | E8: Transaktion & Scope | F8: Anmeldestrategie, Verantwortlichkeiten und Long-stop-/Termination-Regelung festlegen. | G8: Maßnahme für TRX-08 dokumentiert, fachlich abgenommen und durch belastbare Evidenz geschlossen. | H8: Kritisch | M8: Nicht gestartet | N8: 0 | Q8: Closing-Bedingung | R8: Evidenz im VDR; Reviewer-Freigabe | S8: Fristüberschreitung oder Score ≥17 | T8: Condition precedent, Long-stop Date
A9: M-005 | B9: Zu prüfen | C9: R-005 / COR-01 | D9: Pre-Signing | E9: Corporate & Governance | F9: Register und Vollmachten vor Closing bereinigen. | G9: Maßnahme für COR-01 dokumentiert, fachlich abgenommen und durch belastbare Evidenz geschlossen. | H9: Kritisch | M9: Nicht gestartet | N9: 0 | Q9: Closing-Bedingung | R9: Evidenz im VDR; Reviewer-Freigabe | S9: Fristüberschreitung oder Score ≥17 | T9: Closing Deliverable, Garantie
A10: M-006 | B10: Zu prüfen | C10: R-006 / COR-02 | D10: SPA / Signing | E10: Corporate & Governance | F10: Alle Rechte ablösen oder in Kaufpreis und Closing-Mechanik integrieren. | G10: Maßnahme für COR-02 dokumentiert, fachlich abgenommen und durch belastbare Evidenz geschlossen. | H10: Kritisch | M10: Nicht gestartet | N10: 0 | Q10: Bewertung/Kaufpreis | R10: Evidenz im VDR; Reviewer-Freigabe | S10: Fristüberschreitung oder Score ≥17 | T10: Closing-Bedingung, Freistellung
A11: M-007 | B11: Zu prüfen | C11: R-007 / COR-03 | D11: SPA / Signing | E11: Corporate & Governance | F11: Payoff Letter und Freigaben als Closing Deliverables verlangen. | G11: Maßnahme für COR-03 dokumentiert, fachlich abgenommen und durch belastbare Evidenz geschlossen. | H11: Kritisch | M11: Nicht gestartet | N11: 0 | Q11: Finanzierung | R11: Evidenz im VDR; Reviewer-Freigabe | S11: Fristüberschreitung oder Score ≥17 | T11: Debt payoff, Release Condition
A12: M-008 | B12: Zu prüfen | C12: R-008 / COR-05 | D12: Pre-Signing | E12: Corporate & Governance | F12: Waiver/Zustimmungen vor Signing oder als Closing-Bedingung beschaffen. | G12: Maßnahme für COR-05 dokumentiert, fachlich abgenommen und durch belastbare Evidenz geschlossen. | H12: Kritisch | M12: Nicht gestartet | N12: 0 | Q12: Closing-Bedingung | R12: Evidenz im VDR; Reviewer-Freigabe | S12: Fristüberschreitung oder Score ≥17 | T12: Consent Condition
A13: M-009 | B13: Zu prüfen | C13: R-009 / COR-07 | D13: Day 1 / 100 Tage | E13: Corporate & Governance | F13: TSA oder neue Stand-alone-Verträge mit marktgerechten Konditionen vereinbaren. | G13: Maßnahme für COR-07 dokumentiert, fachlich abgenommen und durch belastbare Evidenz geschlossen. | H13: Kritisch | M13: Nicht gestartet | N13: 0 | Q13: Integration/100-Tage-Plan | R13: Evidenz im VDR; Reviewer-Freigabe | S13: Fristüberschreitung oder Score ≥17 | T13: TSA, Covenant
A14: M-010 | B14: Zu prüfen | C14: R-010 / FIN-01 | D14: SPA / Signing | E14: Financial | F14: Datenbereinigung, Abschlussgarantie und belastbare Closing Accounts verlangen. | G14: Maßnahme für FIN-01 dokumentiert, fachlich abgenommen und durch belastbare Evidenz geschlossen. | H14: Kritisch | M14: Nicht gestartet | N14: 0 | Q14: Bewertung/Kaufpreis | R14: Evidenz im VDR; Reviewer-Freigabe | S14: Fristüberschreitung oder Score ≥17 | T14: Closing Accounts, Garantie
A15: M-011 | B15: Zu prüfen | C15: R-011 / FIN-03 | D15: SPA / Signing | E15: Financial | F15: Umsatz/EBITDA normalisieren und Garantie bzw. Escrow für Fehlbuchungen vereinbaren. | G15: Maßnahme für FIN-03 dokumentiert, fachlich abgenommen und durch belastbare Evidenz geschlossen. | H15: Kritisch | M15: Nicht gestartet | N15: 0 | Q15: Bewertung/Kaufpreis | R15: Evidenz im VDR; Reviewer-Freigabe | S15: Fristüberschreitung oder Score ≥17 | T15: Kaufpreisanpassung, Garantie
A16: M-012 | B16: Zu prüfen | C16: R-012 / FIN-04 | D16: SPA / Signing | E16: Financial | F16: Nur belegte, nachhaltige Adjustments akzeptieren und Bewertungsbasis anpassen. | G16: Maßnahme für FIN-04 dokumentiert, fachlich abgenommen und durch belastbare Evidenz geschlossen. | H16: Kritisch | M16: Nicht gestartet | N16: 0 | Q16: Bewertung/Kaufpreis | R16: Evidenz im VDR; Reviewer-Freigabe | S16: Fristüberschreitung oder Score ≥17 | T16: Preisformel, Earn-out
... A64: M-060 | B64: Zu prüfen | C64: R-060 / HR-06 | D64: Pre-Signing | E64: HR & Pensions | F64: Mitbestimmungsfahrplan und Kommunikationsplan als kritischen Pfad führen. | G64: Maßnahme für HR-06 dokumentiert, fachlich abgenommen und durch belastbare Evidenz geschlossen. | H64: Kritisch | M64: Nicht gestartet | N64: 0 | Q64: Closing-Bedingung | R64: Evidenz im VDR; Reviewer-Freigabe | S64: Fristüberschreitung oder Score ≥17 | T64: Covenant

Sheet 06_Q&A
A1: Q&A-Tracker
A2: Fragen konkret, neutral und entscheidungsorientiert formulieren. Mündliche Antworten schriftlich bestätigen und mit Evidenz verknüpfen.
A4: Q&A-ID | B4: Erstellt am | C4: Prüfbereich | D4: Check-/Dok-Ref. | E4: Frage | F4: Begründung / Entscheidungskontext | G4: Priorität | H4: Empfänger | I4: Fragesteller | J4: Fällig | K4: Antwort am | L4: Status | M4: Antwort | N4: Evidenz / VDR-Link | O4: Nachfrage / Next Step | P4: Alter (Tage) | Q4: Überfällig? | R4: Reviewer
A5: Q-001 | L5: Entwurf | P5: =IF(B5="","",IF(K5<>"",K5-B5,TODAY()-B5)) | Q5: =IF(OR(J5="",L5="Beantwortet",L5="Geschlossen"),"",IF(TODAY()>J5,"Ja","Nein"))
A6: Q-002 | L6: Entwurf | P6: =IF(B6="","",IF(K6<>"",K6-B6,TODAY()-B6)) | Q6: =IF(OR(J6="",L6="Beantwortet",L6="Geschlossen"),"",IF(TODAY()>J6,"Ja","Nein"))
A7: Q-003 | L7: Entwurf | P7: =IF(B7="","",IF(K7<>"",K7-B7,TODAY()-B7)) | Q7: =IF(OR(J7="",L7="Beantwortet",L7="Geschlossen"),"",IF(TODAY()>J7,"Ja","Nein"))
A8: Q-004 | L8: Entwurf | P8: =IF(B8="","",IF(K8<>"",K8-B8,TODAY()-B8)) | Q8: =IF(OR(J8="",L8="Beantwortet",L8="Geschlossen"),"",IF(TODAY()>J8,"Ja","Nein"))
A9: Q-005 | L9: Entwurf | P9: =IF(B9="","",IF(K9<>"",K9-B9,TODAY()-B9)) | Q9: =IF(OR(J9="",L9="Beantwortet",L9="Geschlossen"),"",IF(TODAY()>J9,"Ja","Nein"))
A10: Q-006 | L10: Entwurf | P10: =IF(B10="","",IF(K10<>"",K10-B10,TODAY()-B10)) | Q10: =IF(OR(J10="",L10="Beantwortet",L10="Geschlossen"),"",IF(TODAY()>J10,"Ja","Nein"))
A11: Q-007 | L11: Entwurf | P11: =IF(B11="","",IF(K11<>"",K11-B11,TODAY()-B11)) | Q11: =IF(OR(J11="",L11="Beantwortet",L11="Geschlossen"),"",IF(TODAY()>J11,"Ja","Nein"))
A12: Q-008 | L12: Entwurf | P12: =IF(B12="","",IF(K12<>"",K12-B12,TODAY()-B12)) | Q12: =IF(OR(J12="",L12="Beantwortet",L12="Geschlossen"),"",IF(TODAY()>J12,"Ja","Nein"))
A13: Q-009 | L13: Entwurf | P13: =IF(B13="","",IF(K13<>"",K13-B13,TODAY()-B13)) | Q13: =IF(OR(J13="",L13="Beantwortet",L13="Geschlossen"),"",IF(TODAY()>J13,"Ja","Nein"))
A14: Q-010 | L14: Entwurf | P14: =IF(B14="","",IF(K14<>"",K14-B14,TODAY()-B14)) | Q14: =IF(OR(J14="",L14="Beantwortet",L14="Geschlossen"),"",IF(TODAY()>J14,"Ja","Nein"))
A15: Q-011 | L15: Entwurf | P15: =IF(B15="","",IF(K15<>"",K15-B15,TODAY()-B15)) | Q15: =IF(OR(J15="",L15="Beantwortet",L15="Geschlossen"),"",IF(TODAY()>J15,"Ja","Nein"))
A16: Q-012 | L16: Entwurf | P16: =IF(B16="","",IF(K16<>"",K16-B16,TODAY()-B16)) | Q16: =IF(OR(J16="",L16="Beantwortet",L16="Geschlossen"),"",IF(TODAY()>J16,"Ja","Nein"))
... A104: Q-100 | L104: Entwurf | P104: =IF(B104="","",IF(K104<>"",K104-B104,TODAY()-B104)) | Q104: =IF(OR(J104="",L104="Beantwortet",L104="Geschlossen"),"",IF(TODAY()>J104,"Ja","Nein"))

Sheet 07_Finanzanalyse
A1: Finanzanalyse
A2: Eingaben positiv erfassen (auch Aufwendungen und Schulden); Formeln ziehen Kosten ab. Periodenbezeichnungen können überschrieben werden.
A4: Kennzahl | B4: 2022A | C4: 2023A | D4: 2024A | E4: LTM / aktuell | F4: Budget | G4: Δ LTM vs. 2024 | H4: Δ LTM vs. Budget | I4: Kommentar / Quelle
A5: Umsatz | G5: =IFERROR(E5/D5-1,"") | H5: =IFERROR(E5/F5-1,"")
A6: Umsatzkosten (COGS) | G6: =IFERROR(E6/D6-1,"") | H6: =IFERROR(E6/F6-1,"")
A7: Bruttoergebnis | B7: =B5-B6 -> 0 | C7: =C5-C6 -> 0 | D7: =D5-D6 -> 0 | E7: =E5-E6 -> 0 | F7: =F5-F6 -> 0 | G7: =IFERROR(E7/D7-1,"") | H7: =IFERROR(E7/F7-1,"")
A8: Bruttomarge | B8: =IFERROR(B7/B5,"") | C8: =IFERROR(C7/C5,"") | D8: =IFERROR(D7/D5,"") | E8: =IFERROR(E7/E5,"") | F8: =IFERROR(F7/F5,"") | G8: =IFERROR(E8/D8-1,"") | H8: =IFERROR(E8/F8-1,"")
A9: Personalaufwand | G9: =IFERROR(E9/D9-1,"") | H9: =IFERROR(E9/F9-1,"")
A10: Sonstige Opex | G10: =IFERROR(E10/D10-1,"") | H10: =IFERROR(E10/F10-1,"")
A11: EBITDA berichtet | G11: =IFERROR(E11/D11-1,"") | H11: =IFERROR(E11/F11-1,"")
A12: QoE-Anpassungen (netto) | G12: =IFERROR(E12/D12-1,"") | H12: =IFERROR(E12/F12-1,"")
A13: EBITDA normalisiert | B13: =B11+B12 -> 0 | C13: =C11+C12 -> 0 | D13: =D11+D12 -> 0 | E13: =E11+E12 -> 0 | F13: =F11+F12 -> 0 | G13: =IFERROR(E13/D13-1,"") | H13: =IFERROR(E13/F13-1,"")
A14: EBITDA-Marge normalisiert | B14: =IFERROR(B13/B5,"") | C14: =IFERROR(C13/C5,"") | D14: =IFERROR(D13/D5,"") | E14: =IFERROR(E13/E5,"") | F14: =IFERROR(F13/F5,"") | G14: =IFERROR(E14/D14-1,"") | H14: =IFERROR(E14/F14-1,"")
A15: Abschreibungen | G15: =IFERROR(E15/D15-1,"") | H15: =IFERROR(E15/F15-1,"")
A16: EBIT normalisiert | B16: =B13-B15 -> 0 | C16: =C13-C15 -> 0 | D16: =D13-D15 -> 0 | E16: =E13-E15 -> 0 | F16: =F13-F15 -> 0 | G16: =IFERROR(E16/D16-1,"") | H16: =IFERROR(E16/F16-1,"")
A17: Nettozinsaufwand | G17: =IFERROR(E17/D17-1,"") | H17: =IFERROR(E17/F17-1,"")
A18: Ertragsteuern | G18: =IFERROR(E18/D18-1,"") | H18: =IFERROR(E18/F18-1,"")
A19: Jahresergebnis (vereinfachte Sicht) | B19: =B16-B17-B18 -> 0 | C19: =C16-C17-C18 -> 0 | D19: =D16-D17-D18 -> 0 | E19: =E16-E17-E18 -> 0 | F19: =F16-F17-F18 -> 0 | G19: =IFERROR(E19/D19-1,"") | H19: =IFERROR(E19/F19-1,"")
A20: Operativer Cashflow | G20: =IFERROR(E20/D20-1,"") | H20: =IFERROR(E20/F20-1,"")
A21: Capex | G21: =IFERROR(E21/D21-1,"") | H21: =IFERROR(E21/F21-1,"")
A22: Free Cashflow | B22: =B20-B21 -> 0 | C22: =C20-C21 -> 0 | D22: =D20-D21 -> 0 | E22: =E20-E21 -> 0 | F22: =F20-F21 -> 0 | G22: =IFERROR(E22/D22-1,"") | H22: =IFERROR(E22/F22-1,"")
A23: Cash | G23: =IFERROR(E23/D23-1,"") | H23: =IFERROR(E23/F23-1,"")
A24: Finanzschulden | G24: =IFERROR(E24/D24-1,"") | H24: =IFERROR(E24/F24-1,"")
A25: Leasingverbindlichkeiten | G25: =IFERROR(E25/D25-1,"") | H25: =IFERROR(E25/F25-1,"")
A26: Sonstige debt-like Positionen | G26: =IFERROR(E26/D26-1,"") | H26: =IFERROR(E26/F26-1,"")
A27: Net Debt | B27: =B24+B25+B26-B23 -> 0 | C27: =C24+C25+C26-C23 -> 0 | D27: =D24+D25+D26-D23 -> 0 | E27: =E24+E25+E26-E23 -> 0 | F27: =F24+F25+F26-F23 -> 0 | G27: =IFERROR(E27/D27-1,"") | H27: =IFERROR(E27/F27-1,"")
A28: Vorräte | G28: =IFERROR(E28/D28-1,"") | H28: =IFERROR(E28/F28-1,"")
A29: Forderungen L&L | G29: =IFERROR(E29/D29-1,"") | H29: =IFERROR(E29/F29-1,"")
A30: Vertragsvermögenswerte | G30: =IFERROR(E30/D30-1,"") | H30: =IFERROR(E30/F30-1,"")
A31: Sonstige operative kurzfristige Aktiva | G31: =IFERROR(E31/D31-1,"") | H31: =IFERROR(E31/F31-1,"")
A32: Verbindlichkeiten L&L | G32: =IFERROR(E32/D32-1,"") | H32: =IFERROR(E32/F32-1,"")
A33: Deferred Revenue / Vertragsverbindlichkeiten | G33: =IFERROR(E33/D33-1,"") | H33: =IFERROR(E33/F33-1,"")
A34: Sonstige operative kurzfristige Passiva | G34: =IFERROR(E34/D34-1,"") | H34: =IFERROR(E34/F34-1,"")
A35: Net Working Capital | B35: =B28+B29+B30+B31-B32-B33-B34 -> 0 | C35: =C28+C29+C30+C31-C32-C33-C34 -> 0 | D35: =D28+D29+D30+D31-D32-D33-D34 -> 0 | E35: =E28+E29+E30+E31-E32-E33-E34 -> 0 | F35: =F28+F29+F30+F31-F32-F33-F34 -> 0 | G35: =IFERROR(E35/D35-1,"") | H35: =IFERROR(E35/F35-1,"")
A36: NWC in % Umsatz | B36: =IFERROR(B35/B5,"") | C36: =IFERROR(C35/C5,"") | D36: =IFERROR(D35/D5,"") | E36: =IFERROR(E35/E5,"") | F36: =IFERROR(F35/F5,"") | G36: =IFERROR(E36/D36-1,"") | H36: =IFERROR(E36/F36-1,"")
A37: DSO | B37: =IFERROR(B29/B5*365,"") | C37: =IFERROR(C29/C5*365,"") | D37: =IFERROR(D29/D5*365,"") | E37: =IFERROR(E29/E5*365,"") | F37: =IFERROR(F29/F5*365,"") | G37: =IFERROR(E37/D37-1,"") | H37: =IFERROR(E37/F37-1,"")
A38: DIO | B38: =IFERROR(B28/B6*365,"") | C38: =IFERROR(C28/C6*365,"") | D38: =IFERROR(D28/D6*365,"") | E38: =IFERROR(E28/E6*365,"") | F38: =IFERROR(F28/F6*365,"") | G38: =IFERROR(E38/D38-1,"") | H38: =IFERROR(E38/F38-1,"")
A39: DPO | B39: =IFERROR(B32/B6*365,"") | C39: =IFERROR(C32/C6*365,"") | D39: =IFERROR(D32/D6*365,"") | E39: =IFERROR(E32/E6*365,"") | F39: =IFERROR(F32/F6*365,"") | G39: =IFERROR(E39/D39-1,"") | H39: =IFERROR(E39/F39-1,"")
A40: Headcount (FTE) | G40: =IFERROR(E40/D40-1,"") | H40: =IFERROR(E40/F40-1,"")
A41: Umsatz je FTE | B41: =IFERROR(B5/B40,"") | C41: =IFERROR(C5/C40,"") | D41: =IFERROR(D5/D40,"") | E41: =IFERROR(E5/E40,"") | F41: =IFERROR(F5/F40,"") | G41: =IFERROR(E41/D41-1,"") | H41: =IFERROR(E41/F41-1,"")
A42: EBITDA je FTE | B42: =IFERROR(B13/B40,"") | C42: =IFERROR(C13/C40,"") | D42: =IFERROR(D13/D40,"") | E42: =IFERROR(E13/E40,"") | F42: =IFERROR(F13/F40,"") | G42: =IFERROR(E42/D42-1,"") | H42: =IFERROR(E42/F42-1,"")

Sheet 08_QoE
A1: Quality-of-Earnings-Brücke
A2: Nur belegte Normalisierungen erfassen. Synergien des Käufers gehören grundsätzlich nicht in das historische normalisierte EBITDA.
A4: EBITDA berichtet (LTM)
A5: Akzeptierte Anpassungen | B5: =SUM(H10:H49) -> 0
A6: EBITDA normalisiert | B6: =B4+B5 -> 0
A7: Anpassungen in % berichtet | B7: =IFERROR(B5/B4,"")
A9: Adj.-ID | B9: Kategorie | C9: Prüfansatz / Beschreibung | D9: Richtung | E9: Periode | F9: Management-Betrag (€) | G9: DD-Vorschlag (€) | H9: Akzeptierter Betrag (€) | I9: Evidenz | J9: Wiederkehrend? | K9: Cash / Non-Cash | L9: Konfidenz | M9: Status | N9: Owner | O9: Quelle / Ref. | P9: Kommentar
A10: ADJ-001 | B10: Einmalkosten | C10: Restrukturierung, Rechtsfall oder Transaktionskosten auf echte Einmaligkeit prüfen. | D10: + | E10: LTM | J10: Zu prüfen | M10: Offen
A11: ADJ-002 | B11: Einmalertrag | C11: Versicherungs-/Vergleichsertrag oder Anlagenverkauf aus nachhaltigem Ergebnis entfernen. | D11: − | E11: LTM | J11: Zu prüfen | M11: Offen
A12: ADJ-003 | B12: Owner / Related Party | C12: Vergütung, Miete und Services auf Marktniveau normalisieren. | D12: +/− | E12: LTM | J12: Zu prüfen | M12: Offen
A13: ADJ-004 | B13: Run-rate | C13: Umgesetzte Preis-/Kostenänderung nur ab wirksamen Datum und mit Evidenz annualisieren. | D13: +/− | E13: LTM | J13: Zu prüfen | M13: Offen
A14: ADJ-005 | B14: Accounting Error | C14: Periodenfremde oder fehlerhafte Buchung korrigieren. | D14: +/− | E14: LTM | J14: Zu prüfen | M14: Offen
A15: ADJ-006 | B15: Unterinvestition | C15: Fehlende laufende Kosten oder Maintenance-Aufwand ergänzen. | D15: − | E15: LTM | J15: Zu prüfen | M15: Offen
A16: ADJ-007 | B16: Stand-alone Costs | C16: Nach Carve-out notwendige Corporate-/IT-/Insurance-Kosten ergänzen. | D16: − | E16: LTM | J16: Zu prüfen | M16: Offen
A17: ADJ-008 | B17: Synergie | C17: Käufer-Synergie separat vom Target-QoE ausweisen. | D17: separat | E17: LTM | J17: Zu prüfen | M17: Offen
A18: ADJ-009 | B18: FX / Commodity | C18: Außergewöhnliche Effekte nur bei klar definierter Normalbasis beurteilen. | D18: +/− | E18: LTM | J18: Zu prüfen | M18: Offen
A19: ADJ-010 | B19: Kunden-/Vertragsereignis | C19: Verlorenen/gewonnenen Großkunden mit Start-/Enddatum und Marge berücksichtigen. | D19: +/− | E19: LTM | J19: Zu prüfen | M19: Offen
A20: ADJ-011 | B20: Personal | C20: Offene Stellen, Bonus, Gehaltsanpassung und Freelancer-Run-rate normalisieren. | D20: − | E20: LTM | J20: Zu prüfen | M20: Offen
A21: ADJ-012 | B21: Sonstige | C21: Jede weitere Anpassung mit Gegenkonto, Cash-Wirkung und Wiederkehr belegen. | D21: +/− | E21: LTM | J21: Zu prüfen | M21: Offen
A22: ADJ-013 | E22: LTM | J22: Zu prüfen | M22: Offen
A23: ADJ-014 | E23: LTM | J23: Zu prüfen | M23: Offen
A24: ADJ-015 | E24: LTM | J24: Zu prüfen | M24: Offen
A25: ADJ-016 | E25: LTM | J25: Zu prüfen | M25: Offen
A26: ADJ-017 | E26: LTM | J26: Zu prüfen | M26: Offen
A27: ADJ-018 | E27: LTM | J27: Zu prüfen | M27: Offen
A28: ADJ-019 | E28: LTM | J28: Zu prüfen | M28: Offen
A29: ADJ-020 | E29: LTM | J29: Zu prüfen | M29: Offen
A30: ADJ-021 | E30: LTM | J30: Zu prüfen | M30: Offen
A31: ADJ-022 | E31: LTM | J31: Zu prüfen | M31: Offen
A32: ADJ-023 | E32: LTM | J32: Zu prüfen | M32: Offen
A33: ADJ-024 | E33: LTM | J33: Zu prüfen | M33: Offen
... A49: ADJ-040 | E49: LTM | J49: Zu prüfen | M49: Offen

Sheet 09_NWC_NetDebt
A1: Net Working Capital & Net Debt
A2: Monatswerte als positive Beträge erfassen; der Faktor +1/−1 steuert die NWC-Wirkung. Net-Debt-Positionen separat auf wirtschaftlichen Finanzierungscharakter prüfen.
A4: NWC-Monatsanalyse
A5: Komponente | B5: Faktor | C5: Monat -11 | D5: Monat -10 | E5: Monat -9 | F5: Monat -8 | G5: Monat -7 | H5: Monat -6 | I5: Monat -5 | J5: Monat -4 | K5: Monat -3 | L5: Monat -2 | M5: Monat -1 | N5: Monat 0 | O5: Durchschnitt | P5: Median | Q5: Minimum | R5: Maximum | S5: Kommentar / Definition
A6: Vorräte | B6: 1 | O6: =IF(COUNTA(C6:N6)=0,"",AVERAGE(C6:N6)) | P6: =IF(COUNTA(C6:N6)=0,"",MEDIAN(C6:N6)) | Q6: =IF(COUNTA(C6:N6)=0,"",MIN(C6:N6)) | R6: =IF(COUNTA(C6:N6)=0,"",MAX(C6:N6))
A7: Forderungen L&L | B7: 1 | O7: =IF(COUNTA(C7:N7)=0,"",AVERAGE(C7:N7)) | P7: =IF(COUNTA(C7:N7)=0,"",MEDIAN(C7:N7)) | Q7: =IF(COUNTA(C7:N7)=0,"",MIN(C7:N7)) | R7: =IF(COUNTA(C7:N7)=0,"",MAX(C7:N7))
A8: Vertragsvermögenswerte | B8: 1 | O8: =IF(COUNTA(C8:N8)=0,"",AVERAGE(C8:N8)) | P8: =IF(COUNTA(C8:N8)=0,"",MEDIAN(C8:N8)) | Q8: =IF(COUNTA(C8:N8)=0,"",MIN(C8:N8)) | R8: =IF(COUNTA(C8:N8)=0,"",MAX(C8:N8))
A9: Sonstige operative kurzfristige Aktiva | B9: 1 | O9: =IF(COUNTA(C9:N9)=0,"",AVERAGE(C9:N9)) | P9: =IF(COUNTA(C9:N9)=0,"",MEDIAN(C9:N9)) | Q9: =IF(COUNTA(C9:N9)=0,"",MIN(C9:N9)) | R9: =IF(COUNTA(C9:N9)=0,"",MAX(C9:N9))
A10: Verbindlichkeiten L&L | B10: -1 | O10: =IF(COUNTA(C10:N10)=0,"",AVERAGE(C10:N10)) | P10: =IF(COUNTA(C10:N10)=0,"",MEDIAN(C10:N10)) | Q10: =IF(COUNTA(C10:N10)=0,"",MIN(C10:N10)) | R10: =IF(COUNTA(C10:N10)=0,"",MAX(C10:N10))
A11: Deferred Revenue / Vertragsverbindlichkeiten | B11: -1 | O11: =IF(COUNTA(C11:N11)=0,"",AVERAGE(C11:N11)) | P11: =IF(COUNTA(C11:N11)=0,"",MEDIAN(C11:N11)) | Q11: =IF(COUNTA(C11:N11)=0,"",MIN(C11:N11)) | R11: =IF(COUNTA(C11:N11)=0,"",MAX(C11:N11))
A12: Sonstige operative kurzfristige Passiva | B12: -1 | O12: =IF(COUNTA(C12:N12)=0,"",AVERAGE(C12:N12)) | P12: =IF(COUNTA(C12:N12)=0,"",MEDIAN(C12:N12)) | Q12: =IF(COUNTA(C12:N12)=0,"",MIN(C12:N12)) | R12: =IF(COUNTA(C12:N12)=0,"",MAX(C12:N12))
A13: Net Working Capital | C13: =SUMPRODUCT($B$6:$B$12,C$6:C$12) -> 0 | D13: =SUMPRODUCT($B$6:$B$12,D$6:D$12) -> 0 | E13: =SUMPRODUCT($B$6:$B$12,E$6:E$12) -> 0 | F13: =SUMPRODUCT($B$6:$B$12,F$6:F$12) -> 0 | G13: =SUMPRODUCT($B$6:$B$12,G$6:G$12) -> 0 | H13: =SUMPRODUCT($B$6:$B$12,H$6:H$12) -> 0 | I13: =SUMPRODUCT($B$6:$B$12,I$6:I$12) -> 0 | J13: =SUMPRODUCT($B$6:$B$12,J$6:J$12) -> 0 | ... N13: =SUMPRODUCT($B$6:$B$12,N$6:N$12) -> 0 | O13: =AVERAGE(C13:N13) -> 0 | P13: =MEDIAN(C13:N13) -> 0 | Q13: =MIN(C13:N13) -> 0 | R13: =MAX(C13:N13) -> 0
A14: Vorgeschlagenes NWC-Peg | C14: =P13 -> 0 | S14: Ausgangspunkt: Median; Saisonalität, Wachstum, Bilanzierungsänderungen und Ausreißer separat würdigen.
A17: Net-Debt-/Debt-like-Brücke
A18: Position | B18: Kategorie | C18: Betrag (€) | D18: Einbeziehen? | E18: Vorzeichen | F18: Einbezogener Betrag (€) | G18: Begründung | H18: Evidenz | I18: SPA-Behandlung | J18: Owner
A19: Frei verfügbares Cash | B19: Cash-like | D19: Zu prüfen | E19: -1 | F19: =IF(D19="Ja",C19*E19,0) -> 0
A20: Gesperrtes / regulatorisches Cash | B20: Excluded cash | D20: Zu prüfen | E20: 0 | F20: =IF(D20="Ja",C20*E20,0) -> 0
A21: Bankdarlehen | B21: Debt | D21: Zu prüfen | E21: 1 | F21: =IF(D21="Ja",C21*E21,0) -> 0
A22: Aufgelaufene Zinsen / Vorfälligkeit | B22: Debt-like | D22: Zu prüfen | E22: 1 | F22: =IF(D22="Ja",C22*E22,0) -> 0
A23: Gesellschafterdarlehen | B23: Debt | D23: Zu prüfen | E23: 1 | F23: =IF(D23="Ja",C23*E23,0) -> 0
A24: Leasingverbindlichkeiten | B24: Debt-like | D24: Zu prüfen | E24: 1 | F24: =IF(D24="Ja",C24*E24,0) -> 0
A25: Factoring / Reverse Factoring | B25: Debt-like | D25: Zu prüfen | E25: 1 | F25: =IF(D25="Ja",C25*E25,0) -> 0
A26: Cash Pool Saldo | B26: Debt/Cash | D26: Zu prüfen | E26: 1 | F26: =IF(D26="Ja",C26*E26,0) -> 0
A27: Unbezahlte Dividenden / Leakage | B27: Debt-like | D27: Zu prüfen | E27: 1 | F27: =IF(D27="Ja",C27*E27,0) -> 0
A28: Transaktionsboni | B28: Debt-like | D28: Zu prüfen | E28: 1 | F28: =IF(D28="Ja",C28*E28,0) -> 0
A29: Überfällige Steuern / Sozialabgaben | B29: Debt-like | D29: Zu prüfen | E29: 1 | F29: =IF(D29="Ja",C29*E29,0) -> 0
A30: Capex-Kreditoren | B30: Debt-like | D30: Zu prüfen | E30: 1 | F30: =IF(D30="Ja",C30*E30,0) -> 0
... A35: Sonstige | B35: Case-by-case | D35: Zu prüfen | E35: 1 | F35: =IF(D35="Ja",C35*E35,0) -> 0
E37: Net Debt gesamt | F37: =SUM(F19:F35) -> 0

Sheet 10_Verträge
A1: Vertragsprüfung
A2: Wesentliche Verträge einzeln erfassen. Finanzdaten, Vertragsregister und tatsächliche Durchführung gegeneinander abstimmen.
A4: Vertrags-ID | B4: Vertragstyp | C4: Gegenpartei | D4: Konzernzuordnung | E4: Leistungsgegenstand | F4: Jahreswert (€) | G4: Marge / Kritikalität | H4: Beginn | I4: Ende | J4: Autom. Verlängerung | K4: Kündigungsfrist | L4: Change of Control | M4: Abtretung | N4: Exklusivität / MFN | O4: Mindestabnahme | P4: Haftung / Cap | Q4: Freistellungen | R4: SLA / Vertragsstrafe | S4: Datenschutz / Security | T4: IP-Rechte | U4: Rechtswahl / Gerichtsstand | V4: Consent nötig? | W4: Risiko | X4: Maßnahme | Y4: Owner | Z4: Status | AA4: VDR-Link | AB4: Checklisten-Ref.
A5: V-001
A6: V-002
A7: V-003
A8: V-004
A9: V-005
A10: V-006
A11: V-007
A12: V-008
A13: V-009
A14: V-010
A15: V-011
A16: V-012
... A64: V-060

Sheet 11_IT_Cyber
A1: IT- & Cyber-Vertiefung
A2: Vertiefungsmatrix für IT & Cyber. Ergebnisse in die Master-Checkliste und das Risikoregister zurückspiegeln.
A4: ID | B4: Thema | C4: Prüffrage | D4: Evidenz | E4: Test / Analyse | F4: Red Flags | G4: Reifegrad / Ergebnis | H4: Risiko | I4: Empfohlene Maßnahme | J4: Owner | K4: Fällig | L4: Status | M4: Master-Ref.
A5: 11-01 | B5: IT-Strategie | C5: Unterstützen IT-Strategie, Architektur und Budget den Business Plan? | D5: IT-Roadmap, Architektur, Budget, Projektportfolio | E5: Business-Alignment, Investitionslücke, Abhängigkeiten und Nutzen prüfen. | F5: Keine Roadmap, Projekte ohne Budget, Architektur blockiert Wachstum | I5: Finanzierte IT-Roadmap mit Day-1- und 100-Tage-Prioritäten erstellen. | J5: CIO / CISO | L5: Nicht begonnen | M5: IT-01
A6: 11-02 | B6: Asset Inventory | C6: Sind Hardware, Software, Cloud-Assets und Datenbestände vollständig inventarisiert? | D6: CMDB, Inventar, Cloud-Accounts, SaaS-Liste, Datenkatalog | E6: Stichprobe gegen Netzwerk, Rechnungen und Identitätsprovider. | F6: Unbekannte Server/Cloud Accounts, Shadow IT | I6: Discovery durchführen und Eigentümer/Lifecycle für kritische Assets festlegen. | J6: CIO / CISO | L6: Nicht begonnen | M6: IT-02
A7: 11-03 | B7: Legacy & EOL | C7: Welche Systeme sind veraltet oder nicht mehr unterstützt? | D7: Versionsliste, Supportverträge, technische Schulden | E7: EOL-Daten, Kritikalität, Ersatzplan und Kosten bewerten. | F7: Kernsystem ohne Patches, Hersteller-Support beendet | I7: Sofortkompensation und finanzierte Modernisierungs-Roadmap vorsehen. | J7: CIO / CISO | L7: Nicht begonnen | M7: IT-03
A8: 11-04 | B8: IAM & MFA | C8: Sind Identitäten, privilegierte Zugriffe und MFA wirksam kontrolliert? | D8: IdP, Rollen, Admin-Konten, Joiner/Mover/Leaver, MFA-Abdeckung | E8: User-/Rollenstichprobe, Dormant Accounts und MFA/PAM-Abdeckung testen. | F8: Geteilte Admin-Konten, ehemalige Mitarbeiter aktiv, kein MFA | I8: MFA/PAM und sofortige Zugriffsbereinigung als Pre-/Post-Closing-Maßnahme. | J8: CIO / CISO | L8: Nicht begonnen | M8: IT-04
A9: 11-05 | B9: Vulnerability & Patch | C9: Werden Schwachstellen und Patches risikobasiert fristgerecht behandelt? | D9: Scannerberichte, Patch-KPIs, Ausnahmen, Penetrationstests | E9: Externe Angriffsfläche und kritische Findings auf Alter/Closure prüfen. | F9: Internet-exponierte kritische Lücke, kein Scan, dauerhafte Ausnahme | I9: Kritische Findings vor Closing schließen und SLA/Monitoring etablieren. | J9: CIO / CISO | L9: Nicht begonnen | M9: IT-05
A10: 11-06 | B10: Security Incidents | C10: Sind Cybervorfälle vollständig erfasst, untersucht und gemeldet? | D10: Incident Register, Forensikberichte, Versicherungsfälle, Behördenmeldungen | E10: Timeline, Root Cause, Persistenz, Datenabfluss und Remediation validieren. | F10: Ransomware ohne Forensik, nicht gemeldeter Datenabfluss | I10: Unabhängige Kompromittierungsprüfung, Meldung und spezifische Freistellung. | J10: CIO / CISO | L10: Nicht begonnen | M10: IT-06
A11: 11-07 | B11: Backup & Recovery | C11: Sind Backups geschützt und Wiederherstellungen nachweislich erfolgreich? | D11: Backup-Konfiguration, Restore-Tests, RPO/RTO, Offline/Immutable Copies | E11: Stichproben-Restore kritischer Systeme; Trennung von Admin-Domänen prüfen. | F11: Backup online löschbar, kein Restore-Test, RPO nicht erfüllt | I11: Immutable Backup und Recovery-Test vor Closing bzw. Day 1 umsetzen. | J11: CIO / CISO | L11: Nicht begonnen | M11: IT-07
A12: 11-08 | B12: Disaster Recovery | C12: Sind DR- und BCP-Pläne realistisch, aktuell und getestet? | D12: DR-Plan, Abhängigkeiten, Testberichte, Krisenkontakte | E12: Tabletop und technische Tests gegen RTO/RPO auswerten. | F12: Plan ohne kritische SaaS/Provider, Test dauerhaft verschoben | I12: End-to-end-Test und Lückenschließung mit klarer Finanzierung planen. | J12: CIO / CISO | L12: Nicht begonnen | M12: IT-08
A13: 11-09 | B13: Cloud & Outsourcing | C13: Sind Provider-, Cloud- und Managed-Service-Risiken kontrolliert? | D13: Providerverträge, Architektur, SOC-Berichte, Exit-Pläne | E13: Shared Responsibility, SLA, Datenort, Subprocessor, Konzentration und Exit prüfen. | F13: Kein Exit/Export, Admin beim Provider, ungeklärter Datenstandort | I13: Exit-/TSA-Plan, Vertragsnachträge und technische Kontrollen vereinbaren. | J13: CIO / CISO | L13: Nicht begonnen | M13: IT-09
A14: 11-10 | B14: Softwarelizenzen | C14: Sind Nutzungsrechte ausreichend und übertragen sich bei Closing? | D14: Lizenzverträge, Nutzer-/Core-Zahlen, Auditkorrespondenz | E14: Effective License Position und Change-of-Control/Assignment prüfen. | F14: Unterlizenzierung, Auditandrohung, Konzernlizenz endet | I14: True-up/Neulizenzierung budgetieren und Verkäuferfreistellung sichern. | J14: CIO / CISO | L14: Nicht begonnen | M14: IT-10
A15: 11-11 | B15: Secure SDLC | C15: Sind Entwicklung, Änderungen und Secrets angemessen geschützt? | D15: Repositories, CI/CD, Change Tickets, Scanberichte, Secret Management | E15: Branch Protection, Reviews, SAST/SCA, Deploy-Rechte und Secrets testen. | F15: Secrets im Code, direkte Produktionseinspielung, keine Reviews | I15: Pipeline-Gates, Secret Rotation und Segregation of Duties einführen. | J15: CIO / CISO | L15: Nicht begonnen | M15: IT-11
A16: 11-12 | B16: IT-Trennung | C16: Sind Systeme, Daten, Domains und Verträge vom Verkäufer trennbar? | D16: Dependency Map, Mandanten, Netzwerk, Domains, Lizenzen, TSA-Entwurf | E16: Separation Workstreams, Datenmigration, Kosten und kritischen Pfad validieren. | F16: Gemeinsamer Tenant ohne Export, Verkäufer besitzt Domain/Quellcode | I16: Detaillierten Separation-/TSA-Plan mit Exit-Kriterien vertraglich fixieren. | J16: CIO / CISO | L16: Nicht begonnen | M16: IT-12

Sheet 12_HR
A1: HR- & Pensions-Vertiefung
A2: Vertiefungsmatrix für HR & Pensions. Ergebnisse in die Master-Checkliste und das Risikoregister zurückspiegeln.
A4: ID | B4: Thema | C4: Prüffrage | D4: Evidenz | E4: Test / Analyse | F4: Red Flags | G4: Reifegrad / Ergebnis | H4: Risiko | I4: Empfohlene Maßnahme | J4: Owner | K4: Fällig | L4: Status | M4: Master-Ref.
A5: 12-01 | B5: Belegschaftsstruktur | C5: Sind Headcount, FTE, Kosten und Organisationsstruktur vollständig? | D5: Mitarbeiterliste, Organigramm, Payroll-Abgleich, Kostenstellen | E5: HR-Liste zu Payroll und GuV abstimmen; Trends nach Standort/Funktion. | F5: Ghost Employees, unbesetzte Schlüsselrollen, inkonsistenter Headcount | I5: Daten bereinigen und Zielorganisation/Schlüsselrollen festlegen. | J5: CHRO / HR | L5: Nicht begonnen | M5: HR-01
A6: 12-02 | B6: Arbeitsverträge | C6: Sind Verträge, Befristungen und nachvertragliche Pflichten wirksam? | D6: Vertragsmuster, Schlüsselverträge, Nachträge, Policies | E6: Risikostichprobe nach Land, Seniorität und Sonderklausel. | F6: Unwirksame Befristung, unklare IP-Abtretung, unbegrenzte Bonuszusage | I6: Nachträge/Heilung und Garantie für Altansprüche vereinbaren. | J6: CHRO / HR | L6: Nicht begonnen | M6: HR-02
A7: 12-03 | B7: Vergütung & Boni | C7: Sind Fix-, variable und aktienbasierte Vergütung vollständig und rückgestellt? | D7: Payroll, Bonuspläne, Provisionen, ESOP/VSOP, Rückstellungen | E7: Planregeln nachrechnen; Zielerreichung und Closing-/Acceleration-Effekt. | F7: Nicht rückgestellter Bonus, garantierte Provision trotz Storno | I7: Debt-like Behandlung bzw. Verkäuferkosten und klare Cut-off-Regeln vereinbaren. | J7: CHRO / HR | L7: Nicht begonnen | M7: HR-03
A8: 12-04 | B8: Schlüsselpersonen | C8: Welche Personen sind für Umsatz, Produkt, Betrieb und Wissen kritisch? | D8: Talent Review, Nachfolgeplanung, Kündigungsfristen, Retention | E8: Key-Person-Matrix mit Abwanderungswahrscheinlichkeit und Impact. | F8: Founder-/Ein-Personen-Abhängigkeit, angekündigte Kündigung | I8: Retention, Nachfolge und Wissensübergabe vor Signing/Closing sichern. | J8: CHRO / HR | L8: Nicht begonnen | M8: HR-04
A9: 12-05 | B9: Fluktuation & Fehlzeiten | C9: Deuten Turnover, Krankenstand oder Engagement auf strukturelle Probleme? | D9: Ein-/Austritte, Gründe, Fehlzeiten, Surveys 36 Monate | E9: Kohorten/Benchmarks nach Manager, Standort und Funktion. | F9: Spike bei Leistungsträgern, hohe Langzeiterkrankung, toxisches Team | I9: Ursachenmaßnahmen und realistische Recruiting-/Produktivitätskosten einplanen. | J9: CHRO / HR | L9: Nicht begonnen | M9: HR-05
A10: 12-06 | B10: Mitbestimmung & Tarif | C10: Sind Betriebsrat, Tarifbindung und Informations-/Konsultationspflichten beachtet? | D10: Betriebsvereinbarungen, Tarifverträge, Gremien, Verhandlungsstatus | E10: Transaktions- und Integrationsschritte gegen Pflichten/Fristen planen. | F10: Unterlassene Konsultation, nachwirkende Vereinbarung, Streikrisiko | I10: Mitbestimmungsfahrplan und Kommunikationsplan als kritischen Pfad führen. | J10: CHRO / HR | L10: Nicht begonnen | M10: HR-06
A11: 12-07 | B11: Pensionen | C11: Sind Pensionsverpflichtungen, Planvermögen und Risiken vollständig bewertet? | D11: Versicherungsmathematik, Planregeln, Vermögen, Begünstigte | E11: Aktuarielle Annahmen, Funding, Indexierung und Change-of-Control prüfen. | F11: Unterdeckung, veraltete Sterbetafel, harte Garantie | I11: Debt-like Adjustierung, Escrow oder spezifische Freistellung vereinbaren. | J11: CHRO / HR | L11: Nicht begonnen | M11: HR-07
A12: 12-08 | B12: Freelancer | C12: Besteht Risiko aus Scheinselbstständigkeit oder Arbeitnehmerüberlassung? | D12: Freelancer-/Agenturverträge, Einsatzdaten, Weisungen, AÜG-Erlaubnisse | E12: Status anhand tatsächlicher Durchführung und Dauer beurteilen. | F12: Langjährige Vollzeitintegration, keine AÜG-Erlaubnis | I12: Status bereinigen, Nachzahlung quantifizieren und Freistellung verlangen. | J12: CHRO / HR | L12: Nicht begonnen | M12: HR-08
A13: 12-09 | B13: Arbeitsstreitigkeiten | C13: Sind individuelle und kollektive HR-Streitigkeiten angemessen erfasst? | D13: Fallliste, Anwaltsschreiben, Vergleiche, Beschwerden | E13: Exposure und Musterwirkung je Fall; Abgleich mit Rückstellungen. | F13: Diskriminierungsmuster, Whistleblower-Retaliation | I13: Spezifische Abhilfe, Training und ggf. Freistellung/Escrow. | J13: CHRO / HR | L13: Nicht begonnen | M13: HR-09
A14: 12-10 | B14: Transaktionseffekte | C14: Lösen Closing, Kontrollwechsel oder Integration Zahlungen/Kündigungsrechte aus? | D14: Change-of-Control-Klauseln, MIP, Bonus- und Abfindungspläne | E14: Trigger, Kosten, Steuer/Sozialversicherung und Retention-Wirkung berechnen. | F14: Single-/Double-Trigger ohne Cap, Verkäufer hat Kosten nicht berücksichtigt | I14: Kosten als debt-like behandeln und neue Retention-Struktur abstimmen. | J14: CHRO / HR | L14: Nicht begonnen | M14: HR-10

Sheet 13_Steuern
A1: Tax-Due-Diligence-Vertiefung
A2: Vertiefungsmatrix für Tax. Ergebnisse in die Master-Checkliste und das Risikoregister zurückspiegeln.
A4: ID | B4: Thema | C4: Prüffrage | D4: Evidenz | E4: Test / Analyse | F4: Red Flags | G4: Reifegrad / Ergebnis | H4: Risiko | I4: Empfohlene Maßnahme | J4: Owner | K4: Fällig | L4: Status | M4: Master-Ref.
A5: 13-01 | B5: Ertragsteuern | C5: Sind Körperschaft-/Gewerbesteuererklärungen vollständig, fristgerecht und plausibel? | D5: Erklärungen, Bescheide, Überleitungen, Steuerkonten 5 Jahre | E5: Erklärung zu Abschluss überleiten; offene Jahre und Zinsen quantifizieren. | F5: Dauerhafte Vorbehalte, hohe Mehrsteuern, unerklärte Differenzen | I5: Exposure je Jahr quantifizieren und Steuerfreistellung vereinbaren. | J5: Head of Tax | L5: Nicht begonnen | M5: TAX-01
A6: 13-02 | B6: Betriebsprüfungen | C6: Welche Prüfungen, Einsprüche und verbindlichen Auskünfte sind offen? | D6: Prüfungsberichte, Anordnungen, Einsprüche, Korrespondenz | E6: Status, Streitwert, Wahrscheinlichkeit und Verjährung juristisch würdigen. | F6: Wiederkehrende Feststellungen, aggressive Position ohne Gutachten | I6: Spezifische Steuerfreistellung und Verfahrenskontrolle des Käufers regeln. | J6: Head of Tax | L6: Nicht begonnen | M6: TAX-02
A7: 13-03 | B7: Verlustvorträge | C7: Sind steuerliche Verlust- und Zinsvorträge werthaltig und transaktionsfest? | D7: Feststellungsbescheide, Organigramm, Beteiligungsänderungen | E7: Nutzbarkeit, Mindestbesteuerung und schädliche Ereignisse prüfen. | F7: Verfall durch Anteilseignerwechsel, nicht fortführbarer Geschäftsbetrieb | I7: Wert nur bei belastbarer Nutzbarkeit berücksichtigen; Struktur anpassen. | J7: Head of Tax | L7: Nicht begonnen | M7: TAX-03
A8: 13-04 | B8: Umsatzsteuer | C8: Sind Leistungen, Steuersätze, Reverse Charge und Vorsteuer korrekt? | D8: USt-Voranmeldungen, Zusammenfassende Meldungen, Rechnungsstichproben | E8: Datenanalytische Tests nach Land/Steuercode und Rechnungskette. | F8: Fehlende Registrierung, falscher Steuersatz, formell fehlerhafte Rechnungen | I8: Selbstanzeige/Korrektur prüfen, Reserve und Freistellung vorsehen. | J8: Head of Tax | L8: Nicht begonnen | M8: TAX-04
A9: 13-05 | B9: Lohnsteuer & Sozialversicherung | C9: Sind Vergütung, Benefits und Statusfeststellungen korrekt behandelt? | D9: Lohnkonten, Prüfberichte, Firmenwagen, Reisekosten, Freelancer | E9: Stichproben und Statusanalyse; Brutto-/Netto- und Haftungswirkung rechnen. | F9: Scheinselbstständigkeit, steuerfreie Pauschalen ohne Nachweis | I9: Nachmeldung, Rückstellung und spezifische Freistellung umsetzen. | J9: Head of Tax | L9: Nicht begonnen | M9: TAX-05
A10: 13-06 | B10: Verrechnungspreise | C10: Sind konzerninterne Preise fremdüblich und dokumentiert? | D10: Master/Local File, Intercompany-Verträge, Benchmarking | E10: Funktions-/Risikoanalyse, Margen und Dokumentationsfristen prüfen. | F10: Keine Dokumentation, Dauerverluste, IP-/Finanzierungsentgelt ohne Benchmark | I10: Dokumentation nachholen, Exposure modellieren und Freistellung vereinbaren. | J10: Head of Tax | L10: Nicht begonnen | M10: TAX-06
A11: 13-07 | B11: Betriebsstätten | C11: Bestehen nicht registrierte Betriebsstätten oder lokale Steuerpflichten? | D11: Mitarbeiter-/Projektorte, Homeoffice, Vertretervollmachten, Reisen | E11: Nexus je Land anhand Tätigkeit, Dauer und Abschlussvollmacht analysieren. | F11: Dauerhafte Teams ohne Registrierung, abhängiger Vertreter | I11: Registrieren, historische Risiken quantifizieren und Struktur bereinigen. | J11: Head of Tax | L11: Nicht begonnen | M11: TAX-07
A12: 13-08 | B12: Quellensteuern | C12: Wurden Quellensteuern auf Zinsen, Lizenzen und Dividenden korrekt behandelt? | D12: Zahlungsdaten, Verträge, Ansässigkeitsbescheinigungen | E12: Zahlungsströme, DBA-/Richtlinienentlastung und Beneficial Ownership prüfen. | F12: Net-of-tax-Klauseln, fehlende Bescheinigungen, Treaty Shopping | I12: Gross-up-Risiko quantifizieren und Dokumentation/Klauseln korrigieren. | J12: Head of Tax | L12: Nicht begonnen | M12: TAX-08
A13: 13-09 | B13: Umstrukturierungen | C13: Wurden frühere Umwandlungen und Übertragungen steuerneutral umgesetzt? | D13: Umwandlungsverträge, Bilanzen, Gutachten, Sperrfristakten | E13: Buchwerte, Gegenleistungen und Sperrfristen prüfen. | F13: Laufende Sperrfrist, fehlender Einbringungsnachweis | I13: Transaktion an Sperrfristen anpassen oder spezifische Freistellung verlangen. | J13: Head of Tax | L13: Nicht begonnen | M13: TAX-09
A14: 13-10 | B14: Tax Compliance | C14: Ist das Steuerkontrollsystem wirksam und sind Fristen/Verantwortungen klar? | D14: Tax CMS, Kalender, Richtlinien, Kontrollnachweise | E14: Design und Stichproben der Schlüsselkontrollen beurteilen. | F14: Ein-Personen-Abhängigkeit, Fristversäumnisse, keine Kontrolldokumentation | I14: Tax-CMS-Remediation mit Verantwortlichen und Fristen in 100-Tage-Plan. | J14: Head of Tax | L14: Nicht begonnen | M14: TAX-10
A15: 13-11 | B15: Transaktionssteuern | C15: Welche Grunderwerb-, Stempel-, Umsatz- oder Transfersteuern löst die Struktur aus? | D15: Immobilien-/Asset-Liste, Strukturplan, Jurisdiktionen | E15: Steuern und Meldepflichten je Schritt rechnen; Alternativen vergleichen. | F15: Unbudgetierte Grunderwerbsteuer, doppelte Belastung, Fristkritik | I15: Struktur optimieren und Kostentragung sowie Filing-Pflichten vertraglich regeln. | J15: Head of Tax | L15: Nicht begonnen | M15: TAX-11

Sheet 14_Deal_Mechanismen
A1: Deal-Mechanismen & Entscheidungshilfe
A2: Die Auswahl folgt dem Finding: quantifizieren, Doppelzählungen vermeiden und rechtliche/steuerliche Wirksamkeit prüfen.
A4: Mechanismus | B4: Geeignet für | C4: Typische Anwendungsfälle | D4: Zentrale Ausgestaltung | E4: Adressiertes Risiko | F4: Federführung | G4: Konkrete Entscheidung / Bezug | H4: Status
A5: Kaufpreisanpassung | B5: Quantifizierbare Wertabweichung | C5: NWC, Net Debt, nicht nachhaltiges EBITDA, Catch-up-Capex | D5: Definitionen, Beispielrechnung, Accounting Principles und Streitverfahren präzise regeln. | E5: Bewertungsrisiko und Doppelzählung | F5: CFO / M&A | H5: Zu prüfen
A6: Locked Box / Leakage | B6: Historischer Preisstichtag | C6: Belastbare Bilanz, stabile Entwicklung, gute Informationsrechte | D6: Permitted Leakage abschließend definieren; Zins und Bring-down berücksichtigen. | E6: Risiko nach Locked-Box-Stichtag | F6: Legal / Finance | H6: Zu prüfen
A7: Closing Accounts | B7: Unsichere Closing-Bilanz | C7: Volatiles NWC, Refinanzierung, Carve-out | D7: Hierarchie der Regeln und Expert Determination festlegen. | E7: Streit über Bilanzierung | F7: Finance / Legal | H7: Zu prüfen
A8: Spezifische Freistellung | B8: Bekanntes Einzelrisiko | C8: Steuerprüfung, Rechtsstreit, Umwelt, IP, Cyber | D8: Trigger, Laufzeit, Cap, Kontrolle des Verfahrens und Brutto-/Nettoeffekt regeln. | E8: Bekanntes Risiko meist aus W&I ausgeschlossen | F8: Legal / Tax | H8: Zu prüfen
A9: Escrow / Holdback | B9: Unsicheres oder schwer vollstreckbares Risiko | C9: Offene Freistellung, TSA-Exit, Kaufpreisstreit | D9: Freigabemechanik, Laufzeit und Zugriff klar definieren. | E9: Liquiditäts-/Insolvenzrisiko Verkäufer | F9: Legal / Treasury | H9: Zu prüfen
A10: Garantie | B10: Unbekanntes Risiko / Tatsachenstand | C10: Eigentum, Abschlüsse, Compliance, Verträge | D10: Knowledge, Materiality Scrape, Disclosure und Haftungsgrenzen abstimmen. | E10: Beweis-/Kenntnisrisiko | F10: Legal | H10: Zu prüfen
A11: Closing-Bedingung | B11: Vor Vollzug zwingend zu lösendes Risiko | C11: Genehmigung, Consent, Refinanzierung, Lizenz, Key Person | D11: Objektiv messbares Deliverable und Long-stop-Folge bestimmen. | E11: Vollzugsrisiko | F11: Legal / M&A | H11: Zu prüfen
A12: Covenant | B12: Verhalten zwischen Signing und Closing bzw. danach | C12: Ordinary course, Remediation, Informationspflicht | D12: Zustimmungsschwellen, Reporting und Rechtsfolge festlegen. | E12: Wertabfluss/Verhaltensrisiko | F12: Legal / Business | H12: Zu prüfen
A13: Earn-out | B13: Unsicherheit der künftigen Leistung | C13: Kundenkonzentration, Pipeline, Wachstum, Founder Transition | D13: KPI manipulationsfest definieren; Governance und Accounting regeln. | E13: Streit und Fehlanreize | F13: M&A / Finance | H13: Zu prüfen
A14: W&I-Versicherung | B14: Übertragung allgemeiner Garantiehaftung | C14: Breite DD und marktkonforme Garantien | D14: Ausschlüsse und bekannte Risiken separat absichern. | E14: Deckungslücken | F14: Legal / Insurance | H14: Zu prüfen
A15: TSA | B15: Temporäre Verkäuferabhängigkeit | C15: IT, Finance, HR, Procurement, Facilities | D15: Servicekatalog, SLA, Security, Preis, Exit und Verlängerung regeln. | E15: Betriebsunterbrechung | F15: Integration / Legal | H15: Zu prüfen
A16: Payoff & Release | B16: Ablösung Finanzierung/Sicherheiten | C16: Bankdarlehen, Pfandrechte, Garantien | D16: Funds Flow, Zins bis Closing und bedingungslose Freigabe koordinieren. | E16: Eigentums-/Finanzierungsrisiko | F16: Treasury / Legal | H16: Zu prüfen
... A19: Abbruch / No-go | B19: Nicht mitigierbares oder illegales Risiko | C19: Sanktionen, Korruption, fehlendes Kern-IP, existenzielle Genehmigung | D19: Entscheidung anhand vorab definierter Kriterien und dokumentierter Evidenz. | E19: Reputations-/Existenzrisiko | F19: Investment Committee | H19: Zu prüfen

Sheet 15_Quellen
A1: Quellen & methodische Hinweise
A2: Quellen dienen als Startpunkt. Für konkrete Entscheidungen sind aktuelle Primärquellen und qualifizierte Fachberater heranzuziehen.
A4: Quellen-ID | B4: Titel | C4: Herausgeber | D4: URL | E4: Verwendung | F4: Hinweis | G4: Abrufdatum
A5: S01 | B5: Due-Diligence-Prüfung – Überblick | C5: Wikipedia | D5: https://de.wikipedia.org/wiki/Due-Diligence-Pr%C3%BCfung | E5: Begriffe, Ziele und Prüfungsarten | F5: Sekundärquelle; fachlich verifizieren | G5: 46301
A6: S02 | B6: Due-Diligence-Prüfung | C6: Validatis | D6: https://www.validatis.de/kyc-prozess/news-fachwissen/due-diligence-pruefung/ | E6: Ablauf und Bericht | F6: Praxisüberblick | G6: 46301
A7: S03 | B7: Deal Advisory / Due Diligence | C7: BDO Deutschland | D7: https://www.bdo.de/de-de/services/advisory/deal-advisory/due-diligence | E7: Prüfungsbereiche und Transaktionsbezug | F7: Praxisüberblick | G7: 46301
A8: S04 | B8: Due-Diligence-Prüfungen | C8: Schultze & Braun | D8: https://www.schultze-braun.de/leistungen/wirtschaftspruefung/due-diligence-pruefungen | E8: Zweck und Prüfungsfelder | F8: Praxisüberblick | G8: 46301
A9: S05 | B9: Due-Diligence-Ablauf | C9: Sattler & Partner | D9: https://sattlerundpartner.de/de/due-diligence-ablauf/ | E9: Projektablauf und Phasen | F9: Praxisüberblick | G9: 46301
A10: S06 | B10: Datenschutz-Grundverordnung | C10: EUR-Lex | D10: https://eur-lex.europa.eu/eli/reg/2016/679/oj | E10: Datenschutzprüfung | F10: Primärrecht; aktuelle Fassung prüfen | G10: 46301
A11: S07 | B11: Cybersecurity Framework 2.0 | C11: NIST | D11: https://www.nist.gov/cyberframework | E11: Cyber-Governance und Kontrollen | F11: Frei zugänglicher Standard | G11: 46301
A12: S08 | B12: IT-Grundschutz | C12: BSI | D12: https://www.bsi.bund.de/grundschutz | E12: IT-Sicherheitsmethodik | F12: Frei zugängliche Methodik | G12: 46301
A13: S09 | B13: Gesetze im Internet – GwG | C13: BMJ/BfJ | D13: https://www.gesetze-im-internet.de/gwg_2017/ | E13: AML/KYC | F13: Primärquelle; aktuelle Fassung prüfen | G13: 46301
A14: S10 | B14: Transfer Pricing Guidelines | C14: OECD | D14: https://www.oecd.org/tax/transfer-pricing/oecd-transfer-pricing-guidelines-for-multinational-enterprises-and-tax-administrations-20769717.htm | E14: Verrechnungspreise | F14: Internationale Leitlinie | G14: 46301
A15: S11 | B15: Due Diligence – Grundlagen | C15: Buchhaltung einfach sicher | D15: https://www.buchhaltung-einfach-sicher.de/bwl/due-diligence | E15: Prüfungsbereiche | F15: Sekundärquelle | G15: 46301
A16: S12 | B16: Hinweisgeberschutzgesetz | C16: BMJ/BfJ | D16: https://www.gesetze-im-internet.de/hinschg/ | E16: Hinweisgebersystem | F16: Primärquelle; aktuelle Fassung prüfen | G16: 46301
... A19: S15 | B19: Due Diligence – Videoeinführung | C19: YouTube | D19: https://www.youtube.com/watch?v=fP3Nzk8h5iw&t=157 | E19: Ergänzende Einführung | F19: Keine Primärquelle | G19: 46301
