Workbook

Sheet Uebersicht
A1: TVF ALTWERT – gerettete Zahlen
A3: Quelle | B3: Inhalt | C3: Zeilen
A4: database.sql | B4: projekte | C4: 153
A5: database.sql | B5: kostenarten | C5: 108
A6: database.sql | B6: buchungen (aggregiert) | C6: 10509
A7: database.sql | B7: buchungen_agg_auftrag_periode | C7: 685
A8: database.sql | B8: buchungen_agg_periode | C8: 8
A9: Excel-Dateien | B9: Blätter exportiert | C9: 19
A12: Hinweis: Buchungen sind auf Auftrag×Periode und Kostenart summiert (keine 10.509 Einzelzeilen im Excel).
A13: Vollständige Belege bleiben in db/database.sql. CSVs liegen unter zahlen/.

Sheet Projekte
A1: projekt_nr | B1: projektname | C1: projektart | D1: status | E1: budget_umsatz | F1: budget_kosten
A2: P4102157208 | B2: Waggonverschrottung | C2: RECYCLING
A3: P4102157411 | B3: ARGE RB Chemiepark Krefeld | C3: SONSTIGES
A4: P4102157414 | B4: Krandemontage | C4: SONSTIGES
A5: P4102157420 | B5: ARGE RB GWA+SGA 4 | C5: SONSTIGES
A6: P4102157429 | B6: Covestro - Rückbau LEV O13 | C6: BAU
A7: P4102157431 | B7: RB drei Sandfilter | C7: SONSTIGES
A8: P4102157436 | B8: Sanierung Kompensatoren | C8: BAU
A9: P4102157439 | B9: RB Sperrmüllschereefeld | C9: SONSTIGES
A10: P4102157440 | B10: tkse RB 2025 | C10: SONSTIGES
A11: P4102157442 | B11: RB Leitstand Flämmaschine | C11: SONSTIGES
A12: P4102157443 | B12: Medice Arzneim. RB 2 Tanks | C12: SONSTIGES
A13: P4102157445 | B13: RB 2 Stahlwände Lüra Halle | C13: SONSTIGES
... A154: W4102654947 | B154: CB-TV 200 Hr. Adil | C154: SONSTIGES

Sheet Kostenarten
A1: kostenart_nr | B1: bezeichnung | C1: klr_typ | D1: db_stufe | E1: guv_gruppe
A2: 201000.0 | B2: Sonstige periodenfremde Aufwendungen | C2: AUTO | D2: 3
A3: 340050.0 | B3: Fremdleistungen Wartung/Pflege | C3: AUTO | D3: 1
A4: 392000.0 | B4: Bestandsveränderungen unfertige Erzeugni | C4: AUTO | D4: 3
A5: 830510.0 | B5: Erlöse Abrisse/Demontagen | C5: AUTO | D5: 1
A6: 7611200.0 | B6: Lohnverr. Gruppe 2 | C6: AUTO | D6: 1
A7: 7612000.0 | B7: Verrechnung Geräte | C7: AUTO | D7: 3
A8: 7801020.0 | B8: Gemeinkostenzuschläge 12 % TVF Altwert | C8: AUTO | D8: 3
A9: 330900.0 | B9: Erhaltene Skonti | C9: AUTO | D9: 3
A10: 401000.0 | B10: Aufwand Diesel | C10: AUTO | D10: 1
A11: 7611100.0 | B11: Lohnverr. Gruppe1 | C11: AUTO | D11: 1
A12: 430120.0 | B12: Sonstige Versicherungen | C12: AUTO | D12: 3
A13: 411100.0 | B13: Arbeitskleidung und Arbeitschutzbedarf | C13: AUTO | D13: 3
... A109: 400010.0 | B109: Instandhaltung Lastkraftwagen | C109: AUTO | D109: 3

Sheet Buch_Periode
A1: geschaeftsjahr | B1: periode | C1: summe_wert | D1: anzahl
C2: -361720.87 | D2: 1
A3: 2026 | B3: 1 | C3: 3400.72 | D3: 1114
A4: 2026 | B4: 2 | C4: -102745.45 | D4: 1452
A5: 2026 | B5: 3 | C5: -26736.68 | D5: 1667
A6: 2026 | B6: 4 | C6: -121673.39 | D6: 1618
A7: 2026 | B7: 5 | C7: 60196.64 | D7: 1481
A8: 2026 | B8: 6 | C8: -40137.29 | D8: 1607
A9: 2026 | B9: 7 | C9: -134025.42 | D9: 1569

Sheet Buch_Projekt
A1: auftrag | B1: summe_wert | C1: anzahl
A2: W4102154411 | B2: -471490.44 | C2: 599
B3: -361720.87 | C3: 1
A4: P4102307433 | B4: -340000 | C4: 381
A5: W4102504222 | B5: 330945.91 | C5: 448
A6: W4102604411 | B6: -311659.58 | C6: 388
A7: P4102157453 | B7: 310103.49 | C7: 321
A8: W4102304411 | B8: -239877.66 | C8: 459
A9: W4102504951 | B9: 101941.74 | C9: 28
A10: P4102608263 | B10: -69639.61 | C10: 296
A11: P4102307444 | B11: -66000 | C11: 103
A12: P4102658225 | B12: 63000 | C12: 9
A13: W4102304611 | B13: 60077.82 | C13: 212
A14: W4102504262 | B14: 56472.63 | C14: 119
A15: W4102654411 | B15: -50206.3 | C15: 232
... A155: W4102607081 | B155: 0 | C155: 28

Sheet Buch_Kostenart
A1: kostenart | B1: summe_wert | C1: anzahl
A2: 7801020.0 | B2: -1366941.2 | C2: 884
A3: 830510.0 | B3: -392267.57 | C3: 858
B4: -361720.87 | C4: 1
A5: 392000.0 | B5: 310103.49 | C5: 243
A6: 470020.0 | B6: 81996 | C6: 67
A7: 410130.0 | B7: 67438 | C7: 38
A8: 400122.0 | B8: 64936.13 | C8: 126
A9: 431010.0 | B9: 63951.15 | C9: 70
A10: 201000.0 | B10: 55572.04 | C10: 61
A11: 470025.0 | B11: 54022.7 | C11: 7
A12: 220000.0 | B12: 51592 | C12: 2
A13: 430020.0 | B13: 47216 | C13: 22
A14: 400030.0 | B14: 46967.97 | C14: 4
A15: 274200.0 | B15: -46186.04 | C15: 2
A16: 430120.0 | B16: 40917.11 | C16: 140
... A110: 265900.0 | B110: 0 | C110: 2

Sheet Buch_AuftragPeriode
A1: geschaeftsjahr | B1: periode | C1: auftrag | D1: summe_wert | E1: anzahl
D2: -361720.87 | E2: 1
A3: 2026 | B3: 1 | C3: P4102157208 | D3: 0 | E3: 6
A4: 2026 | B4: 1 | C4: P4102157414 | D4: 0 | E4: 6
A5: 2026 | B5: 1 | C5: P4102157420 | D5: 0 | E5: 8
A6: 2026 | B6: 1 | C6: P4102157429 | D6: 0 | E6: 16
A7: 2026 | B7: 1 | C7: P4102157440 | D7: 0 | E7: 6
A8: 2026 | B8: 1 | C8: P4102157443 | D8: 0 | E8: 4
A9: 2026 | B9: 1 | C9: P4102157447 | D9: 0 | E9: 2
A10: 2026 | B10: 1 | C10: P4102157449 | D10: 0 | E10: 37
A11: 2026 | B11: 1 | C11: P4102157451 | D11: 0 | E11: 50
A12: 2026 | B12: 1 | C12: P4102157453 | D12: 0 | E12: 44
A13: 2026 | B13: 1 | C13: P4102157455 | D13: 0 | E13: 13
A14: 2026 | B14: 1 | C14: P4102157457 | D14: 0 | E14: 4
... A686: 2026 | B686: 7 | C686: W4102654947 | D686: 350.27 | E686: 2

Sheet Import Monatsdaten_Import Monat
C2: Importierte Monats-GuV
C3: Befüllung über TVF_Import.ts. Eine Zeile je Jahr und Monat. Vorhandene Monate werden gezielt ersetzt. Originalquellen bleiben erhalten.
C6: Jahr | D6: Monat | E6: Umsatz | F6: Bestand | G6: Sonstige_Ertraege | H6: Materialaufwand | I6: Personalaufwand | J6: Sonstiger_Aufwand | K6: Abschreibungen | L6: Finanzergebnis | M6: Neutrales_Ergebnis
C63: SharePoint-Verknüpfungen (Dateien im selben Ordner)
C64: Diese Datei | D64: Import Monatsdaten.xlsx

Sheet GuV_GuV
C2: GuV und EBITDA
C3: Importierte Monatsdaten haben Vorrang vor dem Originalexport. Quelle je Monat in Zeile 23. Aufwendungen negativ, Beträge in EUR.
C5: Position | F5: 1 | G5: 2 | H5: 3 | I5: 4 | J5: 5 | K5: 6 | L5: 7 | M5: 8 | N5: 9 | O5: 10 | P5: 11 | Q5: 12
C6: Position | D6: YTD | E6: Anteil | F6: Jan | G6: Feb | H6: Mär | I6: Apr | J6: Mai | K6: Jun | L6: Jul | M6: Aug | N6: Sep | O6: Okt | P6: Nov | Q6: Dez
C7: Umsatzerlöse | D7: =SUMIFS(F7:Q7,$F$5:$Q$5,"<="&'[Steuerung.xlsx]Steuerung'!$F$7) | E7: =IF($D$9=0,"n.a.",D7/$D$9) | F7: =IF(COUNTIFS('[Import Monatsdaten.xlsx]Import Monatsdaten'!$C$7:$C$8,'[Steuerung.xlsx]Steuerung'!$F$6,'[Import Monatsdaten.xlsx]Import Monatsdaten'!$D$7:$D$8,1)>0,SUMIFS('[Import Monatsdaten.xlsx]Import Monatsdaten'!$E$7:$E$8,'[Import Monatsdaten.xlsx]Import Monatsdaten'!$C$7:$C$8,'[Steuerung.xlsx]Steuerung'!$F$6,'[Import Monatsdaten.xlsx]Import Monatsdaten'!$D$7:$D$8,1),IF(COUNTIFS('[D Finanzen.xlsx]D Finanzen'!$A$45:$A$115,'[Steuerung.xlsx]Steuerung'!$F$6,'[D Finanzen.xlsx]D Finanzen'!$B$45:$B$115,F$5)=0,"",SUMIFS('[D Finanzen.xlsx]D Finanzen'!$E$45:$E$115,'[D Finanzen.xlsx]D Finanzen'!$A$45:$A$115,'[Steuerung.xlsx]Steuerung'!$F$6,'[D Finanzen.xlsx]D Finanzen'!$B$45:$B$115,F$5,'[D Finanzen.xlsx]D Finanzen'!$C$45:$C$115,10))) | G7: =IF(COUNTIFS('[Import Monatsdaten.xlsx]Import Monatsdaten'!$C$7:$C$8,'[Steuerung.xlsx]Steuerung'!$F$6,'[Import Monatsdaten.xlsx]Import Monatsdaten'!$D$7:$D$8,2)>0,SUMIFS('[Import Monatsdaten.xlsx]Import Monatsdaten'!$E$7:$E$8,'[Import Monatsdaten.xlsx]Import Monatsdaten'!$C$7:$C$8,'[Steuerung.xlsx]Steuerung'!$F$6,'[Import Monatsdaten.xlsx]Import Monatsdaten'!$D$7:$D$8,2),IF(COUNTIFS('[D Finanzen.xlsx]D Finanzen'!$A$45:$A$115,'[Steuerung.xlsx]Steuerung'!$F$6,'[D Finanzen.xlsx]D Finanzen'!$B$45:$B$115,G$5)=0,"",SUMIFS('[D Finanzen.xlsx]D Finanzen'!$E$45:$E$115,'[D Finanzen.xlsx]D Finanzen'!$A$45:$A$115,'[Steuerung.xlsx]Steuerung'!$F$6,'[D Finanzen.xlsx]D Finanzen'!$B$45:$B$115,G$5,'[D Finanzen.xlsx]D Finanzen'!$C$45:$C$115,10))) | H7: =IF(COUNTIFS('[Import Monatsdaten.xlsx]Import Monatsdaten'!$C$7:$C$8,'[Steuerung.xlsx]Steuerung'!$F$6,'[Import Monatsdaten.xlsx]Import Monatsdaten'!$D$7:$D$8,3)>0,SUMIFS('[Import Monatsdaten.xlsx]Import Monatsdaten'!$E$7:$E$8,'[Import Monatsdaten.xlsx]Import Monatsdaten'!$C$7:$C$8,'[Steuerung.xlsx]Steuerung'!$F$6,'[Import Monatsdaten.xlsx]Import Monatsdaten'!$D$7:$D$8,3),IF(COUNTIFS('[D Finanzen.xlsx]D Finanzen'!$A$45:$A$115,'[Steuerung.xlsx]Steuerung'!$F$6,'[D Finanzen.xlsx]D Finanzen'!$B$45:$B$115,H$5)=0,"",SUMIFS('[D Finanzen.xlsx]D Finanzen'!$E$45:$E$115,'[D Finanzen.xlsx]D Finanzen'!$A$45:$A$115,'[Steuerung.xlsx]Steuerung'!$F$6,'[D Finanzen.xlsx]D Finanzen'!$B$45:$B$115,H$5,'[D Finanzen.xlsx]D Finanzen'!$C$45:$C$115,10))) | I7: =IF(COUNTIFS('[Import Monatsdaten.xlsx]Import Monatsdaten'!$C$7:$C$8,'[Steuerung.xlsx]Steuerung'!$F$6,'[Import Monatsdaten.xlsx]Import Monatsdaten'!$D$7:$D$8,4)>0,SUMIFS('[Import Monatsdaten.xlsx]Import Monatsdaten'!$E$7:$E$8,'[Import Monatsdaten.xlsx]Import Monatsdaten'!$C$7:$C$8,'[Steuerung.xlsx]Steuerung'!$F$6,'[Import Monatsdaten.xlsx]Import Monatsdaten'!$D$7:$D$8,4),IF(COUNTIFS('[D Finanzen.xlsx]D Finanzen'!$A$45:$A$115,'[Steuerung.xlsx]Steuerung'!$F$6,'[D Finanzen.xlsx]D Finanzen'!$B$45:$B$115,I$5)=0,"",SUMIFS('[D Finanzen.xlsx]D Finanzen'!$E$45:$E$115,'[D Finanzen.xlsx]D Finanzen'!$A$45:$A$115,'[Steuerung.xlsx]Steuerung'!$F$6,'[D Finanzen.xlsx]D Finanzen'!$B$45:$B$115,I$5,'[D Finanzen.xlsx]D Finanzen'!$C$45:$C$115,10))) | J7: =IF(COUNTIFS('[Import Monatsdaten.xlsx]Import Monatsdaten'!$C$7:$C$8,'[Steuerung.xlsx]Steuerung'!$F$6,'[Import Monatsdaten.xlsx]Import Monatsdaten'!$D$7:$D$8,5)>0,SUMIFS('[Import Monatsdaten.xlsx]Import Monatsdaten'!$E$7:$E$8,'[Import Monatsdaten.xlsx]Import Monatsdaten'!$C$7:$C$8,'[Steuerung.xlsx]Steuerung'!$F$6,'[Import Monatsdaten.xlsx]Import Monatsdaten'!$D$7:$D$8,5),IF(COUNTIFS('[D Finanzen.xlsx]D Finanzen'!$A$45:$A$115,'[Steuerung.xlsx]Steuerung'!$F$6,'[D Finanzen.xlsx]D Finanzen'!$B$45:$B$115,J$5)=0,"",SUMIFS('[D Finanzen.xlsx]D Finanzen'!$E$45:$E$115,'[D Finanzen.xlsx]D Finanzen'!$A$45:$A$115,'[Steuerung.xlsx]Steuerung'!$F$6,'[D Finanzen.xlsx]D Finanzen'!$B$45:$B$115,J$5,'[D Finanzen.xlsx]D Finanzen'!$C$45:$C$115,10))) | K7: =IF(COUNTIFS('[Import Monatsdaten.xlsx]Import Monatsdaten'!$C$7:$C$8,'[Steuerung.xlsx]Steuerung'!$F$6,'[Import Monatsdaten.xlsx]Import Monatsdaten'!$D$7:$D$8,6)>0,SUMIFS('[Import Monatsdaten.xlsx]Import Monatsdaten'!$E$7:$E$8,'[Import Monatsdaten.xlsx]Import Monatsdaten'!$C$7:$C$8,'[Steuerung.xlsx]Steuerung'!$F$6,'[Import Monatsdaten.xlsx]Import Monatsdaten'!$D$7:$D$8,6),IF(COUNTIFS('[D Finanzen.xlsx]D Finanzen'!$A$45:$A$115,'[Steuerung.xlsx]Steuerung'!$F$6,'[D Finanzen.xlsx]D Finanzen'!$B$45:$B$115,K$5)=0,"",SUMIFS('[D Finanzen.xlsx]D Finanzen'!$E$45:$E$115,'[D Finanzen.xlsx]D Finanzen'!$A$45:$A$115,'[Steuerung.xlsx]Steuerung'!$F$6,'[D Finanzen.xlsx]D Finanzen'!$B$45:$B$115,K$5,'[D Finanzen.xlsx]D Finanzen'!$C$45:$C$115,10))) | L7: =IF(COUNTIFS('[Import Monatsdaten.xlsx]Import Monatsdaten'!$C$7:$C$8,'[Steuerung.xlsx]Steuerung'!$F$6,'[Import Monatsdaten.xlsx]Import Monatsdaten'!$D$7:$D$8,7)>0,SUMIFS('[Import Monatsdaten.xlsx]Import Monatsdaten'!$E$7:$E$8,'[Import Monatsdaten.xlsx]Import Monatsdaten'!$C$7:$C$8,'[Steuerung.xlsx]Steuerung'!$F$6,'[Import Monatsdaten.xlsx]Import Monatsdaten'!$D$7:$D$8,7),IF(COUNTIFS('[D Finanzen.xlsx]D Finanzen'!$A$45:$A$115,'[Steuerung.xlsx]Steuerung'!$F$6,'[D Finanzen.xlsx]D Finanzen'!$B$45:$B$115,L$5)=0,"",SUMIFS('[D Finanzen.xlsx]D Finanzen'!$E$45:$E$115,'[D Finanzen.xlsx]D Finanzen'!$A$45:$A$115,'[Steuerung.xlsx]Steuerung'!$F$6,'[D Finanzen.xlsx]D Finanzen'!$B$45:$B$115,L$5,'[D Finanzen.xlsx]D Finanzen'!$C$45:$C$115,10))) | M7: =IF(COUNTIFS('[Import Monatsdaten.xlsx]Import Monatsdaten'!$C$7:$C$8,'[Steuerung.xlsx]Steuerung'!$F$6,'[Import Monatsdaten.xlsx]Import Monatsdaten'!$D$7:$D$8,8)>0,SUMIFS('[Import Monatsdaten.xlsx]Import Monatsdaten'!$E$7:$E$8,'[Import Monatsdaten.xlsx]Import Monatsdaten'!$C$7:$C$8,'[Steuerung.xlsx]Steuerung'!$F$6,'[Import Monatsdaten.xlsx]Import Monatsdaten'!$D$7:$D$8,8),IF(COUNTIFS('[D Finanzen.xlsx]D Finanzen'!$A$45:$A$115,'[Steuerung.xlsx]Steuerung'!$F$6,'[D Finanzen.xlsx]D Finanzen'!$B$45:$B$115,M$5)=0,"",SUMIFS('[D Finanzen.xlsx]D Finanzen'!$E$45:$E$115,'[D Finanzen.xlsx]D Finanzen'!$A$45:$A$115,'[Steuerung.xlsx]Steuerung'!$F$6,'[D Finanzen.xlsx]D Finanzen'!$B$45:$B$115,M$5,'[D Finanzen.xlsx]D Finanzen'!$C$45:$C$115,10))) | N7: =IF(COUNTIFS('[Import Monatsdaten.xlsx]Import Monatsdaten'!$C$7:$C$8,'[Steuerung.xlsx]Steuerung'!$F$6,'[Import Monatsdaten.xlsx]Import Monatsdaten'!$D$7:$D$8,9)>0,SUMIFS('[Import Monatsdaten.xlsx]Import Monatsdaten'!$E$7:$E$8,'[Import Monatsdaten.xlsx]Import Monatsdaten'!$C$7:$C$8,'[Steuerung.xlsx]Steuerung'!$F$6,'[Import Monatsdaten.xlsx]Import Monatsdaten'!$D$7:$D$8,9),IF(COUNTIFS('[D Finanzen.xlsx]D Finanzen'!$A$45:$A$115,'[Steuerung.xlsx]Steuerung'!$F$6,'[D Finanzen.xlsx]D Finanzen'!$B$45:$B$115,N$5)=0,"",SUMIFS('[D Finanzen.xlsx]D Finanzen'!$E$45:$E$115,'[D Finanzen.xlsx]D Finanzen'!$A$45:$A$115,'[Steuerung.xlsx]Steuerung'!$F$6,'[D Finanzen.xlsx]D Finanzen'!$B$45:$B$115,N$5,'[D Finanzen.xlsx]D Finanzen'!$C$45:$C$115,10))) | O7: =IF(COUNTIFS('[Import Monatsdaten.xlsx]Import Monatsdaten'!$C$7:$C$8,'[Steuerung.xlsx]Steuerung'!$F$6,'[Import Monatsdaten.xlsx]Import Monatsdaten'!$D$7:$D$8,10)>0,SUMIFS('[Import Monatsdaten.xlsx]Import Monatsdaten'!$E$7:$E$8,'[Import Monatsdaten.xlsx]Import Monatsdaten'!$C$7:$C$8,'[Steuerung.xlsx]Steuerung'!$F$6,'[Import Monatsdaten.xlsx]Import Monatsdaten'!$D$7:$D$8,10),IF(COUNTIFS('[D Finanzen.xlsx]D Finanzen'!$A$45:$A$115,'[Steuerung.xlsx]Steuerung'!$F$6,'[D Finanzen.xlsx]D Finanzen'!$B$45:$B$115,O$5)=0,"",SUMIFS('[D Finanzen.xlsx]D Finanzen'!$E$45:$E$115,'[D Finanzen.xlsx]D Finanzen'!$A$45:$A$115,'[Steuerung.xlsx]Steuerung'!$F$6,'[D Finanzen.xlsx]D Finanzen'!$B$45:$B$115,O$5,'[D Finanzen.xlsx]D Finanzen'!$C$45:$C$115,10))) | P7: =IF(COUNTIFS('[Import Monatsdaten.xlsx]Import Monatsdaten'!$C$7:$C$8,'[Steuerung.xlsx]Steuerung'!$F$6,'[Import Monatsdaten.xlsx]Import Monatsdaten'!$D$7:$D$8,11)>0,SUMIFS('[Import Monatsdaten.xlsx]Import Monatsdaten'!$E$7:$E$8,'[Import Monatsdaten.xlsx]Import Monatsdaten'!$C$7:$C$8,'[Steuerung.xlsx]Steuerung'!$F$6,'[Import Monatsdaten.xlsx]Import Monatsdaten'!$D$7:$D$8,11),IF(COUNTIFS('[D Finanzen.xlsx]D Finanzen'!$A$45:$A$115,'[Steuerung.xlsx]Steuerung'!$F$6,'[D Finanzen.xlsx]D Finanzen'!$B$45:$B$115,P$5)=0,"",SUMIFS('[D Finanzen.xlsx]D Finanzen'!$E$45:$E$115,'[D Finanzen.xlsx]D Finanzen'!$A$45:$A$115,'[Steuerung.xlsx]Steuerung'!$F$6,'[D Finanzen.xlsx]D Finanzen'!$B$45:$B$115,P$5,'[D Finanzen.xlsx]D Finanzen'!$C$45:$C$115,10))) | Q7: =IF(COUNTIFS('[Import Monatsdaten.xlsx]Import Monatsdaten'!$C$7:$C$8,'[Steuerung.xlsx]Steuerung'!$F$6,'[Import Monatsdaten.xlsx]Import Monatsdaten'!$D$7:$D$8,12)>0,SUMIFS('[Import Monatsdaten.xlsx]Import Monatsdaten'!$E$7:$E$8,'[Import Monatsdaten.xlsx]Import Monatsdaten'!$C$7:$C$8,'[Steuerung.xlsx]Steuerung'!$F$6,'[Import Monatsdaten.xlsx]Import Monatsdaten'!$D$7:$D$8,12),IF(COUNTIFS('[D Finanzen.xlsx]D Finanzen'!$A$45:$A$115,'[Steuerung.xlsx]Steuerung'!$F$6,'[D Finanzen.xlsx]D Finanzen'!$B$45:$B$115,Q$5)=0,"",SUMIFS('[D Finanzen.xlsx]D Finanzen'!$E$45:$E$115,'[D Finanzen.xlsx]D Finanzen'!$A$45:$A$115,'[Steuerung.xlsx]Steuerung'!$F$6,'[D Finanzen.xlsx]D Finanzen'!$B$45:$B$115,Q$5,'[D Finanzen.xlsx]D Finanzen'!$C$45:$C$115,10)))
C8: Bestandsveränderungen | D8: =SUMIFS(F8:Q8,$F$5:$Q$5,"<="&'[Steuerung.xlsx]Steuerung'!$F$7) | E8: =IF($D$9=0,"n.a.",D8/$D$9) | F8: =IF(COUNTIFS('[Import Monatsdaten.xlsx]Import Monatsdaten'!$C$7:$C$8,'[Steuerung.xlsx]Steuerung'!$F$6,'[Import Monatsdaten.xlsx]Import Monatsdaten'!$D$7:$D$8,1)>0,SUMIFS('[Import Monatsdaten.xlsx]Import Monatsdaten'!$F$7:$F$8,'[Import Monatsdaten.xlsx]Import Monatsdaten'!$C$7:$C$8,'[Steuerung.xlsx]Steuerung'!$F$6,'[Import Monatsdaten.xlsx]Import Monatsdaten'!$D$7:$D$8,1),IF(COUNTIFS('[D Finanzen.xlsx]D Finanzen'!$A$45:$A$115,'[Steuerung.xlsx]Steuerung'!$F$6,'[D Finanzen.xlsx]D Finanzen'!$B$45:$B$115,F$5)=0,"",SUMIFS('[D Finanzen.xlsx]D Finanzen'!$E$45:$E$115,'[D Finanzen.xlsx]D Finanzen'!$A$45:$A$115,'[Steuerung.xlsx]Steuerung'!$F$6,'[D Finanzen.xlsx]D Finanzen'!$B$45:$B$115,F$5,'[D Finanzen.xlsx]D Finanzen'!$C$45:$C$115,20))) | G8: =IF(COUNTIFS('[Import Monatsdaten.xlsx]Import Monatsdaten'!$C$7:$C$8,'[Steuerung.xlsx]Steuerung'!$F$6,'[Import Monatsdaten.xlsx]Import Monatsdaten'!$D$7:$D$8,2)>0,SUMIFS('[Import Monatsdaten.xlsx]Import Monatsdaten'!$F$7:$F$8,'[Import Monatsdaten.xlsx]Import Monatsdaten'!$C$7:$C$8,'[Steuerung.xlsx]Steuerung'!$F$6,'[Import Monatsdaten.xlsx]Import Monatsdaten'!$D$7:$D$8,2),IF(COUNTIFS('[D Finanzen.xlsx]D Finanzen'!$A$45:$A$115,'[Steuerung.xlsx]Steuerung'!$F$6,'[D Finanzen.xlsx]D Finanzen'!$B$45:$B$115,G$5)=0,"",SUMIFS('[D Finanzen.xlsx]D Finanzen'!$E$45:$E$115,'[D Finanzen.xlsx]D Finanzen'!$A$45:$A$115,'[Steuerung.xlsx]Steuerung'!$F$6,'[D Finanzen.xlsx]D Finanzen'!$B$45:$B$115,G$5,'[D Finanzen.xlsx]D Finanzen'!$C$45:$C$115,20))) | H8: =IF(COUNTIFS('[Import Monatsdaten.xlsx]Import Monatsdaten'!$C$7:$C$8,'[Steuerung.xlsx]Steuerung'!$F$6,'[Import Monatsdaten.xlsx]Import Monatsdaten'!$D$7:$D$8,3)>0,SUMIFS('[Import Monatsdaten.xlsx]Import Monatsdaten'!$F$7:$F$8,'[Import Monatsdaten.xlsx]Import Monatsdaten'!$C$7:$C$8,'[Steuerung.xlsx]Steuerung'!$F$6,'[Import Monatsdaten.xlsx]Import Monatsdaten'!$D$7:$D$8,3),IF(COUNTIFS('[D Finanzen.xlsx]D Finanzen'!$A$45:$A$115,'[Steuerung.xlsx]Steuerung'!$F$6,'[D Finanzen.xlsx]D Finanzen'!$B$45:$B$115,H$5)=0,"",SUMIFS('[D Finanzen.xlsx]D Finanzen'!$E$45:$E$115,'[D Finanzen.xlsx]D Finanzen'!$A$45:$A$115,'[Steuerung.xlsx]Steuerung'!$F$6,'[D Finanzen.xlsx]D Finanzen'!$B$45:$B$115,H$5,'[D Finanzen.xlsx]D Finanzen'!$C$45:$C$115,20))) | I8: =IF(COUNTIFS('[Import Monatsdaten.xlsx]Import Monatsdaten'!$C$7:$C$8,'[Steuerung.xlsx]Steuerung'!$F$6,'[Import Monatsdaten.xlsx]Import Monatsdaten'!$D$7:$D$8,4)>0,SUMIFS('[Import Monatsdaten.xlsx]Import Monatsdaten'!$F$7:$F$8,'[Import Monatsdaten.xlsx]Import Monatsdaten'!$C$7:$C$8,'[Steuerung.xlsx]Steuerung'!$F$6,'[Import Monatsdaten.xlsx]Import Monatsdaten'!$D$7:$D$8,4),IF(COUNTIFS('[D Finanzen.xlsx]D Finanzen'!$A$45:$A$115,'[Steuerung.xlsx]Steuerung'!$F$6,'[D Finanzen.xlsx]D Finanzen'!$B$45:$B$115,I$5)=0,"",SUMIFS('[D Finanzen.xlsx]D Finanzen'!$E$45:$E$115,'[D Finanzen.xlsx]D Finanzen'!$A$45:$A$115,'[Steuerung.xlsx]Steuerung'!$F$6,'[D Finanzen.xlsx]D Finanzen'!$B$45:$B$115,I$5,'[D Finanzen.xlsx]D Finanzen'!$C$45:$C$115,20))) | J8: =IF(COUNTIFS('[Import Monatsdaten.xlsx]Import Monatsdaten'!$C$7:$C$8,'[Steuerung.xlsx]Steuerung'!$F$6,'[Import Monatsdaten.xlsx]Import Monatsdaten'!$D$7:$D$8,5)>0,SUMIFS('[Import Monatsdaten.xlsx]Import Monatsdaten'!$F$7:$F$8,'[Import Monatsdaten.xlsx]Import Monatsdaten'!$C$7:$C$8,'[Steuerung.xlsx]Steuerung'!$F$6,'[Import Monatsdaten.xlsx]Import Monatsdaten'!$D$7:$D$8,5),IF(COUNTIFS('[D Finanzen.xlsx]D Finanzen'!$A$45:$A$115,'[Steuerung.xlsx]Steuerung'!$F$6,'[D Finanzen.xlsx]D Finanzen'!$B$45:$B$115,J$5)=0,"",SUMIFS('[D Finanzen.xlsx]D Finanzen'!$E$45:$E$115,'[D Finanzen.xlsx]D Finanzen'!$A$45:$A$115,'[Steuerung.xlsx]Steuerung'!$F$6,'[D Finanzen.xlsx]D Finanzen'!$B$45:$B$115,J$5,'[D Finanzen.xlsx]D Finanzen'!$C$45:$C$115,20))) | K8: =IF(COUNTIFS('[Import Monatsdaten.xlsx]Import Monatsdaten'!$C$7:$C$8,'[Steuerung.xlsx]Steuerung'!$F$6,'[Import Monatsdaten.xlsx]Import Monatsdaten'!$D$7:$D$8,6)>0,SUMIFS('[Import Monatsdaten.xlsx]Import Monatsdaten'!$F$7:$F$8,'[Import Monatsdaten.xlsx]Import Monatsdaten'!$C$7:$C$8,'[Steuerung.xlsx]Steuerung'!$F$6,'[Import Monatsdaten.xlsx]Import Monatsdaten'!$D$7:$D$8,6),IF(COUNTIFS('[D Finanzen.xlsx]D Finanzen'!$A$45:$A$115,'[Steuerung.xlsx]Steuerung'!$F$6,'[D Finanzen.xlsx]D Finanzen'!$B$45:$B$115,K$5)=0,"",SUMIFS('[D Finanzen.xlsx]D Finanzen'!$E$45:$E$115,'[D Finanzen.xlsx]D Finanzen'!$A$45:$A$115,'[Steuerung.xlsx]Steuerung'!$F$6,'[D Finanzen.xlsx]D Finanzen'!$B$45:$B$115,K$5,'[D Finanzen.xlsx]D Finanzen'!$C$45:$C$115,20))) | L8: =IF(COUNTIFS('[Import Monatsdaten.xlsx]Import Monatsdaten'!$C$7:$C$8,'[Steuerung.xlsx]Steuerung'!$F$6,'[Import Monatsdaten.xlsx]Import Monatsdaten'!$D$7:$D$8,7)>0,SUMIFS('[Import Monatsdaten.xlsx]Import Monatsdaten'!$F$7:$F$8,'[Import Monatsdaten.xlsx]Import Monatsdaten'!$C$7:$C$8,'[Steuerung.xlsx]Steuerung'!$F$6,'[Import Monatsdaten.xlsx]Import Monatsdaten'!$D$7:$D$8,7),IF(COUNTIFS('[D Finanzen.xlsx]D Finanzen'!$A$45:$A$115,'[Steuerung.xlsx]Steuerung'!$F$6,'[D Finanzen.xlsx]D Finanzen'!$B$45:$B$115,L$5)=0,"",SUMIFS('[D Finanzen.xlsx]D Finanzen'!$E$45:$E$115,'[D Finanzen.xlsx]D Finanzen'!$A$45:$A$115,'[Steuerung.xlsx]Steuerung'!$F$6,'[D Finanzen.xlsx]D Finanzen'!$B$45:$B$115,L$5,'[D Finanzen.xlsx]D Finanzen'!$C$45:$C$115,20))) | M8: =IF(COUNTIFS('[Import Monatsdaten.xlsx]Import Monatsdaten'!$C$7:$C$8,'[Steuerung.xlsx]Steuerung'!$F$6,'[Import Monatsdaten.xlsx]Import Monatsdaten'!$D$7:$D$8,8)>0,SUMIFS('[Import Monatsdaten.xlsx]Import Monatsdaten'!$F$7:$F$8,'[Import Monatsdaten.xlsx]Import Monatsdaten'!$C$7:$C$8,'[Steuerung.xlsx]Steuerung'!$F$6,'[Import Monatsdaten.xlsx]Import Monatsdaten'!$D$7:$D$8,8),IF(COUNTIFS('[D Finanzen.xlsx]D Finanzen'!$A$45:$A$115,'[Steuerung.xlsx]Steuerung'!$F$6,'[D Finanzen.xlsx]D Finanzen'!$B$45:$B$115,M$5)=0,"",SUMIFS('[D Finanzen.xlsx]D Finanzen'!$E$45:$E$115,'[D Finanzen.xlsx]D Finanzen'!$A$45:$A$115,'[Steuerung.xlsx]Steuerung'!$F$6,'[D Finanzen.xlsx]D Finanzen'!$B$45:$B$115,M$5,'[D Finanzen.xlsx]D Finanzen'!$C$45:$C$115,20))) | N8: =IF(COUNTIFS('[Import Monatsdaten.xlsx]Import Monatsdaten'!$C$7:$C$8,'[Steuerung.xlsx]Steuerung'!$F$6,'[Import Monatsdaten.xlsx]Import Monatsdaten'!$D$7:$D$8,9)>0,SUMIFS('[Import Monatsdaten.xlsx]Import Monatsdaten'!$F$7:$F$8,'[Import Monatsdaten.xlsx]Import Monatsdaten'!$C$7:$C$8,'[Steuerung.xlsx]Steuerung'!$F$6,'[Import Monatsdaten.xlsx]Import Monatsdaten'!$D$7:$D$8,9),IF(COUNTIFS('[D Finanzen.xlsx]D Finanzen'!$A$45:$A$115,'[Steuerung.xlsx]Steuerung'!$F$6,'[D Finanzen.xlsx]D Finanzen'!$B$45:$B$115,N$5)=0,"",SUMIFS('[D Finanzen.xlsx]D Finanzen'!$E$45:$E$115,'[D Finanzen.xlsx]D Finanzen'!$A$45:$A$115,'[Steuerung.xlsx]Steuerung'!$F$6,'[D Finanzen.xlsx]D Finanzen'!$B$45:$B$115,N$5,'[D Finanzen.xlsx]D Finanzen'!$C$45:$C$115,20))) | O8: =IF(COUNTIFS('[Import Monatsdaten.xlsx]Import Monatsdaten'!$C$7:$C$8,'[Steuerung.xlsx]Steuerung'!$F$6,'[Import Monatsdaten.xlsx]Import Monatsdaten'!$D$7:$D$8,10)>0,SUMIFS('[Import Monatsdaten.xlsx]Import Monatsdaten'!$F$7:$F$8,'[Import Monatsdaten.xlsx]Import Monatsdaten'!$C$7:$C$8,'[Steuerung.xlsx]Steuerung'!$F$6,'[Import Monatsdaten.xlsx]Import Monatsdaten'!$D$7:$D$8,10),IF(COUNTIFS('[D Finanzen.xlsx]D Finanzen'!$A$45:$A$115,'[Steuerung.xlsx]Steuerung'!$F$6,'[D Finanzen.xlsx]D Finanzen'!$B$45:$B$115,O$5)=0,"",SUMIFS('[D Finanzen.xlsx]D Finanzen'!$E$45:$E$115,'[D Finanzen.xlsx]D Finanzen'!$A$45:$A$115,'[Steuerung.xlsx]Steuerung'!$F$6,'[D Finanzen.xlsx]D Finanzen'!$B$45:$B$115,O$5,'[D Finanzen.xlsx]D Finanzen'!$C$45:$C$115,20))) | P8: =IF(COUNTIFS('[Import Monatsdaten.xlsx]Import Monatsdaten'!$C$7:$C$8,'[Steuerung.xlsx]Steuerung'!$F$6,'[Import Monatsdaten.xlsx]Import Monatsdaten'!$D$7:$D$8,11)>0,SUMIFS('[Import Monatsdaten.xlsx]Import Monatsdaten'!$F$7:$F$8,'[Import Monatsdaten.xlsx]Import Monatsdaten'!$C$7:$C$8,'[Steuerung.xlsx]Steuerung'!$F$6,'[Import Monatsdaten.xlsx]Import Monatsdaten'!$D$7:$D$8,11),IF(COUNTIFS('[D Finanzen.xlsx]D Finanzen'!$A$45:$A$115,'[Steuerung.xlsx]Steuerung'!$F$6,'[D Finanzen.xlsx]D Finanzen'!$B$45:$B$115,P$5)=0,"",SUMIFS('[D Finanzen.xlsx]D Finanzen'!$E$45:$E$115,'[D Finanzen.xlsx]D Finanzen'!$A$45:$A$115,'[Steuerung.xlsx]Steuerung'!$F$6,'[D Finanzen.xlsx]D Finanzen'!$B$45:$B$115,P$5,'[D Finanzen.xlsx]D Finanzen'!$C$45:$C$115,20))) | Q8: =IF(COUNTIFS('[Import Monatsdaten.xlsx]Import Monatsdaten'!$C$7:$C$8,'[Steuerung.xlsx]Steuerung'!$F$6,'[Import Monatsdaten.xlsx]Import Monatsdaten'!$D$7:$D$8,12)>0,SUMIFS('[Import Monatsdaten.xlsx]Import Monatsdaten'!$F$7:$F$8,'[Import Monatsdaten.xlsx]Import Monatsdaten'!$C$7:$C$8,'[Steuerung.xlsx]Steuerung'!$F$6,'[Import Monatsdaten.xlsx]Import Monatsdaten'!$D$7:$D$8,12),IF(COUNTIFS('[D Finanzen.xlsx]D Finanzen'!$A$45:$A$115,'[Steuerung.xlsx]Steuerung'!$F$6,'[D Finanzen.xlsx]D Finanzen'!$B$45:$B$115,Q$5)=0,"",SUMIFS('[D Finanzen.xlsx]D Finanzen'!$E$45:$E$115,'[D Finanzen.xlsx]D Finanzen'!$A$45:$A$115,'[Steuerung.xlsx]Steuerung'!$F$6,'[D Finanzen.xlsx]D Finanzen'!$B$45:$B$115,Q$5,'[D Finanzen.xlsx]D Finanzen'!$C$45:$C$115,20)))
C9: Gesamtleistung | D9: =SUMIFS(F9:Q9,$F$5:$Q$5,"<="&'[Steuerung.xlsx]Steuerung'!$F$7) | E9: =IF($D$9=0,"n.a.",D9/$D$9) | F9: =IF(F7="","",SUM(F7:F8)) | G9: =IF(G7="","",SUM(G7:G8)) | H9: =IF(H7="","",SUM(H7:H8)) | I9: =IF(I7="","",SUM(I7:I8)) | J9: =IF(J7="","",SUM(J7:J8)) | K9: =IF(K7="","",SUM(K7:K8)) | L9: =IF(L7="","",SUM(L7:L8)) | M9: =IF(M7="","",SUM(M7:M8)) | ... Q9: =IF(Q7="","",SUM(Q7:Q8))
C10: Sonstige betriebliche Erträge | D10: =SUMIFS(F10:Q10,$F$5:$Q$5,"<="&'[Steuerung.xlsx]Steuerung'!$F$7) | E10: =IF($D$9=0,"n.a.",D10/$D$9) | F10: =IF(COUNTIFS('[Import Monatsdaten.xlsx]Import Monatsdaten'!$C$7:$C$8,'[Steuerung.xlsx]Steuerung'!$F$6,'[Import Monatsdaten.xlsx]Import Monatsdaten'!$D$7:$D$8,1)>0,SUMIFS('[Import Monatsdaten.xlsx]Import Monatsdaten'!$G$7:$G$8,'[Import Monatsdaten.xlsx]Import Monatsdaten'!$C$7:$C$8,'[Steuerung.xlsx]Steuerung'!$F$6,'[Import Monatsdaten.xlsx]Import Monatsdaten'!$D$7:$D$8,1),IF(COUNTIFS('[D Finanzen.xlsx]D Finanzen'!$A$45:$A$115,'[Steuerung.xlsx]Steuerung'!$F$6,'[D Finanzen.xlsx]D Finanzen'!$B$45:$B$115,F$5)=0,"",SUMIFS('[D Finanzen.xlsx]D Finanzen'!$E$45:$E$115,'[D Finanzen.xlsx]D Finanzen'!$A$45:$A$115,'[Steuerung.xlsx]Steuerung'!$F$6,'[D Finanzen.xlsx]D Finanzen'!$B$45:$B$115,F$5,'[D Finanzen.xlsx]D Finanzen'!$C$45:$C$115,30))) | G10: =IF(COUNTIFS('[Import Monatsdaten.xlsx]Import Monatsdaten'!$C$7:$C$8,'[Steuerung.xlsx]Steuerung'!$F$6,'[Import Monatsdaten.xlsx]Import Monatsdaten'!$D$7:$D$8,2)>0,SUMIFS('[Import Monatsdaten.xlsx]Import Monatsdaten'!$G$7:$G$8,'[Import Monatsdaten.xlsx]Import Monatsdaten'!$C$7:$C$8,'[Steuerung.xlsx]Steuerung'!$F$6,'[Import Monatsdaten.xlsx]Import Monatsdaten'!$D$7:$D$8,2),IF(COUNTIFS('[D Finanzen.xlsx]D Finanzen'!$A$45:$A$115,'[Steuerung.xlsx]Steuerung'!$F$6,'[D Finanzen.xlsx]D Finanzen'!$B$45:$B$115,G$5)=0,"",SUMIFS('[D Finanzen.xlsx]D Finanzen'!$E$45:$E$115,'[D Finanzen.xlsx]D Finanzen'!$A$45:$A$115,'[Steuerung.xlsx]Steuerung'!$F$6,'[D Finanzen.xlsx]D Finanzen'!$B$45:$B$115,G$5,'[D Finanzen.xlsx]D Finanzen'!$C$45:$C$115,30))) | H10: =IF(COUNTIFS('[Import Monatsdaten.xlsx]Import Monatsdaten'!$C$7:$C$8,'[Steuerung.xlsx]Steuerung'!$F$6,'[Import Monatsdaten.xlsx]Import Monatsdaten'!$D$7:$D$8,3)>0,SUMIFS('[Import Monatsdaten.xlsx]Import Monatsdaten'!$G$7:$G$8,'[Import Monatsdaten.xlsx]Import Monatsdaten'!$C$7:$C$8,'[Steuerung.xlsx]Steuerung'!$F$6,'[Import Monatsdaten.xlsx]Import Monatsdaten'!$D$7:$D$8,3),IF(COUNTIFS('[D Finanzen.xlsx]D Finanzen'!$A$45:$A$115,'[Steuerung.xlsx]Steuerung'!$F$6,'[D Finanzen.xlsx]D Finanzen'!$B$45:$B$115,H$5)=0,"",SUMIFS('[D Finanzen.xlsx]D Finanzen'!$E$45:$E$115,'[D Finanzen.xlsx]D Finanzen'!$A$45:$A$115,'[Steuerung.xlsx]Steuerung'!$F$6,'[D Finanzen.xlsx]D Finanzen'!$B$45:$B$115,H$5,'[D Finanzen.xlsx]D Finanzen'!$C$45:$C$115,30))) | I10: =IF(COUNTIFS('[Import Monatsdaten.xlsx]Import Monatsdaten'!$C$7:$C$8,'[Steuerung.xlsx]Steuerung'!$F$6,'[Import Monatsdaten.xlsx]Import Monatsdaten'!$D$7:$D$8,4)>0,SUMIFS('[Import Monatsdaten.xlsx]Import Monatsdaten'!$G$7:$G$8,'[Import Monatsdaten.xlsx]Import Monatsdaten'!$C$7:$C$8,'[Steuerung.xlsx]Steuerung'!$F$6,'[Import Monatsdaten.xlsx]Import Monatsdaten'!$D$7:$D$8,4),IF(COUNTIFS('[D Finanzen.xlsx]D Finanzen'!$A$45:$A$115,'[Steuerung.xlsx]Steuerung'!$F$6,'[D Finanzen.xlsx]D Finanzen'!$B$45:$B$115,I$5)=0,"",SUMIFS('[D Finanzen.xlsx]D Finanzen'!$E$45:$E$115,'[D Finanzen.xlsx]D Finanzen'!$A$45:$A$115,'[Steuerung.xlsx]Steuerung'!$F$6,'[D Finanzen.xlsx]D Finanzen'!$B$45:$B$115,I$5,'[D Finanzen.xlsx]D Finanzen'!$C$45:$C$115,30))) | J10: =IF(COUNTIFS('[Import Monatsdaten.xlsx]Import Monatsdaten'!$C$7:$C$8,'[Steuerung.xlsx]Steuerung'!$F$6,'[Import Monatsdaten.xlsx]Import Monatsdaten'!$D$7:$D$8,5)>0,SUMIFS('[Import Monatsdaten.xlsx]Import Monatsdaten'!$G$7:$G$8,'[Import Monatsdaten.xlsx]Import Monatsdaten'!$C$7:$C$8,'[Steuerung.xlsx]Steuerung'!$F$6,'[Import Monatsdaten.xlsx]Import Monatsdaten'!$D$7:$D$8,5),IF(COUNTIFS('[D Finanzen.xlsx]D Finanzen'!$A$45:$A$115,'[Steuerung.xlsx]Steuerung'!$F$6,'[D Finanzen.xlsx]D Finanzen'!$B$45:$B$115,J$5)=0,"",SUMIFS('[D Finanzen.xlsx]D Finanzen'!$E$45:$E$115,'[D Finanzen.xlsx]D Finanzen'!$A$45:$A$115,'[Steuerung.xlsx]Steuerung'!$F$6,'[D Finanzen.xlsx]D Finanzen'!$B$45:$B$115,J$5,'[D Finanzen.xlsx]D Finanzen'!$C$45:$C$115,30))) | K10: =IF(COUNTIFS('[Import Monatsdaten.xlsx]Import Monatsdaten'!$C$7:$C$8,'[Steuerung.xlsx]Steuerung'!$F$6,'[Import Monatsdaten.xlsx]Import Monatsdaten'!$D$7:$D$8,6)>0,SUMIFS('[Import Monatsdaten.xlsx]Import Monatsdaten'!$G$7:$G$8,'[Import Monatsdaten.xlsx]Import Monatsdaten'!$C$7:$C$8,'[Steuerung.xlsx]Steuerung'!$F$6,'[Import Monatsdaten.xlsx]Import Monatsdaten'!$D$7:$D$8,6),IF(COUNTIFS('[D Finanzen.xlsx]D Finanzen'!$A$45:$A$115,'[Steuerung.xlsx]Steuerung'!$F$6,'[D Finanzen.xlsx]D Finanzen'!$B$45:$B$115,K$5)=0,"",SUMIFS('[D Finanzen.xlsx]D Finanzen'!$E$45:$E$115,'[D Finanzen.xlsx]D Finanzen'!$A$45:$A$115,'[Steuerung.xlsx]Steuerung'!$F$6,'[D Finanzen.xlsx]D Finanzen'!$B$45:$B$115,K$5,'[D Finanzen.xlsx]D Finanzen'!$C$45:$C$115,30))) | L10: =IF(COUNTIFS('[Import Monatsdaten.xlsx]Import Monatsdaten'!$C$7:$C$8,'[Steuerung.xlsx]Steuerung'!$F$6,'[Import Monatsdaten.xlsx]Import Monatsdaten'!$D$7:$D$8,7)>0,SUMIFS('[Import Monatsdaten.xlsx]Import Monatsdaten'!$G$7:$G$8,'[Import Monatsdaten.xlsx]Import Monatsdaten'!$C$7:$C$8,'[Steuerung.xlsx]Steuerung'!$F$6,'[Import Monatsdaten.xlsx]Import Monatsdaten'!$D$7:$D$8,7),IF(COUNTIFS('[D Finanzen.xlsx]D Finanzen'!$A$45:$A$115,'[Steuerung.xlsx]Steuerung'!$F$6,'[D Finanzen.xlsx]D Finanzen'!$B$45:$B$115,L$5)=0,"",SUMIFS('[D Finanzen.xlsx]D Finanzen'!$E$45:$E$115,'[D Finanzen.xlsx]D Finanzen'!$A$45:$A$115,'[Steuerung.xlsx]Steuerung'!$F$6,'[D Finanzen.xlsx]D Finanzen'!$B$45:$B$115,L$5,'[D Finanzen.xlsx]D Finanzen'!$C$45:$C$115,30))) | M10: =IF(COUNTIFS('[Import Monatsdaten.xlsx]Import Monatsdaten'!$C$7:$C$8,'[Steuerung.xlsx]Steuerung'!$F$6,'[Import Monatsdaten.xlsx]Import Monatsdaten'!$D$7:$D$8,8)>0,SUMIFS('[Import Monatsdaten.xlsx]Import Monatsdaten'!$G$7:$G$8,'[Import Monatsdaten.xlsx]Import Monatsdaten'!$C$7:$C$8,'[Steuerung.xlsx]Steuerung'!$F$6,'[Import Monatsdaten.xlsx]Import Monatsdaten'!$D$7:$D$8,8),IF(COUNTIFS('[D Finanzen.xlsx]D Finanzen'!$A$45:$A$115,'[Steuerung.xlsx]Steuerung'!$F$6,'[D Finanzen.xlsx]D Finanzen'!$B$45:$B$115,M$5)=0,"",SUMIFS('[D Finanzen.xlsx]D Finanzen'!$E$45:$E$115,'[D Finanzen.xlsx]D Finanzen'!$A$45:$A$115,'[Steuerung.xlsx]Steuerung'!$F$6,'[D Finanzen.xlsx]D Finanzen'!$B$45:$B$115,M$5,'[D Finanzen.xlsx]D Finanzen'!$C$45:$C$115,30))) | N10: =IF(COUNTIFS('[Import Monatsdaten.xlsx]Import Monatsdaten'!$C$7:$C$8,'[Steuerung.xlsx]Steuerung'!$F$6,'[Import Monatsdaten.xlsx]Import Monatsdaten'!$D$7:$D$8,9)>0,SUMIFS('[Import Monatsdaten.xlsx]Import Monatsdaten'!$G$7:$G$8,'[Import Monatsdaten.xlsx]Import Monatsdaten'!$C$7:$C$8,'[Steuerung.xlsx]Steuerung'!$F$6,'[Import Monatsdaten.xlsx]Import Monatsdaten'!$D$7:$D$8,9),IF(COUNTIFS('[D Finanzen.xlsx]D Finanzen'!$A$45:$A$115,'[Steuerung.xlsx]Steuerung'!$F$6,'[D Finanzen.xlsx]D Finanzen'!$B$45:$B$115,N$5)=0,"",SUMIFS('[D Finanzen.xlsx]D Finanzen'!$E$45:$E$115,'[D Finanzen.xlsx]D Finanzen'!$A$45:$A$115,'[Steuerung.xlsx]Steuerung'!$F$6,'[D Finanzen.xlsx]D Finanzen'!$B$45:$B$115,N$5,'[D Finanzen.xlsx]D Finanzen'!$C$45:$C$115,30))) | O10: =IF(COUNTIFS('[Import Monatsdaten.xlsx]Import Monatsdaten'!$C$7:$C$8,'[Steuerung.xlsx]Steuerung'!$F$6,'[Import Monatsdaten.xlsx]Import Monatsdaten'!$D$7:$D$8,10)>0,SUMIFS('[Import Monatsdaten.xlsx]Import Monatsdaten'!$G$7:$G$8,'[Import Monatsdaten.xlsx]Import Monatsdaten'!$C$7:$C$8,'[Steuerung.xlsx]Steuerung'!$F$6,'[Import Monatsdaten.xlsx]Import Monatsdaten'!$D$7:$D$8,10),IF(COUNTIFS('[D Finanzen.xlsx]D Finanzen'!$A$45:$A$115,'[Steuerung.xlsx]Steuerung'!$F$6,'[D Finanzen.xlsx]D Finanzen'!$B$45:$B$115,O$5)=0,"",SUMIFS('[D Finanzen.xlsx]D Finanzen'!$E$45:$E$115,'[D Finanzen.xlsx]D Finanzen'!$A$45:$A$115,'[Steuerung.xlsx]Steuerung'!$F$6,'[D Finanzen.xlsx]D Finanzen'!$B$45:$B$115,O$5,'[D Finanzen.xlsx]D Finanzen'!$C$45:$C$115,30))) | P10: =IF(COUNTIFS('[Import Monatsdaten.xlsx]Import Monatsdaten'!$C$7:$C$8,'[Steuerung.xlsx]Steuerung'!$F$6,'[Import Monatsdaten.xlsx]Import Monatsdaten'!$D$7:$D$8,11)>0,SUMIFS('[Import Monatsdaten.xlsx]Import Monatsdaten'!$G$7:$G$8,'[Import Monatsdaten.xlsx]Import Monatsdaten'!$C$7:$C$8,'[Steuerung.xlsx]Steuerung'!$F$6,'[Import Monatsdaten.xlsx]Import Monatsdaten'!$D$7:$D$8,11),IF(COUNTIFS('[D Finanzen.xlsx]D Finanzen'!$A$45:$A$115,'[Steuerung.xlsx]Steuerung'!$F$6,'[D Finanzen.xlsx]D Finanzen'!$B$45:$B$115,P$5)=0,"",SUMIFS('[D Finanzen.xlsx]D Finanzen'!$E$45:$E$115,'[D Finanzen.xlsx]D Finanzen'!$A$45:$A$115,'[Steuerung.xlsx]Steuerung'!$F$6,'[D Finanzen.xlsx]D Finanzen'!$B$45:$B$115,P$5,'[D Finanzen.xlsx]D Finanzen'!$C$45:$C$115,30))) | Q10: =IF(COUNTIFS('[Import Monatsdaten.xlsx]Import Monatsdaten'!$C$7:$C$8,'[Steuerung.xlsx]Steuerung'!$F$6,'[Import Monatsdaten.xlsx]Import Monatsdaten'!$D$7:$D$8,12)>0,SUMIFS('[Import Monatsdaten.xlsx]Import Monatsdaten'!$G$7:$G$8,'[Import Monatsdaten.xlsx]Import Monatsdaten'!$C$7:$C$8,'[Steuerung.xlsx]Steuerung'!$F$6,'[Import Monatsdaten.xlsx]Import Monatsdaten'!$D$7:$D$8,12),IF(COUNTIFS('[D Finanzen.xlsx]D Finanzen'!$A$45:$A$115,'[Steuerung.xlsx]Steuerung'!$F$6,'[D Finanzen.xlsx]D Finanzen'!$B$45:$B$115,Q$5)=0,"",SUMIFS('[D Finanzen.xlsx]D Finanzen'!$E$45:$E$115,'[D Finanzen.xlsx]D Finanzen'!$A$45:$A$115,'[Steuerung.xlsx]Steuerung'!$F$6,'[D Finanzen.xlsx]D Finanzen'!$B$45:$B$115,Q$5,'[D Finanzen.xlsx]D Finanzen'!$C$45:$C$115,30)))
C11: Materialaufwand | D11: =SUMIFS(F11:Q11,$F$5:$Q$5,"<="&'[Steuerung.xlsx]Steuerung'!$F$7) | E11: =IF($D$9=0,"n.a.",D11/$D$9) | F11: =IF(COUNTIFS('[Import Monatsdaten.xlsx]Import Monatsdaten'!$C$7:$C$8,'[Steuerung.xlsx]Steuerung'!$F$6,'[Import Monatsdaten.xlsx]Import Monatsdaten'!$D$7:$D$8,1)>0,SUMIFS('[Import Monatsdaten.xlsx]Import Monatsdaten'!$H$7:$H$8,'[Import Monatsdaten.xlsx]Import Monatsdaten'!$C$7:$C$8,'[Steuerung.xlsx]Steuerung'!$F$6,'[Import Monatsdaten.xlsx]Import Monatsdaten'!$D$7:$D$8,1),IF(COUNTIFS('[D Finanzen.xlsx]D Finanzen'!$A$45:$A$115,'[Steuerung.xlsx]Steuerung'!$F$6,'[D Finanzen.xlsx]D Finanzen'!$B$45:$B$115,F$5)=0,"",SUMIFS('[D Finanzen.xlsx]D Finanzen'!$E$45:$E$115,'[D Finanzen.xlsx]D Finanzen'!$A$45:$A$115,'[Steuerung.xlsx]Steuerung'!$F$6,'[D Finanzen.xlsx]D Finanzen'!$B$45:$B$115,F$5,'[D Finanzen.xlsx]D Finanzen'!$C$45:$C$115,40))) | G11: =IF(COUNTIFS('[Import Monatsdaten.xlsx]Import Monatsdaten'!$C$7:$C$8,'[Steuerung.xlsx]Steuerung'!$F$6,'[Import Monatsdaten.xlsx]Import Monatsdaten'!$D$7:$D$8,2)>0,SUMIFS('[Import Monatsdaten.xlsx]Import Monatsdaten'!$H$7:$H$8,'[Import Monatsdaten.xlsx]Import Monatsdaten'!$C$7:$C$8,'[Steuerung.xlsx]Steuerung'!$F$6,'[Import Monatsdaten.xlsx]Import Monatsdaten'!$D$7:$D$8,2),IF(COUNTIFS('[D Finanzen.xlsx]D Finanzen'!$A$45:$A$115,'[Steuerung.xlsx]Steuerung'!$F$6,'[D Finanzen.xlsx]D Finanzen'!$B$45:$B$115,G$5)=0,"",SUMIFS('[D Finanzen.xlsx]D Finanzen'!$E$45:$E$115,'[D Finanzen.xlsx]D Finanzen'!$A$45:$A$115,'[Steuerung.xlsx]Steuerung'!$F$6,'[D Finanzen.xlsx]D Finanzen'!$B$45:$B$115,G$5,'[D Finanzen.xlsx]D Finanzen'!$C$45:$C$115,40))) | H11: =IF(COUNTIFS('[Import Monatsdaten.xlsx]Import Monatsdaten'!$C$7:$C$8,'[Steuerung.xlsx]Steuerung'!$F$6,'[Import Monatsdaten.xlsx]Import Monatsdaten'!$D$7:$D$8,3)>0,SUMIFS('[Import Monatsdaten.xlsx]Import Monatsdaten'!$H$7:$H$8,'[Import Monatsdaten.xlsx]Import Monatsdaten'!$C$7:$C$8,'[Steuerung.xlsx]Steuerung'!$F$6,'[Import Monatsdaten.xlsx]Import Monatsdaten'!$D$7:$D$8,3),IF(COUNTIFS('[D Finanzen.xlsx]D Finanzen'!$A$45:$A$115,'[Steuerung.xlsx]Steuerung'!$F$6,'[D Finanzen.xlsx]D Finanzen'!$B$45:$B$115,H$5)=0,"",SUMIFS('[D Finanzen.xlsx]D Finanzen'!$E$45:$E$115,'[D Finanzen.xlsx]D Finanzen'!$A$45:$A$115,'[Steuerung.xlsx]Steuerung'!$F$6,'[D Finanzen.xlsx]D Finanzen'!$B$45:$B$115,H$5,'[D Finanzen.xlsx]D Finanzen'!$C$45:$C$115,40))) | I11: =IF(COUNTIFS('[Import Monatsdaten.xlsx]Import Monatsdaten'!$C$7:$C$8,'[Steuerung.xlsx]Steuerung'!$F$6,'[Import Monatsdaten.xlsx]Import Monatsdaten'!$D$7:$D$8,4)>0,SUMIFS('[Import Monatsdaten.xlsx]Import Monatsdaten'!$H$7:$H$8,'[Import Monatsdaten.xlsx]Import Monatsdaten'!$C$7:$C$8,'[Steuerung.xlsx]Steuerung'!$F$6,'[Import Monatsdaten.xlsx]Import Monatsdaten'!$D$7:$D$8,4),IF(COUNTIFS('[D Finanzen.xlsx]D Finanzen'!$A$45:$A$115,'[Steuerung.xlsx]Steuerung'!$F$6,'[D Finanzen.xlsx]D Finanzen'!$B$45:$B$115,I$5)=0,"",SUMIFS('[D Finanzen.xlsx]D Finanzen'!$E$45:$E$115,'[D Finanzen.xlsx]D Finanzen'!$A$45:$A$115,'[Steuerung.xlsx]Steuerung'!$F$6,'[D Finanzen.xlsx]D Finanzen'!$B$45:$B$115,I$5,'[D Finanzen.xlsx]D Finanzen'!$C$45:$C$115,40))) | J11: =IF(COUNTIFS('[Import Monatsdaten.xlsx]Import Monatsdaten'!$C$7:$C$8,'[Steuerung.xlsx]Steuerung'!$F$6,'[Import Monatsdaten.xlsx]Import Monatsdaten'!$D$7:$D$8,5)>0,SUMIFS('[Import Monatsdaten.xlsx]Import Monatsdaten'!$H$7:$H$8,'[Import Monatsdaten.xlsx]Import Monatsdaten'!$C$7:$C$8,'[Steuerung.xlsx]Steuerung'!$F$6,'[Import Monatsdaten.xlsx]Import Monatsdaten'!$D$7:$D$8,5),IF(COUNTIFS('[D Finanzen.xlsx]D Finanzen'!$A$45:$A$115,'[Steuerung.xlsx]Steuerung'!$F$6,'[D Finanzen.xlsx]D Finanzen'!$B$45:$B$115,J$5)=0,"",SUMIFS('[D Finanzen.xlsx]D Finanzen'!$E$45:$E$115,'[D Finanzen.xlsx]D Finanzen'!$A$45:$A$115,'[Steuerung.xlsx]Steuerung'!$F$6,'[D Finanzen.xlsx]D Finanzen'!$B$45:$B$115,J$5,'[D Finanzen.xlsx]D Finanzen'!$C$45:$C$115,40))) | K11: =IF(COUNTIFS('[Import Monatsdaten.xlsx]Import Monatsdaten'!$C$7:$C$8,'[Steuerung.xlsx]Steuerung'!$F$6,'[Import Monatsdaten.xlsx]Import Monatsdaten'!$D$7:$D$8,6)>0,SUMIFS('[Import Monatsdaten.xlsx]Import Monatsdaten'!$H$7:$H$8,'[Import Monatsdaten.xlsx]Import Monatsdaten'!$C$7:$C$8,'[Steuerung.xlsx]Steuerung'!$F$6,'[Import Monatsdaten.xlsx]Import Monatsdaten'!$D$7:$D$8,6),IF(COUNTIFS('[D Finanzen.xlsx]D Finanzen'!$A$45:$A$115,'[Steuerung.xlsx]Steuerung'!$F$6,'[D Finanzen.xlsx]D Finanzen'!$B$45:$B$115,K$5)=0,"",SUMIFS('[D Finanzen.xlsx]D Finanzen'!$E$45:$E$115,'[D Finanzen.xlsx]D Finanzen'!$A$45:$A$115,'[Steuerung.xlsx]Steuerung'!$F$6,'[D Finanzen.xlsx]D Finanzen'!$B$45:$B$115,K$5,'[D Finanzen.xlsx]D Finanzen'!$C$45:$C$115,40))) | L11: =IF(COUNTIFS('[Import Monatsdaten.xlsx]Import Monatsdaten'!$C$7:$C$8,'[Steuerung.xlsx]Steuerung'!$F$6,'[Import Monatsdaten.xlsx]Import Monatsdaten'!$D$7:$D$8,7)>0,SUMIFS('[Import Monatsdaten.xlsx]Import Monatsdaten'!$H$7:$H$8,'[Import Monatsdaten.xlsx]Import Monatsdaten'!$C$7:$C$8,'[Steuerung.xlsx]Steuerung'!$F$6,'[Import Monatsdaten.xlsx]Import Monatsdaten'!$D$7:$D$8,7),IF(COUNTIFS('[D Finanzen.xlsx]D Finanzen'!$A$45:$A$115,'[Steuerung.xlsx]Steuerung'!$F$6,'[D Finanzen.xlsx]D Finanzen'!$B$45:$B$115,L$5)=0,"",SUMIFS('[D Finanzen.xlsx]D Finanzen'!$E$45:$E$115,'[D Finanzen.xlsx]D Finanzen'!$A$45:$A$115,'[Steuerung.xlsx]Steuerung'!$F$6,'[D Finanzen.xlsx]D Finanzen'!$B$45:$B$115,L$5,'[D Finanzen.xlsx]D Finanzen'!$C$45:$C$115,40))) | M11: =IF(COUNTIFS('[Import Monatsdaten.xlsx]Import Monatsdaten'!$C$7:$C$8,'[Steuerung.xlsx]Steuerung'!$F$6,'[Import Monatsdaten.xlsx]Import Monatsdaten'!$D$7:$D$8,8)>0,SUMIFS('[Import Monatsdaten.xlsx]Import Monatsdaten'!$H$7:$H$8,'[Import Monatsdaten.xlsx]Import Monatsdaten'!$C$7:$C$8,'[Steuerung.xlsx]Steuerung'!$F$6,'[Import Monatsdaten.xlsx]Import Monatsdaten'!$D$7:$D$8,8),IF(COUNTIFS('[D Finanzen.xlsx]D Finanzen'!$A$45:$A$115,'[Steuerung.xlsx]Steuerung'!$F$6,'[D Finanzen.xlsx]D Finanzen'!$B$45:$B$115,M$5)=0,"",SUMIFS('[D Finanzen.xlsx]D Finanzen'!$E$45:$E$115,'[D Finanzen.xlsx]D Finanzen'!$A$45:$A$115,'[Steuerung.xlsx]Steuerung'!$F$6,'[D Finanzen.xlsx]D Finanzen'!$B$45:$B$115,M$5,'[D Finanzen.xlsx]D Finanzen'!$C$45:$C$115,40))) | N11: =IF(COUNTIFS('[Import Monatsdaten.xlsx]Import Monatsdaten'!$C$7:$C$8,'[Steuerung.xlsx]Steuerung'!$F$6,'[Import Monatsdaten.xlsx]Import Monatsdaten'!$D$7:$D$8,9)>0,SUMIFS('[Import Monatsdaten.xlsx]Import Monatsdaten'!$H$7:$H$8,'[Import Monatsdaten.xlsx]Import Monatsdaten'!$C$7:$C$8,'[Steuerung.xlsx]Steuerung'!$F$6,'[Import Monatsdaten.xlsx]Import Monatsdaten'!$D$7:$D$8,9),IF(COUNTIFS('[D Finanzen.xlsx]D Finanzen'!$A$45:$A$115,'[Steuerung.xlsx]Steuerung'!$F$6,'[D Finanzen.xlsx]D Finanzen'!$B$45:$B$115,N$5)=0,"",SUMIFS('[D Finanzen.xlsx]D Finanzen'!$E$45:$E$115,'[D Finanzen.xlsx]D Finanzen'!$A$45:$A$115,'[Steuerung.xlsx]Steuerung'!$F$6,'[D Finanzen.xlsx]D Finanzen'!$B$45:$B$115,N$5,'[D Finanzen.xlsx]D Finanzen'!$C$45:$C$115,40))) | O11: =IF(COUNTIFS('[Import Monatsdaten.xlsx]Import Monatsdaten'!$C$7:$C$8,'[Steuerung.xlsx]Steuerung'!$F$6,'[Import Monatsdaten.xlsx]Import Monatsdaten'!$D$7:$D$8,10)>0,SUMIFS('[Import Monatsdaten.xlsx]Import Monatsdaten'!$H$7:$H$8,'[Import Monatsdaten.xlsx]Import Monatsdaten'!$C$7:$C$8,'[Steuerung.xlsx]Steuerung'!$F$6,'[Import Monatsdaten.xlsx]Import Monatsdaten'!$D$7:$D$8,10),IF(COUNTIFS('[D Finanzen.xlsx]D Finanzen'!$A$45:$A$115,'[Steuerung.xlsx]Steuerung'!$F$6,'[D Finanzen.xlsx]D Finanzen'!$B$45:$B$115,O$5)=0,"",SUMIFS('[D Finanzen.xlsx]D Finanzen'!$E$45:$E$115,'[D Finanzen.xlsx]D Finanzen'!$A$45:$A$115,'[Steuerung.xlsx]Steuerung'!$F$6,'[D Finanzen.xlsx]D Finanzen'!$B$45:$B$115,O$5,'[D Finanzen.xlsx]D Finanzen'!$C$45:$C$115,40))) | P11: =IF(COUNTIFS('[Import Monatsdaten.xlsx]Import Monatsdaten'!$C$7:$C$8,'[Steuerung.xlsx]Steuerung'!$F$6,'[Import Monatsdaten.xlsx]Import Monatsdaten'!$D$7:$D$8,11)>0,SUMIFS('[Import Monatsdaten.xlsx]Import Monatsdaten'!$H$7:$H$8,'[Import Monatsdaten.xlsx]Import Monatsdaten'!$C$7:$C$8,'[Steuerung.xlsx]Steuerung'!$F$6,'[Import Monatsdaten.xlsx]Import Monatsdaten'!$D$7:$D$8,11),IF(COUNTIFS('[D Finanzen.xlsx]D Finanzen'!$A$45:$A$115,'[Steuerung.xlsx]Steuerung'!$F$6,'[D Finanzen.xlsx]D Finanzen'!$B$45:$B$115,P$5)=0,"",SUMIFS('[D Finanzen.xlsx]D Finanzen'!$E$45:$E$115,'[D Finanzen.xlsx]D Finanzen'!$A$45:$A$115,'[Steuerung.xlsx]Steuerung'!$F$6,'[D Finanzen.xlsx]D Finanzen'!$B$45:$B$115,P$5,'[D Finanzen.xlsx]D Finanzen'!$C$45:$C$115,40))) | Q11: =IF(COUNTIFS('[Import Monatsdaten.xlsx]Import Monatsdaten'!$C$7:$C$8,'[Steuerung.xlsx]Steuerung'!$F$6,'[Import Monatsdaten.xlsx]Import Monatsdaten'!$D$7:$D$8,12)>0,SUMIFS('[Import Monatsdaten.xlsx]Import Monatsdaten'!$H$7:$H$8,'[Import Monatsdaten.xlsx]Import Monatsdaten'!$C$7:$C$8,'[Steuerung.xlsx]Steuerung'!$F$6,'[Import Monatsdaten.xlsx]Import Monatsdaten'!$D$7:$D$8,12),IF(COUNTIFS('[D Finanzen.xlsx]D Finanzen'!$A$45:$A$115,'[Steuerung.xlsx]Steuerung'!$F$6,'[D Finanzen.xlsx]D Finanzen'!$B$45:$B$115,Q$5)=0,"",SUMIFS('[D Finanzen.xlsx]D Finanzen'!$E$45:$E$115,'[D Finanzen.xlsx]D Finanzen'!$A$45:$A$115,'[Steuerung.xlsx]Steuerung'!$F$6,'[D Finanzen.xlsx]D Finanzen'!$B$45:$B$115,Q$5,'[D Finanzen.xlsx]D Finanzen'!$C$45:$C$115,40)))
C12: Personalaufwand | D12: =SUMIFS(F12:Q12,$F$5:$Q$5,"<="&'[Steuerung.xlsx]Steuerung'!$F$7) | E12: =IF($D$9=0,"n.a.",D12/$D$9) | F12: =IF(COUNTIFS('[Import Monatsdaten.xlsx]Import Monatsdaten'!$C$7:$C$8,'[Steuerung.xlsx]Steuerung'!$F$6,'[Import Monatsdaten.xlsx]Import Monatsdaten'!$D$7:$D$8,1)>0,SUMIFS('[Import Monatsdaten.xlsx]Import Monatsdaten'!$I$7:$I$8,'[Import Monatsdaten.xlsx]Import Monatsdaten'!$C$7:$C$8,'[Steuerung.xlsx]Steuerung'!$F$6,'[Import Monatsdaten.xlsx]Import Monatsdaten'!$D$7:$D$8,1),IF(COUNTIFS('[D Finanzen.xlsx]D Finanzen'!$A$45:$A$115,'[Steuerung.xlsx]Steuerung'!$F$6,'[D Finanzen.xlsx]D Finanzen'!$B$45:$B$115,F$5)=0,"",SUMIFS('[D Finanzen.xlsx]D Finanzen'!$E$45:$E$115,'[D Finanzen.xlsx]D Finanzen'!$A$45:$A$115,'[Steuerung.xlsx]Steuerung'!$F$6,'[D Finanzen.xlsx]D Finanzen'!$B$45:$B$115,F$5,'[D Finanzen.xlsx]D Finanzen'!$C$45:$C$115,50))) | G12: =IF(COUNTIFS('[Import Monatsdaten.xlsx]Import Monatsdaten'!$C$7:$C$8,'[Steuerung.xlsx]Steuerung'!$F$6,'[Import Monatsdaten.xlsx]Import Monatsdaten'!$D$7:$D$8,2)>0,SUMIFS('[Import Monatsdaten.xlsx]Import Monatsdaten'!$I$7:$I$8,'[Import Monatsdaten.xlsx]Import Monatsdaten'!$C$7:$C$8,'[Steuerung.xlsx]Steuerung'!$F$6,'[Import Monatsdaten.xlsx]Import Monatsdaten'!$D$7:$D$8,2),IF(COUNTIFS('[D Finanzen.xlsx]D Finanzen'!$A$45:$A$115,'[Steuerung.xlsx]Steuerung'!$F$6,'[D Finanzen.xlsx]D Finanzen'!$B$45:$B$115,G$5)=0,"",SUMIFS('[D Finanzen.xlsx]D Finanzen'!$E$45:$E$115,'[D Finanzen.xlsx]D Finanzen'!$A$45:$A$115,'[Steuerung.xlsx]Steuerung'!$F$6,'[D Finanzen.xlsx]D Finanzen'!$B$45:$B$115,G$5,'[D Finanzen.xlsx]D Finanzen'!$C$45:$C$115,50))) | H12: =IF(COUNTIFS('[Import Monatsdaten.xlsx]Import Monatsdaten'!$C$7:$C$8,'[Steuerung.xlsx]Steuerung'!$F$6,'[Import Monatsdaten.xlsx]Import Monatsdaten'!$D$7:$D$8,3)>0,SUMIFS('[Import Monatsdaten.xlsx]Import Monatsdaten'!$I$7:$I$8,'[Import Monatsdaten.xlsx]Import Monatsdaten'!$C$7:$C$8,'[Steuerung.xlsx]Steuerung'!$F$6,'[Import Monatsdaten.xlsx]Import Monatsdaten'!$D$7:$D$8,3),IF(COUNTIFS('[D Finanzen.xlsx]D Finanzen'!$A$45:$A$115,'[Steuerung.xlsx]Steuerung'!$F$6,'[D Finanzen.xlsx]D Finanzen'!$B$45:$B$115,H$5)=0,"",SUMIFS('[D Finanzen.xlsx]D Finanzen'!$E$45:$E$115,'[D Finanzen.xlsx]D Finanzen'!$A$45:$A$115,'[Steuerung.xlsx]Steuerung'!$F$6,'[D Finanzen.xlsx]D Finanzen'!$B$45:$B$115,H$5,'[D Finanzen.xlsx]D Finanzen'!$C$45:$C$115,50))) | I12: =IF(COUNTIFS('[Import Monatsdaten.xlsx]Import Monatsdaten'!$C$7:$C$8,'[Steuerung.xlsx]Steuerung'!$F$6,'[Import Monatsdaten.xlsx]Import Monatsdaten'!$D$7:$D$8,4)>0,SUMIFS('[Import Monatsdaten.xlsx]Import Monatsdaten'!$I$7:$I$8,'[Import Monatsdaten.xlsx]Import Monatsdaten'!$C$7:$C$8,'[Steuerung.xlsx]Steuerung'!$F$6,'[Import Monatsdaten.xlsx]Import Monatsdaten'!$D$7:$D$8,4),IF(COUNTIFS('[D Finanzen.xlsx]D Finanzen'!$A$45:$A$115,'[Steuerung.xlsx]Steuerung'!$F$6,'[D Finanzen.xlsx]D Finanzen'!$B$45:$B$115,I$5)=0,"",SUMIFS('[D Finanzen.xlsx]D Finanzen'!$E$45:$E$115,'[D Finanzen.xlsx]D Finanzen'!$A$45:$A$115,'[Steuerung.xlsx]Steuerung'!$F$6,'[D Finanzen.xlsx]D Finanzen'!$B$45:$B$115,I$5,'[D Finanzen.xlsx]D Finanzen'!$C$45:$C$115,50))) | J12: =IF(COUNTIFS('[Import Monatsdaten.xlsx]Import Monatsdaten'!$C$7:$C$8,'[Steuerung.xlsx]Steuerung'!$F$6,'[Import Monatsdaten.xlsx]Import Monatsdaten'!$D$7:$D$8,5)>0,SUMIFS('[Import Monatsdaten.xlsx]Import Monatsdaten'!$I$7:$I$8,'[Import Monatsdaten.xlsx]Import Monatsdaten'!$C$7:$C$8,'[Steuerung.xlsx]Steuerung'!$F$6,'[Import Monatsdaten.xlsx]Import Monatsdaten'!$D$7:$D$8,5),IF(COUNTIFS('[D Finanzen.xlsx]D Finanzen'!$A$45:$A$115,'[Steuerung.xlsx]Steuerung'!$F$6,'[D Finanzen.xlsx]D Finanzen'!$B$45:$B$115,J$5)=0,"",SUMIFS('[D Finanzen.xlsx]D Finanzen'!$E$45:$E$115,'[D Finanzen.xlsx]D Finanzen'!$A$45:$A$115,'[Steuerung.xlsx]Steuerung'!$F$6,'[D Finanzen.xlsx]D Finanzen'!$B$45:$B$115,J$5,'[D Finanzen.xlsx]D Finanzen'!$C$45:$C$115,50))) | K12: =IF(COUNTIFS('[Import Monatsdaten.xlsx]Import Monatsdaten'!$C$7:$C$8,'[Steuerung.xlsx]Steuerung'!$F$6,'[Import Monatsdaten.xlsx]Import Monatsdaten'!$D$7:$D$8,6)>0,SUMIFS('[Import Monatsdaten.xlsx]Import Monatsdaten'!$I$7:$I$8,'[Import Monatsdaten.xlsx]Import Monatsdaten'!$C$7:$C$8,'[Steuerung.xlsx]Steuerung'!$F$6,'[Import Monatsdaten.xlsx]Import Monatsdaten'!$D$7:$D$8,6),IF(COUNTIFS('[D Finanzen.xlsx]D Finanzen'!$A$45:$A$115,'[Steuerung.xlsx]Steuerung'!$F$6,'[D Finanzen.xlsx]D Finanzen'!$B$45:$B$115,K$5)=0,"",SUMIFS('[D Finanzen.xlsx]D Finanzen'!$E$45:$E$115,'[D Finanzen.xlsx]D Finanzen'!$A$45:$A$115,'[Steuerung.xlsx]Steuerung'!$F$6,'[D Finanzen.xlsx]D Finanzen'!$B$45:$B$115,K$5,'[D Finanzen.xlsx]D Finanzen'!$C$45:$C$115,50))) | L12: =IF(COUNTIFS('[Import Monatsdaten.xlsx]Import Monatsdaten'!$C$7:$C$8,'[Steuerung.xlsx]Steuerung'!$F$6,'[Import Monatsdaten.xlsx]Import Monatsdaten'!$D$7:$D$8,7)>0,SUMIFS('[Import Monatsdaten.xlsx]Import Monatsdaten'!$I$7:$I$8,'[Import Monatsdaten.xlsx]Import Monatsdaten'!$C$7:$C$8,'[Steuerung.xlsx]Steuerung'!$F$6,'[Import Monatsdaten.xlsx]Import Monatsdaten'!$D$7:$D$8,7),IF(COUNTIFS('[D Finanzen.xlsx]D Finanzen'!$A$45:$A$115,'[Steuerung.xlsx]Steuerung'!$F$6,'[D Finanzen.xlsx]D Finanzen'!$B$45:$B$115,L$5)=0,"",SUMIFS('[D Finanzen.xlsx]D Finanzen'!$E$45:$E$115,'[D Finanzen.xlsx]D Finanzen'!$A$45:$A$115,'[Steuerung.xlsx]Steuerung'!$F$6,'[D Finanzen.xlsx]D Finanzen'!$B$45:$B$115,L$5,'[D Finanzen.xlsx]D Finanzen'!$C$45:$C$115,50))) | M12: =IF(COUNTIFS('[Import Monatsdaten.xlsx]Import Monatsdaten'!$C$7:$C$8,'[Steuerung.xlsx]Steuerung'!$F$6,'[Import Monatsdaten.xlsx]Import Monatsdaten'!$D$7:$D$8,8)>0,SUMIFS('[Import Monatsdaten.xlsx]Import Monatsdaten'!$I$7:$I$8,'[Import Monatsdaten.xlsx]Import Monatsdaten'!$C$7:$C$8,'[Steuerung.xlsx]Steuerung'!$F$6,'[Import Monatsdaten.xlsx]Import Monatsdaten'!$D$7:$D$8,8),IF(COUNTIFS('[D Finanzen.xlsx]D Finanzen'!$A$45:$A$115,'[Steuerung.xlsx]Steuerung'!$F$6,'[D Finanzen.xlsx]D Finanzen'!$B$45:$B$115,M$5)=0,"",SUMIFS('[D Finanzen.xlsx]D Finanzen'!$E$45:$E$115,'[D Finanzen.xlsx]D Finanzen'!$A$45:$A$115,'[Steuerung.xlsx]Steuerung'!$F$6,'[D Finanzen.xlsx]D Finanzen'!$B$45:$B$115,M$5,'[D Finanzen.xlsx]D Finanzen'!$C$45:$C$115,50))) | N12: =IF(COUNTIFS('[Import Monatsdaten.xlsx]Import Monatsdaten'!$C$7:$C$8,'[Steuerung.xlsx]Steuerung'!$F$6,'[Import Monatsdaten.xlsx]Import Monatsdaten'!$D$7:$D$8,9)>0,SUMIFS('[Import Monatsdaten.xlsx]Import Monatsdaten'!$I$7:$I$8,'[Import Monatsdaten.xlsx]Import Monatsdaten'!$C$7:$C$8,'[Steuerung.xlsx]Steuerung'!$F$6,'[Import Monatsdaten.xlsx]Import Monatsdaten'!$D$7:$D$8,9),IF(COUNTIFS('[D Finanzen.xlsx]D Finanzen'!$A$45:$A$115,'[Steuerung.xlsx]Steuerung'!$F$6,'[D Finanzen.xlsx]D Finanzen'!$B$45:$B$115,N$5)=0,"",SUMIFS('[D Finanzen.xlsx]D Finanzen'!$E$45:$E$115,'[D Finanzen.xlsx]D Finanzen'!$A$45:$A$115,'[Steuerung.xlsx]Steuerung'!$F$6,'[D Finanzen.xlsx]D Finanzen'!$B$45:$B$115,N$5,'[D Finanzen.xlsx]D Finanzen'!$C$45:$C$115,50))) | O12: =IF(COUNTIFS('[Import Monatsdaten.xlsx]Import Monatsdaten'!$C$7:$C$8,'[Steuerung.xlsx]Steuerung'!$F$6,'[Import Monatsdaten.xlsx]Import Monatsdaten'!$D$7:$D$8,10)>0,SUMIFS('[Import Monatsdaten.xlsx]Import Monatsdaten'!$I$7:$I$8,'[Import Monatsdaten.xlsx]Import Monatsdaten'!$C$7:$C$8,'[Steuerung.xlsx]Steuerung'!$F$6,'[Import Monatsdaten.xlsx]Import Monatsdaten'!$D$7:$D$8,10),IF(COUNTIFS('[D Finanzen.xlsx]D Finanzen'!$A$45:$A$115,'[Steuerung.xlsx]Steuerung'!$F$6,'[D Finanzen.xlsx]D Finanzen'!$B$45:$B$115,O$5)=0,"",SUMIFS('[D Finanzen.xlsx]D Finanzen'!$E$45:$E$115,'[D Finanzen.xlsx]D Finanzen'!$A$45:$A$115,'[Steuerung.xlsx]Steuerung'!$F$6,'[D Finanzen.xlsx]D Finanzen'!$B$45:$B$115,O$5,'[D Finanzen.xlsx]D Finanzen'!$C$45:$C$115,50))) | P12: =IF(COUNTIFS('[Import Monatsdaten.xlsx]Import Monatsdaten'!$C$7:$C$8,'[Steuerung.xlsx]Steuerung'!$F$6,'[Import Monatsdaten.xlsx]Import Monatsdaten'!$D$7:$D$8,11)>0,SUMIFS('[Import Monatsdaten.xlsx]Import Monatsdaten'!$I$7:$I$8,'[Import Monatsdaten.xlsx]Import Monatsdaten'!$C$7:$C$8,'[Steuerung.xlsx]Steuerung'!$F$6,'[Import Monatsdaten.xlsx]Import Monatsdaten'!$D$7:$D$8,11),IF(COUNTIFS('[D Finanzen.xlsx]D Finanzen'!$A$45:$A$115,'[Steuerung.xlsx]Steuerung'!$F$6,'[D Finanzen.xlsx]D Finanzen'!$B$45:$B$115,P$5)=0,"",SUMIFS('[D Finanzen.xlsx]D Finanzen'!$E$45:$E$115,'[D Finanzen.xlsx]D Finanzen'!$A$45:$A$115,'[Steuerung.xlsx]Steuerung'!$F$6,'[D Finanzen.xlsx]D Finanzen'!$B$45:$B$115,P$5,'[D Finanzen.xlsx]D Finanzen'!$C$45:$C$115,50))) | Q12: =IF(COUNTIFS('[Import Monatsdaten.xlsx]Import Monatsdaten'!$C$7:$C$8,'[Steuerung.xlsx]Steuerung'!$F$6,'[Import Monatsdaten.xlsx]Import Monatsdaten'!$D$7:$D$8,12)>0,SUMIFS('[Import Monatsdaten.xlsx]Import Monatsdaten'!$I$7:$I$8,'[Import Monatsdaten.xlsx]Import Monatsdaten'!$C$7:$C$8,'[Steuerung.xlsx]Steuerung'!$F$6,'[Import Monatsdaten.xlsx]Import Monatsdaten'!$D$7:$D$8,12),IF(COUNTIFS('[D Finanzen.xlsx]D Finanzen'!$A$45:$A$115,'[Steuerung.xlsx]Steuerung'!$F$6,'[D Finanzen.xlsx]D Finanzen'!$B$45:$B$115,Q$5)=0,"",SUMIFS('[D Finanzen.xlsx]D Finanzen'!$E$45:$E$115,'[D Finanzen.xlsx]D Finanzen'!$A$45:$A$115,'[Steuerung.xlsx]Steuerung'!$F$6,'[D Finanzen.xlsx]D Finanzen'!$B$45:$B$115,Q$5,'[D Finanzen.xlsx]D Finanzen'!$C$45:$C$115,50)))
C13: Sonstige betriebliche Aufwendungen | D13: =SUMIFS(F13:Q13,$F$5:$Q$5,"<="&'[Steuerung.xlsx]Steuerung'!$F$7) | E13: =IF($D$9=0,"n.a.",D13/$D$9) | F13: =IF(COUNTIFS('[Import Monatsdaten.xlsx]Import Monatsdaten'!$C$7:$C$8,'[Steuerung.xlsx]Steuerung'!$F$6,'[Import Monatsdaten.xlsx]Import Monatsdaten'!$D$7:$D$8,1)>0,SUMIFS('[Import Monatsdaten.xlsx]Import Monatsdaten'!$J$7:$J$8,'[Import Monatsdaten.xlsx]Import Monatsdaten'!$C$7:$C$8,'[Steuerung.xlsx]Steuerung'!$F$6,'[Import Monatsdaten.xlsx]Import Monatsdaten'!$D$7:$D$8,1),IF(COUNTIFS('[D Finanzen.xlsx]D Finanzen'!$A$45:$A$115,'[Steuerung.xlsx]Steuerung'!$F$6,'[D Finanzen.xlsx]D Finanzen'!$B$45:$B$115,F$5)=0,"",SUMIFS('[D Finanzen.xlsx]D Finanzen'!$E$45:$E$115,'[D Finanzen.xlsx]D Finanzen'!$A$45:$A$115,'[Steuerung.xlsx]Steuerung'!$F$6,'[D Finanzen.xlsx]D Finanzen'!$B$45:$B$115,F$5,'[D Finanzen.xlsx]D Finanzen'!$C$45:$C$115,70))) | G13: =IF(COUNTIFS('[Import Monatsdaten.xlsx]Import Monatsdaten'!$C$7:$C$8,'[Steuerung.xlsx]Steuerung'!$F$6,'[Import Monatsdaten.xlsx]Import Monatsdaten'!$D$7:$D$8,2)>0,SUMIFS('[Import Monatsdaten.xlsx]Import Monatsdaten'!$J$7:$J$8,'[Import Monatsdaten.xlsx]Import Monatsdaten'!$C$7:$C$8,'[Steuerung.xlsx]Steuerung'!$F$6,'[Import Monatsdaten.xlsx]Import Monatsdaten'!$D$7:$D$8,2),IF(COUNTIFS('[D Finanzen.xlsx]D Finanzen'!$A$45:$A$115,'[Steuerung.xlsx]Steuerung'!$F$6,'[D Finanzen.xlsx]D Finanzen'!$B$45:$B$115,G$5)=0,"",SUMIFS('[D Finanzen.xlsx]D Finanzen'!$E$45:$E$115,'[D Finanzen.xlsx]D Finanzen'!$A$45:$A$115,'[Steuerung.xlsx]Steuerung'!$F$6,'[D Finanzen.xlsx]D Finanzen'!$B$45:$B$115,G$5,'[D Finanzen.xlsx]D Finanzen'!$C$45:$C$115,70))) | H13: =IF(COUNTIFS('[Import Monatsdaten.xlsx]Import Monatsdaten'!$C$7:$C$8,'[Steuerung.xlsx]Steuerung'!$F$6,'[Import Monatsdaten.xlsx]Import Monatsdaten'!$D$7:$D$8,3)>0,SUMIFS('[Import Monatsdaten.xlsx]Import Monatsdaten'!$J$7:$J$8,'[Import Monatsdaten.xlsx]Import Monatsdaten'!$C$7:$C$8,'[Steuerung.xlsx]Steuerung'!$F$6,'[Import Monatsdaten.xlsx]Import Monatsdaten'!$D$7:$D$8,3),IF(COUNTIFS('[D Finanzen.xlsx]D Finanzen'!$A$45:$A$115,'[Steuerung.xlsx]Steuerung'!$F$6,'[D Finanzen.xlsx]D Finanzen'!$B$45:$B$115,H$5)=0,"",SUMIFS('[D Finanzen.xlsx]D Finanzen'!$E$45:$E$115,'[D Finanzen.xlsx]D Finanzen'!$A$45:$A$115,'[Steuerung.xlsx]Steuerung'!$F$6,'[D Finanzen.xlsx]D Finanzen'!$B$45:$B$115,H$5,'[D Finanzen.xlsx]D Finanzen'!$C$45:$C$115,70))) | I13: =IF(COUNTIFS('[Import Monatsdaten.xlsx]Import Monatsdaten'!$C$7:$C$8,'[Steuerung.xlsx]Steuerung'!$F$6,'[Import Monatsdaten.xlsx]Import Monatsdaten'!$D$7:$D$8,4)>0,SUMIFS('[Import Monatsdaten.xlsx]Import Monatsdaten'!$J$7:$J$8,'[Import Monatsdaten.xlsx]Import Monatsdaten'!$C$7:$C$8,'[Steuerung.xlsx]Steuerung'!$F$6,'[Import Monatsdaten.xlsx]Import Monatsdaten'!$D$7:$D$8,4),IF(COUNTIFS('[D Finanzen.xlsx]D Finanzen'!$A$45:$A$115,'[Steuerung.xlsx]Steuerung'!$F$6,'[D Finanzen.xlsx]D Finanzen'!$B$45:$B$115,I$5)=0,"",SUMIFS('[D Finanzen.xlsx]D Finanzen'!$E$45:$E$115,'[D Finanzen.xlsx]D Finanzen'!$A$45:$A$115,'[Steuerung.xlsx]Steuerung'!$F$6,'[D Finanzen.xlsx]D Finanzen'!$B$45:$B$115,I$5,'[D Finanzen.xlsx]D Finanzen'!$C$45:$C$115,70))) | J13: =IF(COUNTIFS('[Import Monatsdaten.xlsx]Import Monatsdaten'!$C$7:$C$8,'[Steuerung.xlsx]Steuerung'!$F$6,'[Import Monatsdaten.xlsx]Import Monatsdaten'!$D$7:$D$8,5)>0,SUMIFS('[Import Monatsdaten.xlsx]Import Monatsdaten'!$J$7:$J$8,'[Import Monatsdaten.xlsx]Import Monatsdaten'!$C$7:$C$8,'[Steuerung.xlsx]Steuerung'!$F$6,'[Import Monatsdaten.xlsx]Import Monatsdaten'!$D$7:$D$8,5),IF(COUNTIFS('[D Finanzen.xlsx]D Finanzen'!$A$45:$A$115,'[Steuerung.xlsx]Steuerung'!$F$6,'[D Finanzen.xlsx]D Finanzen'!$B$45:$B$115,J$5)=0,"",SUMIFS('[D Finanzen.xlsx]D Finanzen'!$E$45:$E$115,'[D Finanzen.xlsx]D Finanzen'!$A$45:$A$115,'[Steuerung.xlsx]Steuerung'!$F$6,'[D Finanzen.xlsx]D Finanzen'!$B$45:$B$115,J$5,'[D Finanzen.xlsx]D Finanzen'!$C$45:$C$115,70))) | K13: =IF(COUNTIFS('[Import Monatsdaten.xlsx]Import Monatsdaten'!$C$7:$C$8,'[Steuerung.xlsx]Steuerung'!$F$6,'[Import Monatsdaten.xlsx]Import Monatsdaten'!$D$7:$D$8,6)>0,SUMIFS('[Import Monatsdaten.xlsx]Import Monatsdaten'!$J$7:$J$8,'[Import Monatsdaten.xlsx]Import Monatsdaten'!$C$7:$C$8,'[Steuerung.xlsx]Steuerung'!$F$6,'[Import Monatsdaten.xlsx]Import Monatsdaten'!$D$7:$D$8,6),IF(COUNTIFS('[D Finanzen.xlsx]D Finanzen'!$A$45:$A$115,'[Steuerung.xlsx]Steuerung'!$F$6,'[D Finanzen.xlsx]D Finanzen'!$B$45:$B$115,K$5)=0,"",SUMIFS('[D Finanzen.xlsx]D Finanzen'!$E$45:$E$115,'[D Finanzen.xlsx]D Finanzen'!$A$45:$A$115,'[Steuerung.xlsx]Steuerung'!$F$6,'[D Finanzen.xlsx]D Finanzen'!$B$45:$B$115,K$5,'[D Finanzen.xlsx]D Finanzen'!$C$45:$C$115,70))) | L13: =IF(COUNTIFS('[Import Monatsdaten.xlsx]Import Monatsdaten'!$C$7:$C$8,'[Steuerung.xlsx]Steuerung'!$F$6,'[Import Monatsdaten.xlsx]Import Monatsdaten'!$D$7:$D$8,7)>0,SUMIFS('[Import Monatsdaten.xlsx]Import Monatsdaten'!$J$7:$J$8,'[Import Monatsdaten.xlsx]Import Monatsdaten'!$C$7:$C$8,'[Steuerung.xlsx]Steuerung'!$F$6,'[Import Monatsdaten.xlsx]Import Monatsdaten'!$D$7:$D$8,7),IF(COUNTIFS('[D Finanzen.xlsx]D Finanzen'!$A$45:$A$115,'[Steuerung.xlsx]Steuerung'!$F$6,'[D Finanzen.xlsx]D Finanzen'!$B$45:$B$115,L$5)=0,"",SUMIFS('[D Finanzen.xlsx]D Finanzen'!$E$45:$E$115,'[D Finanzen.xlsx]D Finanzen'!$A$45:$A$115,'[Steuerung.xlsx]Steuerung'!$F$6,'[D Finanzen.xlsx]D Finanzen'!$B$45:$B$115,L$5,'[D Finanzen.xlsx]D Finanzen'!$C$45:$C$115,70))) | M13: =IF(COUNTIFS('[Import Monatsdaten.xlsx]Import Monatsdaten'!$C$7:$C$8,'[Steuerung.xlsx]Steuerung'!$F$6,'[Import Monatsdaten.xlsx]Import Monatsdaten'!$D$7:$D$8,8)>0,SUMIFS('[Import Monatsdaten.xlsx]Import Monatsdaten'!$J$7:$J$8,'[Import Monatsdaten.xlsx]Import Monatsdaten'!$C$7:$C$8,'[Steuerung.xlsx]Steuerung'!$F$6,'[Import Monatsdaten.xlsx]Import Monatsdaten'!$D$7:$D$8,8),IF(COUNTIFS('[D Finanzen.xlsx]D Finanzen'!$A$45:$A$115,'[Steuerung.xlsx]Steuerung'!$F$6,'[D Finanzen.xlsx]D Finanzen'!$B$45:$B$115,M$5)=0,"",SUMIFS('[D Finanzen.xlsx]D Finanzen'!$E$45:$E$115,'[D Finanzen.xlsx]D Finanzen'!$A$45:$A$115,'[Steuerung.xlsx]Steuerung'!$F$6,'[D Finanzen.xlsx]D Finanzen'!$B$45:$B$115,M$5,'[D Finanzen.xlsx]D Finanzen'!$C$45:$C$115,70))) | N13: =IF(COUNTIFS('[Import Monatsdaten.xlsx]Import Monatsdaten'!$C$7:$C$8,'[Steuerung.xlsx]Steuerung'!$F$6,'[Import Monatsdaten.xlsx]Import Monatsdaten'!$D$7:$D$8,9)>0,SUMIFS('[Import Monatsdaten.xlsx]Import Monatsdaten'!$J$7:$J$8,'[Import Monatsdaten.xlsx]Import Monatsdaten'!$C$7:$C$8,'[Steuerung.xlsx]Steuerung'!$F$6,'[Import Monatsdaten.xlsx]Import Monatsdaten'!$D$7:$D$8,9),IF(COUNTIFS('[D Finanzen.xlsx]D Finanzen'!$A$45:$A$115,'[Steuerung.xlsx]Steuerung'!$F$6,'[D Finanzen.xlsx]D Finanzen'!$B$45:$B$115,N$5)=0,"",SUMIFS('[D Finanzen.xlsx]D Finanzen'!$E$45:$E$115,'[D Finanzen.xlsx]D Finanzen'!$A$45:$A$115,'[Steuerung.xlsx]Steuerung'!$F$6,'[D Finanzen.xlsx]D Finanzen'!$B$45:$B$115,N$5,'[D Finanzen.xlsx]D Finanzen'!$C$45:$C$115,70))) | O13: =IF(COUNTIFS('[Import Monatsdaten.xlsx]Import Monatsdaten'!$C$7:$C$8,'[Steuerung.xlsx]Steuerung'!$F$6,'[Import Monatsdaten.xlsx]Import Monatsdaten'!$D$7:$D$8,10)>0,SUMIFS('[Import Monatsdaten.xlsx]Import Monatsdaten'!$J$7:$J$8,'[Import Monatsdaten.xlsx]Import Monatsdaten'!$C$7:$C$8,'[Steuerung.xlsx]Steuerung'!$F$6,'[Import Monatsdaten.xlsx]Import Monatsdaten'!$D$7:$D$8,10),IF(COUNTIFS('[D Finanzen.xlsx]D Finanzen'!$A$45:$A$115,'[Steuerung.xlsx]Steuerung'!$F$6,'[D Finanzen.xlsx]D Finanzen'!$B$45:$B$115,O$5)=0,"",SUMIFS('[D Finanzen.xlsx]D Finanzen'!$E$45:$E$115,'[D Finanzen.xlsx]D Finanzen'!$A$45:$A$115,'[Steuerung.xlsx]Steuerung'!$F$6,'[D Finanzen.xlsx]D Finanzen'!$B$45:$B$115,O$5,'[D Finanzen.xlsx]D Finanzen'!$C$45:$C$115,70))) | P13: =IF(COUNTIFS('[Import Monatsdaten.xlsx]Import Monatsdaten'!$C$7:$C$8,'[Steuerung.xlsx]Steuerung'!$F$6,'[Import Monatsdaten.xlsx]Import Monatsdaten'!$D$7:$D$8,11)>0,SUMIFS('[Import Monatsdaten.xlsx]Import Monatsdaten'!$J$7:$J$8,'[Import Monatsdaten.xlsx]Import Monatsdaten'!$C$7:$C$8,'[Steuerung.xlsx]Steuerung'!$F$6,'[Import Monatsdaten.xlsx]Import Monatsdaten'!$D$7:$D$8,11),IF(COUNTIFS('[D Finanzen.xlsx]D Finanzen'!$A$45:$A$115,'[Steuerung.xlsx]Steuerung'!$F$6,'[D Finanzen.xlsx]D Finanzen'!$B$45:$B$115,P$5)=0,"",SUMIFS('[D Finanzen.xlsx]D Finanzen'!$E$45:$E$115,'[D Finanzen.xlsx]D Finanzen'!$A$45:$A$115,'[Steuerung.xlsx]Steuerung'!$F$6,'[D Finanzen.xlsx]D Finanzen'!$B$45:$B$115,P$5,'[D Finanzen.xlsx]D Finanzen'!$C$45:$C$115,70))) | Q13: =IF(COUNTIFS('[Import Monatsdaten.xlsx]Import Monatsdaten'!$C$7:$C$8,'[Steuerung.xlsx]Steuerung'!$F$6,'[Import Monatsdaten.xlsx]Import Monatsdaten'!$D$7:$D$8,12)>0,SUMIFS('[Import Monatsdaten.xlsx]Import Monatsdaten'!$J$7:$J$8,'[Import Monatsdaten.xlsx]Import Monatsdaten'!$C$7:$C$8,'[Steuerung.xlsx]Steuerung'!$F$6,'[Import Monatsdaten.xlsx]Import Monatsdaten'!$D$7:$D$8,12),IF(COUNTIFS('[D Finanzen.xlsx]D Finanzen'!$A$45:$A$115,'[Steuerung.xlsx]Steuerung'!$F$6,'[D Finanzen.xlsx]D Finanzen'!$B$45:$B$115,Q$5)=0,"",SUMIFS('[D Finanzen.xlsx]D Finanzen'!$E$45:$E$115,'[D Finanzen.xlsx]D Finanzen'!$A$45:$A$115,'[Steuerung.xlsx]Steuerung'!$F$6,'[D Finanzen.xlsx]D Finanzen'!$B$45:$B$115,Q$5,'[D Finanzen.xlsx]D Finanzen'!$C$45:$C$115,70)))
C14: EBITDA aus Staffel | D14: =SUMIFS(F14:Q14,$F$5:$Q$5,"<="&'[Steuerung.xlsx]Steuerung'!$F$7) | E14: =IF($D$9=0,"n.a.",D14/$D$9) | F14: =IF(F7="","",SUM(F9:F13)) | G14: =IF(G7="","",SUM(G9:G13)) | H14: =IF(H7="","",SUM(H9:H13)) | I14: =IF(I7="","",SUM(I9:I13)) | J14: =IF(J7="","",SUM(J9:J13)) | K14: =IF(K7="","",SUM(K9:K13)) | L14: =IF(L7="","",SUM(L9:L13)) | M14: =IF(M7="","",SUM(M9:M13)) | ... Q14: =IF(Q7="","",SUM(Q9:Q13))
C15: Abschreibungen | D15: =SUMIFS(F15:Q15,$F$5:$Q$5,"<="&'[Steuerung.xlsx]Steuerung'!$F$7) | E15: =IF($D$9=0,"n.a.",D15/$D$9) | F15: =IF(COUNTIFS('[Import Monatsdaten.xlsx]Import Monatsdaten'!$C$7:$C$8,'[Steuerung.xlsx]Steuerung'!$F$6,'[Import Monatsdaten.xlsx]Import Monatsdaten'!$D$7:$D$8,1)>0,SUMIFS('[Import Monatsdaten.xlsx]Import Monatsdaten'!$K$7:$K$8,'[Import Monatsdaten.xlsx]Import Monatsdaten'!$C$7:$C$8,'[Steuerung.xlsx]Steuerung'!$F$6,'[Import Monatsdaten.xlsx]Import Monatsdaten'!$D$7:$D$8,1),IF(COUNTIFS('[D Finanzen.xlsx]D Finanzen'!$A$45:$A$115,'[Steuerung.xlsx]Steuerung'!$F$6,'[D Finanzen.xlsx]D Finanzen'!$B$45:$B$115,F$5)=0,"",SUMIFS('[D Finanzen.xlsx]D Finanzen'!$E$45:$E$115,'[D Finanzen.xlsx]D Finanzen'!$A$45:$A$115,'[Steuerung.xlsx]Steuerung'!$F$6,'[D Finanzen.xlsx]D Finanzen'!$B$45:$B$115,F$5,'[D Finanzen.xlsx]D Finanzen'!$C$45:$C$115,60))) | G15: =IF(COUNTIFS('[Import Monatsdaten.xlsx]Import Monatsdaten'!$C$7:$C$8,'[Steuerung.xlsx]Steuerung'!$F$6,'[Import Monatsdaten.xlsx]Import Monatsdaten'!$D$7:$D$8,2)>0,SUMIFS('[Import Monatsdaten.xlsx]Import Monatsdaten'!$K$7:$K$8,'[Import Monatsdaten.xlsx]Import Monatsdaten'!$C$7:$C$8,'[Steuerung.xlsx]Steuerung'!$F$6,'[Import Monatsdaten.xlsx]Import Monatsdaten'!$D$7:$D$8,2),IF(COUNTIFS('[D Finanzen.xlsx]D Finanzen'!$A$45:$A$115,'[Steuerung.xlsx]Steuerung'!$F$6,'[D Finanzen.xlsx]D Finanzen'!$B$45:$B$115,G$5)=0,"",SUMIFS('[D Finanzen.xlsx]D Finanzen'!$E$45:$E$115,'[D Finanzen.xlsx]D Finanzen'!$A$45:$A$115,'[Steuerung.xlsx]Steuerung'!$F$6,'[D Finanzen.xlsx]D Finanzen'!$B$45:$B$115,G$5,'[D Finanzen.xlsx]D Finanzen'!$C$45:$C$115,60))) | H15: =IF(COUNTIFS('[Import Monatsdaten.xlsx]Import Monatsdaten'!$C$7:$C$8,'[Steuerung.xlsx]Steuerung'!$F$6,'[Import Monatsdaten.xlsx]Import Monatsdaten'!$D$7:$D$8,3)>0,SUMIFS('[Import Monatsdaten.xlsx]Import Monatsdaten'!$K$7:$K$8,'[Import Monatsdaten.xlsx]Import Monatsdaten'!$C$7:$C$8,'[Steuerung.xlsx]Steuerung'!$F$6,'[Import Monatsdaten.xlsx]Import Monatsdaten'!$D$7:$D$8,3),IF(COUNTIFS('[D Finanzen.xlsx]D Finanzen'!$A$45:$A$115,'[Steuerung.xlsx]Steuerung'!$F$6,'[D Finanzen.xlsx]D Finanzen'!$B$45:$B$115,H$5)=0,"",SUMIFS('[D Finanzen.xlsx]D Finanzen'!$E$45:$E$115,'[D Finanzen.xlsx]D Finanzen'!$A$45:$A$115,'[Steuerung.xlsx]Steuerung'!$F$6,'[D Finanzen.xlsx]D Finanzen'!$B$45:$B$115,H$5,'[D Finanzen.xlsx]D Finanzen'!$C$45:$C$115,60))) | I15: =IF(COUNTIFS('[Import Monatsdaten.xlsx]Import Monatsdaten'!$C$7:$C$8,'[Steuerung.xlsx]Steuerung'!$F$6,'[Import Monatsdaten.xlsx]Import Monatsdaten'!$D$7:$D$8,4)>0,SUMIFS('[Import Monatsdaten.xlsx]Import Monatsdaten'!$K$7:$K$8,'[Import Monatsdaten.xlsx]Import Monatsdaten'!$C$7:$C$8,'[Steuerung.xlsx]Steuerung'!$F$6,'[Import Monatsdaten.xlsx]Import Monatsdaten'!$D$7:$D$8,4),IF(COUNTIFS('[D Finanzen.xlsx]D Finanzen'!$A$45:$A$115,'[Steuerung.xlsx]Steuerung'!$F$6,'[D Finanzen.xlsx]D Finanzen'!$B$45:$B$115,I$5)=0,"",SUMIFS('[D Finanzen.xlsx]D Finanzen'!$E$45:$E$115,'[D Finanzen.xlsx]D Finanzen'!$A$45:$A$115,'[Steuerung.xlsx]Steuerung'!$F$6,'[D Finanzen.xlsx]D Finanzen'!$B$45:$B$115,I$5,'[D Finanzen.xlsx]D Finanzen'!$C$45:$C$115,60))) | J15: =IF(COUNTIFS('[Import Monatsdaten.xlsx]Import Monatsdaten'!$C$7:$C$8,'[Steuerung.xlsx]Steuerung'!$F$6,'[Import Monatsdaten.xlsx]Import Monatsdaten'!$D$7:$D$8,5)>0,SUMIFS('[Import Monatsdaten.xlsx]Import Monatsdaten'!$K$7:$K$8,'[Import Monatsdaten.xlsx]Import Monatsdaten'!$C$7:$C$8,'[Steuerung.xlsx]Steuerung'!$F$6,'[Import Monatsdaten.xlsx]Import Monatsdaten'!$D$7:$D$8,5),IF(COUNTIFS('[D Finanzen.xlsx]D Finanzen'!$A$45:$A$115,'[Steuerung.xlsx]Steuerung'!$F$6,'[D Finanzen.xlsx]D Finanzen'!$B$45:$B$115,J$5)=0,"",SUMIFS('[D Finanzen.xlsx]D Finanzen'!$E$45:$E$115,'[D Finanzen.xlsx]D Finanzen'!$A$45:$A$115,'[Steuerung.xlsx]Steuerung'!$F$6,'[D Finanzen.xlsx]D Finanzen'!$B$45:$B$115,J$5,'[D Finanzen.xlsx]D Finanzen'!$C$45:$C$115,60))) | K15: =IF(COUNTIFS('[Import Monatsdaten.xlsx]Import Monatsdaten'!$C$7:$C$8,'[Steuerung.xlsx]Steuerung'!$F$6,'[Import Monatsdaten.xlsx]Import Monatsdaten'!$D$7:$D$8,6)>0,SUMIFS('[Import Monatsdaten.xlsx]Import Monatsdaten'!$K$7:$K$8,'[Import Monatsdaten.xlsx]Import Monatsdaten'!$C$7:$C$8,'[Steuerung.xlsx]Steuerung'!$F$6,'[Import Monatsdaten.xlsx]Import Monatsdaten'!$D$7:$D$8,6),IF(COUNTIFS('[D Finanzen.xlsx]D Finanzen'!$A$45:$A$115,'[Steuerung.xlsx]Steuerung'!$F$6,'[D Finanzen.xlsx]D Finanzen'!$B$45:$B$115,K$5)=0,"",SUMIFS('[D Finanzen.xlsx]D Finanzen'!$E$45:$E$115,'[D Finanzen.xlsx]D Finanzen'!$A$45:$A$115,'[Steuerung.xlsx]Steuerung'!$F$6,'[D Finanzen.xlsx]D Finanzen'!$B$45:$B$115,K$5,'[D Finanzen.xlsx]D Finanzen'!$C$45:$C$115,60))) | L15: =IF(COUNTIFS('[Import Monatsdaten.xlsx]Import Monatsdaten'!$C$7:$C$8,'[Steuerung.xlsx]Steuerung'!$F$6,'[Import Monatsdaten.xlsx]Import Monatsdaten'!$D$7:$D$8,7)>0,SUMIFS('[Import Monatsdaten.xlsx]Import Monatsdaten'!$K$7:$K$8,'[Import Monatsdaten.xlsx]Import Monatsdaten'!$C$7:$C$8,'[Steuerung.xlsx]Steuerung'!$F$6,'[Import Monatsdaten.xlsx]Import Monatsdaten'!$D$7:$D$8,7),IF(COUNTIFS('[D Finanzen.xlsx]D Finanzen'!$A$45:$A$115,'[Steuerung.xlsx]Steuerung'!$F$6,'[D Finanzen.xlsx]D Finanzen'!$B$45:$B$115,L$5)=0,"",SUMIFS('[D Finanzen.xlsx]D Finanzen'!$E$45:$E$115,'[D Finanzen.xlsx]D Finanzen'!$A$45:$A$115,'[Steuerung.xlsx]Steuerung'!$F$6,'[D Finanzen.xlsx]D Finanzen'!$B$45:$B$115,L$5,'[D Finanzen.xlsx]D Finanzen'!$C$45:$C$115,60))) | M15: =IF(COUNTIFS('[Import Monatsdaten.xlsx]Import Monatsdaten'!$C$7:$C$8,'[Steuerung.xlsx]Steuerung'!$F$6,'[Import Monatsdaten.xlsx]Import Monatsdaten'!$D$7:$D$8,8)>0,SUMIFS('[Import Monatsdaten.xlsx]Import Monatsdaten'!$K$7:$K$8,'[Import Monatsdaten.xlsx]Import Monatsdaten'!$C$7:$C$8,'[Steuerung.xlsx]Steuerung'!$F$6,'[Import Monatsdaten.xlsx]Import Monatsdaten'!$D$7:$D$8,8),IF(COUNTIFS('[D Finanzen.xlsx]D Finanzen'!$A$45:$A$115,'[Steuerung.xlsx]Steuerung'!$F$6,'[D Finanzen.xlsx]D Finanzen'!$B$45:$B$115,M$5)=0,"",SUMIFS('[D Finanzen.xlsx]D Finanzen'!$E$45:$E$115,'[D Finanzen.xlsx]D Finanzen'!$A$45:$A$115,'[Steuerung.xlsx]Steuerung'!$F$6,'[D Finanzen.xlsx]D Finanzen'!$B$45:$B$115,M$5,'[D Finanzen.xlsx]D Finanzen'!$C$45:$C$115,60))) | N15: =IF(COUNTIFS('[Import Monatsdaten.xlsx]Import Monatsdaten'!$C$7:$C$8,'[Steuerung.xlsx]Steuerung'!$F$6,'[Import Monatsdaten.xlsx]Import Monatsdaten'!$D$7:$D$8,9)>0,SUMIFS('[Import Monatsdaten.xlsx]Import Monatsdaten'!$K$7:$K$8,'[Import Monatsdaten.xlsx]Import Monatsdaten'!$C$7:$C$8,'[Steuerung.xlsx]Steuerung'!$F$6,'[Import Monatsdaten.xlsx]Import Monatsdaten'!$D$7:$D$8,9),IF(COUNTIFS('[D Finanzen.xlsx]D Finanzen'!$A$45:$A$115,'[Steuerung.xlsx]Steuerung'!$F$6,'[D Finanzen.xlsx]D Finanzen'!$B$45:$B$115,N$5)=0,"",SUMIFS('[D Finanzen.xlsx]D Finanzen'!$E$45:$E$115,'[D Finanzen.xlsx]D Finanzen'!$A$45:$A$115,'[Steuerung.xlsx]Steuerung'!$F$6,'[D Finanzen.xlsx]D Finanzen'!$B$45:$B$115,N$5,'[D Finanzen.xlsx]D Finanzen'!$C$45:$C$115,60))) | O15: =IF(COUNTIFS('[Import Monatsdaten.xlsx]Import Monatsdaten'!$C$7:$C$8,'[Steuerung.xlsx]Steuerung'!$F$6,'[Import Monatsdaten.xlsx]Import Monatsdaten'!$D$7:$D$8,10)>0,SUMIFS('[Import Monatsdaten.xlsx]Import Monatsdaten'!$K$7:$K$8,'[Import Monatsdaten.xlsx]Import Monatsdaten'!$C$7:$C$8,'[Steuerung.xlsx]Steuerung'!$F$6,'[Import Monatsdaten.xlsx]Import Monatsdaten'!$D$7:$D$8,10),IF(COUNTIFS('[D Finanzen.xlsx]D Finanzen'!$A$45:$A$115,'[Steuerung.xlsx]Steuerung'!$F$6,'[D Finanzen.xlsx]D Finanzen'!$B$45:$B$115,O$5)=0,"",SUMIFS('[D Finanzen.xlsx]D Finanzen'!$E$45:$E$115,'[D Finanzen.xlsx]D Finanzen'!$A$45:$A$115,'[Steuerung.xlsx]Steuerung'!$F$6,'[D Finanzen.xlsx]D Finanzen'!$B$45:$B$115,O$5,'[D Finanzen.xlsx]D Finanzen'!$C$45:$C$115,60))) | P15: =IF(COUNTIFS('[Import Monatsdaten.xlsx]Import Monatsdaten'!$C$7:$C$8,'[Steuerung.xlsx]Steuerung'!$F$6,'[Import Monatsdaten.xlsx]Import Monatsdaten'!$D$7:$D$8,11)>0,SUMIFS('[Import Monatsdaten.xlsx]Import Monatsdaten'!$K$7:$K$8,'[Import Monatsdaten.xlsx]Import Monatsdaten'!$C$7:$C$8,'[Steuerung.xlsx]Steuerung'!$F$6,'[Import Monatsdaten.xlsx]Import Monatsdaten'!$D$7:$D$8,11),IF(COUNTIFS('[D Finanzen.xlsx]D Finanzen'!$A$45:$A$115,'[Steuerung.xlsx]Steuerung'!$F$6,'[D Finanzen.xlsx]D Finanzen'!$B$45:$B$115,P$5)=0,"",SUMIFS('[D Finanzen.xlsx]D Finanzen'!$E$45:$E$115,'[D Finanzen.xlsx]D Finanzen'!$A$45:$A$115,'[Steuerung.xlsx]Steuerung'!$F$6,'[D Finanzen.xlsx]D Finanzen'!$B$45:$B$115,P$5,'[D Finanzen.xlsx]D Finanzen'!$C$45:$C$115,60))) | Q15: =IF(COUNTIFS('[Import Monatsdaten.xlsx]Import Monatsdaten'!$C$7:$C$8,'[Steuerung.xlsx]Steuerung'!$F$6,'[Import Monatsdaten.xlsx]Import Monatsdaten'!$D$7:$D$8,12)>0,SUMIFS('[Import Monatsdaten.xlsx]Import Monatsdaten'!$K$7:$K$8,'[Import Monatsdaten.xlsx]Import Monatsdaten'!$C$7:$C$8,'[Steuerung.xlsx]Steuerung'!$F$6,'[Import Monatsdaten.xlsx]Import Monatsdaten'!$D$7:$D$8,12),IF(COUNTIFS('[D Finanzen.xlsx]D Finanzen'!$A$45:$A$115,'[Steuerung.xlsx]Steuerung'!$F$6,'[D Finanzen.xlsx]D Finanzen'!$B$45:$B$115,Q$5)=0,"",SUMIFS('[D Finanzen.xlsx]D Finanzen'!$E$45:$E$115,'[D Finanzen.xlsx]D Finanzen'!$A$45:$A$115,'[Steuerung.xlsx]Steuerung'!$F$6,'[D Finanzen.xlsx]D Finanzen'!$B$45:$B$115,Q$5,'[D Finanzen.xlsx]D Finanzen'!$C$45:$C$115,60)))
C16: EBIT | D16: =SUMIFS(F16:Q16,$F$5:$Q$5,"<="&'[Steuerung.xlsx]Steuerung'!$F$7) | E16: =IF($D$9=0,"n.a.",D16/$D$9) | F16: =IF(F7="","",SUM(F14:F15)) | G16: =IF(G7="","",SUM(G14:G15)) | H16: =IF(H7="","",SUM(H14:H15)) | I16: =IF(I7="","",SUM(I14:I15)) | J16: =IF(J7="","",SUM(J14:J15)) | K16: =IF(K7="","",SUM(K14:K15)) | L16: =IF(L7="","",SUM(L14:L15)) | M16: =IF(M7="","",SUM(M14:M15)) | ... Q16: =IF(Q7="","",SUM(Q14:Q15))
C17: Finanzergebnis | D17: =SUMIFS(F17:Q17,$F$5:$Q$5,"<="&'[Steuerung.xlsx]Steuerung'!$F$7) | E17: =IF($D$9=0,"n.a.",D17/$D$9) | F17: =IF(COUNTIFS('[Import Monatsdaten.xlsx]Import Monatsdaten'!$C$7:$C$8,'[Steuerung.xlsx]Steuerung'!$F$6,'[Import Monatsdaten.xlsx]Import Monatsdaten'!$D$7:$D$8,1)>0,SUMIFS('[Import Monatsdaten.xlsx]Import Monatsdaten'!$L$7:$L$8,'[Import Monatsdaten.xlsx]Import Monatsdaten'!$C$7:$C$8,'[Steuerung.xlsx]Steuerung'!$F$6,'[Import Monatsdaten.xlsx]Import Monatsdaten'!$D$7:$D$8,1),IF(COUNTIFS('[D Finanzen.xlsx]D Finanzen'!$A$45:$A$115,'[Steuerung.xlsx]Steuerung'!$F$6,'[D Finanzen.xlsx]D Finanzen'!$B$45:$B$115,F$5)=0,"",SUMIFS('[D Finanzen.xlsx]D Finanzen'!$E$45:$E$115,'[D Finanzen.xlsx]D Finanzen'!$A$45:$A$115,'[Steuerung.xlsx]Steuerung'!$F$6,'[D Finanzen.xlsx]D Finanzen'!$B$45:$B$115,F$5,'[D Finanzen.xlsx]D Finanzen'!$C$45:$C$115,80))) | G17: =IF(COUNTIFS('[Import Monatsdaten.xlsx]Import Monatsdaten'!$C$7:$C$8,'[Steuerung.xlsx]Steuerung'!$F$6,'[Import Monatsdaten.xlsx]Import Monatsdaten'!$D$7:$D$8,2)>0,SUMIFS('[Import Monatsdaten.xlsx]Import Monatsdaten'!$L$7:$L$8,'[Import Monatsdaten.xlsx]Import Monatsdaten'!$C$7:$C$8,'[Steuerung.xlsx]Steuerung'!$F$6,'[Import Monatsdaten.xlsx]Import Monatsdaten'!$D$7:$D$8,2),IF(COUNTIFS('[D Finanzen.xlsx]D Finanzen'!$A$45:$A$115,'[Steuerung.xlsx]Steuerung'!$F$6,'[D Finanzen.xlsx]D Finanzen'!$B$45:$B$115,G$5)=0,"",SUMIFS('[D Finanzen.xlsx]D Finanzen'!$E$45:$E$115,'[D Finanzen.xlsx]D Finanzen'!$A$45:$A$115,'[Steuerung.xlsx]Steuerung'!$F$6,'[D Finanzen.xlsx]D Finanzen'!$B$45:$B$115,G$5,'[D Finanzen.xlsx]D Finanzen'!$C$45:$C$115,80))) | H17: =IF(COUNTIFS('[Import Monatsdaten.xlsx]Import Monatsdaten'!$C$7:$C$8,'[Steuerung.xlsx]Steuerung'!$F$6,'[Import Monatsdaten.xlsx]Import Monatsdaten'!$D$7:$D$8,3)>0,SUMIFS('[Import Monatsdaten.xlsx]Import Monatsdaten'!$L$7:$L$8,'[Import Monatsdaten.xlsx]Import Monatsdaten'!$C$7:$C$8,'[Steuerung.xlsx]Steuerung'!$F$6,'[Import Monatsdaten.xlsx]Import Monatsdaten'!$D$7:$D$8,3),IF(COUNTIFS('[D Finanzen.xlsx]D Finanzen'!$A$45:$A$115,'[Steuerung.xlsx]Steuerung'!$F$6,'[D Finanzen.xlsx]D Finanzen'!$B$45:$B$115,H$5)=0,"",SUMIFS('[D Finanzen.xlsx]D Finanzen'!$E$45:$E$115,'[D Finanzen.xlsx]D Finanzen'!$A$45:$A$115,'[Steuerung.xlsx]Steuerung'!$F$6,'[D Finanzen.xlsx]D Finanzen'!$B$45:$B$115,H$5,'[D Finanzen.xlsx]D Finanzen'!$C$45:$C$115,80))) | I17: =IF(COUNTIFS('[Import Monatsdaten.xlsx]Import Monatsdaten'!$C$7:$C$8,'[Steuerung.xlsx]Steuerung'!$F$6,'[Import Monatsdaten.xlsx]Import Monatsdaten'!$D$7:$D$8,4)>0,SUMIFS('[Import Monatsdaten.xlsx]Import Monatsdaten'!$L$7:$L$8,'[Import Monatsdaten.xlsx]Import Monatsdaten'!$C$7:$C$8,'[Steuerung.xlsx]Steuerung'!$F$6,'[Import Monatsdaten.xlsx]Import Monatsdaten'!$D$7:$D$8,4),IF(COUNTIFS('[D Finanzen.xlsx]D Finanzen'!$A$45:$A$115,'[Steuerung.xlsx]Steuerung'!$F$6,'[D Finanzen.xlsx]D Finanzen'!$B$45:$B$115,I$5)=0,"",SUMIFS('[D Finanzen.xlsx]D Finanzen'!$E$45:$E$115,'[D Finanzen.xlsx]D Finanzen'!$A$45:$A$115,'[Steuerung.xlsx]Steuerung'!$F$6,'[D Finanzen.xlsx]D Finanzen'!$B$45:$B$115,I$5,'[D Finanzen.xlsx]D Finanzen'!$C$45:$C$115,80))) | J17: =IF(COUNTIFS('[Import Monatsdaten.xlsx]Import Monatsdaten'!$C$7:$C$8,'[Steuerung.xlsx]Steuerung'!$F$6,'[Import Monatsdaten.xlsx]Import Monatsdaten'!$D$7:$D$8,5)>0,SUMIFS('[Import Monatsdaten.xlsx]Import Monatsdaten'!$L$7:$L$8,'[Import Monatsdaten.xlsx]Import Monatsdaten'!$C$7:$C$8,'[Steuerung.xlsx]Steuerung'!$F$6,'[Import Monatsdaten.xlsx]Import Monatsdaten'!$D$7:$D$8,5),IF(COUNTIFS('[D Finanzen.xlsx]D Finanzen'!$A$45:$A$115,'[Steuerung.xlsx]Steuerung'!$F$6,'[D Finanzen.xlsx]D Finanzen'!$B$45:$B$115,J$5)=0,"",SUMIFS('[D Finanzen.xlsx]D Finanzen'!$E$45:$E$115,'[D Finanzen.xlsx]D Finanzen'!$A$45:$A$115,'[Steuerung.xlsx]Steuerung'!$F$6,'[D Finanzen.xlsx]D Finanzen'!$B$45:$B$115,J$5,'[D Finanzen.xlsx]D Finanzen'!$C$45:$C$115,80))) | K17: =IF(COUNTIFS('[Import Monatsdaten.xlsx]Import Monatsdaten'!$C$7:$C$8,'[Steuerung.xlsx]Steuerung'!$F$6,'[Import Monatsdaten.xlsx]Import Monatsdaten'!$D$7:$D$8,6)>0,SUMIFS('[Import Monatsdaten.xlsx]Import Monatsdaten'!$L$7:$L$8,'[Import Monatsdaten.xlsx]Import Monatsdaten'!$C$7:$C$8,'[Steuerung.xlsx]Steuerung'!$F$6,'[Import Monatsdaten.xlsx]Import Monatsdaten'!$D$7:$D$8,6),IF(COUNTIFS('[D Finanzen.xlsx]D Finanzen'!$A$45:$A$115,'[Steuerung.xlsx]Steuerung'!$F$6,'[D Finanzen.xlsx]D Finanzen'!$B$45:$B$115,K$5)=0,"",SUMIFS('[D Finanzen.xlsx]D Finanzen'!$E$45:$E$115,'[D Finanzen.xlsx]D Finanzen'!$A$45:$A$115,'[Steuerung.xlsx]Steuerung'!$F$6,'[D Finanzen.xlsx]D Finanzen'!$B$45:$B$115,K$5,'[D Finanzen.xlsx]D Finanzen'!$C$45:$C$115,80))) | L17: =IF(COUNTIFS('[Import Monatsdaten.xlsx]Import Monatsdaten'!$C$7:$C$8,'[Steuerung.xlsx]Steuerung'!$F$6,'[Import Monatsdaten.xlsx]Import Monatsdaten'!$D$7:$D$8,7)>0,SUMIFS('[Import Monatsdaten.xlsx]Import Monatsdaten'!$L$7:$L$8,'[Import Monatsdaten.xlsx]Import Monatsdaten'!$C$7:$C$8,'[Steuerung.xlsx]Steuerung'!$F$6,'[Import Monatsdaten.xlsx]Import Monatsdaten'!$D$7:$D$8,7),IF(COUNTIFS('[D Finanzen.xlsx]D Finanzen'!$A$45:$A$115,'[Steuerung.xlsx]Steuerung'!$F$6,'[D Finanzen.xlsx]D Finanzen'!$B$45:$B$115,L$5)=0,"",SUMIFS('[D Finanzen.xlsx]D Finanzen'!$E$45:$E$115,'[D Finanzen.xlsx]D Finanzen'!$A$45:$A$115,'[Steuerung.xlsx]Steuerung'!$F$6,'[D Finanzen.xlsx]D Finanzen'!$B$45:$B$115,L$5,'[D Finanzen.xlsx]D Finanzen'!$C$45:$C$115,80))) | M17: =IF(COUNTIFS('[Import Monatsdaten.xlsx]Import Monatsdaten'!$C$7:$C$8,'[Steuerung.xlsx]Steuerung'!$F$6,'[Import Monatsdaten.xlsx]Import Monatsdaten'!$D$7:$D$8,8)>0,SUMIFS('[Import Monatsdaten.xlsx]Import Monatsdaten'!$L$7:$L$8,'[Import Monatsdaten.xlsx]Import Monatsdaten'!$C$7:$C$8,'[Steuerung.xlsx]Steuerung'!$F$6,'[Import Monatsdaten.xlsx]Import Monatsdaten'!$D$7:$D$8,8),IF(COUNTIFS('[D Finanzen.xlsx]D Finanzen'!$A$45:$A$115,'[Steuerung.xlsx]Steuerung'!$F$6,'[D Finanzen.xlsx]D Finanzen'!$B$45:$B$115,M$5)=0,"",SUMIFS('[D Finanzen.xlsx]D Finanzen'!$E$45:$E$115,'[D Finanzen.xlsx]D Finanzen'!$A$45:$A$115,'[Steuerung.xlsx]Steuerung'!$F$6,'[D Finanzen.xlsx]D Finanzen'!$B$45:$B$115,M$5,'[D Finanzen.xlsx]D Finanzen'!$C$45:$C$115,80))) | N17: =IF(COUNTIFS('[Import Monatsdaten.xlsx]Import Monatsdaten'!$C$7:$C$8,'[Steuerung.xlsx]Steuerung'!$F$6,'[Import Monatsdaten.xlsx]Import Monatsdaten'!$D$7:$D$8,9)>0,SUMIFS('[Import Monatsdaten.xlsx]Import Monatsdaten'!$L$7:$L$8,'[Import Monatsdaten.xlsx]Import Monatsdaten'!$C$7:$C$8,'[Steuerung.xlsx]Steuerung'!$F$6,'[Import Monatsdaten.xlsx]Import Monatsdaten'!$D$7:$D$8,9),IF(COUNTIFS('[D Finanzen.xlsx]D Finanzen'!$A$45:$A$115,'[Steuerung.xlsx]Steuerung'!$F$6,'[D Finanzen.xlsx]D Finanzen'!$B$45:$B$115,N$5)=0,"",SUMIFS('[D Finanzen.xlsx]D Finanzen'!$E$45:$E$115,'[D Finanzen.xlsx]D Finanzen'!$A$45:$A$115,'[Steuerung.xlsx]Steuerung'!$F$6,'[D Finanzen.xlsx]D Finanzen'!$B$45:$B$115,N$5,'[D Finanzen.xlsx]D Finanzen'!$C$45:$C$115,80))) | O17: =IF(COUNTIFS('[Import Monatsdaten.xlsx]Import Monatsdaten'!$C$7:$C$8,'[Steuerung.xlsx]Steuerung'!$F$6,'[Import Monatsdaten.xlsx]Import Monatsdaten'!$D$7:$D$8,10)>0,SUMIFS('[Import Monatsdaten.xlsx]Import Monatsdaten'!$L$7:$L$8,'[Import Monatsdaten.xlsx]Import Monatsdaten'!$C$7:$C$8,'[Steuerung.xlsx]Steuerung'!$F$6,'[Import Monatsdaten.xlsx]Import Monatsdaten'!$D$7:$D$8,10),IF(COUNTIFS('[D Finanzen.xlsx]D Finanzen'!$A$45:$A$115,'[Steuerung.xlsx]Steuerung'!$F$6,'[D Finanzen.xlsx]D Finanzen'!$B$45:$B$115,O$5)=0,"",SUMIFS('[D Finanzen.xlsx]D Finanzen'!$E$45:$E$115,'[D Finanzen.xlsx]D Finanzen'!$A$45:$A$115,'[Steuerung.xlsx]Steuerung'!$F$6,'[D Finanzen.xlsx]D Finanzen'!$B$45:$B$115,O$5,'[D Finanzen.xlsx]D Finanzen'!$C$45:$C$115,80))) | P17: =IF(COUNTIFS('[Import Monatsdaten.xlsx]Import Monatsdaten'!$C$7:$C$8,'[Steuerung.xlsx]Steuerung'!$F$6,'[Import Monatsdaten.xlsx]Import Monatsdaten'!$D$7:$D$8,11)>0,SUMIFS('[Import Monatsdaten.xlsx]Import Monatsdaten'!$L$7:$L$8,'[Import Monatsdaten.xlsx]Import Monatsdaten'!$C$7:$C$8,'[Steuerung.xlsx]Steuerung'!$F$6,'[Import Monatsdaten.xlsx]Import Monatsdaten'!$D$7:$D$8,11),IF(COUNTIFS('[D Finanzen.xlsx]D Finanzen'!$A$45:$A$115,'[Steuerung.xlsx]Steuerung'!$F$6,'[D Finanzen.xlsx]D Finanzen'!$B$45:$B$115,P$5)=0,"",SUMIFS('[D Finanzen.xlsx]D Finanzen'!$E$45:$E$115,'[D Finanzen.xlsx]D Finanzen'!$A$45:$A$115,'[Steuerung.xlsx]Steuerung'!$F$6,'[D Finanzen.xlsx]D Finanzen'!$B$45:$B$115,P$5,'[D Finanzen.xlsx]D Finanzen'!$C$45:$C$115,80))) | Q17: =IF(COUNTIFS('[Import Monatsdaten.xlsx]Import Monatsdaten'!$C$7:$C$8,'[Steuerung.xlsx]Steuerung'!$F$6,'[Import Monatsdaten.xlsx]Import Monatsdaten'!$D$7:$D$8,12)>0,SUMIFS('[Import Monatsdaten.xlsx]Import Monatsdaten'!$L$7:$L$8,'[Import Monatsdaten.xlsx]Import Monatsdaten'!$C$7:$C$8,'[Steuerung.xlsx]Steuerung'!$F$6,'[Import Monatsdaten.xlsx]Import Monatsdaten'!$D$7:$D$8,12),IF(COUNTIFS('[D Finanzen.xlsx]D Finanzen'!$A$45:$A$115,'[Steuerung.xlsx]Steuerung'!$F$6,'[D Finanzen.xlsx]D Finanzen'!$B$45:$B$115,Q$5)=0,"",SUMIFS('[D Finanzen.xlsx]D Finanzen'!$E$45:$E$115,'[D Finanzen.xlsx]D Finanzen'!$A$45:$A$115,'[Steuerung.xlsx]Steuerung'!$F$6,'[D Finanzen.xlsx]D Finanzen'!$B$45:$B$115,Q$5,'[D Finanzen.xlsx]D Finanzen'!$C$45:$C$115,80)))
C18: Ergebnis aus Staffel | D18: =SUMIFS(F18:Q18,$F$5:$Q$5,"<="&'[Steuerung.xlsx]Steuerung'!$F$7) | E18: =IF($D$9=0,"n.a.",D18/$D$9) | F18: =IF(F7="","",SUM(F16:F17)) | G18: =IF(G7="","",SUM(G16:G17)) | H18: =IF(H7="","",SUM(H16:H17)) | I18: =IF(I7="","",SUM(I16:I17)) | J18: =IF(J7="","",SUM(J16:J17)) | K18: =IF(K7="","",SUM(K16:K17)) | L18: =IF(L7="","",SUM(L16:L17)) | M18: =IF(M7="","",SUM(M16:M17)) | ... Q18: =IF(Q7="","",SUM(Q16:Q17))
C20: EBITDA Cockpit-Definition | D20: =SUMIFS(F20:Q20,$F$5:$Q$5,"<="&'[Steuerung.xlsx]Steuerung'!$F$7) | E20: =IF($D$9=0,"n.a.",D20/$D$9) | F20: =IF(COUNTIFS('[Import Monatsdaten.xlsx]Import Monatsdaten'!$C$7:$C$8,'[Steuerung.xlsx]Steuerung'!$F$6,'[Import Monatsdaten.xlsx]Import Monatsdaten'!$D$7:$D$8,1)>0,F14,IF(COUNTIFS('[D Finanzen.xlsx]D Finanzen'!$A$8:$A$16,'[Steuerung.xlsx]Steuerung'!$F$6,'[D Finanzen.xlsx]D Finanzen'!$B$8:$B$16,F$5)=0,"",SUMIFS('[D Finanzen.xlsx]D Finanzen'!$F$8:$F$16,'[D Finanzen.xlsx]D Finanzen'!$A$8:$A$16,'[Steuerung.xlsx]Steuerung'!$F$6,'[D Finanzen.xlsx]D Finanzen'!$B$8:$B$16,F$5))) | G20: =IF(COUNTIFS('[Import Monatsdaten.xlsx]Import Monatsdaten'!$C$7:$C$8,'[Steuerung.xlsx]Steuerung'!$F$6,'[Import Monatsdaten.xlsx]Import Monatsdaten'!$D$7:$D$8,2)>0,G14,IF(COUNTIFS('[D Finanzen.xlsx]D Finanzen'!$A$8:$A$16,'[Steuerung.xlsx]Steuerung'!$F$6,'[D Finanzen.xlsx]D Finanzen'!$B$8:$B$16,G$5)=0,"",SUMIFS('[D Finanzen.xlsx]D Finanzen'!$F$8:$F$16,'[D Finanzen.xlsx]D Finanzen'!$A$8:$A$16,'[Steuerung.xlsx]Steuerung'!$F$6,'[D Finanzen.xlsx]D Finanzen'!$B$8:$B$16,G$5))) | H20: =IF(COUNTIFS('[Import Monatsdaten.xlsx]Import Monatsdaten'!$C$7:$C$8,'[Steuerung.xlsx]Steuerung'!$F$6,'[Import Monatsdaten.xlsx]Import Monatsdaten'!$D$7:$D$8,3)>0,H14,IF(COUNTIFS('[D Finanzen.xlsx]D Finanzen'!$A$8:$A$16,'[Steuerung.xlsx]Steuerung'!$F$6,'[D Finanzen.xlsx]D Finanzen'!$B$8:$B$16,H$5)=0,"",SUMIFS('[D Finanzen.xlsx]D Finanzen'!$F$8:$F$16,'[D Finanzen.xlsx]D Finanzen'!$A$8:$A$16,'[Steuerung.xlsx]Steuerung'!$F$6,'[D Finanzen.xlsx]D Finanzen'!$B$8:$B$16,H$5))) | I20: =IF(COUNTIFS('[Import Monatsdaten.xlsx]Import Monatsdaten'!$C$7:$C$8,'[Steuerung.xlsx]Steuerung'!$F$6,'[Import Monatsdaten.xlsx]Import Monatsdaten'!$D$7:$D$8,4)>0,I14,IF(COUNTIFS('[D Finanzen.xlsx]D Finanzen'!$A$8:$A$16,'[Steuerung.xlsx]Steuerung'!$F$6,'[D Finanzen.xlsx]D Finanzen'!$B$8:$B$16,I$5)=0,"",SUMIFS('[D Finanzen.xlsx]D Finanzen'!$F$8:$F$16,'[D Finanzen.xlsx]D Finanzen'!$A$8:$A$16,'[Steuerung.xlsx]Steuerung'!$F$6,'[D Finanzen.xlsx]D Finanzen'!$B$8:$B$16,I$5))) | J20: =IF(COUNTIFS('[Import Monatsdaten.xlsx]Import Monatsdaten'!$C$7:$C$8,'[Steuerung.xlsx]Steuerung'!$F$6,'[Import Monatsdaten.xlsx]Import Monatsdaten'!$D$7:$D$8,5)>0,J14,IF(COUNTIFS('[D Finanzen.xlsx]D Finanzen'!$A$8:$A$16,'[Steuerung.xlsx]Steuerung'!$F$6,'[D Finanzen.xlsx]D Finanzen'!$B$8:$B$16,J$5)=0,"",SUMIFS('[D Finanzen.xlsx]D Finanzen'!$F$8:$F$16,'[D Finanzen.xlsx]D Finanzen'!$A$8:$A$16,'[Steuerung.xlsx]Steuerung'!$F$6,'[D Finanzen.xlsx]D Finanzen'!$B$8:$B$16,J$5))) | K20: =IF(COUNTIFS('[Import Monatsdaten.xlsx]Import Monatsdaten'!$C$7:$C$8,'[Steuerung.xlsx]Steuerung'!$F$6,'[Import Monatsdaten.xlsx]Import Monatsdaten'!$D$7:$D$8,6)>0,K14,IF(COUNTIFS('[D Finanzen.xlsx]D Finanzen'!$A$8:$A$16,'[Steuerung.xlsx]Steuerung'!$F$6,'[D Finanzen.xlsx]D Finanzen'!$B$8:$B$16,K$5)=0,"",SUMIFS('[D Finanzen.xlsx]D Finanzen'!$F$8:$F$16,'[D Finanzen.xlsx]D Finanzen'!$A$8:$A$16,'[Steuerung.xlsx]Steuerung'!$F$6,'[D Finanzen.xlsx]D Finanzen'!$B$8:$B$16,K$5))) | L20: =IF(COUNTIFS('[Import Monatsdaten.xlsx]Import Monatsdaten'!$C$7:$C$8,'[Steuerung.xlsx]Steuerung'!$F$6,'[Import Monatsdaten.xlsx]Import Monatsdaten'!$D$7:$D$8,7)>0,L14,IF(COUNTIFS('[D Finanzen.xlsx]D Finanzen'!$A$8:$A$16,'[Steuerung.xlsx]Steuerung'!$F$6,'[D Finanzen.xlsx]D Finanzen'!$B$8:$B$16,L$5)=0,"",SUMIFS('[D Finanzen.xlsx]D Finanzen'!$F$8:$F$16,'[D Finanzen.xlsx]D Finanzen'!$A$8:$A$16,'[Steuerung.xlsx]Steuerung'!$F$6,'[D Finanzen.xlsx]D Finanzen'!$B$8:$B$16,L$5))) | M20: =IF(COUNTIFS('[Import Monatsdaten.xlsx]Import Monatsdaten'!$C$7:$C$8,'[Steuerung.xlsx]Steuerung'!$F$6,'[Import Monatsdaten.xlsx]Import Monatsdaten'!$D$7:$D$8,8)>0,M14,IF(COUNTIFS('[D Finanzen.xlsx]D Finanzen'!$A$8:$A$16,'[Steuerung.xlsx]Steuerung'!$F$6,'[D Finanzen.xlsx]D Finanzen'!$B$8:$B$16,M$5)=0,"",SUMIFS('[D Finanzen.xlsx]D Finanzen'!$F$8:$F$16,'[D Finanzen.xlsx]D Finanzen'!$A$8:$A$16,'[Steuerung.xlsx]Steuerung'!$F$6,'[D Finanzen.xlsx]D Finanzen'!$B$8:$B$16,M$5))) | N20: =IF(COUNTIFS('[Import Monatsdaten.xlsx]Import Monatsdaten'!$C$7:$C$8,'[Steuerung.xlsx]Steuerung'!$F$6,'[Import Monatsdaten.xlsx]Import Monatsdaten'!$D$7:$D$8,9)>0,N14,IF(COUNTIFS('[D Finanzen.xlsx]D Finanzen'!$A$8:$A$16,'[Steuerung.xlsx]Steuerung'!$F$6,'[D Finanzen.xlsx]D Finanzen'!$B$8:$B$16,N$5)=0,"",SUMIFS('[D Finanzen.xlsx]D Finanzen'!$F$8:$F$16,'[D Finanzen.xlsx]D Finanzen'!$A$8:$A$16,'[Steuerung.xlsx]Steuerung'!$F$6,'[D Finanzen.xlsx]D Finanzen'!$B$8:$B$16,N$5))) | O20: =IF(COUNTIFS('[Import Monatsdaten.xlsx]Import Monatsdaten'!$C$7:$C$8,'[Steuerung.xlsx]Steuerung'!$F$6,'[Import Monatsdaten.xlsx]Import Monatsdaten'!$D$7:$D$8,10)>0,O14,IF(COUNTIFS('[D Finanzen.xlsx]D Finanzen'!$A$8:$A$16,'[Steuerung.xlsx]Steuerung'!$F$6,'[D Finanzen.xlsx]D Finanzen'!$B$8:$B$16,O$5)=0,"",SUMIFS('[D Finanzen.xlsx]D Finanzen'!$F$8:$F$16,'[D Finanzen.xlsx]D Finanzen'!$A$8:$A$16,'[Steuerung.xlsx]Steuerung'!$F$6,'[D Finanzen.xlsx]D Finanzen'!$B$8:$B$16,O$5))) | P20: =IF(COUNTIFS('[Import Monatsdaten.xlsx]Import Monatsdaten'!$C$7:$C$8,'[Steuerung.xlsx]Steuerung'!$F$6,'[Import Monatsdaten.xlsx]Import Monatsdaten'!$D$7:$D$8,11)>0,P14,IF(COUNTIFS('[D Finanzen.xlsx]D Finanzen'!$A$8:$A$16,'[Steuerung.xlsx]Steuerung'!$F$6,'[D Finanzen.xlsx]D Finanzen'!$B$8:$B$16,P$5)=0,"",SUMIFS('[D Finanzen.xlsx]D Finanzen'!$F$8:$F$16,'[D Finanzen.xlsx]D Finanzen'!$A$8:$A$16,'[Steuerung.xlsx]Steuerung'!$F$6,'[D Finanzen.xlsx]D Finanzen'!$B$8:$B$16,P$5))) | Q20: =IF(COUNTIFS('[Import Monatsdaten.xlsx]Import Monatsdaten'!$C$7:$C$8,'[Steuerung.xlsx]Steuerung'!$F$6,'[Import Monatsdaten.xlsx]Import Monatsdaten'!$D$7:$D$8,12)>0,Q14,IF(COUNTIFS('[D Finanzen.xlsx]D Finanzen'!$A$8:$A$16,'[Steuerung.xlsx]Steuerung'!$F$6,'[D Finanzen.xlsx]D Finanzen'!$B$8:$B$16,Q$5)=0,"",SUMIFS('[D Finanzen.xlsx]D Finanzen'!$F$8:$F$16,'[D Finanzen.xlsx]D Finanzen'!$A$8:$A$16,'[Steuerung.xlsx]Steuerung'!$F$6,'[D Finanzen.xlsx]D Finanzen'!$B$8:$B$16,Q$5)))
C21: Differenz EBITDA-Definition | D21: =SUMIFS(F21:Q21,$F$5:$Q$5,"<="&'[Steuerung.xlsx]Steuerung'!$F$7) | E21: =IF($D$9=0,"n.a.",D21/$D$9) | F21: =IF(F7="","",ROUND(F14-F20,2)) | G21: =IF(G7="","",ROUND(G14-G20,2)) | H21: =IF(H7="","",ROUND(H14-H20,2)) | I21: =IF(I7="","",ROUND(I14-I20,2)) | J21: =IF(J7="","",ROUND(J14-J20,2)) | K21: =IF(K7="","",ROUND(K14-K20,2)) | L21: =IF(L7="","",ROUND(L14-L20,2)) | M21: =IF(M7="","",ROUND(M14-M20,2)) | ... Q21: =IF(Q7="","",ROUND(Q14-Q20,2))
C23: Quelle je Monat | F23: =IF(COUNTIFS('[Import Monatsdaten.xlsx]Import Monatsdaten'!$C$7:$C$8,'[Steuerung.xlsx]Steuerung'!$F$6,'[Import Monatsdaten.xlsx]Import Monatsdaten'!$D$7:$D$8,1)>0,"CSV-Import","Originalexport") | G23: =IF(COUNTIFS('[Import Monatsdaten.xlsx]Import Monatsdaten'!$C$7:$C$8,'[Steuerung.xlsx]Steuerung'!$F$6,'[Import Monatsdaten.xlsx]Import Monatsdaten'!$D$7:$D$8,2)>0,"CSV-Import","Originalexport") | H23: =IF(COUNTIFS('[Import Monatsdaten.xlsx]Import Monatsdaten'!$C$7:$C$8,'[Steuerung.xlsx]Steuerung'!$F$6,'[Import Monatsdaten.xlsx]Import Monatsdaten'!$D$7:$D$8,3)>0,"CSV-Import","Originalexport") | I23: =IF(COUNTIFS('[Import Monatsdaten.xlsx]Import Monatsdaten'!$C$7:$C$8,'[Steuerung.xlsx]Steuerung'!$F$6,'[Import Monatsdaten.xlsx]Import Monatsdaten'!$D$7:$D$8,4)>0,"CSV-Import","Originalexport") | J23: =IF(COUNTIFS('[Import Monatsdaten.xlsx]Import Monatsdaten'!$C$7:$C$8,'[Steuerung.xlsx]Steuerung'!$F$6,'[Import Monatsdaten.xlsx]Import Monatsdaten'!$D$7:$D$8,5)>0,"CSV-Import","Originalexport") | K23: =IF(COUNTIFS('[Import Monatsdaten.xlsx]Import Monatsdaten'!$C$7:$C$8,'[Steuerung.xlsx]Steuerung'!$F$6,'[Import Monatsdaten.xlsx]Import Monatsdaten'!$D$7:$D$8,6)>0,"CSV-Import","Originalexport") | L23: =IF(COUNTIFS('[Import Monatsdaten.xlsx]Import Monatsdaten'!$C$7:$C$8,'[Steuerung.xlsx]Steuerung'!$F$6,'[Import Monatsdaten.xlsx]Import Monatsdaten'!$D$7:$D$8,7)>0,"CSV-Import","Originalexport") | M23: =IF(COUNTIFS('[Import Monatsdaten.xlsx]Import Monatsdaten'!$C$7:$C$8,'[Steuerung.xlsx]Steuerung'!$F$6,'[Import Monatsdaten.xlsx]Import Monatsdaten'!$D$7:$D$8,8)>0,"CSV-Import","Originalexport") | N23: =IF(COUNTIFS('[Import Monatsdaten.xlsx]Import Monatsdaten'!$C$7:$C$8,'[Steuerung.xlsx]Steuerung'!$F$6,'[Import Monatsdaten.xlsx]Import Monatsdaten'!$D$7:$D$8,9)>0,"CSV-Import","Originalexport") | O23: =IF(COUNTIFS('[Import Monatsdaten.xlsx]Import Monatsdaten'!$C$7:$C$8,'[Steuerung.xlsx]Steuerung'!$F$6,'[Import Monatsdaten.xlsx]Import Monatsdaten'!$D$7:$D$8,10)>0,"CSV-Import","Originalexport") | P23: =IF(COUNTIFS('[Import Monatsdaten.xlsx]Import Monatsdaten'!$C$7:$C$8,'[Steuerung.xlsx]Steuerung'!$F$6,'[Import Monatsdaten.xlsx]Import Monatsdaten'!$D$7:$D$8,11)>0,"CSV-Import","Originalexport") | Q23: =IF(COUNTIFS('[Import Monatsdaten.xlsx]Import Monatsdaten'!$C$7:$C$8,'[Steuerung.xlsx]Steuerung'!$F$6,'[Import Monatsdaten.xlsx]Import Monatsdaten'!$D$7:$D$8,12)>0,"CSV-Import","Originalexport")
C24: Neutrales Ergebnis | D24: =SUMIFS(F24:Q24,$F$5:$Q$5,"<="&'[Steuerung.xlsx]Steuerung'!$F$7) | F24: =IF(COUNTIFS('[Import Monatsdaten.xlsx]Import Monatsdaten'!$C$7:$C$8,'[Steuerung.xlsx]Steuerung'!$F$6,'[Import Monatsdaten.xlsx]Import Monatsdaten'!$D$7:$D$8,1)>0,SUMIFS('[Import Monatsdaten.xlsx]Import Monatsdaten'!$M$7:$M$8,'[Import Monatsdaten.xlsx]Import Monatsdaten'!$C$7:$C$8,'[Steuerung.xlsx]Steuerung'!$F$6,'[Import Monatsdaten.xlsx]Import Monatsdaten'!$D$7:$D$8,1),SUMIFS('[D Finanzen.xlsx]D Finanzen'!$G$8:$G$16,'[D Finanzen.xlsx]D Finanzen'!$A$8:$A$16,'[Steuerung.xlsx]Steuerung'!$F$6,'[D Finanzen.xlsx]D Finanzen'!$B$8:$B$16,1)) | G24: =IF(COUNTIFS('[Import Monatsdaten.xlsx]Import Monatsdaten'!$C$7:$C$8,'[Steuerung.xlsx]Steuerung'!$F$6,'[Import Monatsdaten.xlsx]Import Monatsdaten'!$D$7:$D$8,2)>0,SUMIFS('[Import Monatsdaten.xlsx]Import Monatsdaten'!$M$7:$M$8,'[Import Monatsdaten.xlsx]Import Monatsdaten'!$C$7:$C$8,'[Steuerung.xlsx]Steuerung'!$F$6,'[Import Monatsdaten.xlsx]Import Monatsdaten'!$D$7:$D$8,2),SUMIFS('[D Finanzen.xlsx]D Finanzen'!$G$8:$G$16,'[D Finanzen.xlsx]D Finanzen'!$A$8:$A$16,'[Steuerung.xlsx]Steuerung'!$F$6,'[D Finanzen.xlsx]D Finanzen'!$B$8:$B$16,2)) | H24: =IF(COUNTIFS('[Import Monatsdaten.xlsx]Import Monatsdaten'!$C$7:$C$8,'[Steuerung.xlsx]Steuerung'!$F$6,'[Import Monatsdaten.xlsx]Import Monatsdaten'!$D$7:$D$8,3)>0,SUMIFS('[Import Monatsdaten.xlsx]Import Monatsdaten'!$M$7:$M$8,'[Import Monatsdaten.xlsx]Import Monatsdaten'!$C$7:$C$8,'[Steuerung.xlsx]Steuerung'!$F$6,'[Import Monatsdaten.xlsx]Import Monatsdaten'!$D$7:$D$8,3),SUMIFS('[D Finanzen.xlsx]D Finanzen'!$G$8:$G$16,'[D Finanzen.xlsx]D Finanzen'!$A$8:$A$16,'[Steuerung.xlsx]Steuerung'!$F$6,'[D Finanzen.xlsx]D Finanzen'!$B$8:$B$16,3)) | I24: =IF(COUNTIFS('[Import Monatsdaten.xlsx]Import Monatsdaten'!$C$7:$C$8,'[Steuerung.xlsx]Steuerung'!$F$6,'[Import Monatsdaten.xlsx]Import Monatsdaten'!$D$7:$D$8,4)>0,SUMIFS('[Import Monatsdaten.xlsx]Import Monatsdaten'!$M$7:$M$8,'[Import Monatsdaten.xlsx]Import Monatsdaten'!$C$7:$C$8,'[Steuerung.xlsx]Steuerung'!$F$6,'[Import Monatsdaten.xlsx]Import Monatsdaten'!$D$7:$D$8,4),SUMIFS('[D Finanzen.xlsx]D Finanzen'!$G$8:$G$16,'[D Finanzen.xlsx]D Finanzen'!$A$8:$A$16,'[Steuerung.xlsx]Steuerung'!$F$6,'[D Finanzen.xlsx]D Finanzen'!$B$8:$B$16,4)) | J24: =IF(COUNTIFS('[Import Monatsdaten.xlsx]Import Monatsdaten'!$C$7:$C$8,'[Steuerung.xlsx]Steuerung'!$F$6,'[Import Monatsdaten.xlsx]Import Monatsdaten'!$D$7:$D$8,5)>0,SUMIFS('[Import Monatsdaten.xlsx]Import Monatsdaten'!$M$7:$M$8,'[Import Monatsdaten.xlsx]Import Monatsdaten'!$C$7:$C$8,'[Steuerung.xlsx]Steuerung'!$F$6,'[Import Monatsdaten.xlsx]Import Monatsdaten'!$D$7:$D$8,5),SUMIFS('[D Finanzen.xlsx]D Finanzen'!$G$8:$G$16,'[D Finanzen.xlsx]D Finanzen'!$A$8:$A$16,'[Steuerung.xlsx]Steuerung'!$F$6,'[D Finanzen.xlsx]D Finanzen'!$B$8:$B$16,5)) | K24: =IF(COUNTIFS('[Import Monatsdaten.xlsx]Import Monatsdaten'!$C$7:$C$8,'[Steuerung.xlsx]Steuerung'!$F$6,'[Import Monatsdaten.xlsx]Import Monatsdaten'!$D$7:$D$8,6)>0,SUMIFS('[Import Monatsdaten.xlsx]Import Monatsdaten'!$M$7:$M$8,'[Import Monatsdaten.xlsx]Import Monatsdaten'!$C$7:$C$8,'[Steuerung.xlsx]Steuerung'!$F$6,'[Import Monatsdaten.xlsx]Import Monatsdaten'!$D$7:$D$8,6),SUMIFS('[D Finanzen.xlsx]D Finanzen'!$G$8:$G$16,'[D Finanzen.xlsx]D Finanzen'!$A$8:$A$16,'[Steuerung.xlsx]Steuerung'!$F$6,'[D Finanzen.xlsx]D Finanzen'!$B$8:$B$16,6)) | L24: =IF(COUNTIFS('[Import Monatsdaten.xlsx]Import Monatsdaten'!$C$7:$C$8,'[Steuerung.xlsx]Steuerung'!$F$6,'[Import Monatsdaten.xlsx]Import Monatsdaten'!$D$7:$D$8,7)>0,SUMIFS('[Import Monatsdaten.xlsx]Import Monatsdaten'!$M$7:$M$8,'[Import Monatsdaten.xlsx]Import Monatsdaten'!$C$7:$C$8,'[Steuerung.xlsx]Steuerung'!$F$6,'[Import Monatsdaten.xlsx]Import Monatsdaten'!$D$7:$D$8,7),SUMIFS('[D Finanzen.xlsx]D Finanzen'!$G$8:$G$16,'[D Finanzen.xlsx]D Finanzen'!$A$8:$A$16,'[Steuerung.xlsx]Steuerung'!$F$6,'[D Finanzen.xlsx]D Finanzen'!$B$8:$B$16,7)) | M24: =IF(COUNTIFS('[Import Monatsdaten.xlsx]Import Monatsdaten'!$C$7:$C$8,'[Steuerung.xlsx]Steuerung'!$F$6,'[Import Monatsdaten.xlsx]Import Monatsdaten'!$D$7:$D$8,8)>0,SUMIFS('[Import Monatsdaten.xlsx]Import Monatsdaten'!$M$7:$M$8,'[Import Monatsdaten.xlsx]Import Monatsdaten'!$C$7:$C$8,'[Steuerung.xlsx]Steuerung'!$F$6,'[Import Monatsdaten.xlsx]Import Monatsdaten'!$D$7:$D$8,8),SUMIFS('[D Finanzen.xlsx]D Finanzen'!$G$8:$G$16,'[D Finanzen.xlsx]D Finanzen'!$A$8:$A$16,'[Steuerung.xlsx]Steuerung'!$F$6,'[D Finanzen.xlsx]D Finanzen'!$B$8:$B$16,8)) | N24: =IF(COUNTIFS('[Import Monatsdaten.xlsx]Import Monatsdaten'!$C$7:$C$8,'[Steuerung.xlsx]Steuerung'!$F$6,'[Import Monatsdaten.xlsx]Import Monatsdaten'!$D$7:$D$8,9)>0,SUMIFS('[Import Monatsdaten.xlsx]Import Monatsdaten'!$M$7:$M$8,'[Import Monatsdaten.xlsx]Import Monatsdaten'!$C$7:$C$8,'[Steuerung.xlsx]Steuerung'!$F$6,'[Import Monatsdaten.xlsx]Import Monatsdaten'!$D$7:$D$8,9),SUMIFS('[D Finanzen.xlsx]D Finanzen'!$G$8:$G$16,'[D Finanzen.xlsx]D Finanzen'!$A$8:$A$16,'[Steuerung.xlsx]Steuerung'!$F$6,'[D Finanzen.xlsx]D Finanzen'!$B$8:$B$16,9)) | O24: =IF(COUNTIFS('[Import Monatsdaten.xlsx]Import Monatsdaten'!$C$7:$C$8,'[Steuerung.xlsx]Steuerung'!$F$6,'[Import Monatsdaten.xlsx]Import Monatsdaten'!$D$7:$D$8,10)>0,SUMIFS('[Import Monatsdaten.xlsx]Import Monatsdaten'!$M$7:$M$8,'[Import Monatsdaten.xlsx]Import Monatsdaten'!$C$7:$C$8,'[Steuerung.xlsx]Steuerung'!$F$6,'[Import Monatsdaten.xlsx]Import Monatsdaten'!$D$7:$D$8,10),SUMIFS('[D Finanzen.xlsx]D Finanzen'!$G$8:$G$16,'[D Finanzen.xlsx]D Finanzen'!$A$8:$A$16,'[Steuerung.xlsx]Steuerung'!$F$6,'[D Finanzen.xlsx]D Finanzen'!$B$8:$B$16,10)) | P24: =IF(COUNTIFS('[Import Monatsdaten.xlsx]Import Monatsdaten'!$C$7:$C$8,'[Steuerung.xlsx]Steuerung'!$F$6,'[Import Monatsdaten.xlsx]Import Monatsdaten'!$D$7:$D$8,11)>0,SUMIFS('[Import Monatsdaten.xlsx]Import Monatsdaten'!$M$7:$M$8,'[Import Monatsdaten.xlsx]Import Monatsdaten'!$C$7:$C$8,'[Steuerung.xlsx]Steuerung'!$F$6,'[Import Monatsdaten.xlsx]Import Monatsdaten'!$D$7:$D$8,11),SUMIFS('[D Finanzen.xlsx]D Finanzen'!$G$8:$G$16,'[D Finanzen.xlsx]D Finanzen'!$A$8:$A$16,'[Steuerung.xlsx]Steuerung'!$F$6,'[D Finanzen.xlsx]D Finanzen'!$B$8:$B$16,11)) | Q24: =IF(COUNTIFS('[Import Monatsdaten.xlsx]Import Monatsdaten'!$C$7:$C$8,'[Steuerung.xlsx]Steuerung'!$F$6,'[Import Monatsdaten.xlsx]Import Monatsdaten'!$D$7:$D$8,12)>0,SUMIFS('[Import Monatsdaten.xlsx]Import Monatsdaten'!$M$7:$M$8,'[Import Monatsdaten.xlsx]Import Monatsdaten'!$C$7:$C$8,'[Steuerung.xlsx]Steuerung'!$F$6,'[Import Monatsdaten.xlsx]Import Monatsdaten'!$D$7:$D$8,12),SUMIFS('[D Finanzen.xlsx]D Finanzen'!$G$8:$G$16,'[D Finanzen.xlsx]D Finanzen'!$A$8:$A$16,'[Steuerung.xlsx]Steuerung'!$F$6,'[D Finanzen.xlsx]D Finanzen'!$B$8:$B$16,12))
C63: SharePoint-Verknüpfungen (Dateien im selben Ordner)
C64: Diese Datei | D64: GuV.xlsx
C65: Liest aus | D65: D Finanzen.xlsx | E65: D Finanzen
C66: Liest aus | D66: Import Monatsdaten.xlsx | E66: Import Monatsdaten
C67: Liest aus | D67: Steuerung.xlsx | E67: Steuerung

Sheet FC Eingabe_FC Eingabe
C2: Forecast-Eingabe
C3: Änderungen gegenüber dem exportierten Forecast. Positive Kosten erhöhen den Aufwand. Ist-Monate werden als gesperrt gekennzeichnet.
C6: Jahr | D6: Monat | E6: Region | F6: Auftrag / Projekt | G6: Δ Umsatz EUR | H6: Δ Bestand EUR | I6: Δ Kosten EUR | J6: Kommentar | K6: Status | L6: Δ EBITDA EUR
K7: =IF(COUNTA(C7:J7)=0,"",IF(OR(C7<>'[Steuerung.xlsx]Steuerung'!$F$6,D7<1,D7>12),"Periode prüfen",IF(D7<='[Steuerung.xlsx]Steuerung'!$F$8,"IST gesperrt",IF(OR(E7="",F7="",COUNT(G7:I7)<>3),"Angaben fehlen","Wirksam")))) | L7: =IF(K7="Wirksam",SUM(G7:H7)-I7,IF(K7="","","n.a."))
K8: =IF(COUNTA(C8:J8)=0,"",IF(OR(C8<>'[Steuerung.xlsx]Steuerung'!$F$6,D8<1,D8>12),"Periode prüfen",IF(D8<='[Steuerung.xlsx]Steuerung'!$F$8,"IST gesperrt",IF(OR(E8="",F8="",COUNT(G8:I8)<>3),"Angaben fehlen","Wirksam")))) | L8: =IF(K8="Wirksam",SUM(G8:H8)-I8,IF(K8="","","n.a."))
K9: =IF(COUNTA(C9:J9)=0,"",IF(OR(C9<>'[Steuerung.xlsx]Steuerung'!$F$6,D9<1,D9>12),"Periode prüfen",IF(D9<='[Steuerung.xlsx]Steuerung'!$F$8,"IST gesperrt",IF(OR(E9="",F9="",COUNT(G9:I9)<>3),"Angaben fehlen","Wirksam")))) | L9: =IF(K9="Wirksam",SUM(G9:H9)-I9,IF(K9="","","n.a."))
K10: =IF(COUNTA(C10:J10)=0,"",IF(OR(C10<>'[Steuerung.xlsx]Steuerung'!$F$6,D10<1,D10>12),"Periode prüfen",IF(D10<='[Steuerung.xlsx]Steuerung'!$F$8,"IST gesperrt",IF(OR(E10="",F10="",COUNT(G10:I10)<>3),"Angaben fehlen","Wirksam")))) | L10: =IF(K10="Wirksam",SUM(G10:H10)-I10,IF(K10="","","n.a."))
K11: =IF(COUNTA(C11:J11)=0,"",IF(OR(C11<>'[Steuerung.xlsx]Steuerung'!$F$6,D11<1,D11>12),"Periode prüfen",IF(D11<='[Steuerung.xlsx]Steuerung'!$F$8,"IST gesperrt",IF(OR(E11="",F11="",COUNT(G11:I11)<>3),"Angaben fehlen","Wirksam")))) | L11: =IF(K11="Wirksam",SUM(G11:H11)-I11,IF(K11="","","n.a."))
K12: =IF(COUNTA(C12:J12)=0,"",IF(OR(C12<>'[Steuerung.xlsx]Steuerung'!$F$6,D12<1,D12>12),"Periode prüfen",IF(D12<='[Steuerung.xlsx]Steuerung'!$F$8,"IST gesperrt",IF(OR(E12="",F12="",COUNT(G12:I12)<>3),"Angaben fehlen","Wirksam")))) | L12: =IF(K12="Wirksam",SUM(G12:H12)-I12,IF(K12="","","n.a."))
K13: =IF(COUNTA(C13:J13)=0,"",IF(OR(C13<>'[Steuerung.xlsx]Steuerung'!$F$6,D13<1,D13>12),"Periode prüfen",IF(D13<='[Steuerung.xlsx]Steuerung'!$F$8,"IST gesperrt",IF(OR(E13="",F13="",COUNT(G13:I13)<>3),"Angaben fehlen","Wirksam")))) | L13: =IF(K13="Wirksam",SUM(G13:H13)-I13,IF(K13="","","n.a."))
K14: =IF(COUNTA(C14:J14)=0,"",IF(OR(C14<>'[Steuerung.xlsx]Steuerung'!$F$6,D14<1,D14>12),"Periode prüfen",IF(D14<='[Steuerung.xlsx]Steuerung'!$F$8,"IST gesperrt",IF(OR(E14="",F14="",COUNT(G14:I14)<>3),"Angaben fehlen","Wirksam")))) | L14: =IF(K14="Wirksam",SUM(G14:H14)-I14,IF(K14="","","n.a."))
K15: =IF(COUNTA(C15:J15)=0,"",IF(OR(C15<>'[Steuerung.xlsx]Steuerung'!$F$6,D15<1,D15>12),"Periode prüfen",IF(D15<='[Steuerung.xlsx]Steuerung'!$F$8,"IST gesperrt",IF(OR(E15="",F15="",COUNT(G15:I15)<>3),"Angaben fehlen","Wirksam")))) | L15: =IF(K15="Wirksam",SUM(G15:H15)-I15,IF(K15="","","n.a."))
K16: =IF(COUNTA(C16:J16)=0,"",IF(OR(C16<>'[Steuerung.xlsx]Steuerung'!$F$6,D16<1,D16>12),"Periode prüfen",IF(D16<='[Steuerung.xlsx]Steuerung'!$F$8,"IST gesperrt",IF(OR(E16="",F16="",COUNT(G16:I16)<>3),"Angaben fehlen","Wirksam")))) | L16: =IF(K16="Wirksam",SUM(G16:H16)-I16,IF(K16="","","n.a."))
K17: =IF(COUNTA(C17:J17)=0,"",IF(OR(C17<>'[Steuerung.xlsx]Steuerung'!$F$6,D17<1,D17>12),"Periode prüfen",IF(D17<='[Steuerung.xlsx]Steuerung'!$F$8,"IST gesperrt",IF(OR(E17="",F17="",COUNT(G17:I17)<>3),"Angaben fehlen","Wirksam")))) | L17: =IF(K17="Wirksam",SUM(G17:H17)-I17,IF(K17="","","n.a."))
K18: =IF(COUNTA(C18:J18)=0,"",IF(OR(C18<>'[Steuerung.xlsx]Steuerung'!$F$6,D18<1,D18>12),"Periode prüfen",IF(D18<='[Steuerung.xlsx]Steuerung'!$F$8,"IST gesperrt",IF(OR(E18="",F18="",COUNT(G18:I18)<>3),"Angaben fehlen","Wirksam")))) | L18: =IF(K18="Wirksam",SUM(G18:H18)-I18,IF(K18="","","n.a."))
... K506: =IF(COUNTA(C506:J506)=0,"",IF(OR(C506<>'[Steuerung.xlsx]Steuerung'!$F$6,D506<1,D506>12),"Periode prüfen",IF(D506<='[Steuerung.xlsx]Steuerung'!$F$8,"IST gesperrt",IF(OR(E506="",F506="",COUNT(G506:I506)<>3),"Angaben fehlen","Wirksam")))) | L506: =IF(K506="Wirksam",SUM(G506:H506)-I506,IF(K506="","","n.a."))
C509: SharePoint-Verknüpfungen (Dateien im selben Ordner)
C510: Diese Datei | D510: FC Eingabe.xlsx
C511: Liest aus | D511: Steuerung.xlsx | E511: Steuerung

Sheet Cockpit_GuV
C2: GuV und EBITDA
C3: Importierte Monatsdaten haben Vorrang vor dem Originalexport. Quelle je Monat in Zeile 23. Aufwendungen negativ, Beträge in EUR.
C5: Position | F5: 1 | G5: 2 | H5: 3 | I5: 4 | J5: 5 | K5: 6 | L5: 7 | M5: 8 | N5: 9 | O5: 10 | P5: 11 | Q5: 12
C6: Position | D6: YTD | E6: Anteil | F6: Jan | G6: Feb | H6: Mär | I6: Apr | J6: Mai | K6: Jun | L6: Jul | M6: Aug | N6: Sep | O6: Okt | P6: Nov | Q6: Dez
C7: Umsatzerlöse | D7: =SUMIFS(F7:Q7,$F$5:$Q$5,"<="&Steuerung!$F$7) | E7: =IF($D$9=0,"n.a.",D7/$D$9) | F7: =IF(COUNTIFS(TVFImportMonate[Jahr],Steuerung!$F$6,TVFImportMonate[Monat],1)>0,SUMIFS(TVFImportMonate[Umsatz],TVFImportMonate[Jahr],Steuerung!$F$6,TVFImportMonate[Monat],1),IF(COUNTIFS('D Finanzen'!$A$45:$A$115,Steuerung!$F$6,'D Finanzen'!$B$45:$B$115,F$5)=0,"",SUMIFS('D Finanzen'!$E$45:$E$115,'D Finanzen'!$A$45:$A$115,Steuerung!$F$6,'D Finanzen'!$B$45:$B$115,F$5,'D Finanzen'!$C$45:$C$115,10))) | G7: =IF(COUNTIFS(TVFImportMonate[Jahr],Steuerung!$F$6,TVFImportMonate[Monat],2)>0,SUMIFS(TVFImportMonate[Umsatz],TVFImportMonate[Jahr],Steuerung!$F$6,TVFImportMonate[Monat],2),IF(COUNTIFS('D Finanzen'!$A$45:$A$115,Steuerung!$F$6,'D Finanzen'!$B$45:$B$115,G$5)=0,"",SUMIFS('D Finanzen'!$E$45:$E$115,'D Finanzen'!$A$45:$A$115,Steuerung!$F$6,'D Finanzen'!$B$45:$B$115,G$5,'D Finanzen'!$C$45:$C$115,10))) | H7: =IF(COUNTIFS(TVFImportMonate[Jahr],Steuerung!$F$6,TVFImportMonate[Monat],3)>0,SUMIFS(TVFImportMonate[Umsatz],TVFImportMonate[Jahr],Steuerung!$F$6,TVFImportMonate[Monat],3),IF(COUNTIFS('D Finanzen'!$A$45:$A$115,Steuerung!$F$6,'D Finanzen'!$B$45:$B$115,H$5)=0,"",SUMIFS('D Finanzen'!$E$45:$E$115,'D Finanzen'!$A$45:$A$115,Steuerung!$F$6,'D Finanzen'!$B$45:$B$115,H$5,'D Finanzen'!$C$45:$C$115,10))) | I7: =IF(COUNTIFS(TVFImportMonate[Jahr],Steuerung!$F$6,TVFImportMonate[Monat],4)>0,SUMIFS(TVFImportMonate[Umsatz],TVFImportMonate[Jahr],Steuerung!$F$6,TVFImportMonate[Monat],4),IF(COUNTIFS('D Finanzen'!$A$45:$A$115,Steuerung!$F$6,'D Finanzen'!$B$45:$B$115,I$5)=0,"",SUMIFS('D Finanzen'!$E$45:$E$115,'D Finanzen'!$A$45:$A$115,Steuerung!$F$6,'D Finanzen'!$B$45:$B$115,I$5,'D Finanzen'!$C$45:$C$115,10))) | J7: =IF(COUNTIFS(TVFImportMonate[Jahr],Steuerung!$F$6,TVFImportMonate[Monat],5)>0,SUMIFS(TVFImportMonate[Umsatz],TVFImportMonate[Jahr],Steuerung!$F$6,TVFImportMonate[Monat],5),IF(COUNTIFS('D Finanzen'!$A$45:$A$115,Steuerung!$F$6,'D Finanzen'!$B$45:$B$115,J$5)=0,"",SUMIFS('D Finanzen'!$E$45:$E$115,'D Finanzen'!$A$45:$A$115,Steuerung!$F$6,'D Finanzen'!$B$45:$B$115,J$5,'D Finanzen'!$C$45:$C$115,10))) | K7: =IF(COUNTIFS(TVFImportMonate[Jahr],Steuerung!$F$6,TVFImportMonate[Monat],6)>0,SUMIFS(TVFImportMonate[Umsatz],TVFImportMonate[Jahr],Steuerung!$F$6,TVFImportMonate[Monat],6),IF(COUNTIFS('D Finanzen'!$A$45:$A$115,Steuerung!$F$6,'D Finanzen'!$B$45:$B$115,K$5)=0,"",SUMIFS('D Finanzen'!$E$45:$E$115,'D Finanzen'!$A$45:$A$115,Steuerung!$F$6,'D Finanzen'!$B$45:$B$115,K$5,'D Finanzen'!$C$45:$C$115,10))) | L7: =IF(COUNTIFS(TVFImportMonate[Jahr],Steuerung!$F$6,TVFImportMonate[Monat],7)>0,SUMIFS(TVFImportMonate[Umsatz],TVFImportMonate[Jahr],Steuerung!$F$6,TVFImportMonate[Monat],7),IF(COUNTIFS('D Finanzen'!$A$45:$A$115,Steuerung!$F$6,'D Finanzen'!$B$45:$B$115,L$5)=0,"",SUMIFS('D Finanzen'!$E$45:$E$115,'D Finanzen'!$A$45:$A$115,Steuerung!$F$6,'D Finanzen'!$B$45:$B$115,L$5,'D Finanzen'!$C$45:$C$115,10))) | M7: =IF(COUNTIFS(TVFImportMonate[Jahr],Steuerung!$F$6,TVFImportMonate[Monat],8)>0,SUMIFS(TVFImportMonate[Umsatz],TVFImportMonate[Jahr],Steuerung!$F$6,TVFImportMonate[Monat],8),IF(COUNTIFS('D Finanzen'!$A$45:$A$115,Steuerung!$F$6,'D Finanzen'!$B$45:$B$115,M$5)=0,"",SUMIFS('D Finanzen'!$E$45:$E$115,'D Finanzen'!$A$45:$A$115,Steuerung!$F$6,'D Finanzen'!$B$45:$B$115,M$5,'D Finanzen'!$C$45:$C$115,10))) | N7: =IF(COUNTIFS(TVFImportMonate[Jahr],Steuerung!$F$6,TVFImportMonate[Monat],9)>0,SUMIFS(TVFImportMonate[Umsatz],TVFImportMonate[Jahr],Steuerung!$F$6,TVFImportMonate[Monat],9),IF(COUNTIFS('D Finanzen'!$A$45:$A$115,Steuerung!$F$6,'D Finanzen'!$B$45:$B$115,N$5)=0,"",SUMIFS('D Finanzen'!$E$45:$E$115,'D Finanzen'!$A$45:$A$115,Steuerung!$F$6,'D Finanzen'!$B$45:$B$115,N$5,'D Finanzen'!$C$45:$C$115,10))) | O7: =IF(COUNTIFS(TVFImportMonate[Jahr],Steuerung!$F$6,TVFImportMonate[Monat],10)>0,SUMIFS(TVFImportMonate[Umsatz],TVFImportMonate[Jahr],Steuerung!$F$6,TVFImportMonate[Monat],10),IF(COUNTIFS('D Finanzen'!$A$45:$A$115,Steuerung!$F$6,'D Finanzen'!$B$45:$B$115,O$5)=0,"",SUMIFS('D Finanzen'!$E$45:$E$115,'D Finanzen'!$A$45:$A$115,Steuerung!$F$6,'D Finanzen'!$B$45:$B$115,O$5,'D Finanzen'!$C$45:$C$115,10))) | P7: =IF(COUNTIFS(TVFImportMonate[Jahr],Steuerung!$F$6,TVFImportMonate[Monat],11)>0,SUMIFS(TVFImportMonate[Umsatz],TVFImportMonate[Jahr],Steuerung!$F$6,TVFImportMonate[Monat],11),IF(COUNTIFS('D Finanzen'!$A$45:$A$115,Steuerung!$F$6,'D Finanzen'!$B$45:$B$115,P$5)=0,"",SUMIFS('D Finanzen'!$E$45:$E$115,'D Finanzen'!$A$45:$A$115,Steuerung!$F$6,'D Finanzen'!$B$45:$B$115,P$5,'D Finanzen'!$C$45:$C$115,10))) | Q7: =IF(COUNTIFS(TVFImportMonate[Jahr],Steuerung!$F$6,TVFImportMonate[Monat],12)>0,SUMIFS(TVFImportMonate[Umsatz],TVFImportMonate[Jahr],Steuerung!$F$6,TVFImportMonate[Monat],12),IF(COUNTIFS('D Finanzen'!$A$45:$A$115,Steuerung!$F$6,'D Finanzen'!$B$45:$B$115,Q$5)=0,"",SUMIFS('D Finanzen'!$E$45:$E$115,'D Finanzen'!$A$45:$A$115,Steuerung!$F$6,'D Finanzen'!$B$45:$B$115,Q$5,'D Finanzen'!$C$45:$C$115,10)))
C8: Bestandsveränderungen | D8: =SUMIFS(F8:Q8,$F$5:$Q$5,"<="&Steuerung!$F$7) | E8: =IF($D$9=0,"n.a.",D8/$D$9) | F8: =IF(COUNTIFS(TVFImportMonate[Jahr],Steuerung!$F$6,TVFImportMonate[Monat],1)>0,SUMIFS(TVFImportMonate[Bestand],TVFImportMonate[Jahr],Steuerung!$F$6,TVFImportMonate[Monat],1),IF(COUNTIFS('D Finanzen'!$A$45:$A$115,Steuerung!$F$6,'D Finanzen'!$B$45:$B$115,F$5)=0,"",SUMIFS('D Finanzen'!$E$45:$E$115,'D Finanzen'!$A$45:$A$115,Steuerung!$F$6,'D Finanzen'!$B$45:$B$115,F$5,'D Finanzen'!$C$45:$C$115,20))) | G8: =IF(COUNTIFS(TVFImportMonate[Jahr],Steuerung!$F$6,TVFImportMonate[Monat],2)>0,SUMIFS(TVFImportMonate[Bestand],TVFImportMonate[Jahr],Steuerung!$F$6,TVFImportMonate[Monat],2),IF(COUNTIFS('D Finanzen'!$A$45:$A$115,Steuerung!$F$6,'D Finanzen'!$B$45:$B$115,G$5)=0,"",SUMIFS('D Finanzen'!$E$45:$E$115,'D Finanzen'!$A$45:$A$115,Steuerung!$F$6,'D Finanzen'!$B$45:$B$115,G$5,'D Finanzen'!$C$45:$C$115,20))) | H8: =IF(COUNTIFS(TVFImportMonate[Jahr],Steuerung!$F$6,TVFImportMonate[Monat],3)>0,SUMIFS(TVFImportMonate[Bestand],TVFImportMonate[Jahr],Steuerung!$F$6,TVFImportMonate[Monat],3),IF(COUNTIFS('D Finanzen'!$A$45:$A$115,Steuerung!$F$6,'D Finanzen'!$B$45:$B$115,H$5)=0,"",SUMIFS('D Finanzen'!$E$45:$E$115,'D Finanzen'!$A$45:$A$115,Steuerung!$F$6,'D Finanzen'!$B$45:$B$115,H$5,'D Finanzen'!$C$45:$C$115,20))) | I8: =IF(COUNTIFS(TVFImportMonate[Jahr],Steuerung!$F$6,TVFImportMonate[Monat],4)>0,SUMIFS(TVFImportMonate[Bestand],TVFImportMonate[Jahr],Steuerung!$F$6,TVFImportMonate[Monat],4),IF(COUNTIFS('D Finanzen'!$A$45:$A$115,Steuerung!$F$6,'D Finanzen'!$B$45:$B$115,I$5)=0,"",SUMIFS('D Finanzen'!$E$45:$E$115,'D Finanzen'!$A$45:$A$115,Steuerung!$F$6,'D Finanzen'!$B$45:$B$115,I$5,'D Finanzen'!$C$45:$C$115,20))) | J8: =IF(COUNTIFS(TVFImportMonate[Jahr],Steuerung!$F$6,TVFImportMonate[Monat],5)>0,SUMIFS(TVFImportMonate[Bestand],TVFImportMonate[Jahr],Steuerung!$F$6,TVFImportMonate[Monat],5),IF(COUNTIFS('D Finanzen'!$A$45:$A$115,Steuerung!$F$6,'D Finanzen'!$B$45:$B$115,J$5)=0,"",SUMIFS('D Finanzen'!$E$45:$E$115,'D Finanzen'!$A$45:$A$115,Steuerung!$F$6,'D Finanzen'!$B$45:$B$115,J$5,'D Finanzen'!$C$45:$C$115,20))) | K8: =IF(COUNTIFS(TVFImportMonate[Jahr],Steuerung!$F$6,TVFImportMonate[Monat],6)>0,SUMIFS(TVFImportMonate[Bestand],TVFImportMonate[Jahr],Steuerung!$F$6,TVFImportMonate[Monat],6),IF(COUNTIFS('D Finanzen'!$A$45:$A$115,Steuerung!$F$6,'D Finanzen'!$B$45:$B$115,K$5)=0,"",SUMIFS('D Finanzen'!$E$45:$E$115,'D Finanzen'!$A$45:$A$115,Steuerung!$F$6,'D Finanzen'!$B$45:$B$115,K$5,'D Finanzen'!$C$45:$C$115,20))) | L8: =IF(COUNTIFS(TVFImportMonate[Jahr],Steuerung!$F$6,TVFImportMonate[Monat],7)>0,SUMIFS(TVFImportMonate[Bestand],TVFImportMonate[Jahr],Steuerung!$F$6,TVFImportMonate[Monat],7),IF(COUNTIFS('D Finanzen'!$A$45:$A$115,Steuerung!$F$6,'D Finanzen'!$B$45:$B$115,L$5)=0,"",SUMIFS('D Finanzen'!$E$45:$E$115,'D Finanzen'!$A$45:$A$115,Steuerung!$F$6,'D Finanzen'!$B$45:$B$115,L$5,'D Finanzen'!$C$45:$C$115,20))) | M8: =IF(COUNTIFS(TVFImportMonate[Jahr],Steuerung!$F$6,TVFImportMonate[Monat],8)>0,SUMIFS(TVFImportMonate[Bestand],TVFImportMonate[Jahr],Steuerung!$F$6,TVFImportMonate[Monat],8),IF(COUNTIFS('D Finanzen'!$A$45:$A$115,Steuerung!$F$6,'D Finanzen'!$B$45:$B$115,M$5)=0,"",SUMIFS('D Finanzen'!$E$45:$E$115,'D Finanzen'!$A$45:$A$115,Steuerung!$F$6,'D Finanzen'!$B$45:$B$115,M$5,'D Finanzen'!$C$45:$C$115,20))) | N8: =IF(COUNTIFS(TVFImportMonate[Jahr],Steuerung!$F$6,TVFImportMonate[Monat],9)>0,SUMIFS(TVFImportMonate[Bestand],TVFImportMonate[Jahr],Steuerung!$F$6,TVFImportMonate[Monat],9),IF(COUNTIFS('D Finanzen'!$A$45:$A$115,Steuerung!$F$6,'D Finanzen'!$B$45:$B$115,N$5)=0,"",SUMIFS('D Finanzen'!$E$45:$E$115,'D Finanzen'!$A$45:$A$115,Steuerung!$F$6,'D Finanzen'!$B$45:$B$115,N$5,'D Finanzen'!$C$45:$C$115,20))) | O8: =IF(COUNTIFS(TVFImportMonate[Jahr],Steuerung!$F$6,TVFImportMonate[Monat],10)>0,SUMIFS(TVFImportMonate[Bestand],TVFImportMonate[Jahr],Steuerung!$F$6,TVFImportMonate[Monat],10),IF(COUNTIFS('D Finanzen'!$A$45:$A$115,Steuerung!$F$6,'D Finanzen'!$B$45:$B$115,O$5)=0,"",SUMIFS('D Finanzen'!$E$45:$E$115,'D Finanzen'!$A$45:$A$115,Steuerung!$F$6,'D Finanzen'!$B$45:$B$115,O$5,'D Finanzen'!$C$45:$C$115,20))) | P8: =IF(COUNTIFS(TVFImportMonate[Jahr],Steuerung!$F$6,TVFImportMonate[Monat],11)>0,SUMIFS(TVFImportMonate[Bestand],TVFImportMonate[Jahr],Steuerung!$F$6,TVFImportMonate[Monat],11),IF(COUNTIFS('D Finanzen'!$A$45:$A$115,Steuerung!$F$6,'D Finanzen'!$B$45:$B$115,P$5)=0,"",SUMIFS('D Finanzen'!$E$45:$E$115,'D Finanzen'!$A$45:$A$115,Steuerung!$F$6,'D Finanzen'!$B$45:$B$115,P$5,'D Finanzen'!$C$45:$C$115,20))) | Q8: =IF(COUNTIFS(TVFImportMonate[Jahr],Steuerung!$F$6,TVFImportMonate[Monat],12)>0,SUMIFS(TVFImportMonate[Bestand],TVFImportMonate[Jahr],Steuerung!$F$6,TVFImportMonate[Monat],12),IF(COUNTIFS('D Finanzen'!$A$45:$A$115,Steuerung!$F$6,'D Finanzen'!$B$45:$B$115,Q$5)=0,"",SUMIFS('D Finanzen'!$E$45:$E$115,'D Finanzen'!$A$45:$A$115,Steuerung!$F$6,'D Finanzen'!$B$45:$B$115,Q$5,'D Finanzen'!$C$45:$C$115,20)))
C9: Gesamtleistung | D9: =SUMIFS(F9:Q9,$F$5:$Q$5,"<="&Steuerung!$F$7) | E9: =IF($D$9=0,"n.a.",D9/$D$9) | F9: =IF(F7="","",SUM(F7:F8)) | G9: =IF(G7="","",SUM(G7:G8)) | H9: =IF(H7="","",SUM(H7:H8)) | I9: =IF(I7="","",SUM(I7:I8)) | J9: =IF(J7="","",SUM(J7:J8)) | K9: =IF(K7="","",SUM(K7:K8)) | L9: =IF(L7="","",SUM(L7:L8)) | M9: =IF(M7="","",SUM(M7:M8)) | ... Q9: =IF(Q7="","",SUM(Q7:Q8))
C10: Sonstige betriebliche Erträge | D10: =SUMIFS(F10:Q10,$F$5:$Q$5,"<="&Steuerung!$F$7) | E10: =IF($D$9=0,"n.a.",D10/$D$9) | F10: =IF(COUNTIFS(TVFImportMonate[Jahr],Steuerung!$F$6,TVFImportMonate[Monat],1)>0,SUMIFS(TVFImportMonate[Sonstige_Ertraege],TVFImportMonate[Jahr],Steuerung!$F$6,TVFImportMonate[Monat],1),IF(COUNTIFS('D Finanzen'!$A$45:$A$115,Steuerung!$F$6,'D Finanzen'!$B$45:$B$115,F$5)=0,"",SUMIFS('D Finanzen'!$E$45:$E$115,'D Finanzen'!$A$45:$A$115,Steuerung!$F$6,'D Finanzen'!$B$45:$B$115,F$5,'D Finanzen'!$C$45:$C$115,30))) | G10: =IF(COUNTIFS(TVFImportMonate[Jahr],Steuerung!$F$6,TVFImportMonate[Monat],2)>0,SUMIFS(TVFImportMonate[Sonstige_Ertraege],TVFImportMonate[Jahr],Steuerung!$F$6,TVFImportMonate[Monat],2),IF(COUNTIFS('D Finanzen'!$A$45:$A$115,Steuerung!$F$6,'D Finanzen'!$B$45:$B$115,G$5)=0,"",SUMIFS('D Finanzen'!$E$45:$E$115,'D Finanzen'!$A$45:$A$115,Steuerung!$F$6,'D Finanzen'!$B$45:$B$115,G$5,'D Finanzen'!$C$45:$C$115,30))) | H10: =IF(COUNTIFS(TVFImportMonate[Jahr],Steuerung!$F$6,TVFImportMonate[Monat],3)>0,SUMIFS(TVFImportMonate[Sonstige_Ertraege],TVFImportMonate[Jahr],Steuerung!$F$6,TVFImportMonate[Monat],3),IF(COUNTIFS('D Finanzen'!$A$45:$A$115,Steuerung!$F$6,'D Finanzen'!$B$45:$B$115,H$5)=0,"",SUMIFS('D Finanzen'!$E$45:$E$115,'D Finanzen'!$A$45:$A$115,Steuerung!$F$6,'D Finanzen'!$B$45:$B$115,H$5,'D Finanzen'!$C$45:$C$115,30))) | I10: =IF(COUNTIFS(TVFImportMonate[Jahr],Steuerung!$F$6,TVFImportMonate[Monat],4)>0,SUMIFS(TVFImportMonate[Sonstige_Ertraege],TVFImportMonate[Jahr],Steuerung!$F$6,TVFImportMonate[Monat],4),IF(COUNTIFS('D Finanzen'!$A$45:$A$115,Steuerung!$F$6,'D Finanzen'!$B$45:$B$115,I$5)=0,"",SUMIFS('D Finanzen'!$E$45:$E$115,'D Finanzen'!$A$45:$A$115,Steuerung!$F$6,'D Finanzen'!$B$45:$B$115,I$5,'D Finanzen'!$C$45:$C$115,30))) | J10: =IF(COUNTIFS(TVFImportMonate[Jahr],Steuerung!$F$6,TVFImportMonate[Monat],5)>0,SUMIFS(TVFImportMonate[Sonstige_Ertraege],TVFImportMonate[Jahr],Steuerung!$F$6,TVFImportMonate[Monat],5),IF(COUNTIFS('D Finanzen'!$A$45:$A$115,Steuerung!$F$6,'D Finanzen'!$B$45:$B$115,J$5)=0,"",SUMIFS('D Finanzen'!$E$45:$E$115,'D Finanzen'!$A$45:$A$115,Steuerung!$F$6,'D Finanzen'!$B$45:$B$115,J$5,'D Finanzen'!$C$45:$C$115,30))) | K10: =IF(COUNTIFS(TVFImportMonate[Jahr],Steuerung!$F$6,TVFImportMonate[Monat],6)>0,SUMIFS(TVFImportMonate[Sonstige_Ertraege],TVFImportMonate[Jahr],Steuerung!$F$6,TVFImportMonate[Monat],6),IF(COUNTIFS('D Finanzen'!$A$45:$A$115,Steuerung!$F$6,'D Finanzen'!$B$45:$B$115,K$5)=0,"",SUMIFS('D Finanzen'!$E$45:$E$115,'D Finanzen'!$A$45:$A$115,Steuerung!$F$6,'D Finanzen'!$B$45:$B$115,K$5,'D Finanzen'!$C$45:$C$115,30))) | L10: =IF(COUNTIFS(TVFImportMonate[Jahr],Steuerung!$F$6,TVFImportMonate[Monat],7)>0,SUMIFS(TVFImportMonate[Sonstige_Ertraege],TVFImportMonate[Jahr],Steuerung!$F$6,TVFImportMonate[Monat],7),IF(COUNTIFS('D Finanzen'!$A$45:$A$115,Steuerung!$F$6,'D Finanzen'!$B$45:$B$115,L$5)=0,"",SUMIFS('D Finanzen'!$E$45:$E$115,'D Finanzen'!$A$45:$A$115,Steuerung!$F$6,'D Finanzen'!$B$45:$B$115,L$5,'D Finanzen'!$C$45:$C$115,30))) | M10: =IF(COUNTIFS(TVFImportMonate[Jahr],Steuerung!$F$6,TVFImportMonate[Monat],8)>0,SUMIFS(TVFImportMonate[Sonstige_Ertraege],TVFImportMonate[Jahr],Steuerung!$F$6,TVFImportMonate[Monat],8),IF(COUNTIFS('D Finanzen'!$A$45:$A$115,Steuerung!$F$6,'D Finanzen'!$B$45:$B$115,M$5)=0,"",SUMIFS('D Finanzen'!$E$45:$E$115,'D Finanzen'!$A$45:$A$115,Steuerung!$F$6,'D Finanzen'!$B$45:$B$115,M$5,'D Finanzen'!$C$45:$C$115,30))) | N10: =IF(COUNTIFS(TVFImportMonate[Jahr],Steuerung!$F$6,TVFImportMonate[Monat],9)>0,SUMIFS(TVFImportMonate[Sonstige_Ertraege],TVFImportMonate[Jahr],Steuerung!$F$6,TVFImportMonate[Monat],9),IF(COUNTIFS('D Finanzen'!$A$45:$A$115,Steuerung!$F$6,'D Finanzen'!$B$45:$B$115,N$5)=0,"",SUMIFS('D Finanzen'!$E$45:$E$115,'D Finanzen'!$A$45:$A$115,Steuerung!$F$6,'D Finanzen'!$B$45:$B$115,N$5,'D Finanzen'!$C$45:$C$115,30))) | O10: =IF(COUNTIFS(TVFImportMonate[Jahr],Steuerung!$F$6,TVFImportMonate[Monat],10)>0,SUMIFS(TVFImportMonate[Sonstige_Ertraege],TVFImportMonate[Jahr],Steuerung!$F$6,TVFImportMonate[Monat],10),IF(COUNTIFS('D Finanzen'!$A$45:$A$115,Steuerung!$F$6,'D Finanzen'!$B$45:$B$115,O$5)=0,"",SUMIFS('D Finanzen'!$E$45:$E$115,'D Finanzen'!$A$45:$A$115,Steuerung!$F$6,'D Finanzen'!$B$45:$B$115,O$5,'D Finanzen'!$C$45:$C$115,30))) | P10: =IF(COUNTIFS(TVFImportMonate[Jahr],Steuerung!$F$6,TVFImportMonate[Monat],11)>0,SUMIFS(TVFImportMonate[Sonstige_Ertraege],TVFImportMonate[Jahr],Steuerung!$F$6,TVFImportMonate[Monat],11),IF(COUNTIFS('D Finanzen'!$A$45:$A$115,Steuerung!$F$6,'D Finanzen'!$B$45:$B$115,P$5)=0,"",SUMIFS('D Finanzen'!$E$45:$E$115,'D Finanzen'!$A$45:$A$115,Steuerung!$F$6,'D Finanzen'!$B$45:$B$115,P$5,'D Finanzen'!$C$45:$C$115,30))) | Q10: =IF(COUNTIFS(TVFImportMonate[Jahr],Steuerung!$F$6,TVFImportMonate[Monat],12)>0,SUMIFS(TVFImportMonate[Sonstige_Ertraege],TVFImportMonate[Jahr],Steuerung!$F$6,TVFImportMonate[Monat],12),IF(COUNTIFS('D Finanzen'!$A$45:$A$115,Steuerung!$F$6,'D Finanzen'!$B$45:$B$115,Q$5)=0,"",SUMIFS('D Finanzen'!$E$45:$E$115,'D Finanzen'!$A$45:$A$115,Steuerung!$F$6,'D Finanzen'!$B$45:$B$115,Q$5,'D Finanzen'!$C$45:$C$115,30)))
C11: Materialaufwand | D11: =SUMIFS(F11:Q11,$F$5:$Q$5,"<="&Steuerung!$F$7) | E11: =IF($D$9=0,"n.a.",D11/$D$9) | F11: =IF(COUNTIFS(TVFImportMonate[Jahr],Steuerung!$F$6,TVFImportMonate[Monat],1)>0,SUMIFS(TVFImportMonate[Materialaufwand],TVFImportMonate[Jahr],Steuerung!$F$6,TVFImportMonate[Monat],1),IF(COUNTIFS('D Finanzen'!$A$45:$A$115,Steuerung!$F$6,'D Finanzen'!$B$45:$B$115,F$5)=0,"",SUMIFS('D Finanzen'!$E$45:$E$115,'D Finanzen'!$A$45:$A$115,Steuerung!$F$6,'D Finanzen'!$B$45:$B$115,F$5,'D Finanzen'!$C$45:$C$115,40))) | G11: =IF(COUNTIFS(TVFImportMonate[Jahr],Steuerung!$F$6,TVFImportMonate[Monat],2)>0,SUMIFS(TVFImportMonate[Materialaufwand],TVFImportMonate[Jahr],Steuerung!$F$6,TVFImportMonate[Monat],2),IF(COUNTIFS('D Finanzen'!$A$45:$A$115,Steuerung!$F$6,'D Finanzen'!$B$45:$B$115,G$5)=0,"",SUMIFS('D Finanzen'!$E$45:$E$115,'D Finanzen'!$A$45:$A$115,Steuerung!$F$6,'D Finanzen'!$B$45:$B$115,G$5,'D Finanzen'!$C$45:$C$115,40))) | H11: =IF(COUNTIFS(TVFImportMonate[Jahr],Steuerung!$F$6,TVFImportMonate[Monat],3)>0,SUMIFS(TVFImportMonate[Materialaufwand],TVFImportMonate[Jahr],Steuerung!$F$6,TVFImportMonate[Monat],3),IF(COUNTIFS('D Finanzen'!$A$45:$A$115,Steuerung!$F$6,'D Finanzen'!$B$45:$B$115,H$5)=0,"",SUMIFS('D Finanzen'!$E$45:$E$115,'D Finanzen'!$A$45:$A$115,Steuerung!$F$6,'D Finanzen'!$B$45:$B$115,H$5,'D Finanzen'!$C$45:$C$115,40))) | I11: =IF(COUNTIFS(TVFImportMonate[Jahr],Steuerung!$F$6,TVFImportMonate[Monat],4)>0,SUMIFS(TVFImportMonate[Materialaufwand],TVFImportMonate[Jahr],Steuerung!$F$6,TVFImportMonate[Monat],4),IF(COUNTIFS('D Finanzen'!$A$45:$A$115,Steuerung!$F$6,'D Finanzen'!$B$45:$B$115,I$5)=0,"",SUMIFS('D Finanzen'!$E$45:$E$115,'D Finanzen'!$A$45:$A$115,Steuerung!$F$6,'D Finanzen'!$B$45:$B$115,I$5,'D Finanzen'!$C$45:$C$115,40))) | J11: =IF(COUNTIFS(TVFImportMonate[Jahr],Steuerung!$F$6,TVFImportMonate[Monat],5)>0,SUMIFS(TVFImportMonate[Materialaufwand],TVFImportMonate[Jahr],Steuerung!$F$6,TVFImportMonate[Monat],5),IF(COUNTIFS('D Finanzen'!$A$45:$A$115,Steuerung!$F$6,'D Finanzen'!$B$45:$B$115,J$5)=0,"",SUMIFS('D Finanzen'!$E$45:$E$115,'D Finanzen'!$A$45:$A$115,Steuerung!$F$6,'D Finanzen'!$B$45:$B$115,J$5,'D Finanzen'!$C$45:$C$115,40))) | K11: =IF(COUNTIFS(TVFImportMonate[Jahr],Steuerung!$F$6,TVFImportMonate[Monat],6)>0,SUMIFS(TVFImportMonate[Materialaufwand],TVFImportMonate[Jahr],Steuerung!$F$6,TVFImportMonate[Monat],6),IF(COUNTIFS('D Finanzen'!$A$45:$A$115,Steuerung!$F$6,'D Finanzen'!$B$45:$B$115,K$5)=0,"",SUMIFS('D Finanzen'!$E$45:$E$115,'D Finanzen'!$A$45:$A$115,Steuerung!$F$6,'D Finanzen'!$B$45:$B$115,K$5,'D Finanzen'!$C$45:$C$115,40))) | L11: =IF(COUNTIFS(TVFImportMonate[Jahr],Steuerung!$F$6,TVFImportMonate[Monat],7)>0,SUMIFS(TVFImportMonate[Materialaufwand],TVFImportMonate[Jahr],Steuerung!$F$6,TVFImportMonate[Monat],7),IF(COUNTIFS('D Finanzen'!$A$45:$A$115,Steuerung!$F$6,'D Finanzen'!$B$45:$B$115,L$5)=0,"",SUMIFS('D Finanzen'!$E$45:$E$115,'D Finanzen'!$A$45:$A$115,Steuerung!$F$6,'D Finanzen'!$B$45:$B$115,L$5,'D Finanzen'!$C$45:$C$115,40))) | M11: =IF(COUNTIFS(TVFImportMonate[Jahr],Steuerung!$F$6,TVFImportMonate[Monat],8)>0,SUMIFS(TVFImportMonate[Materialaufwand],TVFImportMonate[Jahr],Steuerung!$F$6,TVFImportMonate[Monat],8),IF(COUNTIFS('D Finanzen'!$A$45:$A$115,Steuerung!$F$6,'D Finanzen'!$B$45:$B$115,M$5)=0,"",SUMIFS('D Finanzen'!$E$45:$E$115,'D Finanzen'!$A$45:$A$115,Steuerung!$F$6,'D Finanzen'!$B$45:$B$115,M$5,'D Finanzen'!$C$45:$C$115,40))) | N11: =IF(COUNTIFS(TVFImportMonate[Jahr],Steuerung!$F$6,TVFImportMonate[Monat],9)>0,SUMIFS(TVFImportMonate[Materialaufwand],TVFImportMonate[Jahr],Steuerung!$F$6,TVFImportMonate[Monat],9),IF(COUNTIFS('D Finanzen'!$A$45:$A$115,Steuerung!$F$6,'D Finanzen'!$B$45:$B$115,N$5)=0,"",SUMIFS('D Finanzen'!$E$45:$E$115,'D Finanzen'!$A$45:$A$115,Steuerung!$F$6,'D Finanzen'!$B$45:$B$115,N$5,'D Finanzen'!$C$45:$C$115,40))) | O11: =IF(COUNTIFS(TVFImportMonate[Jahr],Steuerung!$F$6,TVFImportMonate[Monat],10)>0,SUMIFS(TVFImportMonate[Materialaufwand],TVFImportMonate[Jahr],Steuerung!$F$6,TVFImportMonate[Monat],10),IF(COUNTIFS('D Finanzen'!$A$45:$A$115,Steuerung!$F$6,'D Finanzen'!$B$45:$B$115,O$5)=0,"",SUMIFS('D Finanzen'!$E$45:$E$115,'D Finanzen'!$A$45:$A$115,Steuerung!$F$6,'D Finanzen'!$B$45:$B$115,O$5,'D Finanzen'!$C$45:$C$115,40))) | P11: =IF(COUNTIFS(TVFImportMonate[Jahr],Steuerung!$F$6,TVFImportMonate[Monat],11)>0,SUMIFS(TVFImportMonate[Materialaufwand],TVFImportMonate[Jahr],Steuerung!$F$6,TVFImportMonate[Monat],11),IF(COUNTIFS('D Finanzen'!$A$45:$A$115,Steuerung!$F$6,'D Finanzen'!$B$45:$B$115,P$5)=0,"",SUMIFS('D Finanzen'!$E$45:$E$115,'D Finanzen'!$A$45:$A$115,Steuerung!$F$6,'D Finanzen'!$B$45:$B$115,P$5,'D Finanzen'!$C$45:$C$115,40))) | Q11: =IF(COUNTIFS(TVFImportMonate[Jahr],Steuerung!$F$6,TVFImportMonate[Monat],12)>0,SUMIFS(TVFImportMonate[Materialaufwand],TVFImportMonate[Jahr],Steuerung!$F$6,TVFImportMonate[Monat],12),IF(COUNTIFS('D Finanzen'!$A$45:$A$115,Steuerung!$F$6,'D Finanzen'!$B$45:$B$115,Q$5)=0,"",SUMIFS('D Finanzen'!$E$45:$E$115,'D Finanzen'!$A$45:$A$115,Steuerung!$F$6,'D Finanzen'!$B$45:$B$115,Q$5,'D Finanzen'!$C$45:$C$115,40)))
C12: Personalaufwand | D12: =SUMIFS(F12:Q12,$F$5:$Q$5,"<="&Steuerung!$F$7) | E12: =IF($D$9=0,"n.a.",D12/$D$9) | F12: =IF(COUNTIFS(TVFImportMonate[Jahr],Steuerung!$F$6,TVFImportMonate[Monat],1)>0,SUMIFS(TVFImportMonate[Personalaufwand],TVFImportMonate[Jahr],Steuerung!$F$6,TVFImportMonate[Monat],1),IF(COUNTIFS('D Finanzen'!$A$45:$A$115,Steuerung!$F$6,'D Finanzen'!$B$45:$B$115,F$5)=0,"",SUMIFS('D Finanzen'!$E$45:$E$115,'D Finanzen'!$A$45:$A$115,Steuerung!$F$6,'D Finanzen'!$B$45:$B$115,F$5,'D Finanzen'!$C$45:$C$115,50))) | G12: =IF(COUNTIFS(TVFImportMonate[Jahr],Steuerung!$F$6,TVFImportMonate[Monat],2)>0,SUMIFS(TVFImportMonate[Personalaufwand],TVFImportMonate[Jahr],Steuerung!$F$6,TVFImportMonate[Monat],2),IF(COUNTIFS('D Finanzen'!$A$45:$A$115,Steuerung!$F$6,'D Finanzen'!$B$45:$B$115,G$5)=0,"",SUMIFS('D Finanzen'!$E$45:$E$115,'D Finanzen'!$A$45:$A$115,Steuerung!$F$6,'D Finanzen'!$B$45:$B$115,G$5,'D Finanzen'!$C$45:$C$115,50))) | H12: =IF(COUNTIFS(TVFImportMonate[Jahr],Steuerung!$F$6,TVFImportMonate[Monat],3)>0,SUMIFS(TVFImportMonate[Personalaufwand],TVFImportMonate[Jahr],Steuerung!$F$6,TVFImportMonate[Monat],3),IF(COUNTIFS('D Finanzen'!$A$45:$A$115,Steuerung!$F$6,'D Finanzen'!$B$45:$B$115,H$5)=0,"",SUMIFS('D Finanzen'!$E$45:$E$115,'D Finanzen'!$A$45:$A$115,Steuerung!$F$6,'D Finanzen'!$B$45:$B$115,H$5,'D Finanzen'!$C$45:$C$115,50))) | I12: =IF(COUNTIFS(TVFImportMonate[Jahr],Steuerung!$F$6,TVFImportMonate[Monat],4)>0,SUMIFS(TVFImportMonate[Personalaufwand],TVFImportMonate[Jahr],Steuerung!$F$6,TVFImportMonate[Monat],4),IF(COUNTIFS('D Finanzen'!$A$45:$A$115,Steuerung!$F$6,'D Finanzen'!$B$45:$B$115,I$5)=0,"",SUMIFS('D Finanzen'!$E$45:$E$115,'D Finanzen'!$A$45:$A$115,Steuerung!$F$6,'D Finanzen'!$B$45:$B$115,I$5,'D Finanzen'!$C$45:$C$115,50))) | J12: =IF(COUNTIFS(TVFImportMonate[Jahr],Steuerung!$F$6,TVFImportMonate[Monat],5)>0,SUMIFS(TVFImportMonate[Personalaufwand],TVFImportMonate[Jahr],Steuerung!$F$6,TVFImportMonate[Monat],5),IF(COUNTIFS('D Finanzen'!$A$45:$A$115,Steuerung!$F$6,'D Finanzen'!$B$45:$B$115,J$5)=0,"",SUMIFS('D Finanzen'!$E$45:$E$115,'D Finanzen'!$A$45:$A$115,Steuerung!$F$6,'D Finanzen'!$B$45:$B$115,J$5,'D Finanzen'!$C$45:$C$115,50))) | K12: =IF(COUNTIFS(TVFImportMonate[Jahr],Steuerung!$F$6,TVFImportMonate[Monat],6)>0,SUMIFS(TVFImportMonate[Personalaufwand],TVFImportMonate[Jahr],Steuerung!$F$6,TVFImportMonate[Monat],6),IF(COUNTIFS('D Finanzen'!$A$45:$A$115,Steuerung!$F$6,'D Finanzen'!$B$45:$B$115,K$5)=0,"",SUMIFS('D Finanzen'!$E$45:$E$115,'D Finanzen'!$A$45:$A$115,Steuerung!$F$6,'D Finanzen'!$B$45:$B$115,K$5,'D Finanzen'!$C$45:$C$115,50))) | L12: =IF(COUNTIFS(TVFImportMonate[Jahr],Steuerung!$F$6,TVFImportMonate[Monat],7)>0,SUMIFS(TVFImportMonate[Personalaufwand],TVFImportMonate[Jahr],Steuerung!$F$6,TVFImportMonate[Monat],7),IF(COUNTIFS('D Finanzen'!$A$45:$A$115,Steuerung!$F$6,'D Finanzen'!$B$45:$B$115,L$5)=0,"",SUMIFS('D Finanzen'!$E$45:$E$115,'D Finanzen'!$A$45:$A$115,Steuerung!$F$6,'D Finanzen'!$B$45:$B$115,L$5,'D Finanzen'!$C$45:$C$115,50))) | M12: =IF(COUNTIFS(TVFImportMonate[Jahr],Steuerung!$F$6,TVFImportMonate[Monat],8)>0,SUMIFS(TVFImportMonate[Personalaufwand],TVFImportMonate[Jahr],Steuerung!$F$6,TVFImportMonate[Monat],8),IF(COUNTIFS('D Finanzen'!$A$45:$A$115,Steuerung!$F$6,'D Finanzen'!$B$45:$B$115,M$5)=0,"",SUMIFS('D Finanzen'!$E$45:$E$115,'D Finanzen'!$A$45:$A$115,Steuerung!$F$6,'D Finanzen'!$B$45:$B$115,M$5,'D Finanzen'!$C$45:$C$115,50))) | N12: =IF(COUNTIFS(TVFImportMonate[Jahr],Steuerung!$F$6,TVFImportMonate[Monat],9)>0,SUMIFS(TVFImportMonate[Personalaufwand],TVFImportMonate[Jahr],Steuerung!$F$6,TVFImportMonate[Monat],9),IF(COUNTIFS('D Finanzen'!$A$45:$A$115,Steuerung!$F$6,'D Finanzen'!$B$45:$B$115,N$5)=0,"",SUMIFS('D Finanzen'!$E$45:$E$115,'D Finanzen'!$A$45:$A$115,Steuerung!$F$6,'D Finanzen'!$B$45:$B$115,N$5,'D Finanzen'!$C$45:$C$115,50))) | O12: =IF(COUNTIFS(TVFImportMonate[Jahr],Steuerung!$F$6,TVFImportMonate[Monat],10)>0,SUMIFS(TVFImportMonate[Personalaufwand],TVFImportMonate[Jahr],Steuerung!$F$6,TVFImportMonate[Monat],10),IF(COUNTIFS('D Finanzen'!$A$45:$A$115,Steuerung!$F$6,'D Finanzen'!$B$45:$B$115,O$5)=0,"",SUMIFS('D Finanzen'!$E$45:$E$115,'D Finanzen'!$A$45:$A$115,Steuerung!$F$6,'D Finanzen'!$B$45:$B$115,O$5,'D Finanzen'!$C$45:$C$115,50))) | P12: =IF(COUNTIFS(TVFImportMonate[Jahr],Steuerung!$F$6,TVFImportMonate[Monat],11)>0,SUMIFS(TVFImportMonate[Personalaufwand],TVFImportMonate[Jahr],Steuerung!$F$6,TVFImportMonate[Monat],11),IF(COUNTIFS('D Finanzen'!$A$45:$A$115,Steuerung!$F$6,'D Finanzen'!$B$45:$B$115,P$5)=0,"",SUMIFS('D Finanzen'!$E$45:$E$115,'D Finanzen'!$A$45:$A$115,Steuerung!$F$6,'D Finanzen'!$B$45:$B$115,P$5,'D Finanzen'!$C$45:$C$115,50))) | Q12: =IF(COUNTIFS(TVFImportMonate[Jahr],Steuerung!$F$6,TVFImportMonate[Monat],12)>0,SUMIFS(TVFImportMonate[Personalaufwand],TVFImportMonate[Jahr],Steuerung!$F$6,TVFImportMonate[Monat],12),IF(COUNTIFS('D Finanzen'!$A$45:$A$115,Steuerung!$F$6,'D Finanzen'!$B$45:$B$115,Q$5)=0,"",SUMIFS('D Finanzen'!$E$45:$E$115,'D Finanzen'!$A$45:$A$115,Steuerung!$F$6,'D Finanzen'!$B$45:$B$115,Q$5,'D Finanzen'!$C$45:$C$115,50)))
C13: Sonstige betriebliche Aufwendungen | D13: =SUMIFS(F13:Q13,$F$5:$Q$5,"<="&Steuerung!$F$7) | E13: =IF($D$9=0,"n.a.",D13/$D$9) | F13: =IF(COUNTIFS(TVFImportMonate[Jahr],Steuerung!$F$6,TVFImportMonate[Monat],1)>0,SUMIFS(TVFImportMonate[Sonstiger_Aufwand],TVFImportMonate[Jahr],Steuerung!$F$6,TVFImportMonate[Monat],1),IF(COUNTIFS('D Finanzen'!$A$45:$A$115,Steuerung!$F$6,'D Finanzen'!$B$45:$B$115,F$5)=0,"",SUMIFS('D Finanzen'!$E$45:$E$115,'D Finanzen'!$A$45:$A$115,Steuerung!$F$6,'D Finanzen'!$B$45:$B$115,F$5,'D Finanzen'!$C$45:$C$115,70))) | G13: =IF(COUNTIFS(TVFImportMonate[Jahr],Steuerung!$F$6,TVFImportMonate[Monat],2)>0,SUMIFS(TVFImportMonate[Sonstiger_Aufwand],TVFImportMonate[Jahr],Steuerung!$F$6,TVFImportMonate[Monat],2),IF(COUNTIFS('D Finanzen'!$A$45:$A$115,Steuerung!$F$6,'D Finanzen'!$B$45:$B$115,G$5)=0,"",SUMIFS('D Finanzen'!$E$45:$E$115,'D Finanzen'!$A$45:$A$115,Steuerung!$F$6,'D Finanzen'!$B$45:$B$115,G$5,'D Finanzen'!$C$45:$C$115,70))) | H13: =IF(COUNTIFS(TVFImportMonate[Jahr],Steuerung!$F$6,TVFImportMonate[Monat],3)>0,SUMIFS(TVFImportMonate[Sonstiger_Aufwand],TVFImportMonate[Jahr],Steuerung!$F$6,TVFImportMonate[Monat],3),IF(COUNTIFS('D Finanzen'!$A$45:$A$115,Steuerung!$F$6,'D Finanzen'!$B$45:$B$115,H$5)=0,"",SUMIFS('D Finanzen'!$E$45:$E$115,'D Finanzen'!$A$45:$A$115,Steuerung!$F$6,'D Finanzen'!$B$45:$B$115,H$5,'D Finanzen'!$C$45:$C$115,70))) | I13: =IF(COUNTIFS(TVFImportMonate[Jahr],Steuerung!$F$6,TVFImportMonate[Monat],4)>0,SUMIFS(TVFImportMonate[Sonstiger_Aufwand],TVFImportMonate[Jahr],Steuerung!$F$6,TVFImportMonate[Monat],4),IF(COUNTIFS('D Finanzen'!$A$45:$A$115,Steuerung!$F$6,'D Finanzen'!$B$45:$B$115,I$5)=0,"",SUMIFS('D Finanzen'!$E$45:$E$115,'D Finanzen'!$A$45:$A$115,Steuerung!$F$6,'D Finanzen'!$B$45:$B$115,I$5,'D Finanzen'!$C$45:$C$115,70))) | J13: =IF(COUNTIFS(TVFImportMonate[Jahr],Steuerung!$F$6,TVFImportMonate[Monat],5)>0,SUMIFS(TVFImportMonate[Sonstiger_Aufwand],TVFImportMonate[Jahr],Steuerung!$F$6,TVFImportMonate[Monat],5),IF(COUNTIFS('D Finanzen'!$A$45:$A$115,Steuerung!$F$6,'D Finanzen'!$B$45:$B$115,J$5)=0,"",SUMIFS('D Finanzen'!$E$45:$E$115,'D Finanzen'!$A$45:$A$115,Steuerung!$F$6,'D Finanzen'!$B$45:$B$115,J$5,'D Finanzen'!$C$45:$C$115,70))) | K13: =IF(COUNTIFS(TVFImportMonate[Jahr],Steuerung!$F$6,TVFImportMonate[Monat],6)>0,SUMIFS(TVFImportMonate[Sonstiger_Aufwand],TVFImportMonate[Jahr],Steuerung!$F$6,TVFImportMonate[Monat],6),IF(COUNTIFS('D Finanzen'!$A$45:$A$115,Steuerung!$F$6,'D Finanzen'!$B$45:$B$115,K$5)=0,"",SUMIFS('D Finanzen'!$E$45:$E$115,'D Finanzen'!$A$45:$A$115,Steuerung!$F$6,'D Finanzen'!$B$45:$B$115,K$5,'D Finanzen'!$C$45:$C$115,70))) | L13: =IF(COUNTIFS(TVFImportMonate[Jahr],Steuerung!$F$6,TVFImportMonate[Monat],7)>0,SUMIFS(TVFImportMonate[Sonstiger_Aufwand],TVFImportMonate[Jahr],Steuerung!$F$6,TVFImportMonate[Monat],7),IF(COUNTIFS('D Finanzen'!$A$45:$A$115,Steuerung!$F$6,'D Finanzen'!$B$45:$B$115,L$5)=0,"",SUMIFS('D Finanzen'!$E$45:$E$115,'D Finanzen'!$A$45:$A$115,Steuerung!$F$6,'D Finanzen'!$B$45:$B$115,L$5,'D Finanzen'!$C$45:$C$115,70))) | M13: =IF(COUNTIFS(TVFImportMonate[Jahr],Steuerung!$F$6,TVFImportMonate[Monat],8)>0,SUMIFS(TVFImportMonate[Sonstiger_Aufwand],TVFImportMonate[Jahr],Steuerung!$F$6,TVFImportMonate[Monat],8),IF(COUNTIFS('D Finanzen'!$A$45:$A$115,Steuerung!$F$6,'D Finanzen'!$B$45:$B$115,M$5)=0,"",SUMIFS('D Finanzen'!$E$45:$E$115,'D Finanzen'!$A$45:$A$115,Steuerung!$F$6,'D Finanzen'!$B$45:$B$115,M$5,'D Finanzen'!$C$45:$C$115,70))) | N13: =IF(COUNTIFS(TVFImportMonate[Jahr],Steuerung!$F$6,TVFImportMonate[Monat],9)>0,SUMIFS(TVFImportMonate[Sonstiger_Aufwand],TVFImportMonate[Jahr],Steuerung!$F$6,TVFImportMonate[Monat],9),IF(COUNTIFS('D Finanzen'!$A$45:$A$115,Steuerung!$F$6,'D Finanzen'!$B$45:$B$115,N$5)=0,"",SUMIFS('D Finanzen'!$E$45:$E$115,'D Finanzen'!$A$45:$A$115,Steuerung!$F$6,'D Finanzen'!$B$45:$B$115,N$5,'D Finanzen'!$C$45:$C$115,70))) | O13: =IF(COUNTIFS(TVFImportMonate[Jahr],Steuerung!$F$6,TVFImportMonate[Monat],10)>0,SUMIFS(TVFImportMonate[Sonstiger_Aufwand],TVFImportMonate[Jahr],Steuerung!$F$6,TVFImportMonate[Monat],10),IF(COUNTIFS('D Finanzen'!$A$45:$A$115,Steuerung!$F$6,'D Finanzen'!$B$45:$B$115,O$5)=0,"",SUMIFS('D Finanzen'!$E$45:$E$115,'D Finanzen'!$A$45:$A$115,Steuerung!$F$6,'D Finanzen'!$B$45:$B$115,O$5,'D Finanzen'!$C$45:$C$115,70))) | P13: =IF(COUNTIFS(TVFImportMonate[Jahr],Steuerung!$F$6,TVFImportMonate[Monat],11)>0,SUMIFS(TVFImportMonate[Sonstiger_Aufwand],TVFImportMonate[Jahr],Steuerung!$F$6,TVFImportMonate[Monat],11),IF(COUNTIFS('D Finanzen'!$A$45:$A$115,Steuerung!$F$6,'D Finanzen'!$B$45:$B$115,P$5)=0,"",SUMIFS('D Finanzen'!$E$45:$E$115,'D Finanzen'!$A$45:$A$115,Steuerung!$F$6,'D Finanzen'!$B$45:$B$115,P$5,'D Finanzen'!$C$45:$C$115,70))) | Q13: =IF(COUNTIFS(TVFImportMonate[Jahr],Steuerung!$F$6,TVFImportMonate[Monat],12)>0,SUMIFS(TVFImportMonate[Sonstiger_Aufwand],TVFImportMonate[Jahr],Steuerung!$F$6,TVFImportMonate[Monat],12),IF(COUNTIFS('D Finanzen'!$A$45:$A$115,Steuerung!$F$6,'D Finanzen'!$B$45:$B$115,Q$5)=0,"",SUMIFS('D Finanzen'!$E$45:$E$115,'D Finanzen'!$A$45:$A$115,Steuerung!$F$6,'D Finanzen'!$B$45:$B$115,Q$5,'D Finanzen'!$C$45:$C$115,70)))
C14: EBITDA aus Staffel | D14: =SUMIFS(F14:Q14,$F$5:$Q$5,"<="&Steuerung!$F$7) | E14: =IF($D$9=0,"n.a.",D14/$D$9) | F14: =IF(F7="","",SUM(F9:F13)) | G14: =IF(G7="","",SUM(G9:G13)) | H14: =IF(H7="","",SUM(H9:H13)) | I14: =IF(I7="","",SUM(I9:I13)) | J14: =IF(J7="","",SUM(J9:J13)) | K14: =IF(K7="","",SUM(K9:K13)) | L14: =IF(L7="","",SUM(L9:L13)) | M14: =IF(M7="","",SUM(M9:M13)) | ... Q14: =IF(Q7="","",SUM(Q9:Q13))
C15: Abschreibungen | D15: =SUMIFS(F15:Q15,$F$5:$Q$5,"<="&Steuerung!$F$7) | E15: =IF($D$9=0,"n.a.",D15/$D$9) | F15: =IF(COUNTIFS(TVFImportMonate[Jahr],Steuerung!$F$6,TVFImportMonate[Monat],1)>0,SUMIFS(TVFImportMonate[Abschreibungen],TVFImportMonate[Jahr],Steuerung!$F$6,TVFImportMonate[Monat],1),IF(COUNTIFS('D Finanzen'!$A$45:$A$115,Steuerung!$F$6,'D Finanzen'!$B$45:$B$115,F$5)=0,"",SUMIFS('D Finanzen'!$E$45:$E$115,'D Finanzen'!$A$45:$A$115,Steuerung!$F$6,'D Finanzen'!$B$45:$B$115,F$5,'D Finanzen'!$C$45:$C$115,60))) | G15: =IF(COUNTIFS(TVFImportMonate[Jahr],Steuerung!$F$6,TVFImportMonate[Monat],2)>0,SUMIFS(TVFImportMonate[Abschreibungen],TVFImportMonate[Jahr],Steuerung!$F$6,TVFImportMonate[Monat],2),IF(COUNTIFS('D Finanzen'!$A$45:$A$115,Steuerung!$F$6,'D Finanzen'!$B$45:$B$115,G$5)=0,"",SUMIFS('D Finanzen'!$E$45:$E$115,'D Finanzen'!$A$45:$A$115,Steuerung!$F$6,'D Finanzen'!$B$45:$B$115,G$5,'D Finanzen'!$C$45:$C$115,60))) | H15: =IF(COUNTIFS(TVFImportMonate[Jahr],Steuerung!$F$6,TVFImportMonate[Monat],3)>0,SUMIFS(TVFImportMonate[Abschreibungen],TVFImportMonate[Jahr],Steuerung!$F$6,TVFImportMonate[Monat],3),IF(COUNTIFS('D Finanzen'!$A$45:$A$115,Steuerung!$F$6,'D Finanzen'!$B$45:$B$115,H$5)=0,"",SUMIFS('D Finanzen'!$E$45:$E$115,'D Finanzen'!$A$45:$A$115,Steuerung!$F$6,'D Finanzen'!$B$45:$B$115,H$5,'D Finanzen'!$C$45:$C$115,60))) | I15: =IF(COUNTIFS(TVFImportMonate[Jahr],Steuerung!$F$6,TVFImportMonate[Monat],4)>0,SUMIFS(TVFImportMonate[Abschreibungen],TVFImportMonate[Jahr],Steuerung!$F$6,TVFImportMonate[Monat],4),IF(COUNTIFS('D Finanzen'!$A$45:$A$115,Steuerung!$F$6,'D Finanzen'!$B$45:$B$115,I$5)=0,"",SUMIFS('D Finanzen'!$E$45:$E$115,'D Finanzen'!$A$45:$A$115,Steuerung!$F$6,'D Finanzen'!$B$45:$B$115,I$5,'D Finanzen'!$C$45:$C$115,60))) | J15: =IF(COUNTIFS(TVFImportMonate[Jahr],Steuerung!$F$6,TVFImportMonate[Monat],5)>0,SUMIFS(TVFImportMonate[Abschreibungen],TVFImportMonate[Jahr],Steuerung!$F$6,TVFImportMonate[Monat],5),IF(COUNTIFS('D Finanzen'!$A$45:$A$115,Steuerung!$F$6,'D Finanzen'!$B$45:$B$115,J$5)=0,"",SUMIFS('D Finanzen'!$E$45:$E$115,'D Finanzen'!$A$45:$A$115,Steuerung!$F$6,'D Finanzen'!$B$45:$B$115,J$5,'D Finanzen'!$C$45:$C$115,60))) | K15: =IF(COUNTIFS(TVFImportMonate[Jahr],Steuerung!$F$6,TVFImportMonate[Monat],6)>0,SUMIFS(TVFImportMonate[Abschreibungen],TVFImportMonate[Jahr],Steuerung!$F$6,TVFImportMonate[Monat],6),IF(COUNTIFS('D Finanzen'!$A$45:$A$115,Steuerung!$F$6,'D Finanzen'!$B$45:$B$115,K$5)=0,"",SUMIFS('D Finanzen'!$E$45:$E$115,'D Finanzen'!$A$45:$A$115,Steuerung!$F$6,'D Finanzen'!$B$45:$B$115,K$5,'D Finanzen'!$C$45:$C$115,60))) | L15: =IF(COUNTIFS(TVFImportMonate[Jahr],Steuerung!$F$6,TVFImportMonate[Monat],7)>0,SUMIFS(TVFImportMonate[Abschreibungen],TVFImportMonate[Jahr],Steuerung!$F$6,TVFImportMonate[Monat],7),IF(COUNTIFS('D Finanzen'!$A$45:$A$115,Steuerung!$F$6,'D Finanzen'!$B$45:$B$115,L$5)=0,"",SUMIFS('D Finanzen'!$E$45:$E$115,'D Finanzen'!$A$45:$A$115,Steuerung!$F$6,'D Finanzen'!$B$45:$B$115,L$5,'D Finanzen'!$C$45:$C$115,60))) | M15: =IF(COUNTIFS(TVFImportMonate[Jahr],Steuerung!$F$6,TVFImportMonate[Monat],8)>0,SUMIFS(TVFImportMonate[Abschreibungen],TVFImportMonate[Jahr],Steuerung!$F$6,TVFImportMonate[Monat],8),IF(COUNTIFS('D Finanzen'!$A$45:$A$115,Steuerung!$F$6,'D Finanzen'!$B$45:$B$115,M$5)=0,"",SUMIFS('D Finanzen'!$E$45:$E$115,'D Finanzen'!$A$45:$A$115,Steuerung!$F$6,'D Finanzen'!$B$45:$B$115,M$5,'D Finanzen'!$C$45:$C$115,60))) | N15: =IF(COUNTIFS(TVFImportMonate[Jahr],Steuerung!$F$6,TVFImportMonate[Monat],9)>0,SUMIFS(TVFImportMonate[Abschreibungen],TVFImportMonate[Jahr],Steuerung!$F$6,TVFImportMonate[Monat],9),IF(COUNTIFS('D Finanzen'!$A$45:$A$115,Steuerung!$F$6,'D Finanzen'!$B$45:$B$115,N$5)=0,"",SUMIFS('D Finanzen'!$E$45:$E$115,'D Finanzen'!$A$45:$A$115,Steuerung!$F$6,'D Finanzen'!$B$45:$B$115,N$5,'D Finanzen'!$C$45:$C$115,60))) | O15: =IF(COUNTIFS(TVFImportMonate[Jahr],Steuerung!$F$6,TVFImportMonate[Monat],10)>0,SUMIFS(TVFImportMonate[Abschreibungen],TVFImportMonate[Jahr],Steuerung!$F$6,TVFImportMonate[Monat],10),IF(COUNTIFS('D Finanzen'!$A$45:$A$115,Steuerung!$F$6,'D Finanzen'!$B$45:$B$115,O$5)=0,"",SUMIFS('D Finanzen'!$E$45:$E$115,'D Finanzen'!$A$45:$A$115,Steuerung!$F$6,'D Finanzen'!$B$45:$B$115,O$5,'D Finanzen'!$C$45:$C$115,60))) | P15: =IF(COUNTIFS(TVFImportMonate[Jahr],Steuerung!$F$6,TVFImportMonate[Monat],11)>0,SUMIFS(TVFImportMonate[Abschreibungen],TVFImportMonate[Jahr],Steuerung!$F$6,TVFImportMonate[Monat],11),IF(COUNTIFS('D Finanzen'!$A$45:$A$115,Steuerung!$F$6,'D Finanzen'!$B$45:$B$115,P$5)=0,"",SUMIFS('D Finanzen'!$E$45:$E$115,'D Finanzen'!$A$45:$A$115,Steuerung!$F$6,'D Finanzen'!$B$45:$B$115,P$5,'D Finanzen'!$C$45:$C$115,60))) | Q15: =IF(COUNTIFS(TVFImportMonate[Jahr],Steuerung!$F$6,TVFImportMonate[Monat],12)>0,SUMIFS(TVFImportMonate[Abschreibungen],TVFImportMonate[Jahr],Steuerung!$F$6,TVFImportMonate[Monat],12),IF(COUNTIFS('D Finanzen'!$A$45:$A$115,Steuerung!$F$6,'D Finanzen'!$B$45:$B$115,Q$5)=0,"",SUMIFS('D Finanzen'!$E$45:$E$115,'D Finanzen'!$A$45:$A$115,Steuerung!$F$6,'D Finanzen'!$B$45:$B$115,Q$5,'D Finanzen'!$C$45:$C$115,60)))
C16: EBIT | D16: =SUMIFS(F16:Q16,$F$5:$Q$5,"<="&Steuerung!$F$7) | E16: =IF($D$9=0,"n.a.",D16/$D$9) | F16: =IF(F7="","",SUM(F14:F15)) | G16: =IF(G7="","",SUM(G14:G15)) | H16: =IF(H7="","",SUM(H14:H15)) | I16: =IF(I7="","",SUM(I14:I15)) | J16: =IF(J7="","",SUM(J14:J15)) | K16: =IF(K7="","",SUM(K14:K15)) | L16: =IF(L7="","",SUM(L14:L15)) | M16: =IF(M7="","",SUM(M14:M15)) | ... Q16: =IF(Q7="","",SUM(Q14:Q15))
C17: Finanzergebnis | D17: =SUMIFS(F17:Q17,$F$5:$Q$5,"<="&Steuerung!$F$7) | E17: =IF($D$9=0,"n.a.",D17/$D$9) | F17: =IF(COUNTIFS(TVFImportMonate[Jahr],Steuerung!$F$6,TVFImportMonate[Monat],1)>0,SUMIFS(TVFImportMonate[Finanzergebnis],TVFImportMonate[Jahr],Steuerung!$F$6,TVFImportMonate[Monat],1),IF(COUNTIFS('D Finanzen'!$A$45:$A$115,Steuerung!$F$6,'D Finanzen'!$B$45:$B$115,F$5)=0,"",SUMIFS('D Finanzen'!$E$45:$E$115,'D Finanzen'!$A$45:$A$115,Steuerung!$F$6,'D Finanzen'!$B$45:$B$115,F$5,'D Finanzen'!$C$45:$C$115,80))) | G17: =IF(COUNTIFS(TVFImportMonate[Jahr],Steuerung!$F$6,TVFImportMonate[Monat],2)>0,SUMIFS(TVFImportMonate[Finanzergebnis],TVFImportMonate[Jahr],Steuerung!$F$6,TVFImportMonate[Monat],2),IF(COUNTIFS('D Finanzen'!$A$45:$A$115,Steuerung!$F$6,'D Finanzen'!$B$45:$B$115,G$5)=0,"",SUMIFS('D Finanzen'!$E$45:$E$115,'D Finanzen'!$A$45:$A$115,Steuerung!$F$6,'D Finanzen'!$B$45:$B$115,G$5,'D Finanzen'!$C$45:$C$115,80))) | H17: =IF(COUNTIFS(TVFImportMonate[Jahr],Steuerung!$F$6,TVFImportMonate[Monat],3)>0,SUMIFS(TVFImportMonate[Finanzergebnis],TVFImportMonate[Jahr],Steuerung!$F$6,TVFImportMonate[Monat],3),IF(COUNTIFS('D Finanzen'!$A$45:$A$115,Steuerung!$F$6,'D Finanzen'!$B$45:$B$115,H$5)=0,"",SUMIFS('D Finanzen'!$E$45:$E$115,'D Finanzen'!$A$45:$A$115,Steuerung!$F$6,'D Finanzen'!$B$45:$B$115,H$5,'D Finanzen'!$C$45:$C$115,80))) | I17: =IF(COUNTIFS(TVFImportMonate[Jahr],Steuerung!$F$6,TVFImportMonate[Monat],4)>0,SUMIFS(TVFImportMonate[Finanzergebnis],TVFImportMonate[Jahr],Steuerung!$F$6,TVFImportMonate[Monat],4),IF(COUNTIFS('D Finanzen'!$A$45:$A$115,Steuerung!$F$6,'D Finanzen'!$B$45:$B$115,I$5)=0,"",SUMIFS('D Finanzen'!$E$45:$E$115,'D Finanzen'!$A$45:$A$115,Steuerung!$F$6,'D Finanzen'!$B$45:$B$115,I$5,'D Finanzen'!$C$45:$C$115,80))) | J17: =IF(COUNTIFS(TVFImportMonate[Jahr],Steuerung!$F$6,TVFImportMonate[Monat],5)>0,SUMIFS(TVFImportMonate[Finanzergebnis],TVFImportMonate[Jahr],Steuerung!$F$6,TVFImportMonate[Monat],5),IF(COUNTIFS('D Finanzen'!$A$45:$A$115,Steuerung!$F$6,'D Finanzen'!$B$45:$B$115,J$5)=0,"",SUMIFS('D Finanzen'!$E$45:$E$115,'D Finanzen'!$A$45:$A$115,Steuerung!$F$6,'D Finanzen'!$B$45:$B$115,J$5,'D Finanzen'!$C$45:$C$115,80))) | K17: =IF(COUNTIFS(TVFImportMonate[Jahr],Steuerung!$F$6,TVFImportMonate[Monat],6)>0,SUMIFS(TVFImportMonate[Finanzergebnis],TVFImportMonate[Jahr],Steuerung!$F$6,TVFImportMonate[Monat],6),IF(COUNTIFS('D Finanzen'!$A$45:$A$115,Steuerung!$F$6,'D Finanzen'!$B$45:$B$115,K$5)=0,"",SUMIFS('D Finanzen'!$E$45:$E$115,'D Finanzen'!$A$45:$A$115,Steuerung!$F$6,'D Finanzen'!$B$45:$B$115,K$5,'D Finanzen'!$C$45:$C$115,80))) | L17: =IF(COUNTIFS(TVFImportMonate[Jahr],Steuerung!$F$6,TVFImportMonate[Monat],7)>0,SUMIFS(TVFImportMonate[Finanzergebnis],TVFImportMonate[Jahr],Steuerung!$F$6,TVFImportMonate[Monat],7),IF(COUNTIFS('D Finanzen'!$A$45:$A$115,Steuerung!$F$6,'D Finanzen'!$B$45:$B$115,L$5)=0,"",SUMIFS('D Finanzen'!$E$45:$E$115,'D Finanzen'!$A$45:$A$115,Steuerung!$F$6,'D Finanzen'!$B$45:$B$115,L$5,'D Finanzen'!$C$45:$C$115,80))) | M17: =IF(COUNTIFS(TVFImportMonate[Jahr],Steuerung!$F$6,TVFImportMonate[Monat],8)>0,SUMIFS(TVFImportMonate[Finanzergebnis],TVFImportMonate[Jahr],Steuerung!$F$6,TVFImportMonate[Monat],8),IF(COUNTIFS('D Finanzen'!$A$45:$A$115,Steuerung!$F$6,'D Finanzen'!$B$45:$B$115,M$5)=0,"",SUMIFS('D Finanzen'!$E$45:$E$115,'D Finanzen'!$A$45:$A$115,Steuerung!$F$6,'D Finanzen'!$B$45:$B$115,M$5,'D Finanzen'!$C$45:$C$115,80))) | N17: =IF(COUNTIFS(TVFImportMonate[Jahr],Steuerung!$F$6,TVFImportMonate[Monat],9)>0,SUMIFS(TVFImportMonate[Finanzergebnis],TVFImportMonate[Jahr],Steuerung!$F$6,TVFImportMonate[Monat],9),IF(COUNTIFS('D Finanzen'!$A$45:$A$115,Steuerung!$F$6,'D Finanzen'!$B$45:$B$115,N$5)=0,"",SUMIFS('D Finanzen'!$E$45:$E$115,'D Finanzen'!$A$45:$A$115,Steuerung!$F$6,'D Finanzen'!$B$45:$B$115,N$5,'D Finanzen'!$C$45:$C$115,80))) | O17: =IF(COUNTIFS(TVFImportMonate[Jahr],Steuerung!$F$6,TVFImportMonate[Monat],10)>0,SUMIFS(TVFImportMonate[Finanzergebnis],TVFImportMonate[Jahr],Steuerung!$F$6,TVFImportMonate[Monat],10),IF(COUNTIFS('D Finanzen'!$A$45:$A$115,Steuerung!$F$6,'D Finanzen'!$B$45:$B$115,O$5)=0,"",SUMIFS('D Finanzen'!$E$45:$E$115,'D Finanzen'!$A$45:$A$115,Steuerung!$F$6,'D Finanzen'!$B$45:$B$115,O$5,'D Finanzen'!$C$45:$C$115,80))) | P17: =IF(COUNTIFS(TVFImportMonate[Jahr],Steuerung!$F$6,TVFImportMonate[Monat],11)>0,SUMIFS(TVFImportMonate[Finanzergebnis],TVFImportMonate[Jahr],Steuerung!$F$6,TVFImportMonate[Monat],11),IF(COUNTIFS('D Finanzen'!$A$45:$A$115,Steuerung!$F$6,'D Finanzen'!$B$45:$B$115,P$5)=0,"",SUMIFS('D Finanzen'!$E$45:$E$115,'D Finanzen'!$A$45:$A$115,Steuerung!$F$6,'D Finanzen'!$B$45:$B$115,P$5,'D Finanzen'!$C$45:$C$115,80))) | Q17: =IF(COUNTIFS(TVFImportMonate[Jahr],Steuerung!$F$6,TVFImportMonate[Monat],12)>0,SUMIFS(TVFImportMonate[Finanzergebnis],TVFImportMonate[Jahr],Steuerung!$F$6,TVFImportMonate[Monat],12),IF(COUNTIFS('D Finanzen'!$A$45:$A$115,Steuerung!$F$6,'D Finanzen'!$B$45:$B$115,Q$5)=0,"",SUMIFS('D Finanzen'!$E$45:$E$115,'D Finanzen'!$A$45:$A$115,Steuerung!$F$6,'D Finanzen'!$B$45:$B$115,Q$5,'D Finanzen'!$C$45:$C$115,80)))
C18: Ergebnis aus Staffel | D18: =SUMIFS(F18:Q18,$F$5:$Q$5,"<="&Steuerung!$F$7) | E18: =IF($D$9=0,"n.a.",D18/$D$9) | F18: =IF(F7="","",SUM(F16:F17)) | G18: =IF(G7="","",SUM(G16:G17)) | H18: =IF(H7="","",SUM(H16:H17)) | I18: =IF(I7="","",SUM(I16:I17)) | J18: =IF(J7="","",SUM(J16:J17)) | K18: =IF(K7="","",SUM(K16:K17)) | L18: =IF(L7="","",SUM(L16:L17)) | M18: =IF(M7="","",SUM(M16:M17)) | ... Q18: =IF(Q7="","",SUM(Q16:Q17))
C20: EBITDA Cockpit-Definition | D20: =SUMIFS(F20:Q20,$F$5:$Q$5,"<="&Steuerung!$F$7) | E20: =IF($D$9=0,"n.a.",D20/$D$9) | F20: =IF(COUNTIFS(TVFImportMonate[Jahr],Steuerung!$F$6,TVFImportMonate[Monat],1)>0,F14,IF(COUNTIFS('D Finanzen'!$A$8:$A$16,Steuerung!$F$6,'D Finanzen'!$B$8:$B$16,F$5)=0,"",SUMIFS('D Finanzen'!$F$8:$F$16,'D Finanzen'!$A$8:$A$16,Steuerung!$F$6,'D Finanzen'!$B$8:$B$16,F$5))) | G20: =IF(COUNTIFS(TVFImportMonate[Jahr],Steuerung!$F$6,TVFImportMonate[Monat],2)>0,G14,IF(COUNTIFS('D Finanzen'!$A$8:$A$16,Steuerung!$F$6,'D Finanzen'!$B$8:$B$16,G$5)=0,"",SUMIFS('D Finanzen'!$F$8:$F$16,'D Finanzen'!$A$8:$A$16,Steuerung!$F$6,'D Finanzen'!$B$8:$B$16,G$5))) | H20: =IF(COUNTIFS(TVFImportMonate[Jahr],Steuerung!$F$6,TVFImportMonate[Monat],3)>0,H14,IF(COUNTIFS('D Finanzen'!$A$8:$A$16,Steuerung!$F$6,'D Finanzen'!$B$8:$B$16,H$5)=0,"",SUMIFS('D Finanzen'!$F$8:$F$16,'D Finanzen'!$A$8:$A$16,Steuerung!$F$6,'D Finanzen'!$B$8:$B$16,H$5))) | I20: =IF(COUNTIFS(TVFImportMonate[Jahr],Steuerung!$F$6,TVFImportMonate[Monat],4)>0,I14,IF(COUNTIFS('D Finanzen'!$A$8:$A$16,Steuerung!$F$6,'D Finanzen'!$B$8:$B$16,I$5)=0,"",SUMIFS('D Finanzen'!$F$8:$F$16,'D Finanzen'!$A$8:$A$16,Steuerung!$F$6,'D Finanzen'!$B$8:$B$16,I$5))) | J20: =IF(COUNTIFS(TVFImportMonate[Jahr],Steuerung!$F$6,TVFImportMonate[Monat],5)>0,J14,IF(COUNTIFS('D Finanzen'!$A$8:$A$16,Steuerung!$F$6,'D Finanzen'!$B$8:$B$16,J$5)=0,"",SUMIFS('D Finanzen'!$F$8:$F$16,'D Finanzen'!$A$8:$A$16,Steuerung!$F$6,'D Finanzen'!$B$8:$B$16,J$5))) | K20: =IF(COUNTIFS(TVFImportMonate[Jahr],Steuerung!$F$6,TVFImportMonate[Monat],6)>0,K14,IF(COUNTIFS('D Finanzen'!$A$8:$A$16,Steuerung!$F$6,'D Finanzen'!$B$8:$B$16,K$5)=0,"",SUMIFS('D Finanzen'!$F$8:$F$16,'D Finanzen'!$A$8:$A$16,Steuerung!$F$6,'D Finanzen'!$B$8:$B$16,K$5))) | L20: =IF(COUNTIFS(TVFImportMonate[Jahr],Steuerung!$F$6,TVFImportMonate[Monat],7)>0,L14,IF(COUNTIFS('D Finanzen'!$A$8:$A$16,Steuerung!$F$6,'D Finanzen'!$B$8:$B$16,L$5)=0,"",SUMIFS('D Finanzen'!$F$8:$F$16,'D Finanzen'!$A$8:$A$16,Steuerung!$F$6,'D Finanzen'!$B$8:$B$16,L$5))) | M20: =IF(COUNTIFS(TVFImportMonate[Jahr],Steuerung!$F$6,TVFImportMonate[Monat],8)>0,M14,IF(COUNTIFS('D Finanzen'!$A$8:$A$16,Steuerung!$F$6,'D Finanzen'!$B$8:$B$16,M$5)=0,"",SUMIFS('D Finanzen'!$F$8:$F$16,'D Finanzen'!$A$8:$A$16,Steuerung!$F$6,'D Finanzen'!$B$8:$B$16,M$5))) | N20: =IF(COUNTIFS(TVFImportMonate[Jahr],Steuerung!$F$6,TVFImportMonate[Monat],9)>0,N14,IF(COUNTIFS('D Finanzen'!$A$8:$A$16,Steuerung!$F$6,'D Finanzen'!$B$8:$B$16,N$5)=0,"",SUMIFS('D Finanzen'!$F$8:$F$16,'D Finanzen'!$A$8:$A$16,Steuerung!$F$6,'D Finanzen'!$B$8:$B$16,N$5))) | O20: =IF(COUNTIFS(TVFImportMonate[Jahr],Steuerung!$F$6,TVFImportMonate[Monat],10)>0,O14,IF(COUNTIFS('D Finanzen'!$A$8:$A$16,Steuerung!$F$6,'D Finanzen'!$B$8:$B$16,O$5)=0,"",SUMIFS('D Finanzen'!$F$8:$F$16,'D Finanzen'!$A$8:$A$16,Steuerung!$F$6,'D Finanzen'!$B$8:$B$16,O$5))) | P20: =IF(COUNTIFS(TVFImportMonate[Jahr],Steuerung!$F$6,TVFImportMonate[Monat],11)>0,P14,IF(COUNTIFS('D Finanzen'!$A$8:$A$16,Steuerung!$F$6,'D Finanzen'!$B$8:$B$16,P$5)=0,"",SUMIFS('D Finanzen'!$F$8:$F$16,'D Finanzen'!$A$8:$A$16,Steuerung!$F$6,'D Finanzen'!$B$8:$B$16,P$5))) | Q20: =IF(COUNTIFS(TVFImportMonate[Jahr],Steuerung!$F$6,TVFImportMonate[Monat],12)>0,Q14,IF(COUNTIFS('D Finanzen'!$A$8:$A$16,Steuerung!$F$6,'D Finanzen'!$B$8:$B$16,Q$5)=0,"",SUMIFS('D Finanzen'!$F$8:$F$16,'D Finanzen'!$A$8:$A$16,Steuerung!$F$6,'D Finanzen'!$B$8:$B$16,Q$5)))
C21: Differenz EBITDA-Definition | D21: =SUMIFS(F21:Q21,$F$5:$Q$5,"<="&Steuerung!$F$7) | E21: =IF($D$9=0,"n.a.",D21/$D$9) | F21: =IF(F7="","",ROUND(F14-F20,2)) | G21: =IF(G7="","",ROUND(G14-G20,2)) | H21: =IF(H7="","",ROUND(H14-H20,2)) | I21: =IF(I7="","",ROUND(I14-I20,2)) | J21: =IF(J7="","",ROUND(J14-J20,2)) | K21: =IF(K7="","",ROUND(K14-K20,2)) | L21: =IF(L7="","",ROUND(L14-L20,2)) | M21: =IF(M7="","",ROUND(M14-M20,2)) | ... Q21: =IF(Q7="","",ROUND(Q14-Q20,2))
C23: Quelle je Monat | F23: =IF(COUNTIFS(TVFImportMonate[Jahr],Steuerung!$F$6,TVFImportMonate[Monat],1)>0,"CSV-Import","Originalexport") | G23: =IF(COUNTIFS(TVFImportMonate[Jahr],Steuerung!$F$6,TVFImportMonate[Monat],2)>0,"CSV-Import","Originalexport") | H23: =IF(COUNTIFS(TVFImportMonate[Jahr],Steuerung!$F$6,TVFImportMonate[Monat],3)>0,"CSV-Import","Originalexport") | I23: =IF(COUNTIFS(TVFImportMonate[Jahr],Steuerung!$F$6,TVFImportMonate[Monat],4)>0,"CSV-Import","Originalexport") | J23: =IF(COUNTIFS(TVFImportMonate[Jahr],Steuerung!$F$6,TVFImportMonate[Monat],5)>0,"CSV-Import","Originalexport") | K23: =IF(COUNTIFS(TVFImportMonate[Jahr],Steuerung!$F$6,TVFImportMonate[Monat],6)>0,"CSV-Import","Originalexport") | L23: =IF(COUNTIFS(TVFImportMonate[Jahr],Steuerung!$F$6,TVFImportMonate[Monat],7)>0,"CSV-Import","Originalexport") | M23: =IF(COUNTIFS(TVFImportMonate[Jahr],Steuerung!$F$6,TVFImportMonate[Monat],8)>0,"CSV-Import","Originalexport") | N23: =IF(COUNTIFS(TVFImportMonate[Jahr],Steuerung!$F$6,TVFImportMonate[Monat],9)>0,"CSV-Import","Originalexport") | O23: =IF(COUNTIFS(TVFImportMonate[Jahr],Steuerung!$F$6,TVFImportMonate[Monat],10)>0,"CSV-Import","Originalexport") | P23: =IF(COUNTIFS(TVFImportMonate[Jahr],Steuerung!$F$6,TVFImportMonate[Monat],11)>0,"CSV-Import","Originalexport") | Q23: =IF(COUNTIFS(TVFImportMonate[Jahr],Steuerung!$F$6,TVFImportMonate[Monat],12)>0,"CSV-Import","Originalexport")
C24: Neutrales Ergebnis | D24: =SUMIFS(F24:Q24,$F$5:$Q$5,"<="&Steuerung!$F$7) | F24: =IF(COUNTIFS(TVFImportMonate[Jahr],Steuerung!$F$6,TVFImportMonate[Monat],1)>0,SUMIFS(TVFImportMonate[Neutrales_Ergebnis],TVFImportMonate[Jahr],Steuerung!$F$6,TVFImportMonate[Monat],1),SUMIFS('D Finanzen'!$G$8:$G$16,'D Finanzen'!$A$8:$A$16,Steuerung!$F$6,'D Finanzen'!$B$8:$B$16,1)) | G24: =IF(COUNTIFS(TVFImportMonate[Jahr],Steuerung!$F$6,TVFImportMonate[Monat],2)>0,SUMIFS(TVFImportMonate[Neutrales_Ergebnis],TVFImportMonate[Jahr],Steuerung!$F$6,TVFImportMonate[Monat],2),SUMIFS('D Finanzen'!$G$8:$G$16,'D Finanzen'!$A$8:$A$16,Steuerung!$F$6,'D Finanzen'!$B$8:$B$16,2)) | H24: =IF(COUNTIFS(TVFImportMonate[Jahr],Steuerung!$F$6,TVFImportMonate[Monat],3)>0,SUMIFS(TVFImportMonate[Neutrales_Ergebnis],TVFImportMonate[Jahr],Steuerung!$F$6,TVFImportMonate[Monat],3),SUMIFS('D Finanzen'!$G$8:$G$16,'D Finanzen'!$A$8:$A$16,Steuerung!$F$6,'D Finanzen'!$B$8:$B$16,3)) | I24: =IF(COUNTIFS(TVFImportMonate[Jahr],Steuerung!$F$6,TVFImportMonate[Monat],4)>0,SUMIFS(TVFImportMonate[Neutrales_Ergebnis],TVFImportMonate[Jahr],Steuerung!$F$6,TVFImportMonate[Monat],4),SUMIFS('D Finanzen'!$G$8:$G$16,'D Finanzen'!$A$8:$A$16,Steuerung!$F$6,'D Finanzen'!$B$8:$B$16,4)) | J24: =IF(COUNTIFS(TVFImportMonate[Jahr],Steuerung!$F$6,TVFImportMonate[Monat],5)>0,SUMIFS(TVFImportMonate[Neutrales_Ergebnis],TVFImportMonate[Jahr],Steuerung!$F$6,TVFImportMonate[Monat],5),SUMIFS('D Finanzen'!$G$8:$G$16,'D Finanzen'!$A$8:$A$16,Steuerung!$F$6,'D Finanzen'!$B$8:$B$16,5)) | K24: =IF(COUNTIFS(TVFImportMonate[Jahr],Steuerung!$F$6,TVFImportMonate[Monat],6)>0,SUMIFS(TVFImportMonate[Neutrales_Ergebnis],TVFImportMonate[Jahr],Steuerung!$F$6,TVFImportMonate[Monat],6),SUMIFS('D Finanzen'!$G$8:$G$16,'D Finanzen'!$A$8:$A$16,Steuerung!$F$6,'D Finanzen'!$B$8:$B$16,6)) | L24: =IF(COUNTIFS(TVFImportMonate[Jahr],Steuerung!$F$6,TVFImportMonate[Monat],7)>0,SUMIFS(TVFImportMonate[Neutrales_Ergebnis],TVFImportMonate[Jahr],Steuerung!$F$6,TVFImportMonate[Monat],7),SUMIFS('D Finanzen'!$G$8:$G$16,'D Finanzen'!$A$8:$A$16,Steuerung!$F$6,'D Finanzen'!$B$8:$B$16,7)) | M24: =IF(COUNTIFS(TVFImportMonate[Jahr],Steuerung!$F$6,TVFImportMonate[Monat],8)>0,SUMIFS(TVFImportMonate[Neutrales_Ergebnis],TVFImportMonate[Jahr],Steuerung!$F$6,TVFImportMonate[Monat],8),SUMIFS('D Finanzen'!$G$8:$G$16,'D Finanzen'!$A$8:$A$16,Steuerung!$F$6,'D Finanzen'!$B$8:$B$16,8)) | N24: =IF(COUNTIFS(TVFImportMonate[Jahr],Steuerung!$F$6,TVFImportMonate[Monat],9)>0,SUMIFS(TVFImportMonate[Neutrales_Ergebnis],TVFImportMonate[Jahr],Steuerung!$F$6,TVFImportMonate[Monat],9),SUMIFS('D Finanzen'!$G$8:$G$16,'D Finanzen'!$A$8:$A$16,Steuerung!$F$6,'D Finanzen'!$B$8:$B$16,9)) | O24: =IF(COUNTIFS(TVFImportMonate[Jahr],Steuerung!$F$6,TVFImportMonate[Monat],10)>0,SUMIFS(TVFImportMonate[Neutrales_Ergebnis],TVFImportMonate[Jahr],Steuerung!$F$6,TVFImportMonate[Monat],10),SUMIFS('D Finanzen'!$G$8:$G$16,'D Finanzen'!$A$8:$A$16,Steuerung!$F$6,'D Finanzen'!$B$8:$B$16,10)) | P24: =IF(COUNTIFS(TVFImportMonate[Jahr],Steuerung!$F$6,TVFImportMonate[Monat],11)>0,SUMIFS(TVFImportMonate[Neutrales_Ergebnis],TVFImportMonate[Jahr],Steuerung!$F$6,TVFImportMonate[Monat],11),SUMIFS('D Finanzen'!$G$8:$G$16,'D Finanzen'!$A$8:$A$16,Steuerung!$F$6,'D Finanzen'!$B$8:$B$16,11)) | Q24: =IF(COUNTIFS(TVFImportMonate[Jahr],Steuerung!$F$6,TVFImportMonate[Monat],12)>0,SUMIFS(TVFImportMonate[Neutrales_Ergebnis],TVFImportMonate[Jahr],Steuerung!$F$6,TVFImportMonate[Monat],12),SUMIFS('D Finanzen'!$G$8:$G$16,'D Finanzen'!$A$8:$A$16,Steuerung!$F$6,'D Finanzen'!$B$8:$B$16,12))

Sheet Cockpit_FC Eingabe
C2: Forecast-Eingabe
C3: Änderungen gegenüber dem exportierten Forecast. Positive Kosten erhöhen den Aufwand. Ist-Monate werden als gesperrt gekennzeichnet.
C6: Jahr | D6: Monat | E6: Region | F6: Auftrag / Projekt | G6: Δ Umsatz EUR | H6: Δ Bestand EUR | I6: Δ Kosten EUR | J6: Kommentar | K6: Status | L6: Δ EBITDA EUR
K7: =IF(COUNTA(C7:J7)=0,"",IF(OR(C7<>Steuerung!$F$6,D7<1,D7>12),"Periode prüfen",IF(D7<=Steuerung!$F$8,"IST gesperrt",IF(OR(E7="",F7="",COUNT(G7:I7)<>3),"Angaben fehlen","Wirksam")))) | L7: =IF(K7="Wirksam",SUM(G7:H7)-I7,IF(K7="","","n.a."))
K8: =IF(COUNTA(C8:J8)=0,"",IF(OR(C8<>Steuerung!$F$6,D8<1,D8>12),"Periode prüfen",IF(D8<=Steuerung!$F$8,"IST gesperrt",IF(OR(E8="",F8="",COUNT(G8:I8)<>3),"Angaben fehlen","Wirksam")))) | L8: =IF(K8="Wirksam",SUM(G8:H8)-I8,IF(K8="","","n.a."))
K9: =IF(COUNTA(C9:J9)=0,"",IF(OR(C9<>Steuerung!$F$6,D9<1,D9>12),"Periode prüfen",IF(D9<=Steuerung!$F$8,"IST gesperrt",IF(OR(E9="",F9="",COUNT(G9:I9)<>3),"Angaben fehlen","Wirksam")))) | L9: =IF(K9="Wirksam",SUM(G9:H9)-I9,IF(K9="","","n.a."))
K10: =IF(COUNTA(C10:J10)=0,"",IF(OR(C10<>Steuerung!$F$6,D10<1,D10>12),"Periode prüfen",IF(D10<=Steuerung!$F$8,"IST gesperrt",IF(OR(E10="",F10="",COUNT(G10:I10)<>3),"Angaben fehlen","Wirksam")))) | L10: =IF(K10="Wirksam",SUM(G10:H10)-I10,IF(K10="","","n.a."))
K11: =IF(COUNTA(C11:J11)=0,"",IF(OR(C11<>Steuerung!$F$6,D11<1,D11>12),"Periode prüfen",IF(D11<=Steuerung!$F$8,"IST gesperrt",IF(OR(E11="",F11="",COUNT(G11:I11)<>3),"Angaben fehlen","Wirksam")))) | L11: =IF(K11="Wirksam",SUM(G11:H11)-I11,IF(K11="","","n.a."))
K12: =IF(COUNTA(C12:J12)=0,"",IF(OR(C12<>Steuerung!$F$6,D12<1,D12>12),"Periode prüfen",IF(D12<=Steuerung!$F$8,"IST gesperrt",IF(OR(E12="",F12="",COUNT(G12:I12)<>3),"Angaben fehlen","Wirksam")))) | L12: =IF(K12="Wirksam",SUM(G12:H12)-I12,IF(K12="","","n.a."))
K13: =IF(COUNTA(C13:J13)=0,"",IF(OR(C13<>Steuerung!$F$6,D13<1,D13>12),"Periode prüfen",IF(D13<=Steuerung!$F$8,"IST gesperrt",IF(OR(E13="",F13="",COUNT(G13:I13)<>3),"Angaben fehlen","Wirksam")))) | L13: =IF(K13="Wirksam",SUM(G13:H13)-I13,IF(K13="","","n.a."))
K14: =IF(COUNTA(C14:J14)=0,"",IF(OR(C14<>Steuerung!$F$6,D14<1,D14>12),"Periode prüfen",IF(D14<=Steuerung!$F$8,"IST gesperrt",IF(OR(E14="",F14="",COUNT(G14:I14)<>3),"Angaben fehlen","Wirksam")))) | L14: =IF(K14="Wirksam",SUM(G14:H14)-I14,IF(K14="","","n.a."))
K15: =IF(COUNTA(C15:J15)=0,"",IF(OR(C15<>Steuerung!$F$6,D15<1,D15>12),"Periode prüfen",IF(D15<=Steuerung!$F$8,"IST gesperrt",IF(OR(E15="",F15="",COUNT(G15:I15)<>3),"Angaben fehlen","Wirksam")))) | L15: =IF(K15="Wirksam",SUM(G15:H15)-I15,IF(K15="","","n.a."))
K16: =IF(COUNTA(C16:J16)=0,"",IF(OR(C16<>Steuerung!$F$6,D16<1,D16>12),"Periode prüfen",IF(D16<=Steuerung!$F$8,"IST gesperrt",IF(OR(E16="",F16="",COUNT(G16:I16)<>3),"Angaben fehlen","Wirksam")))) | L16: =IF(K16="Wirksam",SUM(G16:H16)-I16,IF(K16="","","n.a."))
K17: =IF(COUNTA(C17:J17)=0,"",IF(OR(C17<>Steuerung!$F$6,D17<1,D17>12),"Periode prüfen",IF(D17<=Steuerung!$F$8,"IST gesperrt",IF(OR(E17="",F17="",COUNT(G17:I17)<>3),"Angaben fehlen","Wirksam")))) | L17: =IF(K17="Wirksam",SUM(G17:H17)-I17,IF(K17="","","n.a."))
K18: =IF(COUNTA(C18:J18)=0,"",IF(OR(C18<>Steuerung!$F$6,D18<1,D18>12),"Periode prüfen",IF(D18<=Steuerung!$F$8,"IST gesperrt",IF(OR(E18="",F18="",COUNT(G18:I18)<>3),"Angaben fehlen","Wirksam")))) | L18: =IF(K18="Wirksam",SUM(G18:H18)-I18,IF(K18="","","n.a."))
... K506: =IF(COUNTA(C506:J506)=0,"",IF(OR(C506<>Steuerung!$F$6,D506<1,D506>12),"Periode prüfen",IF(D506<=Steuerung!$F$8,"IST gesperrt",IF(OR(E506="",F506="",COUNT(G506:I506)<>3),"Angaben fehlen","Wirksam")))) | L506: =IF(K506="Wirksam",SUM(G506:H506)-I506,IF(K506="","","n.a."))

Sheet Cockpit_Import Monatsdaten
C2: Importierte Monats-GuV
C3: Befüllung über TVF_Import.ts. Eine Zeile je Jahr und Monat. Vorhandene Monate werden gezielt ersetzt. Originalquellen bleiben erhalten.
C6: Jahr | D6: Monat | E6: Umsatz | F6: Bestand | G6: Sonstige_Ertraege | H6: Materialaufwand | I6: Personalaufwand | J6: Sonstiger_Aufwand | K6: Abschreibungen | L6: Finanzergebnis | M6: Neutrales_Ergebnis
